Workbook

Sheet DONE - BTC Boosted Program
A1: Date | B1: AUM | C1: Gross Performance (%) | D1: Gross Performance (BTC) | E1: Net Performance | F1: Yearly APY | G1: Comments | I1: Investors | J1: Fees | K1: 45640 | L1: 45658 | M1: 45689 | N1: 45717 | O1: 45748 | P1: 45763
A2: 45640 | B2: 11.5681 | C2: 1 | G2: Création du fond | I2: Indigo | J2: 0 | K2: 0 | L2: =K2*$C$3*1+K2+(K3*$C$3*0.15)+(K4*$C$3*0.1)+(K5*$C$3*0.1) | M2: =L2*$C$4*1+L2+(L3*$C$4*0.15)+(L4*$C$4*0.1)+(L5*$C$4*0.1) | N2: =M2*$C$5*1+M2+(M3*$C$5*0.15)+(M4*$C$5*0.1)+(M5*$C$5*0.1) | O2: =N2*$C$6*1+N2+(N3*$C$6*0.15)+(N4*$C$6*0.1)+(N5*$C$6*0.1) | P2: =O2*$C$7*1+O2+(O3*$C$7*0.15)+(O4*$C$7*0.1)+(O5*$C$7*0.1)
A3: 45658 | B3: 11.61 | C3: =(B3*$C$2/B2)-100% | D3: =B3-B2 | E3: =C3*0.8 | F3: =C3*12 | I3: Kyle Gulamerian | J3: 0.15 | K3: 2.0336 | L3: =K3*$C$3*0.85+K3 | M3: =L3*$C$4*0.85+L3 | N3: =M3*$C$5*0.85+M3 | O3: =N3*$C$6*0.85+N3 | P3: =O3*$C$7*0.85+O3
A4: 45689 | B4: 11.73 | C4: =(B4*$C$2/B3)-100% | D4: =B4-B3 | E4: =C4*0.8 | F4: =C4*12 | I4: Matthias Reiser | J4: 0.1 | K4: 4.6717 | L4: =K4*$C$3*0.9+K4 | M4: =L4*$C$4*0.9+L4 | N4: =M4*$C$5*0.9+M4 | O4: =N4*$C$6*0.9+N4 | P4: =O4*$C$7*0.9+O4
A5: 45717 | B5: 11.84 | C5: =(B5*$C$2/B4)-100% | D5: =B5-B4 | E5: =C5*0.8 | F5: =C5*12 | I5: Danielle Richetta | J5: 0.1 | K5: 4.8627 | L5: =K5*$C$3*0.9+K5 | M5: =L5*$C$4*0.9+L5 | N5: =M5*$C$5*0.9+M5 | O5: =N5*$C$6*0.9+N5 | P5: =O5*$C$7*0.9+O5
A6: 45747 | B6: 11.95 | C6: =(B6*$C$2/B5)-100% | D6: =B6-B5 | E6: =C6*0.8 | F6: =C6*12 | I6: Total AUM | K6: =SUM(K2:K5) | L6: =SUM(L2:L5) | M6: =SUM(M2:M5) | N6: =SUM(N2:N5) | O6: =SUM(O2:O5) | P6: =SUM(P2:P5)
A7: 45763 | B7: 12.02 | C7: =(B7*$C$2/B6)-100% | D7: =B7-B6 | E7: =C7*0.8 | F7: =C7*12
A8: Closing the fond + transfert the assets in BTC Yield Fund | I8: Indigo | K8: =IFERROR(K2/K$6,"") | L8: =IFERROR(L2/L$6,"") | M8: =IFERROR(M2/M$6,"") | N8: =IFERROR(N2/N$6,"") | O8: =IFERROR(O2/O$6,"") | P8: =IFERROR(P2/P$6,"")
I9: Kyle | K9: =IFERROR(K3/K$6,"") | L9: =IFERROR(L3/L$6,"") | M9: =IFERROR(M3/M$6,"") | N9: =IFERROR(N3/N$6,"") | O9: =IFERROR(O3/O$6,"") | P9: =IFERROR(P3/P$6,"")
A10: Total | B10: 4 Months | C10: =(B7-B2)/B2 | D10: =B7-B2 | E10: =C10*0.8 | F10: =E10/4*12 | I10: Mathias | K10: =IFERROR(K4/K$6,"") | L10: =IFERROR(L4/L$6,"") | M10: =IFERROR(M4/M$6,"") | N10: =IFERROR(N4/N$6,"") | O10: =IFERROR(O4/O$6,"") | P10: =IFERROR(P4/P$6,"")
I11: Danielle Richetta | K11: =IFERROR(K5/K$6,"") | L11: =IFERROR(L5/L$6,"") | M11: =IFERROR(M5/M$6,"") | N11: =IFERROR(N5/N$6,"") | O11: =IFERROR(O5/O$6,"") | P11: =IFERROR(P5/P$6,"")
I12: Total AUM | K12: =SUM(K8:K11) | L12: =SUM(L8:L11) | M12: =SUM(M8:M11) | N12: =SUM(N8:N11) | O12: =SUM(O8:O11) | P12: =SUM(P8:P11)

Sheet DONE - BTC TAC Program
A1: Date | B1: AUM | C1: Gross Performance (%) | D1: Gross Performance (BTC) | E1: Net Performance | F1: Yearly APY | G1: Comments | I1: Investors | J1: Fees | K1: 45748 | L1: 45778 | M1: 45809 | N1: 45839 | O1: 45849
A2: 45748 | B2: 11.4434 | C2: 1 | G2: Création du fond : Invest : Victoria : 0.1492 Nathanaël : 0.4483 Blondish : 4.1210 | I2: Indigo | J2: 0 | K2: 0 | L2: =K2*$C$3*1+K2+(K3*$C$3*$J$3)+(K4*$C$3*$J$4)+(K5*$C$3*$J$5)+(K6*$C$3*$J$6) | M2: =L2*$C$4*1+L2+(L3*$C$4*$J$3)+(L4*$C$4*$J$4)+(L5*$C$4*$J$5)+(L6*$C$4*$J$6) | N2: =M2*$C$5*1+M2+(M3*$C$5*$J$3)+(M4*$C$5*$J$4)+(M5*$C$5*$J$5)+(M6*$C$5*$J$6) | O2: =N2*$C$5*1+N2+(N3*$C$5*$J$3)+(N4*$C$5*$J$4)+(N5*$C$5*$J$5)+(N6*$C$5*$J$6)
A3: 45778 | B3: 11.394 | C3: =(B3*$C$2/B2)-100% | D3: =B3-B2 | E3: =C3*0.8 | F3: =C3*12 | I3: Victoria Pariente-Cohen | J3: 0 | K3: 0.1492 | L3: =K3*$C$3*(1-$J3)+K3 | M3: =L3*$C$4*(1-$J3)+L3 | N3: =M3*$C$5*(1-$J3)+M3 | O3: =N3*$C$6*(1-$J3)+N3
A4: 45807 | B4: 11.3943 | C4: =(B4*$C$2/B3)-100% | D4: =B4-B3 | E4: =C4*0.8 | F4: =C4*12 | I4: Nathanaël Cohen | J4: 0 | K4: 0.4483 | L4: =K4*$C$3*(1-$J4)+K4 | M4: =L4*$C$4*(1-$J4)+L4 | N4: =M4*$C$5*(1-$J4)+M4 | O4: =N4*$C$6*(1-$J4)+N4
A5: 45838 | B5: 11.3943 | C5: =(B5*$C$2/B4)-100% | D5: =B5-B4 | E5: =C5*0.8 | F5: =C5*12 | I5: Thomas Puech | J5: 0 | K5: 6.7249 | L5: =K5*$C$3*(1-$J5)+K5 | M5: =L5*$C$4*(1-$J5)+L5 | N5: =M5*$C$5*(1-$J5)+M5 | O5: =N5*$C$6*(1-$J5)+N5
A6: 45849 | B6: 11.384 | C6: =(B6*$C$2/B5)-100% | D6: =B6-B5 | E6: =C6*0.8 | F6: =C6*12 | G6: End of fund and transfert to BTC Yield Fund | I6: Blondish | J6: 0 | K6: 4.121 | L6: =K6*$C$3*(1-$J6)+K6 | M6: =L6*$C$4*(1-$J6)+L6 | N6: =M6*$C$5*(1-$J6)+M6 | O6: =N6*$C$6*(1-$J6)+N6
A7: Closing the fond + transfert the assets in BTC Yield Fund | I7: Total | K7: =SUM(K2:K6) | L7: =SUM(L2:L6) | M7: =SUM(M2:M6) | N7: =SUM(N2:N6) | O7: =SUM(O2:O6)
A9: Total | B9: 3.5 Months | C9: =(B6-B2)/B2 | D9: =B6-B2 | E9: =C9*0.8 | F9: =E9/3.5*12 | I9: Indigo | K9: =IFERROR(K2/K$7,"") | L9: =IFERROR(L2/L$7,"") | M9: =IFERROR(M2/M$7,"") | N9: =IFERROR(N2/N$7,"") | O9: =IFERROR(O2/O$7,"")
I10: Maman | K10: =IFERROR(K3/K$7,"") | L10: =IFERROR(L3/L$7,"") | M10: =IFERROR(M3/M$7,"") | N10: =IFERROR(N3/N$7,"") | O10: =IFERROR(O3/O$7,"")
I11: Nathanael | K11: =IFERROR(K4/K$7,"") | L11: =IFERROR(L4/L$7,"") | M11: =IFERROR(M4/M$7,"") | N11: =IFERROR(N4/N$7,"") | O11: =IFERROR(O4/O$7,"")
I12: Thomas | K12: =IFERROR(K5/K$7,"") | L12: =IFERROR(L5/L$7,"") | M12: =IFERROR(M5/M$7,"") | N12: =IFERROR(N5/N$7,"") | O12: =IFERROR(O5/O$7,"")
I13: Vivie | K13: =IFERROR(K6/K$7,"") | L13: =IFERROR(L6/L$7,"") | M13: =IFERROR(M6/M$7,"") | N13: =IFERROR(N6/N$7,"") | O13: =IFERROR(O6/O$7,"")
I14: Total AUM | K14: =SUM(K9:K13) | L14: =SUM(L9:L13) | M14: =SUM(M9:M13) | N14: =SUM(N9:N13) | O14: =SUM(O9:O13)

Sheet Done - ETH TAC Program
A1: Date | B1: AUM | C1: Gross Performance (%) | D1: Gross Performance (ETH) | E1: Net Performance | F1: Yearly APY | G1: Comments | I1: Investors | J1: Fees | K1: 45505 | L1: 45536 | M1: 45566 | N1: 45589 | O1: 45597 | P1: 45627 | Q1: 45658 | R1: 45689 | S1: 45717 | T1: 45748 | U1: 45778 | V1: 45809 | W1: 45839 | X1: 45849
A2: 45474 | B2: 61.5 | C2: 1 | G2: Creation du fond | I2: Indigo Fees | J2: 0 | K2: =B2*C3*0.2 | L2: =K2*$C$4*1+K2+(K3*$C$4*0.2) | M2: =L2*$C$5*1+L2+(L3*$C$5*0.2) | N2: =M2*$C$7*1+M2+(M3*$C$7*0.2) | O2: =N2*$C$9*1+N2+(N3*$C$9*0.2) | P2: =O2*$C$10*1+O2+(O3*$C$10*0.2) | Q2: =P2*$C$11*1+P2+(P3*$C$11*0.2) | R2: =Q2*$C$12*1+Q2+(Q3*$C$12*0.2) | S2: =R2*$C$13*1+R2+(R3*$C$13*0.2) | T2: =S2*$C$15*1+S2+(S3*$C$15*0.2) | U2: =T2*$C$17*1+T2+(T3*$C$17*0.2) | V2: =U2*$C$18*1+U2+(U3*$C$18*0.2) | W2: =V2*$C$19*1+V2+(V3*$C$19*0.2) | X2: =W2*$C$20*1+W2
A3: 45505 | B3: 62.27 | C3: =(B3*$C$2/B2)-100% | D3: =B3-B2 | E3: =C3*0.8 | F3: =C3*12 | I3: Jose Molla | J3: 0.2 | K3: =B2*C3*0.8+B2 | L3: =K3*$C$4*0.8+K3 | M3: =L3*$C$5*0.8+L3 | N3: =M3*$C$7*0.8+M3 | O3: =N3*$C$9*0.8+N3 | P3: =O3*$C$10*0.8+O3 | Q3: =P3*$C$11*0.8+P3 | R3: =Q3*$C$12*0.8+Q3 | S3: =R3*$C$13*0.8+R3 | T3: =S3*$C$15*0.8+S3 | U3: =T3*$C$17*0.8+T3 | V3: =U3*$C$18*0.8+U3 | W3: =V3*$C$19*0.8+V3 | X3: =W3*$C$20+W3
A4: 45537 | B4: 62.82 | C4: =(B4*$C$2/B3)-100% | D4: =B4-B3 | E4: =C4*0.8 | F4: =C4*12 | I4: Nathanael Cohen | J4: 0 | K4: 0 | L4: 0 | M4: 17 | N4: =M4*$C$7+M4 | O4: =N4*$C$9+N4 | P4: =O4*$C$10+O4 | Q4: =P4*$C$11+P4 | R4: =Q4*$C$12+Q4 | S4: =R4*$C$13+R4+4.608 | T4: =S4*$C$15+S4+5.226 | U4: =T4*$C$17+T4 | V4: =U4*$C$18+U4 | W4: =V4*$C$19+V4 | X4: =W4*$C$20+W4
A5: 45566 | B5: 63.33 | C5: =(B5/B4)-100% | D5: =B5-B4 | E5: =C5*0.8 | F5: =C5*12 | I5: Blondish | J5: 0 | K5: 0 | L5: 0 | M5: 0 | N5: 120 | O5: =N5*$C$9+N5 | P5: =O5*$C$10+O5 | Q5: =P5*$C$11+P5 | R5: =Q5*$C$12+Q5 | S5: =R5*$C$13+R5 | T5: =S5*$C$15+S5 | U5: =T5*$C$17+T5 | V5: =U5*$C$18+U5 | W5: =V5*$C$19+V5 | X5: =W5*$C$20+W5
A6: 45565 | B6: =17+B5 | C6: 1 | G6: Entrée de Nathanael avec 17 ETH | I6: Total AUM | K6: =SUM(K2:K5) | L6: =SUM(L2:L5) | M6: =SUM(M2:M5) | N6: =SUM(N2:N5) | O6: =SUM(O2:O5) | P6: =SUM(P2:P5) | Q6: =SUM(Q2:Q5) | R6: =SUM(R2:R5) | ... X6: =SUM(X2:X5)
A7: 45589 | B7: 80.72 | C7: =(B7/B6)-100% | D7: =B7-B6 | E7: =C7*0.8 | F7: =C7*12
A8: 45590 | B8: =B7+120 | C8: 1 | G8: Entrée de Blondish avec 120 ETH | I8: Indigo | K8: =IFERROR(K2/K$6,"") | L8: =IFERROR(L2/L$6,"") | M8: =IFERROR(M2/M$6,"") | N8: =IFERROR(N2/N$6,"") | O8: =IFERROR(O2/O$6,"") | P8: =IFERROR(P2/P$6,"") | Q8: =IFERROR(Q2/Q$6,"") | R8: =IFERROR(R2/R$6,"") | ... X8: =IFERROR(X2/X$6,"")
A9: 45597 | B9: 200.72 | C9: =(B9/B8)-100% | D9: =B9-B8 | E9: =C9*0.8 | F9: =C9*12 | I9: Jose | K9: =IFERROR(K3/K$6,"") | L9: =IFERROR(L3/L$6,"") | M9: =IFERROR(M3/M$6,"") | N9: =IFERROR(N3/N$6,"") | O9: =IFERROR(O3/O$6,"") | P9: =IFERROR(P3/P$6,"") | Q9: =IFERROR(Q3/Q$6,"") | R9: =IFERROR(R3/R$6,"") | ... X9: =IFERROR(X3/X$6,"")
A10: 45627 | B10: 200.72 | C10: =(B10/B9)-100% | D10: =B10-B9 | E10: =C10*0.8 | F10: =C10*12 | I10: Nathanael | K10: =IFERROR(K4/K$6,"") | L10: =IFERROR(L4/L$6,"") | M10: =IFERROR(M4/M$6,"") | N10: =IFERROR(N4/N$6,"") | O10: =IFERROR(O4/O$6,"") | P10: =IFERROR(P4/P$6,"") | Q10: =IFERROR(Q4/Q$6,"") | R10: =IFERROR(R4/R$6,"") | ... X10: =IFERROR(X4/X$6,"")
A11: 45658 | B11: 200.72 | C11: =(B11/B10)-100% | D11: =B11-B10 | E11: =C11*0.8 | F11: =C11*12 | I11: Blondish | K11: =IFERROR(K5/K$6,"") | L11: =IFERROR(L5/L$6,"") | M11: =IFERROR(M5/M$6,"") | N11: =IFERROR(N5/N$6,"") | O11: =IFERROR(O5/O$6,"") | P11: =IFERROR(P5/P$6,"") | Q11: =IFERROR(Q5/Q$6,"") | R11: =IFERROR(R5/R$6,"") | ... X11: =IFERROR(X5/X$6,"")
A12: 45689 | B12: 201.847 | C12: =(B12/B11)-100% | D12: =B12-B11 | E12: =C12*0.8 | F12: =C12*12 | I12: Total AUM | K12: =SUM(K8:K11) | L12: =SUM(L8:L11) | M12: =SUM(M8:M11) | N12: =SUM(N8:N11) | O12: =SUM(O8:O11) | P12: =SUM(P8:P11) | Q12: =SUM(Q8:Q11) | R12: =SUM(R8:R11) | ... X12: =SUM(X8:X11)
A13: 45717 | B13: 204.35 | C13: =(B13/B12)-100% | D13: =B13-B12 | E13: =C13*0.8 | F13: =C13*12
A14: 45717 | B14: =B13+4.608 | C14: 1 | G14: Top up de Nathanael avec 4.608 ETH | W14: 8.404 | X14: Refund Tea-Fi hack
A15: 45747 | B15: 209.553 | C15: =(B15/B14)-100% | D15: =B15-B14 | E15: =C15*0.8 | F15: =C15*12
A16: 45748 | B16: =B15+5.226 | C16: 1 | G16: Top up de Nathanael avec 5.226 ETH
A17: 45778 | B17: 217.3475 | C17: =(B17/B16)-100% | D17: =B17-B16 | E17: =C17*0.8 | F17: =C17*12
A18: 45807 | B18: 217.8624 | C18: =(B18/B17)-100% | D18: =B18-B17 | E18: =C18*0.8 | F18: =C18*12
A19: 45838 | B19: 218.3559 | C19: =(B19/B18)-100% | D19: =B19-B18 | E19: =C19*0.8 | F19: =C19*12
A20: 45849 | B20: =209.85+0.14 | C20: =(B20/B19)-100% | D20: =B20-B19 | E20: =C20*0.8 | F20: =C20*12 | G20: End of fund and transfert to ETH Yield Fund
A21: Closing the fond + transfert the assets in ETH Yield Fund
A23: Total | B23: 11.5 Months | C23: =(B20-(B2+17+120+4.608+5.226))/(B2+17+120+4.608+5.226) | D23: =B20-(B2+17+120+4.608+5.226) | E23: =C23*0.8 | F23: =E23/11.5*12
A25: Refund Tea-Fi hack for 8.404 ETH on 03/11/2025
A26: Indigo | B26: 0.0042762316 | C26: =B26*$C$31
A27: Jose | B27: 0.29823391 | C27: =B27*$C$31
A28: Nathanael | B28: 0.12705205 | C28: =B28*$C$31
A29: Blondish | B29: 0.57043781 | C29: =B29*$C$31
A31: Total | B31: =SUM(B26:B29) | C31: 8.404

Sheet Investments
A1: Investment Date | B1: Investor Name | C1: Currency | D1: Amount | E1: Intro Broker Name | F1: IB Percentage | G1: Fee Percentage | H1: Account Type | I1: Transaction Type | J1: Reference ID
A2: 45455 | B2: Jose Molla | C2: BTC | D2: 2.723
A3: 45455 | B3: Jose Molla | C3: ETH TAC | D3: 52.4
A4: 45481 | B4: Jose Molla | C4: BTC | D4: 0.745
A5: 45481 | B5: Jose Molla | C5: ETH TAC | D5: 9.1
A6: 45525 | B6: Kyle Gulamerian | C6: BTC | D6: 0.01
A7: 45525 | B7: Kyle Gulamerian | C7: BTC | D7: 1.99
A8: 45566 | B8: Matthias Reiser | C8: BTC | D8: 4.62
A9: 45566 | B9: Thomas Puech | C9: BTC | D9: 6.5193
A10: 45566 | B10: Danielle Richetta | C10: BTC | D10: 5.2
A11: 45566 | B11: Nathanaël Cohen | C11: ETH TAC | D11: 17
A12: 45589 | B12: Blondish | C12: ETH TAC | D12: 120
A13: 45605 | B13: Danielle Richetta | C13: BTC | D13: -0.27
... A26: 45748 | B26: Thomas Puech | C26: BTC | D26: -6.7249
A27: 45748 | B27: Thomas Puech | C27: BTC TAC | D27: =6.7249
A28: 45763 | B28: Kyle Gulamerian | C28: BTC | D28: 2.101
A29: 45763 | B29: Matthias Reiser | C29: BTC | D29: 4.8357
A30: 45763 | B30: Danielle Richetta | C30: BTC | D30: 5.0335
A31: 45763 | B31: Kyle Gulamerian | C31: BTC Boost | D31: -2.101
A32: 45763 | B32: Matthias Reiser | C32: BTC Boost | D32: -4.8357
A33: 45763 | B33: Danielle Richetta | C33: BTC Boost | D33: -5.0335
A34: 45763 | B34: INDIGO Fees | C34: BTC | D34: 0.0498
A35: 45763 | B35: INDIGO Fees | C35: BTC Boost | D35: -0.0498
A36: 45790 | B36: Kyle Gulamerian | C36: BTC | D36: =-0.1078-2.0023
A37: 45803 | B37: Babak Eftekhari | C37: ETH | D37: 27.01
A38: 45803 | B38: INDIGO DIGITAL ASSET FUND LP | C38: ETH | D38: 175
A39: 45809 | B39: Nathanaël Cohen | C39: ETH | D39: 3.0466
A40: 45807 | B40: Babak Eftekhari | C40: ETH | D40: 32.25
A41: 45809 | B41: danielle Richetta | C41: BTC | D41: -0.13
A42: 45819 | B42: Kabbaj | C42: BTC | D42: 2 | E42: Hicham.kabbaj@sgtm-maroc.com
A43: 45824 | B43: Babak Eftekhari | C43: USDT | D43: =134026.75+1700
A44: 45839 | B44: Nathanaël Cohen | C44: ETH | D44: 2
A45: 45849 | B45: Jose Molla | C45: ETH TAC | D45: -62.6261
A46: 45849 | B46: Nathanaël Cohen | C46: ETH TAC | D46: -26.6797
A47: 45849 | B47: Blondish | C47: ETH TAC | D47: -119.7862
A48: 45849 | B48: Indigo Fees | C48: ETH TAC | D48: -0.898
A49: 45849 | B49: Jose Molla | C49: ETH | D49: 62.6261
A50: 45849 | B50: Nathanaël Cohen | C50: ETH | D50: 26.6797
A51: 45849 | B51: Blondish | C51: ETH | D51: 119.7862
A52: 45849 | B52: Indigo Fees | C52: ETH | D52: 0.898
A53: 45849 | B53: Kabbaj | C53: BTC | D53: 0.9914
A54: 45849 | B54: Victoria Pariente-Cohen | C54: BTC | D54: 0.1484
A55: 45849 | B55: Nathanaël Cohen | C55: BTC | D55: 0.446
... A82: 45894 | B82: Kabbaj | C82: BTC | D82: 0.9102
A83: 45902 | B83: INDIGO DIGITAL ASSET FUND LP | C83: SOL | D83: 1250 | F83: 0 | G83: 0 | H83: investor | I83: DEPOSIT | J83: sol-indigo-digital-asset-fund-lp-45902.0-83
A84: 45904 | B84: Paul Johnson | C84: SOL | D84: 234.17 | E84: Alex Jacobs | F84: 0.04 | G84: 0.16 | H84: investor | I84: DEPOSIT | J84: sol-paul-johnson-45904.0-84
A85: 45904 | B85: Paul Johnson | C85: ETH | D85: 10.44
A86: 45910 | B86: Paul Johnson | C86: ETH | D86: 4.6327
A87: 45912 | B87: Paul Johnson | C87: ETH | D87: 8.96
A88: 45912 | B88: Nathanaël Cohen | C88: ETH | D88: 3.35
A89: 45924 | B89: Babak Eftekhari | C89: USDT | D89: 10000
A90: 45927 | B90: Tomer Zur | C90: ETH | D90: 63.1
A91: 45933 | B91: Paul Johnson | C91: BTC | D91: 0.4395
A92: 45933 | B92: Paul Johnson | C92: SOL | D92: -236.02 | E92: Alex Jacobs | F92: 0.04 | G92: 0.16 | H92: investor | I92: WITHDRAWAL | J92: sol-paul-johnson-45933.0-92
A93: 45933 | B93: Paul Johnson | C93: ETH | D93: -12
A94: 45936 | B94: INDIGO Ventures | C94: USDT | D94: -100000
A95: 45936 | B95: Sacha Oshry | C95: USDT | D95: 100000
A96: 45938 | B96: Tomer Zur | C96: ETH | D96: 10.051
A97: 45939 | B97: Babak Eftekhari | C97: USDT | D97: 20000
A98: 45943 | B98: INDIGO Ventures | C98: USDT | D98: =-32594.55+5000
A99: 45944 | B99: Tomer Zur | C99: ETH | D99: 64.27
A100: 45944 | B100: Babak Eftekhari | C100: ETH | D100: 3.75
A101: 45945 | B101: HALLEY86 | C101: USDT | D101: 99990
A102: 45947 | B102: Babak Eftekhari | C102: ETH | D102: 3.1
A103: 45950 | B103: Tomer Zur | C103: ETH | D103: 6.5417
A104: 45953 | B104: Jose Molla | C104: ETH | D104: 1.2
A105: 45953 | B105: Tomer Zur | C105: ETH | D105: 6.4
A106: 45953 | B106: Jose Molla | C106: SOL | D106: 87.98
A107: 45953 | B107: Jose Molla | C107: BTC | D107: 0.062
A108: 45953 | B108: Jose Molla | C108: USDT | D108: 97695
A109: 45953 | B109: Babak Eftekhari | C109: USDT | D109: 10450
A110: 45964 | B110: Indigo Fees | C110: ETH | D110: 0.03593745
... A128: 45978 | B128: Sam Johnson | C128: SOL | D128: 1800.05
A129: 45978 | B129: Sam Johnson | C129: XRP | D129: 135003 | E129: Ryan Van Der Wall | F129: 0.04 | G129: 0.16 | H129: investor | I129: DEPOSIT | J129: xrp-sam-45978.0-129
A130: 45978 | B130: Tomer Zur | C130: ETH | D130: 6.234
A131: 45982 | B131: Jose Molla | C131: USDT | D131: -47908
A132: 45986 | B132: Sam Johnson | C132: BTC | D132: 1
A133: 45986 | B133: Sam Johnson | C133: XRP | D133: 49000 | E133: Ryan Van Der Wall | F133: 0.04 | G133: 0.16 | H133: investor | I133: DEPOSIT | J133: xrp-sam-45986.0-133
A134: 45986 | B134: Sam Johnson | C134: SOL | D134: 750
A135: 45986 | B135: Sam Johnson | C135: ETH | D135: 35
A136: 45986 | B136: Jose Molla | C136: BTC | D136: 0.548
A137: 45986 | B137: Valeria Cruz | C137: USDT | D137: 50000
A138: 45987 | B138: Matthew Beatty | C138: USDT | D138: 18000
A139: 45987 | B139: Nath & Thomas | C139: USDT | D139: -87937
A140: 45988 | B140: Ventures Life Style | C140: USDT | D140: 100000
A141: 45988 | B141: Nath & Thomas | C141: BTC | D141: 1
A142: 45988 | B142: Vivie & Liana | C142: BTC | D142: 3.411
A143: 45991 | B143: Sam Johnson | C143: BTC | D143: 1.2
A144: 45991 | B144: Sam Johnson | C144: XRP | D144: 45000 | E144: Ryan Van Der Wall | F144: 0.04 | G144: 0.16 | H144: investor | I144: DEPOSIT | J144: xrp-sam-45991.0-144
A145: 45991 | B145: Sam Johnson | C145: SOL | D145: 750
A146: 45991 | B146: Sam Johnson | C146: ETH | D146: 33
A147: 45993 | B147: Tomer Zur | C147: ETH | D147: 9.143
A148: 45995 | B148: INDIGO DIGITAL ASSET FUND LP | C148: SOL | D148: -1285.66 | F148: 0 | G148: 0 | H148: investor | I148: WITHDRAWAL | J148: sol-indigo-digital-asset-fund-lp-45995.0-148
A149: 45995 | B149: Brandon Hood | C149: ETH | D149: 31.37
A150: 45999 | B150: Nath & Thomas | C150: USDT | D150: -213501.6
A151: 45999 | B151: Thomas Puech | C151: USDT | D151: =D150/-2-60000
A152: 45999 | B152: Sam Johnson | C152: XRP | D152: 49500 | E152: Ryan Van Der Wall | F152: 0.04 | G152: 0.16 | H152: investor | I152: DEPOSIT | J152: xrp-sam-45999.0-152
A153: 45999 | B153: Sam Johnson | C153: SOL | D153: 770
A154: 45999 | B154: Sam Johnson | C154: ETH | D154: 34
A155: 45999 | B155: Sam Johnson | C155: BTC | D155: 1.1
...

Sheet BTC Yield Fund
A1: AUM Before | D1: 0 | E1: 3.49 | F1: 3.5 | G1: 5.51 | H1: 5.54 | I1: 21.99 | J1: =22.02 | K1: 21.84 | L1: 21.88 | M1: =L3 | N1: 10.24 | O1: 10.3 | P1: 10.34 | Q1: 10.38 | R1: 3.68 | S1: 15.76 | T1: 15.78 | U1: =13.69+0.044 | V1: 13.6446 | W1: 15.6577 | X1: 15.7177 | Y1: 28.1007 | Z1: 30.2177 | AA1: 29.9777 | AB1: 30.66 | AC1: 30.565 | AD1: 31.49 | AE1: 31.6 | AF1: 31.62 | AG1: 32.14 | AH1: 32.21 | AI1: 32.23 | AJ1: 31.55 | AK1: 32.06 | AL1: 35.36 | AM1: 36.92 | AN1: 41.331 | AO1: 42.58 | AP1: 43.73 | AQ1: 44.4 | AR1: 45.58 | AS1: 40.5905 | AT1: 40.5905 | AU1: 32.82 | AV1: 31.61 | AW1: 32.36 | AX1: 36.24 | AY1: 32.25 | AZ1: 32.4 | BA1: 32.4 | BB1: 33.07 | BC1: 33.25 | BD1: 42.016 | BE1: 38.39 | BF1: 38.541
A2: Top Up / Withdrawals | D2: =SUMIFS(Investments!$D:$D,Investments!$C:$C,"BTC",Investments!$A:$A,D$8) | E2: =SUMIFS(Investments!$D:$D,Investments!$C:$C,"BTC",Investments!$A:$A,E$8) | F2: =SUMIFS(Investments!$D:$D,Investments!$C:$C,"BTC",Investments!$A:$A,F$8) | G2: =SUMIFS(Investments!$D:$D,Investments!$C:$C,"BTC",Investments!$A:$A,G$8) | H2: =SUMIFS(Investments!$D:$D,Investments!$C:$C,"BTC",Investments!$A:$A,H$8) | I2: =SUMIFS(Investments!$D:$D,Investments!$C:$C,"BTC",Investments!$A:$A,I$8) | J2: =SUMIFS(Investments!$D:$D,Investments!$C:$C,"BTC",Investments!$A:$A,J$8) | K2: =SUMIFS(Investments!$D:$D,Investments!$C:$C,"BTC",Investments!$A:$A,K$8) | ... BF2: =SUMIFS(Investments!$D:$D,Investments!$C:$C,"BTC",Investments!$A:$A,BF$8)
A3: AUM After | D3: 3.468 | E3: 3.49 | F3: =3.5+2 | G3: =G1 | H3: =H1+4.62+6.5193+5.2 | I3: =I1 | J3: =J1-0.27 | K3: =K1 | L3: =21.88-0.124 | M3: =21.88-0.124-11.5681 | N3: =N1 | O3: =O1 | P3: =P1 | Q3: =Q1-6.7249 | R3: =R1+12.02 | S3: =S1 | T3: =T1+T2 | U3: =U1-0.13 | V3: =V1+2 | W3: =W1 | X3: =X1+11.384+0.9914 | Y3: =Y1+2.115364 | Z3: =Z1-0.26 | AA3: =AA1+0.6 | AB3: =AB1-0.11 | AC3: =AC1+0.9102 | AD3: =AD1 | AE3: =AE1 | AF3: =AF1+0.4395 | AG3: =AG1+0.062 | AH3: =AH1 | AI3: =AI1-0.283-0.4408 | AJ3: =AJ1+0.4867 | AK3: =AK1+3.3 | AL3: =AL1+1+0.548 | AM3: =AM1+1+3.411 | AN3: =AN1+1.2 | AO3: =AO1+1.1 | AP3: =AP1+0.657 | AQ3: =AQ1+1.17 | AR3: =AR1-4.9895 | AS3: =AS1 | AT3: =AS1-7.7852 | AU3: =AU1-3.4221+2.1577 | AV3: =AV1+0.622+0.1135766 | AW3: =AW1+3.9998-0.12 | AX3: =AX1-3.99 | AY3: =AY1+0.14207 | AZ3: =AZ1 | BA3: =BA1+0.60672 | BB3: =BB1+BB2 | BC3: =BC1+BC2 | BD3: =BD1+BD2 | BE3: =BE1+BE2 | BF3: =BF1+BF2
A4: Gross Performance | E4: =(E3-D3)/D3 | F4: =(F1-E3)/E3 | G4: =(G1-F3)/F3 | H4: =(H1/G1)-100% | I4: =(I1/H3)-100% | J4: =(J1/I1)-100% | K4: =(K1/J3)-100% | L4: =(L1/K1)-100% | N4: =(N1/M3)-100% | O4: =(O1/N1)-100% | P4: =(P1/O1)-100% | Q4: =(Q1/P1)-100% | R4: =(R1-Q3)/Q3 | S4: =(S1/R3)-100% | T4: =(T1/S1)-100% | U4: =(U1-T3)/T3 | V4: =(V1/U3)-100% | W4: =(W1/V3)-100% | X4: =(X1/W1)-100% | Y4: =(Y1/X3)-100% | Z4: =(Z1/Y3)-100% | AA4: =(AA1/Z3)-100% | AB4: =(AB1/AA3)-100% | AC4: =(AC1/AB3)-100% | AD4: =(AD1/AC3)-100% | AE4: =(AE1/AD1)-100% | AF4: =(AF1/AE1)-100% | AG4: =(AG1/AF3)-100% | AH4: =(AH1/AG3)-100% | AI4: =(AI1/AH1)-100% | AJ4: =(AJ1/AI3)-100% | AK4: =(AK1/AJ3)-100% | AL4: =(AL1/AK3)-100% | AM4: =(AM1/AL3)-100% | AN4: =(AN1/AM3)-100% | AO4: =(AO1/AN3)-100% | AP4: =(AP1/AO3)-100% | AQ4: =(AQ1/AP3)-100% | ... AS4: =(AS1/AR3)-100% | AT4: =(AT1/AS1)-100% | AU4: =(AU1/AT3)-100% | AV4: =(AV1/AU3)-100% | AW4: =(AW1/AV3)-100% | AX4: =(AX1/AW3)-100% | AY4: =(AY1/AX3)-100% | AZ4: =(AZ1/AY3)-100% | BA4: =(BA1/AZ1)-100% | BB4: =(BB1-BA3)/BA3 | BC4: =(BC1-BB3)/BB3 | BD4: =(BD1-BC3)/BC3 | BE4: =(BE1-BD3)/BD3 | BF4: =(BF1-BE3)/BE3
A5: Net Performance | E5: =E4*0.8 | F5: =F4*0.8 | G5: =G4*0.8 | H5: =H4*0.8 | I5: =I4*0.8 | J5: =J4*0.8 | K5: =K4*0.8 | L5: =L4*0.8 | N5: =N4*0.8 | O5: =O4*0.8 | P5: =P4*0.8 | Q5: =Q4*0.8 | R5: =R4*0.8 | S5: =S4*0.8 | T5: =T4*0.8 | U5: =U4*0.8 | ... BF5: =BF4*0.8
A6: Yearly APY | E6: =E4*12 | F6: =F4*12 | G6: =G4*12 | H6: =H4*12 | I6: =I4*12 | J6: =J4*12 | K6: =K4*12 | L6: =L4*12 | N6: =N4*12 | O6: =O4*12 | P6: =P4*12 | Q6: =Q4*12 | R6: =R4*12 | S6: =S4*12 | T6: =T4*12 | U6: =U4*12 | ... BF6: =BF4*12
A7: Comments | F7: Invest of Kyle with 2 BTC | H7: Invest of Mathias / Thomas / Daniel with 16.3393 BTC | J7: Withdraw 0.27 from Danielle | L7: Withdraw 0.124 from Danielle | M7: Kyle / Mathias / Danielle go to Boosted Program with 11.5681 BTC | Q7: Thomas go to TAC Program with 6.7249 BTC | R7: Transfert of 12.02 BTC from boosted program for Kyle Gulamerian / Matthias Reiser / Danielle Richetta | T7: Withdraw 0.1078 BTC from Kyle Withdraw 2.0023 BTC from Kyle (all his account) | U7: +0.044 BTC for Gas Fees that has been forgoten Withdraw 0.13 from Danielle Richetta | V7: Kabbaj deposit 2 BTC | X7: Top Up from Kabbaj : 0.9914 BTC Transfert from TAC Program Victoria :0.1484 BTC Nathanael Cohen : 0.4460 BTC Thomas Puech : 6.69 BTC Blondish : 4.0996 BTC | Y7: oliver loisel : 2.115364 BTC | Z7: Withdrawal Danielle Richetta - 0.26 BTC | AA7: Kabbaj : 0.6 BTC | AB7: Withdrawal Danielle Richetta - 0.11 BTC | AC7: Top Up Kabbaj : 0.9102 BTC | AF7: Top Up Paul Johnson: 0.4395 BTC | AG7: Jose Molla BTC 0.062 | AI7: Withdrawal Danielle Richetta - 0.283 BTC Paul Johnson -0.4408 (OUT) | AJ7: Jose Molla BTC 0.4867 | AK7: Sam Johnson BTC 3.30 | AL7: Sam Johnson BTC 1 Jose Molla BTC 0.548 | AM7: Nath & Thomas BTC 1.00 Vivie & Liana BTC 3.411 | AN7: Sam Johnson BTC 1.2 | AO7: Sam Johnson BTC 1.1 | AP7: Thomas Puech : 0.657 BTC | AQ7: Sam Johnson BTC 1.17 | AR7: Matthias Reiser out | AT7: Sam Johnson BTC -7.7852 | AU7: Vivie & Liana - Out -3.4221 Kabbaj BTC 2.1577 | AV7: Nick Smits van Oyen BTC 0.622 Thomas Puech BTC 0.1135766 | AW7: Kyle Gulamerian BTC 3.9998 Danielle Richetta BTC -0.12 | AX7: Kyle Gulamerian BTC -3.99 | AY7: Thomas Puech BTC 0.14207 | BA7: Thomas Puech BTC 0.60672 | BB7: NSVO Holdings BTC 0.1773 | BC7: Jose Molla BTC 2.766 ALOK PAVAN BATRA BTC 6.00 | BD7: Thomas Puech BTC 0.656 Danielle Richetta BTC -4.30 | BE7: Thomas Puech BTC 0.15103283 | BF7: Thomas Puech BTC 0.15103284
A8: Investors | B8: Fees | C8: IB | D8: 45474 | E8: 45505 | F8: 45525 | G8: 45536 | H8: 45566 | I8: 45597 | J8: 45605 | K8: 45627 | L8: 45640 | M8: 45641 | N8: 45658 | O8: 45689 | P8: 45717 | Q8: 45748 | R8: 45763 | S8: 45778 | T8: 45790 | U8: 45809 | V8: 45819 | W8: 45839 | X8: 45849 | Y8: 45862 | Z8: 45863 | AA8: 45869 | AB8: 45889 | AC8: 45894 | AD8: 45901 | AE8: 45930 | AF8: 45933 | AG8: 45953 | AH8: 45961 | AI8: 45966 | AJ8: 45969 | AK8: 45978 | AL8: 45986 | AM8: 45988 | AN8: 45991 | AO8: 45999 | AP8: 46000 | AQ8: 46006 | AR8: 46014 | AS8: 46023 | AT8: 46024 | AU8: 46027 | AV8: 46035 | AW8: 46041 | AX8: 46045 | AY8: 46052 | AZ8: 46054 | BA8: 46056 | BB8: 46059 | BC8: 46065 | BD8: 46066 | BE8: 46077 | BF8: 46081
A9: Indigo Fees | B9: 0 | E9: =D3*E4*$B$10 | F9: =E9*$F$4*1+E9+(E10*$F$4*$B$10) | G9: =F9*$G$4*1+F9+(F10*$G$4*$B$10)+(F11*$G$4*$B$11) | H9: =G9*$H$4*1+G9+(G10*$H$4*$B$10)+(G11*$H$4*$B$11) | I9: =H9*$I$4*1+H9+(H10*$I$4*$B$10)+(H11*$I$4*$B$11)+(H12*$I$4*$B$12)+(H14*$I$4*$B$14) | J9: =I9*$J$4*1+I9+(I10*$J$4*$B$10)+(I11*$J$4*$B$11)+(I12*$J$4*$B$12)+(I14*$J$4*$B$14) | K9: =J9*$K$4*1+J9+(J10*$K$4*$B$10)+(J11*$K$4*$B$11)+(J12*$K$4*$B$12)+(J14*$K$4*$B$14) | L9: =K9*$L$4*1+K9+(K10*$L$4*$B$10)+(K11*$L$4*$B$11)+(K12*$L$4*$B$12)+(K14*$L$4*$B$14) | M9: =L9+L11+L12+L14-2.0336-4.6717-4.8627 | N9: =M9*$N$4*1+M9+(M10*$N$4*$B$10)+(M11*$N$4*$B$11)+(M12*$N$4*$B$12)+(M14*$N$4*$B$14) | O9: =N9*$O$4*1+N9+(N10*$O$4*$B$10)+(N11*$O$4*$B$11)+(N12*$O$4*$B$12)+(N14*$O$4*$B$14) | P9: =O9*$P$4*1+O9+(O10*$P$4*$B$10)+(O11*$P$4*$B$11)+(O12*$P$4*$B$12)+(O14*$P$4*$B$14) | Q9: =P9*$Q$4*1+P9+(P10*$Q$4*$B$10)+(P11*$Q$4*$B$11)+(P12*$Q$4*$B$12)+(P14*$Q$4*$B$14)+(P13*$Q$4*(1-$B13)+P13)-6.7249 | R9: =Q9*$R$4*1+Q9+(Q10*$R$4*$B$10)+(Q11*$R$4*$B$11)+(Q12*$R$4*$B$12)+(Q14*$R$4*$B$14)+0.0498 | S9: =R9*$S$4*1+R9+(R10*$S$4*$B$10)+(R11*$S$4*$B$11)+(R12*$S$4*$B$12)+(R14*$S$4*$B$14) | T9: =S9*$T$4*1+S9+(S10*$T$4*$B$10)+(S11*$T$4*$B$11)+(S12*$T$4*$B$12)+(S14*$T$4*$B$14)+(S11*$T$4*(1-$B11)+S11)-0.1078-2.0023 | U9: =T9*$U$4*1+T9+(T10*$U$4*$B$10)+(T11*$U$4*$B$11)+(T12*$U$4*$B$12)+(T14*$U$4*$B$14) | V9: =U9*$V$4*1+U9+(U10*$V$4*$B$10)+(U11*$V$4*$B$11)+(U12*$V$4*$B$12)+(U14*$V$4*$B$14) | W9: =V9*$W$4*1+V9+(V10*$W$4*$B$10)+(V11*$W$4*$B$11)+(V12*$W$4*$B$12)+(V14*$W$4*$B$14)+(V15*$W$4*$B$15) | X9: =W9*$X$4*1+W9+(W10*$X$4*$B$10)+(W11*$X$4*$B$11)+(W12*$X$4*$B$12)+(W14*$X$4*$B$14)+(W15*$X$4*$B$15) | Y9: =X9*$Y$4*1+X9+(X10*$Y$4*$B$10)+(X11*$Y$4*$B$11)+(X12*$Y$4*$B$12)+(X13*$Y$4*$B$13)+(X14*$Y$4*$B$14)+(X15*$Y$4*$B$15)+(X16*$Y$4*$B$16)+(X17*$Y$4*$B$17)+(X18*$Y$4*$B$18)+(X19*$Y$4*$B$19) | Z9: =Y9*$Z$4*1+Y9+(Y10*$Z$4*$B$10)+(Y11*$Z$4*$B$11)+(Y12*$Z$4*$B$12)+(Y13*$Z$4*$B$13)+(Y14*$Z$4*$B$14)+(Y15*$Z$4*$B$15)+(Y16*$Z$4*$B$16)+(Y17*$Z$4*$B$17)+(Y18*$Z$4*$B$18)+(Y19*$Z$4*$B$19) | AA9: =Z9*$AA$4*1+Z9+(Z10*$AA$4*$B$10)+(Z11*$AA$4*$B$11)+(Z12*$AA$4*$B$12)+(Z13*$AA$4*$B$13)+(Z14*$AA$4*$B$14)+(Z15*$AA$4*$B$15)+(Z16*$AA$4*$B$16)+(Z17*$AA$4*$B$17)+(Z18*$AA$4*$B$18)+(Z19*$AA$4*$B$19) | AB9: =AA9*$AB$4*1+AA9+(AA10*$AB$4*$B$10)+(AA11*$AB$4*$B$11)+(AA12*$AB$4*$B$12)+(AA13*$AB$4*$B$13)+(AA14*$AB$4*$B$14)+(AA15*$AB$4*$B$15)+(AA16*$AB$4*$B$16)+(AA17*$AB$4*$B$17)+(AA18*$AB$4*$B$18)+(AA19*$AB$4*$B$19) | AC9: =AB9*$AC$4*1+AB9+(AB10*$AC$4*$B$10)+(AB11*$AC$4*$B$11)+(AB12*$AC$4*$B$12)+(AB13*$AC$4*$B$13)+(AB14*$AC$4*$B$14)+(AB15*$AC$4*$B$15)+(AB16*$AC$4*$B$16)+(AB17*$AC$4*$B$17)+(AB18*$AC$4*$B$18)+(AB19*$AC$4*$B$19) | AD9: =AC9*$AD$4*1+AC9+(AC10*$AD$4*$B$10)+(AC11*$AD$4*$B$11)+(AC12*$AD$4*$B$12)+(AC13*$AD$4*$B$13)+(AC14*$AD$4*$B$14)+(AC15*$AD$4*$B$15)+(AC16*$AD$4*$B$16)+(AC17*$AD$4*$B$17)+(AC18*$AD$4*$B$18)+(AC19*$AD$4*$B$19) | AE9: =AD9*$AE$4*1+AD9+(AD10*$AE$4*$B$10)+(AD11*$AE$4*$B$11)+(AD12*$AE$4*$B$12)+(AD13*$AE$4*$B$13)+(AD14*$AE$4*$B$14)+(AD15*$AE$4*$B$15)+(AD16*$AE$4*$B$16)+(AD17*$AE$4*$B$17)+(AD18*$AE$4*$B$18)+(AD19*$AE$4*$B$19) | AF9: =AE9*$AF$4*1+AE9+(AE10*$AF$4*$B$10)+(AE11*$AF$4*$B$11)+(AE12*$AF$4*$B$12)+(AE13*$AF$4*$B$13)+(AE14*$AF$4*$B$14)+(AE15*$AF$4*$B$15)+(AE16*$AF$4*$B$16)+(AE17*$AF$4*$B$17)+(AE18*$AF$4*$B$18)+(AE19*$AF$4*$B$19)+(AE20*$AF$4*$B$20)+(AE21*$AF$4*$B$21) | AG9: =AF9*$AG$4*1+AF9+(AF10*$AG$4*$B$10)+(AF11*$AG$4*$B$11)+(AF12*$AG$4*$B$12)+(AF13*$AG$4*$B$13)+(AF14*$AG$4*$B$14)+(AF15*$AG$4*$B$15)+(AF16*$AG$4*$B$16)+(AF17*$AG$4*$B$17)+(AF18*$AG$4*$B$18)+(AF19*$AG$4*$B$19)+(AF20*$AG$4*$B$20)+(AF21*$AG$4*$B$21) | AH9: =AG9*$AH$4*1+AG9+(AG10*$AH$4*$B$10)+(AG11*$AH$4*$B$11)+(AG12*$AH$4*$B$12)+(AG13*$AH$4*$B$13)+(AG14*$AH$4*$B$14)+(AG15*$AH$4*$B$15)+(AG16*$AH$4*$B$16)+(AG17*$AH$4*$B$17)+(AG18*$AH$4*$B$18)+(AG19*$AH$4*$B$19)+(AG20*$AH$4*$B$20)+(AG21*$AH$4*$B$21) | AI9: =AH9*$AI$4*1+AH9+(AH10*$AI$4*$B$10)+(AH11*$AI$4*$B$11)+(AH12*$AI$4*$B$12)+(AH13*$AI$4*$B$13)+(AH14*$AI$4*$B$14)+(AH15*$AI$4*$B$15)+(AH16*$AI$4*$B$16)+(AH17*$AI$4*$B$17)+(AH18*$AI$4*$B$18)+(AH19*$AI$4*$B$19)+(AH20*$AI$4*$B$20)+(AH21*$AI$4*$B$21)+(AH20*$AI$4*(1-$B20-$C20)+AH20)-0.4408 | AJ9: =AI9*$AJ$4*1+AI9+(AI10*$AJ$4*$B$10)+(AI11*$AJ$4*$B$11)+(AI12*$AJ$4*$B$12)+(AI13*$AJ$4*$B$13)+(AI14*$AJ$4*$B$14)+(AI15*$AJ$4*$B$15)+(AI16*$AJ$4*$B$16)+(AI17*$AJ$4*$B$17)+(AI18*$AJ$4*$B$18)+(AI19*$AJ$4*$B$19)+(AI20*$AJ$4*$B$20)+(AI21*$AJ$4*$B$21)+(AI22*$AJ$4*$B$22) | AK9: =AJ9*$AK$4*1+AJ9+(AJ10*$AK$4*$B$10)+(AJ11*$AK$4*$B$11)+(AJ12*$AK$4*$B$12)+(AJ13*$AK$4*$B$13)+(AJ14*$AK$4*$B$14)+(AJ15*$AK$4*$B$15)+(AJ16*$AK$4*$B$16)+(AJ17*$AK$4*$B$17)+(AJ18*$AK$4*$B$18)+(AJ19*$AK$4*$B$19)+(AJ20*$AK$4*$B$20)+(AJ21*$AK$4*$B$21)+(AJ22*$AK$4*$B$22) | AL9: =AK9*$AL$4*1+AK9+(AK10*$AL$4*$B$10)+(AK11*$AL$4*$B$11)+(AK12*$AL$4*$B$12)+(AK13*$AL$4*$B$13)+(AK14*$AL$4*$B$14)+(AK15*$AL$4*$B$15)+(AK16*$AL$4*$B$16)+(AK17*$AL$4*$B$17)+(AK18*$AL$4*$B$18)+(AK19*$AL$4*$B$19)+(AK20*$AL$4*$B$20)+(AK21*$AL$4*$B$21)+(AK22*$AL$4*$B$22)+(AK23*$AL$4*$B$23) | AM9: =AL9*$AM$4*1+AL9+(AL10*$AM$4*$B$10)+(AL11*$AM$4*$B$11)+(AL12*$AM$4*$B$12)+(AL13*$AM$4*$B$13)+(AL14*$AM$4*$B$14)+(AL15*$AM$4*$B$15)+(AL16*$AM$4*$B$16)+(AL17*$AM$4*$B$17)+(AL18*$AM$4*$B$18)+(AL19*$AM$4*$B$19)+(AL20*$AM$4*$B$20)+(AL21*$AM$4*$B$21)+(AL22*$AM$4*$B$22)+(AL23*$AM$4*$B$23)+(AL24*$AM$4*$B$24)+(AL25*$AM$4*$B$25) | AN9: =AM9*$AN$4*1+AM9+(AM10*$AN$4*$B$10)+(AM11*$AN$4*$B$11)+(AM12*$AN$4*$B$12)+(AM13*$AN$4*$B$13)+(AM14*$AN$4*$B$14)+(AM15*$AN$4*$B$15)+(AM16*$AN$4*$B$16)+(AM17*$AN$4*$B$17)+(AM18*$AN$4*$B$18)+(AM19*$AN$4*$B$19)+(AM20*$AN$4*$B$20)+(AM21*$AN$4*$B$21)+(AM22*$AN$4*$B$22)+(AM23*$AN$4*$B$23)+(AM24*$AN$4*$B$24)+(AM25*$AN$4*$B$25) | AO9: =AN9*$AO$4*1+AN9+(AN10*$AO$4*$B$10)+(AN11*$AO$4*$B$11)+(AN12*$AO$4*$B$12)+(AN13*$AO$4*$B$13)+(AN14*$AO$4*$B$14)+(AN15*$AO$4*$B$15)+(AN16*$AO$4*$B$16)+(AN17*$AO$4*$B$17)+(AN18*$AO$4*$B$18)+(AN19*$AO$4*$B$19)+(AN20*$AO$4*$B$20)+(AN21*$AO$4*$B$21)+(AN22*$AO$4*$B$22)+(AN23*$AO$4*$B$23)+(AN24*$AO$4*$B$24)+(AN25*$AO$4*$B$25) | AP9: =AO9*$AP$4*1+AO9+(AO10*$AP$4*$B$10)+(AO11*$AP$4*$B$11)+(AO12*$AP$4*$B$12)+(AO13*$AP$4*$B$13)+(AO14*$AP$4*$B$14)+(AO15*$AP$4*$B$15)+(AO16*$AP$4*$B$16)+(AO17*$AP$4*$B$17)+(AO18*$AP$4*$B$18)+(AO19*$AP$4*$B$19)+(AO20*$AP$4*$B$20)+(AO21*$AP$4*$B$21)+(AO22*$AP$4*$B$22)+(AO23*$AP$4*$B$23)+(AO24*$AP$4*$B$24)+(AO25*$AP$4*$B$25) | AQ9: =AP9*$AQ$4*1+AP9+(AP10*$AQ$4*$B$10)+(AP11*$AQ$4*$B$11)+(AP12*$AQ$4*$B$12)+(AP13*$AQ$4*$B$13)+(AP14*$AQ$4*$B$14)+(AP15*$AQ$4*$B$15)+(AP16*$AQ$4*$B$16)+(AP17*$AQ$4*$B$17)+(AP18*$AQ$4*$B$18)+(AP19*$AQ$4*$B$19)+(AP20*$AQ$4*$B$20)+(AP21*$AQ$4*$B$21)+(AP22*$AQ$4*$B$22)+(AP23*$AQ$4*$B$23)+(AP24*$AQ$4*$B$24)+(AP25*$AQ$4*$B$25) | AR9: =AQ9*$AR$4*1+AQ9+(AQ10*$AR$4*$B$10)+(AQ11*$AR$4*$B$11)+(AQ12*$AR$4*$B$12)+(AQ13*$AR$4*$B$13)+(AQ14*$AR$4*$B$14)+(AQ15*$AR$4*$B$15)+(AQ16*$AR$4*$B$16)+(AQ17*$AR$4*$B$17)+(AQ18*$AR$4*$B$18)+(AQ19*$AR$4*$B$19)+(AQ20*$AR$4*$B$20)+(AQ21*$AR$4*$B$21)+(AQ22*$AR$4*$B$22)+(AQ23*$AR$4*$B$23)+(AQ24*$AR$4*$B$24)+(AQ25*$AR$4*$B$25)+(AQ12*$AR$4*(1-$B12)+AQ12-4.9895) | AS9: =AR9*$AS$4*1+AR9+(AR10*$AS$4*$B$10)+(AR11*$AS$4*$B$11)+(AR12*$AS$4*$B$12)+(AR13*$AS$4*$B$13)+(AR14*$AS$4*$B$14)+(AR15*$AS$4*$B$15)+(AR16*$AS$4*$B$16)+(AR17*$AS$4*$B$17)+(AR18*$AS$4*$B$18)+(AR19*$AS$4*$B$19)+(AR20*$AS$4*$B$20)+(AR21*$AS$4*$B$21)+(AR22*$AS$4*$B$22)+(AR23*$AS$4*$B$23)+(AR24*$AS$4*$B$24)+(AR25*$AS$4*$B$25) | AT9: =AS9*$AT$4*1+AS9+(AS10*$AT$4*$B$10)+(AS11*$AT$4*$B$11)+(AS12*$AT$4*$B$12)+(AS13*$AT$4*$B$13)+(AS14*$AT$4*$B$14)+(AS15*$AT$4*$B$15)+(AS16*$AT$4*$B$16)+(AS17*$AT$4*$B$17)+(AS18*$AT$4*$B$18)+(AS19*$AT$4*$B$19)+(AS20*$AT$4*$B$20)+(AS21*$AT$4*$B$21)+(AS22*$AT$4*$B$22)+(AS23*$AT$4*$B$23)+(AS24*$AT$4*$B$24)+(AS25*$AT$4*$B$25)+(AS22*$AT$4*(1-$B22-$C22)+AS22)-7.7852 | AU9: =AT9*$AU$4*1+AT9+(AT10*$AU$4*$B$10)+(AT11*$AU$4*$B$11)+(AT12*$AU$4*$B$12)+(AT13*$AU$4*$B$13)+(AT14*$AU$4*$B$14)+(AT15*$AU$4*$B$15)+(AT16*$AU$4*$B$16)+(AT17*$AU$4*$B$17)+(AT18*$AU$4*$B$18)+(AT19*$AU$4*$B$19)+(AT20*$AU$4*$B$20)+(AT21*$AU$4*$B$21)+(AT22*$AU$4*$B$22)+(AT23*$AU$4*$B$23)+(AT24*$AU$4*$B$24)+(AT25*$AU$4*$B$25)+(AT25*$AU$4*(1-$B25)+AT25)-3.4221 | AV9: =AU9*$AV$4*1+AU9+(AU10*$AV$4*$B$10)+(AU11*$AV$4*$B$11)+(AU12*$AV$4*$B$12)+(AU13*$AV$4*$B$13)+(AU14*$AV$4*$B$14)+(AU15*$AV$4*$B$15)+(AU16*$AV$4*$B$16)+(AU17*$AV$4*$B$17)+(AU18*$AV$4*$B$18)+(AU19*$AV$4*$B$19)+(AU20*$AV$4*$B$20)+(AU21*$AV$4*$B$21)+(AU22*$AV$4*$B$22)+(AU23*$AV$4*$B$23)+(AU24*$AV$4*$B$24)+(AU25*$AV$4*$B$25)+(AU26*$AV$4*$B$26) | AW9: =AV9*$AW$4*1+AV9+(AV10*$AW$4*$B$10)+(AV11*$AW$4*$B$11)+(AV12*$AW$4*$B$12)+(AV13*$AW$4*$B$13)+(AV14*$AW$4*$B$14)+(AV15*$AW$4*$B$15)+(AV16*$AW$4*$B$16)+(AV17*$AW$4*$B$17)+(AV18*$AW$4*$B$18)+(AV19*$AW$4*$B$19)+(AV20*$AW$4*$B$20)+(AV21*$AW$4*$B$21)+(AV22*$AW$4*$B$22)+(AV23*$AW$4*$B$23)+(AV24*$AW$4*$B$24)+(AV25*$AW$4*$B$25)+(AV26*$AW$4*$B$26) | AX9: =AW9*$AX$4*1+AW9+(AW10*$AX$4*$B$10)+(AW11*$AX$4*$B$11)+(AW12*$AX$4*$B$12)+(AW13*$AX$4*$B$13)+(AW14*$AX$4*$B$14)+(AW15*$AX$4*$B$15)+(AW16*$AX$4*$B$16)+(AW17*$AX$4*$B$17)+(AW18*$AX$4*$B$18)+(AW19*$AX$4*$B$19)+(AW20*$AX$4*$B$20)+(AW21*$AX$4*$B$21)+(AW22*$AX$4*$B$22)+(AW23*$AX$4*$B$23)+(AW24*$AX$4*$B$24)+(AW25*$AX$4*$B$25)+(AW26*$AX$4*$B$26)+AW11*$AX$4*(1-$B11)+AW11-3.99 | AY9: =AX9*$AY$4*1+AX9+(AX10*$AY$4*$B$10)+(AX11*$AY$4*$B$11)+(AX12*$AY$4*$B$12)+(AX13*$AY$4*$B$13)+(AX14*$AY$4*$B$14)+(AX15*$AY$4*$B$15)+(AX16*$AY$4*$B$16)+(AX17*$AY$4*$B$17)+(AX18*$AY$4*$B$18)+(AX19*$AY$4*$B$19)+(AX20*$AY$4*$B$20)+(AX21*$AY$4*$B$21)+(AX22*$AY$4*$B$22)+(AX23*$AY$4*$B$23)+(AX24*$AY$4*$B$24)+(AX25*$AY$4*$B$25)+(AX26*$AY$4*$B$26) | AZ9: =AY9*$AZ$4*1+AY9+(AY10*$AZ$4*$B$10)+(AY11*$AZ$4*$B$11)+(AY12*$AZ$4*$B$12)+(AY13*$AZ$4*$B$13)+(AY14*$AZ$4*$B$14)+(AY15*$AZ$4*$B$15)+(AY16*$AZ$4*$B$16)+(AY17*$AZ$4*$B$17)+(AY18*$AZ$4*$B$18)+(AY19*$AZ$4*$B$19)+(AY20*$AZ$4*$B$20)+(AY21*$AZ$4*$B$21)+(AY22*$AZ$4*$B$22)+(AY23*$AZ$4*$B$23)+(AY24*$AZ$4*$B$24)+(AY25*$AZ$4*$B$25)+(AY26*$AZ$4*$B$26) | BA9: =AZ9*$BA$4*1+AZ9+(AZ10*$BA$4*$B$10)+(AZ11*$BA$4*$B$11)+(AZ12*$BA$4*$B$12)+(AZ13*$BA$4*$B$13)+(AZ14*$BA$4*$B$14)+(AZ15*$BA$4*$B$15)+(AZ16*$BA$4*$B$16)+(AZ17*$BA$4*$B$17)+(AZ18*$BA$4*$B$18)+(AZ19*$BA$4*$B$19)+(AZ20*$BA$4*$B$20)+(AZ21*$BA$4*$B$21)+(AZ22*$BA$4*$B$22)+(AZ23*$BA$4*$B$23)+(AZ24*$BA$4*$B$24)+(AZ25*$BA$4*$B$25)+(AZ26*$BA$4*$B$26) | BB9: =BA9*BB$4*1+BA9+(BA10*BB$4*$B$10)+(BA11*BB$4*$B$11)+(BA12*BB$4*$B$12)+(BA13*BB$4*$B$13)+(BA14*BB$4*$B$14)+(BA15*BB$4*$B$15)+(BA16*BB$4*$B$16)+(BA17*BB$4*$B$17)+(BA18*BB$4*$B$18)+(BA19*BB$4*$B$19)+(BA20*BB$4*$B$20)+(BA21*BB$4*$B$21)+(BA22*BB$4*$B$22)+(BA23*BB$4*$B$23)+(BA24*BB$4*$B$24)+(BA25*BB$4*$B$25)+(BA26*BB$4*$B$26)+SUMIFS(Investments!$D:$D,Investments!$B:$B,$A9,Investments!$C:$C,"BTC",Investments!$A:$A,BB$8) | BC9: =BB9*BC$4*1+BB9+(BB10*BC$4*$B$10)+(BB11*BC$4*$B$11)+(BB12*BC$4*$B$12)+(BB13*BC$4*$B$13)+(BB14*BC$4*$B$14)+(BB15*BC$4*$B$15)+(BB16*BC$4*$B$16)+(BB17*BC$4*$B$17)+(BB18*BC$4*$B$18)+(BB19*BC$4*$B$19)+(BB20*BC$4*$B$20)+(BB21*BC$4*$B$21)+(BB22*BC$4*$B$22)+(BB23*BC$4*$B$23)+(BB24*BC$4*$B$24)+(BB25*BC$4*$B$25)+(BB26*BC$4*$B$26)+SUMIFS(Investments!$D:$D,Investments!$B:$B,$A9,Investments!$C:$C,"BTC",Investments!$A:$A,BC$8) | BD9: =BC9*BD$4*1+BC9+(BC10*BD$4*$B$10)+(BC11*BD$4*$B$11)+(BC12*BD$4*$B$12)+(BC13*BD$4*$B$13)+(BC14*BD$4*$B$14)+(BC15*BD$4*$B$15)+(BC16*BD$4*$B$16)+(BC17*BD$4*$B$17)+(BC18*BD$4*$B$18)+(BC19*BD$4*$B$19)+(BC20*BD$4*$B$20)+(BC21*BD$4*$B$21)+(BC22*BD$4*$B$22)+(BC23*BD$4*$B$23)+(BC24*BD$4*$B$24)+(BC25*BD$4*$B$25)+(BC26*BD$4*$B$26)+(BC27*BD$4*$B$27)+SUMIFS(Investments!$D:$D,Investments!$B:$B,$A9,Investments!$C:$C,"BTC",Investments!$A:$A,BD$8)+BC14*BD$4*(1-$B14)+BC14-4.3 | BE9: =BD9*BE$4*1+BD9+(BD10*BE$4*$B$10)+(BD11*BE$4*$B$11)+(BD12*BE$4*$B$12)+(BD13*BE$4*$B$13)+(BD14*BE$4*$B$14)+(BD15*BE$4*$B$15)+(BD16*BE$4*$B$16)+(BD17*BE$4*$B$17)+(BD18*BE$4*$B$18)+(BD19*BE$4*$B$19)+(BD20*BE$4*$B$20)+(BD21*BE$4*$B$21)+(BD22*BE$4*$B$22)+(BD23*BE$4*$B$23)+(BD24*BE$4*$B$24)+(BD25*BE$4*$B$25)+(BD26*BE$4*$B$26)+(BD27*BE$4*$B$27)+SUMIFS(Investments!$D:$D,Investments!$B:$B,$A9,Investments!$C:$C,"BTC",Investments!$A:$A,BE$8) | BF9: =BE9*BF$4*1+BE9+(BE10*BF$4*$B$10)+(BE11*BF$4*$B$11)+(BE12*BF$4*$B$12)+(BE13*BF$4*$B$13)+(BE14*BF$4*$B$14)+(BE15*BF$4*$B$15)+(BE16*BF$4*$B$16)+(BE17*BF$4*$B$17)+(BE18*BF$4*$B$18)+(BE19*BF$4*$B$19)+(BE20*BF$4*$B$20)+(BE21*BF$4*$B$21)+(BE22*BF$4*$B$22)+(BE23*BF$4*$B$23)+(BE24*BF$4*$B$24)+(BE25*BF$4*$B$25)+(BE26*BF$4*$B$26)+(BE27*BF$4*$B$27)+SUMIFS(Investments!$D:$D,Investments!$B:$B,$A9,Investments!$C:$C,"BTC",Investments!$A:$A,BF$8)
A10: Jose Molla | B10: 0.15 | D10: 3.468 | E10: =D10*E4*(1-$B10)+D10 | F10: =E10*F4*(1-$B10)+E10 | G10: =F10*$G$4*(1-$B10)+F10 | H10: =G10*$H$4*(1-$B10)+G10 | I10: =H10*$I$4*(1-$B10)+H10 | J10: =I10*$J$4*(1-$B10)+I10 | K10: =J10*$K$4*(1-$B10)+J10 | L10: =K10*$L$4*(1-$B10)+K10 | M10: =L10 | N10: =M10*$N$4*(1-$B10)+M10 | O10: =N10*$O$4*(1-$B10)+N10 | P10: =O10*$P$4*(1-$B10)+O10 | Q10: =P10*$Q$4*(1-$B10)+P10 | R10: =Q10*$R$4*(1-$B10)+Q10 | S10: =R10*$S$4*(1-$B10)+R10 | T10: =S10*$T$4*(1-$B10)+S10 | U10: =T10*$U$4*(1-$B10)+T10 | V10: =U10*$V$4*(1-$B10)+U10 | W10: =V10*$W$4*(1-$B10)+V10 | X10: =W10*$X$4*(1-$B10)+W10 | Y10: =X10*$Y$4*(1-$B10)+X10 | Z10: =Y10*$Z$4*(1-$B10)+Y10 | AA10: =Z10*$AA$4*(1-$B10)+Z10 | AB10: =AA10*$AB$4*(1-$B10)+AA10 | AC10: =AB10*$AC$4*(1-$B10)+AB10 | AD10: =AC10*$AD$4*(1-$B10)+AC10 | AE10: =AD10*$AE$4*(1-$B10)+AD10 | AF10: =AE10*$AF$4*(1-$B10)+AE10 | AG10: =AF10*$AG$4*(1-$B10)+AF10+0.062 | AH10: =AG10*$AH$4*(1-$B10)+AG10 | AI10: =AH10*$AI$4*(1-$B10)+AH10 | AJ10: =AI10*$AJ$4*(1-$B10)+AI10+0.4867 | AK10: =AJ10*$AK$4*(1-$B10)+AJ10 | AL10: =AK10*$AL$4*(1-$B10)+AK10+0.548 | AM10: =AL10*$AM$4*(1-$B10)+AL10 | AN10: =AM10*$AN$4*(1-$B10)+AM10 | AO10: =AN10*$AO$4*(1-$B10)+AN10 | AP10: =AO10*$AP$4*(1-$B10)+AO10 | AQ10: =AP10*$AQ$4*(1-$B10)+AP10 | AR10: =AQ10*$AR$4*(1-$B10)+AQ10 | AS10: =AR10*$AS$4*(1-$B10)+AR10 | AT10: =AS10*$AT$4*(1-$B10)+AS10 | AU10: =AT10*$AU$4*(1-$B10)+AT10 | AV10: =AU10*$AV$4*(1-$B10)+AU10 | AW10: =AV10*$AW$4*(1-$B10)+AV10 | AX10: =AW10*$AX$4*(1-$B10)+AW10 | AY10: =AX10*$AY$4*(1-$B10)+AX10 | AZ10: =AY10*$AZ$4*(1-$B10)+AY10 | BA10: =AZ10*$BA$4*(1-$B10)+AZ10 | BB10: =BA10*BB$4*(1-$B10)+BA10+SUMIFS(Investments!$D:$D,Investments!$B:$B,$A10,Investments!$C:$C,"BTC",Investments!$A:$A,BB$8) | BC10: =BB10*BC$4*(1-$B10)+BB10+SUMIFS(Investments!$D:$D,Investments!$B:$B,$A10,Investments!$C:$C,"BTC",Investments!$A:$A,BC$8) | BD10: =BC10*BD$4*(1-$B10)+BC10+SUMIFS(Investments!$D:$D,Investments!$B:$B,$A10,Investments!$C:$C,"BTC",Investments!$A:$A,BD$8) | BE10: =BD10*BE$4*(1-$B10)+BD10+SUMIFS(Investments!$D:$D,Investments!$B:$B,$A10,Investments!$C:$C,"BTC",Investments!$A:$A,BE$8) | BF10: =BE10*BF$4*(1-$B10)+BE10+SUMIFS(Investments!$D:$D,Investments!$B:$B,$A10,Investments!$C:$C,"BTC",Investments!$A:$A,BF$8)
A11: Kyle Gulamerian | B11: 0.15 | E11: 0 | F11: 2 | G11: =F11*$G$4*(1-$B11)+F11 | H11: =G11*$H$4*(1-$B11)+G11 | I11: =H11*$I$4*(1-$B11)+H11 | J11: =I11*$J$4*(1-$B11)+I11 | K11: =J11*$K$4*(1-$B11)+J11 | L11: =K11*$L$4*(1-$B11)+K11 | M11: =L11-L11 | N11: =M11*$N$4*(1-$B11)+M11 | O11: =N11*$O$4*(1-$B11)+N11 | P11: =O11*$P$4*(1-$B11)+O11 | Q11: =P11*$Q$4*(1-$B11)+P11 | R11: =Q11*$R$4*(1-$B11)+Q11+2.101 | S11: =R11*$S$4*(1-$B11)+R11 | T11: =S11*$T$4*(1-$B11)+S11-(S11*$T$4*(1-$B11)+S11) | U11: =T11*$U$4*(1-$B11)+T11 | V11: =U11*$V$4*(1-$B11)+U11-(U11*$V$4*(1-$B11)+U11) | W11: =V11*$W$4*(1-$B11)+V11-(V11*$W$4*(1-$B11)+V11) | X11: =W11*$X$4*(1-$B11)+W11-(W11*$X$4*(1-$B11)+W11) | Y11: =X11*$Y$4*(1-$B11)+X11-(X11*$Y$4*(1-$B11)+X11) | Z11: =Y11*$Z$4*(1-$B11)+Y11-(Y11*$Z$4*(1-$B11)+Y11) | AA11: =Z11*$AA$4*(1-$B11)+Z11-(Z11*$AA$4*(1-$B11)+Z11) | AB11: =AA11*$AB$4*(1-$B11)+AA11-(AA11*$AB$4*(1-$B11)+AA11) | AC11: =AB11*$AC$4*(1-$B11)+AB11-(AB11*$AC$4*(1-$B11)+AB11) | AD11: =AC11*$AD$4*(1-$B11)+AC11-(AC11*$AD$4*(1-$B11)+AC11) | AE11: =AD11*$AE$4*(1-$B11)+AD11-(AD11*$AE$4*(1-$B11)+AD11) | AF11: =AE11*$AF$4*(1-$B11)+AE11-(AE11*$AF$4*(1-$B11)+AE11) | AG11: =AF11*$AG$4*(1-$B11)+AF11-(AF11*$AG$4*(1-$B11)+AF11) | AH11: =AG11*$AH$4*(1-$B11)+AG11-(AG11*$AH$4*(1-$B11)+AG11) | AI11: =AH11*$AI$4*(1-$B11)+AH11-(AH11*$AI$4*(1-$B11)+AH11) | AJ11: =AI11*$AJ$4*(1-$B11)+AI11-(AI11*$AJ$4*(1-$B11)+AI11) | AK11: =AJ11*$AK$4*(1-$B11)+AJ11 | AL11: =AK11*$AL$4*(1-$B11)+AK11 | AM11: =AL11*$AM$4*(1-$B11)+AL11 | AN11: =AM11*$AN$4*(1-$B11)+AM11 | AO11: =AN11*$AO$4*(1-$B11)+AN11 | AP11: =AO11*$AP$4*(1-$B11)+AO11 | AQ11: =AP11*$AQ$4*(1-$B11)+AP11 | AR11: =AQ11*$AR$4*(1-$B11)+AQ11 | AS11: =AR11*$AS$4*(1-$B11)+AR11 | AT11: =AS11*$AT$4*(1-$B11)+AS11 | AU11: =AT11*$AU$4*(1-$B11)+AT11 | AV11: =AU11*$AV$4*(1-$B11)+AU11 | AW11: =AV11*$AW$4*(1-$B11)+AV11+3.9998 | AX11: =AW11*$AX$4*(1-$B11)+AW11-(AW11*$AX$4*(1-$B11)+AW11) | AY11: =AX11*$AY$4*(1-$B11)+AX11 | AZ11: =AY11*$AZ$4*(1-$B11)+AY11 | BA11: =AZ11*$BA$4*(1-$B11)+AZ11 | BB11: =BA11*BB$4*(1-$B11)+BA11+SUMIFS(Investments!$D:$D,Investments!$B:$B,$A11,Investments!$C:$C,"BTC",Investments!$A:$A,BB$8) | BC11: =BB11*BC$4*(1-$B11)+BB11+SUMIFS(Investments!$D:$D,Investments!$B:$B,$A11,Investments!$C:$C,"BTC",Investments!$A:$A,BC$8) | BD11: =BC11*BD$4*(1-$B11)+BC11+SUMIFS(Investments!$D:$D,Investments!$B:$B,$A11,Investments!$C:$C,"BTC",Investments!$A:$A,BD$8) | BE11: =BD11*BE$4*(1-$B11)+BD11+SUMIFS(Investments!$D:$D,Investments!$B:$B,$A11,Investments!$C:$C,"BTC",Investments!$A:$A,BE$8) | BF11: =BE11*BF$4*(1-$B11)+BE11+SUMIFS(Investments!$D:$D,Investments!$B:$B,$A11,Investments!$C:$C,"BTC",Investments!$A:$A,BF$8)
A12: Matthias Reiser | B12: 0.1 | E12: 0 | F12: 0 | G12: 0 | H12: 4.62 | I12: =H12*$I$4*(1-$B12)+H12 | J12: =I12*$J$4*(1-$B12)+I12 | K12: =J12*$K$4*(1-$B12)+J12 | L12: =K12*$L$4*(1-$B12)+K12 | M12: =L12-L12 | N12: =M12*$N$4*(1-$B12)+M12 | O12: =N12*$O$4*(1-$B12)+N12 | P12: =O12*$P$4*(1-$B12)+O12 | Q12: =P12*$Q$4*(1-$B12)+P12 | R12: =Q12*$R$4*(1-$B12)+Q12+4.8357 | S12: =R12*$S$4*(1-$B12)+R12 | T12: =S12*$T$4*(1-$B12)+S12 | U12: =T12*$U$4*(1-$B12)+T12 | V12: =U12*$V$4*(1-$B12)+U12 | W12: =V12*$W$4*(1-$B12)+V12 | X12: =W12*$X$4*(1-$B12)+W12 | Y12: =X12*$Y$4*(1-$B12)+X12 | Z12: =Y12*$Z$4*(1-$B12)+Y12 | AA12: =Z12*$AA$4*(1-$B12)+Z12 | AB12: =AA12*$AB$4*(1-$B12)+AA12 | AC12: =AB12*$AC$4*(1-$B12)+AB12 | AD12: =AC12*$AD$4*(1-$B12)+AC12 | AE12: =AD12*$AE$4*(1-$B12)+AD12 | AF12: =AE12*$AF$4*(1-$B12)+AE12 | AG12: =AF12*$AG$4*(1-$B12)+AF12 | AH12: =AG12*$AH$4*(1-$B12)+AG12 | AI12: =AH12*$AI$4*(1-$B12)+AH12 | AJ12: =AI12*$AJ$4*(1-$B12)+AI12 | AK12: =AJ12*$AK$4*(1-$B12)+AJ12 | AL12: =AK12*$AL$4*(1-$B12)+AK12 | AM12: =AL12*$AM$4*(1-$B12)+AL12 | AN12: =AM12*$AN$4*(1-$B12)+AM12 | AO12: =AN12*$AO$4*(1-$B12)+AN12 | AP12: =AO12*$AP$4*(1-$B12)+AO12 | AQ12: =AP12*$AQ$4*(1-$B12)+AP12 | AR12: =AQ12*$AR$4*(1-$B12)+AQ12-(AQ12*$AR$4*(1-$B12)+AQ12) | AS12: =AR12*$AS$4*(1-$B12)+AR12 | AT12: =AS12*$AT$4*(1-$B12)+AS12 | AU12: =AT12*$AU$4*(1-$B12)+AT12 | AV12: =AU12*$AV$4*(1-$B12)+AU12 | AW12: =AV12*$AW$4*(1-$B12)+AV12 | AX12: =AW12*$AX$4*(1-$B12)+AW12 | AY12: =AX12*$AY$4*(1-$B12)+AX12 | AZ12: =AY12*$AZ$4*(1-$B12)+AY12 | BA12: =AZ12*$BA$4*(1-$B12)+AZ12 | BB12: =BA12*BB$4*(1-$B12)+BA12+SUMIFS(Investments!$D:$D,Investments!$B:$B,$A12,Investments!$C:$C,"BTC",Investments!$A:$A,BB$8) | BC12: =BB12*BC$4*(1-$B12)+BB12+SUMIFS(Investments!$D:$D,Investments!$B:$B,$A12,Investments!$C:$C,"BTC",Investments!$A:$A,BC$8) | BD12: =BC12*BD$4*(1-$B12)+BC12+SUMIFS(Investments!$D:$D,Investments!$B:$B,$A12,Investments!$C:$C,"BTC",Investments!$A:$A,BD$8) | BE12: =BD12*BE$4*(1-$B12)+BD12+SUMIFS(Investments!$D:$D,Investments!$B:$B,$A12,Investments!$C:$C,"BTC",Investments!$A:$A,BE$8) | BF12: =BE12*BF$4*(1-$B12)+BE12+SUMIFS(Investments!$D:$D,Investments!$B:$B,$A12,Investments!$C:$C,"BTC",Investments!$A:$A,BF$8)
A13: Thomas Puech | B13: 0 | E13: 0 | F13: 0 | G13: 0 | H13: 6.5193 | I13: =H13*$I$4*(1-$B13)+H13 | J13: =I13*$J$4*(1-$B13)+I13 | K13: =J13*$K$4*(1-$B13)+J13 | L13: =K13*$L$4*(1-$B13)+K13 | M13: =L13 | N13: =M13*$N$4*(1-$B13)+M13 | O13: =N13*$O$4*(1-$B13)+N13 | P13: =O13*$P$4*(1-$B13)+O13 | Q13: =(P13*$Q$4*(1-$B13)+P13)-(P13*$Q$4*(1-$B13)+P13) | R13: =Q13*$R$4*(1-$B13)+Q13 | S13: =R13*$S$4*(1-$B13)+R13 | T13: =S13*$T$4*(1-$B13)+S13 | U13: =T13*$U$4*(1-$B13)+T13 | V13: =U13*$V$4*(1-$B13)+U13 | W13: =V13*$W$4*(1-$B13)+V13 | X13: =W13*$X$4*(1-$B13)+W13+6.69 | Y13: =X13*$Y$4*(1-$B13)+X13 | Z13: =Y13*$Z$4*(1-$B13)+Y13 | AA13: =Z13*$AA$4*(1-$B13)+Z13 | AB13: =AA13*$AB$4*(1-$B13)+AA13 | AC13: =AB13*$AC$4*(1-$B13)+AB13 | AD13: =AC13*$AD$4*(1-$B13)+AC13 | AE13: =AD13*$AE$4*(1-$B13)+AD13 | AF13: =AE13*$AF$4*(1-$B13)+AE13 | AG13: =AF13*$AG$4*(1-$B13)+AF13 | AH13: =AG13*$AH$4*(1-$B13)+AG13 | AI13: =AH13*$AI$4*(1-$B13)+AH13 | AJ13: =AI13*$AJ$4*(1-$B13)+AI13 | AK13: =AJ13*$AK$4*(1-$B13)+AJ13 | AL13: =AK13*$AL$4*(1-$B13)+AK13 | AM13: =AL13*$AM$4*(1-$B13)+AL13 | AN13: =AM13*$AN$4*(1-$B13)+AM13 | AO13: =AN13*$AO$4*(1-$B13)+AN13 | AP13: =AO13*$AP$4*(1-$B13)+AO13+0.657 | AQ13: =AP13*$AQ$4*(1-$B13)+AP13 | AR13: =AQ13*$AR$4*(1-$B13)+AQ13 | AS13: =AR13*$AS$4*(1-$B13)+AR13 | AT13: =AS13*$AT$4*(1-$B13)+AS13 | AU13: =AT13*$AU$4*(1-$B13)+AT13 | AV13: =AU13*$AV$4*(1-$B13)+AU13+0.1135766 | AW13: =AV13*$AW$4*(1-$B13)+AV13 | AX13: =AW13*$AX$4*(1-$B13)+AW13 | AY13: =AX13*$AY$4*(1-$B13)+AX13+0.14207 | AZ13: =AY13*$AZ$4*(1-$B13)+AY13 | BA13: =AZ13*$BA$4*(1-$B13)+AZ13+0.60672 | BB13: =BA13*BB$4*(1-$B13)+BA13+SUMIFS(Investments!$D:$D,Investments!$B:$B,$A13,Investments!$C:$C,"BTC",Investments!$A:$A,BB$8) | BC13: =BB13*BC$4*(1-$B13)+BB13+SUMIFS(Investments!$D:$D,Investments!$B:$B,$A13,Investments!$C:$C,"BTC",Investments!$A:$A,BC$8) | BD13: =BC13*BD$4*(1-$B13)+BC13+SUMIFS(Investments!$D:$D,Investments!$B:$B,$A13,Investments!$C:$C,"BTC",Investments!$A:$A,BD$8) | BE13: =BD13*BE$4*(1-$B13)+BD13+SUMIFS(Investments!$D:$D,Investments!$B:$B,$A13,Investments!$C:$C,"BTC",Investments!$A:$A,BE$8) | BF13: =BE13*BF$4*(1-$B13)+BE13+SUMIFS(Investments!$D:$D,Investments!$B:$B,$A13,Investments!$C:$C,"BTC",Investments!$A:$A,BF$8)
A14: Danielle Richetta | B14: 0.1 | E14: 0 | F14: 0 | G14: 0 | H14: 5.2 | I14: =H14*$I$4*(1-$B14)+H14 | J14: =I14*$J$4*(1-$B14)+I14-0.27 | K14: =J14*$K$4*(1-$B14)+J14 | L14: =K14*$L$4*(1-$B14)+K14-0.124 | M14: =L14-L14 | N14: =M14*$N$4*(1-$B14)+M14 | O14: =N14*$O$4*(1-$B14)+N14 | P14: =O14*$P$4*(1-$B14)+O14 | Q14: =P14*$Q$4*(1-$B14)+P14 | R14: =Q14*$R$4*(1-$B14)+Q14+5.0334 | S14: =R14*$S$4*(1-$B14)+R14 | T14: =S14*$T$4*(1-$B14)+S14 | U14: =T14*$U$4*(1-$B14)+T14-0.13 | V14: =U14*$V$4*(1-$B14)+U14 | W14: =V14*$W$4*(1-$B14)+V14 | X14: =W14*$X$4*(1-$B14)+W14 | Y14: =X14*$Y$4*(1-$B14)+X14 | Z14: =Y14*$Z$4*(1-$B14)+Y14-0.26 | AA14: =Z14*$AA$4*(1-$B14)+Z14 | AB14: =AA14*$AB$4*(1-$B14)+AA14-0.11 | AC14: =AB14*$AC$4*(1-$B14)+AB14 | AD14: =AC14*$AD$4*(1-$B14)+AC14 | AE14: =AD14*$AE$4*(1-$B14)+AD14 | AF14: =AE14*$AF$4*(1-$B14)+AE14 | AG14: =AF14*$AG$4*(1-$B14)+AF14 | AH14: =AG14*$AH$4*(1-$B14)+AG14 | AI14: =AH14*$AI$4*(1-$B14)+AH14-0.283 | AJ14: =AI14*$AJ$4*(1-$B14)+AI14 | AK14: =AJ14*$AK$4*(1-$B14)+AJ14 | AL14: =AK14*$AL$4*(1-$B14)+AK14 | AM14: =AL14*$AM$4*(1-$B14)+AL14 | AN14: =AM14*$AN$4*(1-$B14)+AM14 | AO14: =AN14*$AO$4*(1-$B14)+AN14 | AP14: =AO14*$AP$4*(1-$B14)+AO14 | AQ14: =AP14*$AQ$4*(1-$B14)+AP14 | AR14: =AQ14*$AR$4*(1-$B14)+AQ14 | AS14: =AR14*$AS$4*(1-$B14)+AR14 | AT14: =AS14*$AT$4*(1-$B14)+AS14 | AU14: =AT14*$AU$4*(1-$B14)+AT14 | AV14: =AU14*$AV$4*(1-$B14)+AU14 | AW14: =AV14*$AW$4*(1-$B14)+AV14-0.12 | AX14: =AW14*$AX$4*(1-$B14)+AW14 | AY14: =AX14*$AY$4*(1-$B14)+AX14 | AZ14: =AY14*$AZ$4*(1-$B14)+AY14 | BA14: =AZ14*$BA$4*(1-$B14)+AZ14 | BB14: =BA14*BB$4*(1-$B14)+BA14+SUMIFS(Investments!$D:$D,Investments!$B:$B,$A14,Investments!$C:$C,"BTC",Investments!$A:$A,BB$8) | BC14: =BB14*BC$4*(1-$B14)+BB14+SUMIFS(Investments!$D:$D,Investments!$B:$B,$A14,Investments!$C:$C,"BTC",Investments!$A:$A,BC$8) | BD14: =BC14*BD$4*(1-$B14)+BC14-(BC14*BD$4*(1-$B14)+BC14) | BE14: =BD14*BE$4*(1-$B14)+BD14-(BD14*BE$4*(1-$B14)+BD14) | BF14: =BE14*BF$4*(1-$B14)+BE14-(BE14*BF$4*(1-$B14)+BE14)
A15: Kabbaj | B15: 0.2 | E15: 0 | F15: 0 | G15: 0 | H15: 0 | I15: 0 | J15: 0 | K15: 0 | L15: 0 | M15: 0 | N15: 0 | O15: 0 | P15: 0 | Q15: 0 | R15: 0 | S15: 0 | T15: 0 | U15: 0 | V15: 2 | W15: =V15*$W$4*(1-$B15)+V15 | X15: =W15*$X$4*(1-$B15)+W15+0.9914 | Y15: =X15*$Y$4*(1-$B15)+X15 | Z15: =Y15*$Z$4*(1-$B15)+Y15 | AA15: =Z15*$AA$4*(1-$B15)+Z15+0.6 | AB15: =AA15*$AB$4*(1-$B15)+AA15 | AC15: =AB15*$AC$4*(1-$B15)+AB15+0.9102 | AD15: =AC15*$AD$4*(1-$B15)+AC15 | AE15: =AD15*$AE$4*(1-$B15)+AD15 | AF15: =AE15*$AF$4*(1-$B15)+AE15 | AG15: =AF15*$AG$4*(1-$B15)+AF15 | AH15: =AG15*$AH$4*(1-$B15)+AG15 | AI15: =AH15*$AI$4*(1-$B15)+AH15 | AJ15: =AI15*$AJ$4*(1-$B15)+AI15 | AK15: =AJ15*$AK$4*(1-$B15)+AJ15 | AL15: =AK15*$AL$4*(1-$B15)+AK15 | AM15: =AL15*$AM$4*(1-$B15)+AL15 | AN15: =AM15*$AN$4*(1-$B15)+AM15 | AO15: =AN15*$AO$4*(1-$B15)+AN15 | AP15: =AO15*$AP$4*(1-$B15)+AO15 | AQ15: =AP15*$AQ$4*(1-$B15)+AP15 | AR15: =AQ15*$AR$4*(1-$B15)+AQ15 | AS15: =AR15*$AS$4*(1-$B15)+AR15 | AT15: =AS15*$AT$4*(1-$B15)+AS15 | AU15: =AT15*$AU$4*(1-$B15)+AT15+2.1577 | AV15: =AU15*$AV$4*(1-$B15)+AU15 | AW15: =AV15*$AW$4*(1-$B15)+AV15 | AX15: =AW15*$AX$4*(1-$B15)+AW15 | AY15: =AX15*$AY$4*(1-$B15)+AX15 | AZ15: =AY15*$AZ$4*(1-$B15)+AY15 | BA15: =AZ15*$BA$4*(1-$B15)+AZ15 | BB15: =BA15*BB$4*(1-$B15)+BA15+SUMIFS(Investments!$D:$D,Investments!$B:$B,$A15,Investments!$C:$C,"BTC",Investments!$A:$A,BB$8) | BC15: =BB15*BC$4*(1-$B15)+BB15+SUMIFS(Investments!$D:$D,Investments!$B:$B,$A15,Investments!$C:$C,"BTC",Investments!$A:$A,BC$8) | BD15: =BC15*BD$4*(1-$B15)+BC15+SUMIFS(Investments!$D:$D,Investments!$B:$B,$A15,Investments!$C:$C,"BTC",Investments!$A:$A,BD$8) | BE15: =BD15*BE$4*(1-$B15)+BD15+SUMIFS(Investments!$D:$D,Investments!$B:$B,$A15,Investments!$C:$C,"BTC",Investments!$A:$A,BE$8) | BF15: =BE15*BF$4*(1-$B15)+BE15+SUMIFS(Investments!$D:$D,Investments!$B:$B,$A15,Investments!$C:$C,"BTC",Investments!$A:$A,BF$8)
A16: Victoria Pariente-Cohen | B16: 0 | E16: 0 | F16: 0 | G16: 0 | H16: 0 | I16: 0 | J16: 0 | K16: 0 | L16: 0 | M16: 0 | N16: 0 | O16: 0 | P16: 0 | Q16: 0 | R16: 0 | S16: 0 | T16: 0 | U16: 0 | V16: 0 | W16: 0 | X16: =W16*$X$4*(1-$B16)+W16+0.1484 | Y16: =X16*$Y$4*(1-$B16)+X16 | Z16: =Y16*$Z$4*(1-$B16)+Y16 | AA16: =Z16*$AA$4*(1-$B16)+Z16 | AB16: =AA16*$AB$4*(1-$B16)+AA16 | AC16: =AB16*$AC$4*(1-$B16)+AB16 | AD16: =AC16*$AD$4*(1-$B16)+AC16 | AE16: =AD16*$AE$4*(1-$B16)+AD16 | AF16: =AE16*$AF$4*(1-$B16)+AE16 | AG16: =AF16*$AG$4*(1-$B16)+AF16 | AH16: =AG16*$AH$4*(1-$B16)+AG16 | AI16: =AH16*$AI$4*(1-$B16)+AH16 | AJ16: =AI16*$AJ$4*(1-$B16)+AI16 | AK16: =AJ16*$AK$4*(1-$B16)+AJ16 | AL16: =AK16*$AL$4*(1-$B16)+AK16 | AM16: =AL16*$AM$4*(1-$B16)+AL16 | AN16: =AM16*$AN$4*(1-$B16)+AM16 | AO16: =AN16*$AO$4*(1-$B16)+AN16 | AP16: =AO16*$AP$4*(1-$B16)+AO16 | AQ16: =AP16*$AQ$4*(1-$B16)+AP16 | AR16: =AQ16*$AR$4*(1-$B16)+AQ16 | AS16: =AR16*$AS$4*(1-$B16)+AR16 | AT16: =AS16*$AT$4*(1-$B16)+AS16 | AU16: =AT16*$AU$4*(1-$B16)+AT16 | AV16: =AU16*$AV$4*(1-$B16)+AU16 | AW16: =AV16*$AW$4*(1-$B16)+AV16 | AX16: =AW16*$AX$4*(1-$B16)+AW16 | AY16: =AX16*$AY$4*(1-$B16)+AX16 | AZ16: =AY16*$AZ$4*(1-$B16)+AY16 | BA16: =AZ16*$BA$4*(1-$B16)+AZ16 | BB16: =BA16*BB$4*(1-$B16)+BA16+SUMIFS(Investments!$D:$D,Investments!$B:$B,$A16,Investments!$C:$C,"BTC",Investments!$A:$A,BB$8) | BC16: =BB16*BC$4*(1-$B16)+BB16+SUMIFS(Investments!$D:$D,Investments!$B:$B,$A16,Investments!$C:$C,"BTC",Investments!$A:$A,BC$8) | BD16: =BC16*BD$4*(1-$B16)+BC16+SUMIFS(Investments!$D:$D,Investments!$B:$B,$A16,Investments!$C:$C,"BTC",Investments!$A:$A,BD$8) | BE16: =BD16*BE$4*(1-$B16)+BD16+SUMIFS(Investments!$D:$D,Investments!$B:$B,$A16,Investments!$C:$C,"BTC",Investments!$A:$A,BE$8) | BF16: =BE16*BF$4*(1-$B16)+BE16+SUMIFS(Investments!$D:$D,Investments!$B:$B,$A16,Investments!$C:$C,"BTC",Investments!$A:$A,BF$8)
A17: Nathanaël Cohen | B17: 0 | E17: 0 | F17: 0 | G17: 0 | H17: 0 | I17: 0 | J17: 0 | K17: 0 | L17: 0 | M17: 0 | N17: 0 | O17: 0 | P17: 0 | Q17: 0 | R17: 0 | S17: 0 | T17: 0 | U17: 0 | V17: 0 | W17: 0 | X17: =W17*$X$4*(1-$B17)+W17+0.446 | Y17: =X17*$Y$4*(1-$B17)+X17 | Z17: =Y17*$Z$4*(1-$B17)+Y17 | AA17: =Z17*$AA$4*(1-$B17)+Z17 | AB17: =AA17*$AB$4*(1-$B17)+AA17 | AC17: =AB17*$AC$4*(1-$B17)+AB17 | AD17: =AC17*$AD$4*(1-$B17)+AC17 | AE17: =AD17*$AE$4*(1-$B17)+AD17 | AF17: =AE17*$AF$4*(1-$B17)+AE17 | AG17: =AF17*$AG$4*(1-$B17)+AF17 | AH17: =AG17*$AH$4*(1-$B17)+AG17 | AI17: =AH17*$AI$4*(1-$B17)+AH17 | AJ17: =AI17*$AJ$4*(1-$B17)+AI17 | AK17: =AJ17*$AK$4*(1-$B17)+AJ17 | AL17: =AK17*$AL$4*(1-$B17)+AK17 | AM17: =AL17*$AM$4*(1-$B17)+AL17 | AN17: =AM17*$AN$4*(1-$B17)+AM17 | AO17: =AN17*$AO$4*(1-$B17)+AN17 | AP17: =AO17*$AP$4*(1-$B17)+AO17 | AQ17: =AP17*$AQ$4*(1-$B17)+AP17 | AR17: =AQ17*$AR$4*(1-$B17)+AQ17 | AS17: =AR17*$AS$4*(1-$B17)+AR17 | AT17: =AS17*$AT$4*(1-$B17)+AS17 | AU17: =AT17*$AU$4*(1-$B17)+AT17 | AV17: =AU17*$AV$4*(1-$B17)+AU17 | AW17: =AV17*$AW$4*(1-$B17)+AV17 | AX17: =AW17*$AX$4*(1-$B17)+AW17 | AY17: =AX17*$AY$4*(1-$B17)+AX17 | AZ17: =AY17*$AZ$4*(1-$B17)+AY17 | BA17: =AZ17*$BA$4*(1-$B17)+AZ17 | BB17: =BA17*BB$4*(1-$B17)+BA17+SUMIFS(Investments!$D:$D,Investments!$B:$B,$A17,Investments!$C:$C,"BTC",Investments!$A:$A,BB$8) | BC17: =BB17*BC$4*(1-$B17)+BB17+SUMIFS(Investments!$D:$D,Investments!$B:$B,$A17,Investments!$C:$C,"BTC",Investments!$A:$A,BC$8) | BD17: =BC17*BD$4*(1-$B17)+BC17+SUMIFS(Investments!$D:$D,Investments!$B:$B,$A17,Investments!$C:$C,"BTC",Investments!$A:$A,BD$8) | BE17: =BD17*BE$4*(1-$B17)+BD17+SUMIFS(Investments!$D:$D,Investments!$B:$B,$A17,Investments!$C:$C,"BTC",Investments!$A:$A,BE$8) | BF17: =BE17*BF$4*(1-$B17)+BE17+SUMIFS(Investments!$D:$D,Investments!$B:$B,$A17,Investments!$C:$C,"BTC",Investments!$A:$A,BF$8)
A18: Blondish | B18: 0 | E18: 0 | F18: 0 | G18: 0 | H18: 0 | I18: 0 | J18: 0 | K18: 0 | L18: 0 | M18: 0 | N18: 0 | O18: 0 | P18: 0 | Q18: 0 | R18: 0 | S18: 0 | T18: 0 | U18: 0 | V18: 0 | W18: 0 | X18: =W18*$X$4*(1-$B18)+W18+4.0996 | Y18: =X18*$Y$4*(1-$B18)+X18 | Z18: =Y18*$Z$4*(1-$B18)+Y18 | AA18: =Z18*$AA$4*(1-$B18)+Z18 | AB18: =AA18*$AB$4*(1-$B18)+AA18 | AC18: =AB18*$AC$4*(1-$B18)+AB18 | AD18: =AC18*$AD$4*(1-$B18)+AC18 | AE18: =AD18*$AE$4*(1-$B18)+AD18 | AF18: =AE18*$AF$4*(1-$B18)+AE18 | AG18: =AF18*$AG$4*(1-$B18)+AF18 | AH18: =AG18*$AH$4*(1-$B18)+AG18 | AI18: =AH18*$AI$4*(1-$B18)+AH18 | AJ18: =AI18*$AJ$4*(1-$B18)+AI18 | AK18: =AJ18*$AK$4*(1-$B18)+AJ18 | AL18: =AK18*$AL$4*(1-$B18)+AK18 | AM18: =AL18*$AM$4*(1-$B18)+AL18 | AN18: =AM18*$AN$4*(1-$B18)+AM18 | AO18: =AN18*$AO$4*(1-$B18)+AN18 | AP18: =AO18*$AP$4*(1-$B18)+AO18 | AQ18: =AP18*$AQ$4*(1-$B18)+AP18 | AR18: =AQ18*$AR$4*(1-$B18)+AQ18 | AS18: =AR18*$AS$4*(1-$B18)+AR18 | AT18: =AS18*$AT$4*(1-$B18)+AS18 | AU18: =AT18*$AU$4*(1-$B18)+AT18 | AV18: =AU18*$AV$4*(1-$B18)+AU18 | AW18: =AV18*$AW$4*(1-$B18)+AV18 | AX18: =AW18*$AX$4*(1-$B18)+AW18 | AY18: =AX18*$AY$4*(1-$B18)+AX18 | AZ18: =AY18*$AZ$4*(1-$B18)+AY18 | BA18: =AZ18*$BA$4*(1-$B18)+AZ18 | BB18: =BA18*BB$4*(1-$B18)+BA18+SUMIFS(Investments!$D:$D,Investments!$B:$B,$A18,Investments!$C:$C,"BTC",Investments!$A:$A,BB$8) | BC18: =BB18*BC$4*(1-$B18)+BB18+SUMIFS(Investments!$D:$D,Investments!$B:$B,$A18,Investments!$C:$C,"BTC",Investments!$A:$A,BC$8) | BD18: =BC18*BD$4*(1-$B18)+BC18+SUMIFS(Investments!$D:$D,Investments!$B:$B,$A18,Investments!$C:$C,"BTC",Investments!$A:$A,BD$8) | BE18: =BD18*BE$4*(1-$B18)+BD18+SUMIFS(Investments!$D:$D,Investments!$B:$B,$A18,Investments!$C:$C,"BTC",Investments!$A:$A,BE$8) | BF18: =BE18*BF$4*(1-$B18)+BE18+SUMIFS(Investments!$D:$D,Investments!$B:$B,$A18,Investments!$C:$C,"BTC",Investments!$A:$A,BF$8)
A19: Oliver Loisel | B19: 0.1 | E19: 0 | F19: 0 | G19: 0 | H19: 0 | I19: 0 | J19: 0 | K19: 0 | L19: 0 | M19: 0 | N19: 0 | O19: 0 | P19: 0 | Q19: 0 | R19: 0 | S19: 0 | T19: 0 | U19: 0 | V19: 0 | W19: 0 | X19: 0 | Y19: =X19*$Y$4*(1-$B19)+X19+2.115364 | Z19: =Y19*$Z$4*(1-$B19)+Y19 | AA19: =Z19*$AA$4*(1-$B19)+Z19 | AB19: =AA19*$AB$4*(1-$B19)+AA19 | AC19: =AB19*$AC$4*(1-$B19)+AB19 | AD19: =AC19*$AD$4*(1-$B19)+AC19 | AE19: =AD19*$AE$4*(1-$B19)+AD19 | AF19: =AE19*$AF$4*(1-$B19)+AE19 | AG19: =AF19*$AG$4*(1-$B19)+AF19 | AH19: =AG19*$AH$4*(1-$B19)+AG19 | AI19: =AH19*$AI$4*(1-$B19)+AH19 | AJ19: =AI19*$AJ$4*(1-$B19)+AI19 | AK19: =AJ19*$AK$4*(1-$B19)+AJ19 | AL19: =AK19*$AL$4*(1-$B19)+AK19 | AM19: =AL19*$AM$4*(1-$B19)+AL19 | AN19: =AM19*$AN$4*(1-$B19)+AM19 | AO19: =AN19*$AO$4*(1-$B19)+AN19 | AP19: =AO19*$AP$4*(1-$B19)+AO19 | AQ19: =AP19*$AQ$4*(1-$B19)+AP19 | AR19: =AQ19*$AR$4*(1-$B19)+AQ19 | AS19: =AR19*$AS$4*(1-$B19)+AR19 | AT19: =AS19*$AT$4*(1-$B19)+AS19 | AU19: =AT19*$AU$4*(1-$B19)+AT19 | AV19: =AU19*$AV$4*(1-$B19)+AU19 | AW19: =AV19*$AW$4*(1-$B19)+AV19 | AX19: =AW19*$AX$4*(1-$B19)+AW19 | AY19: =AX19*$AY$4*(1-$B19)+AX19 | AZ19: =AY19*$AZ$4*(1-$B19)+AY19 | BA19: =AZ19*$BA$4*(1-$B19)+AZ19 | BB19: =BA19*BB$4*(1-$B19)+BA19+SUMIFS(Investments!$D:$D,Investments!$B:$B,$A19,Investments!$C:$C,"BTC",Investments!$A:$A,BB$8) | BC19: =BB19*BC$4*(1-$B19)+BB19+SUMIFS(Investments!$D:$D,Investments!$B:$B,$A19,Investments!$C:$C,"BTC",Investments!$A:$A,BC$8) | BD19: =BC19*BD$4*(1-$B19)+BC19+SUMIFS(Investments!$D:$D,Investments!$B:$B,$A19,Investments!$C:$C,"BTC",Investments!$A:$A,BD$8) | BE19: =BD19*BE$4*(1-$B19)+BD19+SUMIFS(Investments!$D:$D,Investments!$B:$B,$A19,Investments!$C:$C,"BTC",Investments!$A:$A,BE$8) | BF19: =BE19*BF$4*(1-$B19)+BE19+SUMIFS(Investments!$D:$D,Investments!$B:$B,$A19,Investments!$C:$C,"BTC",Investments!$A:$A,BF$8)
A20: Paul Johnson | B20: 0.135 | C20: 0.015 | E20: 0 | F20: 0 | G20: 0 | H20: 0 | I20: 0 | J20: 0 | K20: 0 | L20: 0 | M20: 0 | N20: 0 | O20: 0 | P20: 0 | Q20: 0 | R20: 0 | S20: 0 | T20: 0 | U20: 0 | V20: 0 | W20: 0 | X20: 0 | Y20: 0 | Z20: 0 | AA20: 0 | AB20: 0 | AC20: 0 | AD20: 0 | AE20: 0 | AF20: =AE20*$AF$4*(1-$B20-$C20)+AE20+0.4395 | AG20: =AF20*$AG$4*(1-$B20-$C20)+AF20 | AH20: =AG20*$AH$4*(1-$B20-$C20)+AG20 | AI20: =AH20*$AI$4*(1-$B20-$C20)+AH20-(AH20*$AI$4*(1-$B20-$C20)+AH20) | AJ20: =AI20*$AJ$4*(1-$B20-$C20)+AI20-(AI20*$AJ$4*(1-$B20-$C20)+AI20) | AK20: =AJ20*$AK$4*(1-$B20-$C20)+AJ20 | AL20: =AK20*$AL$4*(1-$B20-$C20)+AK20 | AM20: =AL20*$AM$4*(1-$B20-$C20)+AL20 | AN20: =AM20*$AN$4*(1-$B20-$C20)+AM20 | AO20: =AN20*$AO$4*(1-$B20-$C20)+AN20 | AP20: =AO20*$AP$4*(1-$B20-$C20)+AO20 | AQ20: =AP20*$AQ$4*(1-$B20-$C20)+AP20 | AR20: =AQ20*$AR$4*(1-$B20-$C20)+AQ20 | AS20: =AR20*$AS$4*(1-$B20-$C20)+AR20 | AT20: =AS20*$AT$4*(1-$B20-$C20)+AS20 | AU20: =AT20*$AU$4*(1-$B20-$C20)+AT20 | AV20: =AU20*$AV$4*(1-$B20-$C20)+AU20 | AW20: =AV20*$AW$4*(1-$B20-$C20)+AV20 | AX20: =AW20*$AX$4*(1-$B20-$C20)+AW20 | AY20: =AX20*$AY$4*(1-$B20-$C20)+AX20 | AZ20: =AY20*$AZ$4*(1-$B20-$C20)+AY20 | BA20: =AZ20*$BA$4*(1-$B20-$C20)+AZ20 | BB20: =BA20*BB$4*(1-$B20-$C20)+BA20+SUMIFS(Investments!$D:$D,Investments!$B:$B,$A20,Investments!$C:$C,"BTC",Investments!$A:$A,BB$8) | BC20: =BB20*BC$4*(1-$B20-$C20)+BB20+SUMIFS(Investments!$D:$D,Investments!$B:$B,$A20,Investments!$C:$C,"BTC",Investments!$A:$A,BC$8) | BD20: =BC20*BD$4*(1-$B20-$C20)+BC20+SUMIFS(Investments!$D:$D,Investments!$B:$B,$A20,Investments!$C:$C,"BTC",Investments!$A:$A,BD$8) | BE20: =BD20*BE$4*(1-$B20-$C20)+BD20+SUMIFS(Investments!$D:$D,Investments!$B:$B,$A20,Investments!$C:$C,"BTC",Investments!$A:$A,BE$8) | BF20: =BE20*BF$4*(1-$B20-$C20)+BE20+SUMIFS(Investments!$D:$D,Investments!$B:$B,$A20,Investments!$C:$C,"BTC",Investments!$A:$A,BF$8)
A21: Alex Jacobs | B21: 0.2 | E21: 0 | F21: 0 | G21: 0 | H21: 0 | I21: 0 | J21: 0 | K21: 0 | L21: 0 | M21: 0 | N21: 0 | O21: 0 | P21: 0 | Q21: 0 | R21: 0 | S21: 0 | T21: 0 | U21: 0 | V21: 0 | W21: 0 | X21: 0 | Y21: 0 | Z21: 0 | AA21: 0 | AB21: 0 | AC21: 0 | AD21: 0 | AE21: 0 | AF21: =AE21*$AF$4*(1-$B21)+AE21+(AE20*$AF$4*$C20) | AG21: =AF21*$AG$4*(1-$B21)+AF21+(AF20*$AG$4*$C20) | AH21: =AG21*$AH$4*(1-$B21)+AG21+(AG20*$AH$4*$C20) | AI21: =AH21*$AI$4*(1-$B21)+AH21+(AH20*$AI$4*$C20) | AJ21: =AI21*$AJ$4*(1-$B21)+AI21+(AI20*$AJ$4*$C20) | AK21: =AJ21*$AK$4*(1-$B21)+AJ21+(AJ20*$AK$4*$C20) | AL21: =AK21*$AL$4*(1-$B21)+AK21+(AK20*$AL$4*$C20) | AM21: =AL21*$AM$4*(1-$B21)+AL21+(AL20*$AM$4*$C20) | AN21: =AM21*$AN$4*(1-$B21)+AM21+(AM20*$AN$4*$C20) | AO21: =AN21*$AO$4*(1-$B21)+AN21+(AN20*$AO$4*$C20) | AP21: =AO21*$AP$4*(1-$B21)+AO21+(AO20*$AP$4*$C20) | AQ21: =AP21*$AQ$4*(1-$B21)+AP21+(AP20*$AQ$4*$C20) | AR21: =AQ21*$AR$4*(1-$B21)+AQ21+(AQ20*$AR$4*$C20) | AS21: =AR21*$AS$4*(1-$B21)+AR21+(AR20*$AS$4*$C20) | AT21: =AS21*$AT$4*(1-$B21)+AS21+(AS20*$AT$4*$C20) | AU21: =AT21*$AU$4*(1-$B21)+AT21+(AT20*$AU$4*$C20) | AV21: =AU21*$AV$4*(1-$B21)+AU21+(AU20*$AV$4*$C20) | AW21: =AV21*$AW$4*(1-$B21)+AV21+(AV20*$AW$4*$C20) | AX21: =AW21*$AX$4*(1-$B21)+AW21+(AW20*$AX$4*$C20) | AY21: =AX21*$AY$4*(1-$B21)+AX21+(AX20*$AY$4*$C20) | AZ21: =AY21*$AZ$4*(1-$B21)+AY21+(AY20*$AZ$4*$C20) | BA21: =AZ21*$BA$4*(1-$B21)+AZ21+(AZ20*$BA$4*$C20) | BB21: =BA21*BB$4*(1-$B21)+BA21+(BA20*BB$4*$C20)+SUMIFS(Investments!$D:$D,Investments!$B:$B,$A21,Investments!$C:$C,"BTC",Investments!$A:$A,BB$8) | BC21: =BB21*BC$4*(1-$B21)+BB21+(BB20*BC$4*$C20)+SUMIFS(Investments!$D:$D,Investments!$B:$B,$A21,Investments!$C:$C,"BTC",Investments!$A:$A,BC$8) | BD21: =BC21*BD$4*(1-$B21)+BC21+(BC20*BD$4*$C20)+SUMIFS(Investments!$D:$D,Investments!$B:$B,$A21,Investments!$C:$C,"BTC",Investments!$A:$A,BD$8) | BE21: =BD21*BE$4*(1-$B21)+BD21+(BD20*BE$4*$C20)+SUMIFS(Investments!$D:$D,Investments!$B:$B,$A21,Investments!$C:$C,"BTC",Investments!$A:$A,BE$8) | BF21: =BE21*BF$4*(1-$B21)+BE21+(BE20*BF$4*$C20)+SUMIFS(Investments!$D:$D,Investments!$B:$B,$A21,Investments!$C:$C,"BTC",Investments!$A:$A,BF$8)
A22: Sam Johnson | B22: 0.16 | C22: 0.04 | E22: 0 | F22: 0 | G22: 0 | H22: 0 | I22: =H22*$I$4*(1-$B22)+H22 | J22: =I22*$J$4*(1-$B22)+I22 | K22: =J22*$K$4*(1-$B22)+J22 | L22: =K22*$L$4*(1-$B22)+K22 | M22: =L22 | N22: =M22*$N$4*(1-$B22)+M22 | O22: =N22*$O$4*(1-$B22)+N22 | P22: =O22*$P$4*(1-$B22)+O22 | Q22: =(P22*$Q$4*(1-$B22)+P22)-(P22*$Q$4*(1-$B22)+P22) | R22: =Q22*$R$4*(1-$B22)+Q22 | S22: =R22*$S$4*(1-$B22)+R22 | T22: =S22*$T$4*(1-$B22)+S22 | U22: =T22*$U$4*(1-$B22)+T22 | V22: =U22*$V$4*(1-$B22)+U22 | W22: =V22*$W$4*(1-$B22)+V22 | X22: =W22*$X$4*(1-$B22)+W22 | Y22: =X22*$Y$4*(1-$B22)+X22 | Z22: =Y22*$Z$4*(1-$B22)+Y22 | AA22: =Z22*$AA$4*(1-$B22)+Z22 | AB22: =AA22*$AB$4*(1-$B22)+AA22 | AC22: =AB22*$AC$4*(1-$B22)+AB22 | AD22: =AC22*$AD$4*(1-$B22)+AC22 | AE22: =AD22*$AE$4*(1-$B22)+AD22 | AF22: =AE22*$AF$4*(1-$B22)+AE22 | AG22: =AF22*$AG$4*(1-$B22)+AF22 | AH22: =AG22*$AH$4*(1-$B22)+AG22 | AI22: =AH22*$AI$4*(1-$B22)+AH22 | AJ22: =AI22*$AJ$4*(1-$B22)+AI22 | AK22: =AJ22*$AK$4*(1-$B22-$C22)+AJ22+3.3 | AL22: =AK22*$AL$4*(1-$B22-$C22)+AK22+1 | AM22: =AL22*$AM$4*(1-$B22-$C22)+AL22 | AN22: =AM22*$AN$4*(1-$B22-$C22)+AM22+1.2 | AO22: =AN22*$AO$4*(1-$B22-$C22)+AN22+1.1 | AP22: =AO22*$AP$4*(1-$B22-$C22)+AO22 | AQ22: =AP22*$AQ$4*(1-$B22-$C22)+AP22+1.17 | AR22: =AQ22*$AR$4*(1-$B22-$C22)+AQ22 | AS22: =AR22*$AS$4*(1-$B22-$C22)+AR22 | AT22: =AS22*$AT$4*(1-$B22-$C22)+AS22-(AS22*$AT$4*(1-$B22-$C22)+AS22) | AU22: =AT22*$AU$4*(1-$B22-$C22)+AT22 | AV22: =AU22*$AV$4*(1-$B22-$C22)+AU22 | AW22: =AV22*$AW$4*(1-$B22-$C22)+AV22 | AX22: =AW22*$AX$4*(1-$B22-$C22)+AW22 | AY22: =AX22*$AY$4*(1-$B22-$C22)+AX22 | AZ22: =AY22*$AZ$4*(1-$B22-$C22)+AY22 | BA22: =AZ22*$BA$4*(1-$B22-$C22)+AZ22 | BB22: =BA22*BB$4*(1-$B22-$C22)+BA22+SUMIFS(Investments!$D:$D,Investments!$B:$B,$A22,Investments!$C:$C,"BTC",Investments!$A:$A,BB$8) | BC22: =BB22*BC$4*(1-$B22-$C22)+BB22+SUMIFS(Investments!$D:$D,Investments!$B:$B,$A22,Investments!$C:$C,"BTC",Investments!$A:$A,BC$8) | BD22: =BC22*BD$4*(1-$B22-$C22)+BC22+SUMIFS(Investments!$D:$D,Investments!$B:$B,$A22,Investments!$C:$C,"BTC",Investments!$A:$A,BD$8) | BE22: =BD22*BE$4*(1-$B22-$C22)+BD22+SUMIFS(Investments!$D:$D,Investments!$B:$B,$A22,Investments!$C:$C,"BTC",Investments!$A:$A,BE$8) | BF22: =BE22*BF$4*(1-$B22-$C22)+BE22+SUMIFS(Investments!$D:$D,Investments!$B:$B,$A22,Investments!$C:$C,"BTC",Investments!$A:$A,BF$8)
A23: Ryan Van Der Wall | B23: 0.2 | E23: 0 | F23: 0 | G23: 0 | H23: 0 | I23: 0 | J23: 0 | K23: 0 | L23: 0 | M23: 0 | N23: 0 | O23: 0 | P23: 0 | Q23: 0 | R23: 0 | S23: 0 | T23: 0 | U23: 0 | V23: 0 | W23: 0 | X23: 0 | Y23: 0 | Z23: 0 | AA23: 0 | AB23: 0 | AC23: 0 | AD23: 0 | AE23: 0 | AF23: =AE23*$AF$4*(1-$B23)+AE23+(AE22*$AF$4*$C22) | AG23: =AF23*$AG$4*(1-$B23)+AF23+(AF22*$AG$4*$C22) | AH23: =AG23*$AH$4*(1-$B23)+AG23+(AG22*$AH$4*$C22) | AI23: =AH23*$AI$4*(1-$B23)+AH23+(AH22*$AI$4*$C22) | AJ23: =AI23*$AJ$4*(1-$B23)+AI23+(AI22*$AJ$4*$C22) | AK23: =AJ23*$AK$4*(1-$B23)+AJ23+(AJ22*$AK$4*$C22) | AL23: =AK23*$AL$4*(1-$B23)+AK23+(AK22*$AL$4*$C22) | AM23: =AL23*$AM$4*(1-$B23)+AL23+(AL22*$AM$4*$C22) | AN23: =AM23*$AN$4*(1-$B23)+AM23+(AM22*$AN$4*$C22) | AO23: =AN23*$AO$4*(1-$B23)+AN23+(AN22*$AO$4*$C22) | AP23: =AO23*$AP$4*(1-$B23)+AO23+(AO22*$AP$4*$C22) | AQ23: =AP23*$AQ$4*(1-$B23)+AP23+(AP22*$AQ$4*$C22) | AR23: =AQ23*$AR$4*(1-$B23)+AQ23+(AQ22*$AR$4*$C22) | AS23: =AR23*$AS$4*(1-$B23)+AR23+(AR22*$AS$4*$C22) | AT23: =AS23*$AT$4*(1-$B23)+AS23+(AS22*$AT$4*$C22) | AU23: =AT23*$AU$4*(1-$B23)+AT23+(AT22*$AU$4*$C22) | AV23: =AU23*$AV$4*(1-$B23)+AU23+(AU22*$AV$4*$C22) | AW23: =AV23*$AW$4*(1-$B23)+AV23+(AV22*$AW$4*$C22) | AX23: =AW23*$AX$4*(1-$B23)+AW23+(AW22*$AX$4*$C22) | AY23: =AX23*$AY$4*(1-$B23)+AX23+(AX22*$AY$4*$C22) | AZ23: =AY23*$AZ$4*(1-$B23)+AY23+(AY22*$AZ$4*$C22) | BA23: =AZ23*$BA$4*(1-$B23)+AZ23+(AZ22*$BA$4*$C22) | BB23: =BA23*BB$4*(1-$B23)+BA23+(BA22*BB$4*$C22)+SUMIFS(Investments!$D:$D,Investments!$B:$B,$A23,Investments!$C:$C,"BTC",Investments!$A:$A,BB$8) | BC23: =BB23*BC$4*(1-$B23)+BB23+(BB22*BC$4*$C22)+SUMIFS(Investments!$D:$D,Investments!$B:$B,$A23,Investments!$C:$C,"BTC",Investments!$A:$A,BC$8) | BD23: =BC23*BD$4*(1-$B23)+BC23+(BC22*BD$4*$C22)+SUMIFS(Investments!$D:$D,Investments!$B:$B,$A23,Investments!$C:$C,"BTC",Investments!$A:$A,BD$8) | BE23: =BD23*BE$4*(1-$B23)+BD23+(BD22*BE$4*$C22)+SUMIFS(Investments!$D:$D,Investments!$B:$B,$A23,Investments!$C:$C,"BTC",Investments!$A:$A,BE$8) | BF23: =BE23*BF$4*(1-$B23)+BE23+(BE22*BF$4*$C22)+SUMIFS(Investments!$D:$D,Investments!$B:$B,$A23,Investments!$C:$C,"BTC",Investments!$A:$A,BF$8)
A24: Nath & Thomas | B24: 0 | E24: 0 | F24: 0 | G24: 0 | H24: 0 | I24: 0 | J24: 0 | K24: 0 | L24: 0 | M24: 0 | N24: 0 | O24: 0 | P24: 0 | Q24: 0 | R24: 0 | S24: 0 | T24: 0 | U24: 0 | V24: 0 | W24: 0 | X24: 0 | Y24: =X24*$Y$4*(1-$B24)+X24 | Z24: =Y24*$Z$4*(1-$B24)+Y24 | AA24: =Z24*$AA$4*(1-$B24)+Z24 | AB24: =AA24*$AB$4*(1-$B24)+AA24 | AC24: =AB24*$AC$4*(1-$B24)+AB24 | AD24: =AC24*$AD$4*(1-$B24)+AC24 | AE24: =AD24*$AE$4*(1-$B24)+AD24 | AF24: =AE24*$AF$4*(1-$B24)+AE24 | AG24: =AF24*$AG$4*(1-$B24)+AF24 | AH24: =AG24*$AH$4*(1-$B24)+AG24 | AI24: =AH24*$AI$4*(1-$B24)+AH24 | AJ24: =AI24*$AJ$4*(1-$B24)+AI24 | AK24: =AJ24*$AK$4*(1-$B24)+AJ24 | AL24: =AK24*$AL$4*(1-$B24)+AK24 | AM24: =AL24*$AM$4*(1-$B24)+AL24+1 | AN24: =AM24*$AN$4*(1-$B24)+AM24 | AO24: =AN24*$AO$4*(1-$B24)+AN24 | AP24: =AO24*$AP$4*(1-$B24)+AO24 | AQ24: =AP24*$AQ$4*(1-$B24)+AP24 | AR24: =AQ24*$AR$4*(1-$B24)+AQ24 | AS24: =AR24*$AS$4*(1-$B24)+AR24 | AT24: =AS24*$AT$4*(1-$B24)+AS24 | AU24: =AT24*$AU$4*(1-$B24)+AT24 | AV24: =AU24*$AV$4*(1-$B24)+AU24 | AW24: =AV24*$AW$4*(1-$B24)+AV24 | AX24: =AW24*$AX$4*(1-$B24)+AW24 | AY24: =AX24*$AY$4*(1-$B24)+AX24 | AZ24: =AY24*$AZ$4*(1-$B24)+AY24 | BA24: =AZ24*$BA$4*(1-$B24)+AZ24 | BB24: =BA24*BB$4*(1-$B24)+BA24+SUMIFS(Investments!$D:$D,Investments!$B:$B,$A24,Investments!$C:$C,"BTC",Investments!$A:$A,BB$8) | BC24: =BB24*BC$4*(1-$B24)+BB24+SUMIFS(Investments!$D:$D,Investments!$B:$B,$A24,Investments!$C:$C,"BTC",Investments!$A:$A,BC$8) | BD24: =BC24*BD$4*(1-$B24)+BC24+SUMIFS(Investments!$D:$D,Investments!$B:$B,$A24,Investments!$C:$C,"BTC",Investments!$A:$A,BD$8) | BE24: =BD24*BE$4*(1-$B24)+BD24+SUMIFS(Investments!$D:$D,Investments!$B:$B,$A24,Investments!$C:$C,"BTC",Investments!$A:$A,BE$8) | BF24: =BE24*BF$4*(1-$B24)+BE24+SUMIFS(Investments!$D:$D,Investments!$B:$B,$A24,Investments!$C:$C,"BTC",Investments!$A:$A,BF$8)
A25: Vivie & Liana | B25: 0 | E25: 0 | F25: 0 | G25: 0 | H25: 0 | I25: 0 | J25: 0 | K25: 0 | L25: 0 | M25: 0 | N25: 0 | O25: 0 | P25: 0 | Q25: 0 | R25: 0 | S25: 0 | T25: 0 | U25: 0 | V25: 0 | W25: 0 | X25: 0 | Y25: =X25*$Y$4*(1-$B25)+X25 | Z25: =Y25*$Z$4*(1-$B25)+Y25 | AA25: =Z25*$AA$4*(1-$B25)+Z25 | AB25: =AA25*$AB$4*(1-$B25)+AA25 | AC25: =AB25*$AC$4*(1-$B25)+AB25 | AD25: =AC25*$AD$4*(1-$B25)+AC25 | AE25: =AD25*$AE$4*(1-$B25)+AD25 | AF25: =AE25*$AF$4*(1-$B25)+AE25 | AG25: =AF25*$AG$4*(1-$B25)+AF25 | AH25: =AG25*$AH$4*(1-$B25)+AG25 | AI25: =AH25*$AI$4*(1-$B25)+AH25 | AJ25: =AI25*$AJ$4*(1-$B25)+AI25 | AK25: =AJ25*$AK$4*(1-$B25)+AJ25 | AL25: =AK25*$AL$4*(1-$B25)+AK25 | AM25: =AL25*$AM$4*(1-$B25)+AL25+3.411 | AN25: =AM25*$AN$4*(1-$B25)+AM25 | AO25: =AN25*$AO$4*(1-$B25)+AN25 | AP25: =AO25*$AP$4*(1-$B25)+AO25 | AQ25: =AP25*$AQ$4*(1-$B25)+AP25 | AR25: =AQ25*$AR$4*(1-$B25)+AQ25 | AS25: =AR25*$AS$4*(1-$B25)+AR25 | AT25: =AS25*$AT$4*(1-$B25)+AS25 | AU25: =AT25*$AU$4*(1-$B25)+AT25-(AT25*$AU$4*(1-$B25)+AT25) | AV25: =AU25*$AV$4*(1-$B25)+AU25 | AW25: =AV25*$AW$4*(1-$B25)+AV25 | AX25: =AW25*$AX$4*(1-$B25)+AW25 | AY25: =AX25*$AY$4*(1-$B25)+AX25 | AZ25: =AY25*$AZ$4*(1-$B25)+AY25 | BA25: =AZ25*$BA$4*(1-$B25)+AZ25 | BB25: =BA25*BB$4*(1-$B25)+BA25+SUMIFS(Investments!$D:$D,Investments!$B:$B,$A25,Investments!$C:$C,"BTC",Investments!$A:$A,BB$8) | BC25: =BB25*BC$4*(1-$B25)+BB25+SUMIFS(Investments!$D:$D,Investments!$B:$B,$A25,Investments!$C:$C,"BTC",Investments!$A:$A,BC$8) | BD25: =BC25*BD$4*(1-$B25)+BC25+SUMIFS(Investments!$D:$D,Investments!$B:$B,$A25,Investments!$C:$C,"BTC",Investments!$A:$A,BD$8) | BE25: =BD25*BE$4*(1-$B25)+BD25+SUMIFS(Investments!$D:$D,Investments!$B:$B,$A25,Investments!$C:$C,"BTC",Investments!$A:$A,BE$8) | BF25: =BE25*BF$4*(1-$B25)+BE25+SUMIFS(Investments!$D:$D,Investments!$B:$B,$A25,Investments!$C:$C,"BTC",Investments!$A:$A,BF$8)
A26: NSVO Holdings | B26: 0.2 | E26: 0 | F26: 0 | G26: 0 | H26: 0 | I26: 0 | J26: 0 | K26: 0 | L26: 0 | M26: 0 | N26: 0 | O26: 0 | P26: 0 | Q26: 0 | R26: 0 | S26: 0 | T26: 0 | U26: 0 | V26: 0 | W26: 0 | X26: 0 | Y26: =X26*$Y$4*(1-$B26)+X26 | Z26: =Y26*$Z$4*(1-$B26)+Y26 | AA26: =Z26*$AA$4*(1-$B26)+Z26 | AB26: =AA26*$AB$4*(1-$B26)+AA26 | AC26: =AB26*$AC$4*(1-$B26)+AB26 | AD26: =AC26*$AD$4*(1-$B26)+AC26 | AE26: =AD26*$AE$4*(1-$B26)+AD26 | AF26: =AE26*$AF$4*(1-$B26)+AE26 | AG26: =AF26*$AG$4*(1-$B26)+AF26 | AH26: =AG26*$AH$4*(1-$B26)+AG26 | AI26: =AH26*$AI$4*(1-$B26)+AH26 | AJ26: =AI26*$AJ$4*(1-$B26)+AI26 | AK26: =AJ26*$AK$4*(1-$B26)+AJ26 | AL26: =AK26*$AL$4*(1-$B26)+AK26 | AM26: =AL26*$AM$4*(1-$B26)+AL26 | AN26: =AM26*$AN$4*(1-$B26)+AM26 | AO26: =AN26*$AO$4*(1-$B26)+AN26 | AP26: =AO26*$AP$4*(1-$B26)+AO26 | AQ26: =AP26*$AQ$4*(1-$B26)+AP26 | AR26: =AQ26*$AR$4*(1-$B26)+AQ26 | AS26: =AR26*$AS$4*(1-$B26)+AR26 | AT26: =AS26*$AT$4*(1-$B26)+AS26 | AU26: =AT26*$AU$4*(1-$B26)+AT26-(AT26*$AU$4*(1-$B26)+AT26) | AV26: =AU26*$AV$4*(1-$B26)+AU26+0.622 | AW26: =AV26*$AW$4*(1-$B26)+AV26 | AX26: =AW26*$AX$4*(1-$B26)+AW26 | AY26: =AX26*$AY$4*(1-$B26)+AX26 | AZ26: =AY26*$AZ$4*(1-$B26)+AY26 | BA26: =AZ26*$BA$4*(1-$B26)+AZ26 | BB26: =BA26*BB$4*(1-$B26)+BA26+SUMIFS(Investments!$D:$D,Investments!$B:$B,$A26,Investments!$C:$C,"BTC",Investments!$A:$A,BB$8) | BC26: =BB26*BC$4*(1-$B26)+BB26+SUMIFS(Investments!$D:$D,Investments!$B:$B,$A26,Investments!$C:$C,"BTC",Investments!$A:$A,BC$8) | BD26: =BC26*BD$4*(1-$B26)+BC26+SUMIFS(Investments!$D:$D,Investments!$B:$B,$A26,Investments!$C:$C,"BTC",Investments!$A:$A,BD$8) | BE26: =BD26*BE$4*(1-$B26)+BD26+SUMIFS(Investments!$D:$D,Investments!$B:$B,$A26,Investments!$C:$C,"BTC",Investments!$A:$A,BE$8) | BF26: =BE26*BF$4*(1-$B26)+BE26+SUMIFS(Investments!$D:$D,Investments!$B:$B,$A26,Investments!$C:$C,"BTC",Investments!$A:$A,BF$8)
A27: ALOK PAVAN BATRA | B27: 0.2 | E27: 0 | F27: 0 | G27: 0 | H27: 0 | I27: 0 | J27: 0 | K27: 0 | L27: 0 | M27: 0 | N27: 0 | O27: 0 | P27: 0 | Q27: 0 | R27: 0 | S27: 0 | T27: 0 | U27: 0 | V27: 0 | W27: 0 | X27: 0 | Y27: =X27*$Y$4*(1-$B27)+X27 | Z27: =Y27*$Z$4*(1-$B27)+Y27 | AA27: =Z27*$AA$4*(1-$B27)+Z27 | AB27: =AA27*$AB$4*(1-$B27)+AA27 | AC27: =AB27*$AC$4*(1-$B27)+AB27 | AD27: =AC27*$AD$4*(1-$B27)+AC27 | AE27: =AD27*$AE$4*(1-$B27)+AD27 | AF27: =AE27*$AF$4*(1-$B27)+AE27 | AG27: =AF27*$AG$4*(1-$B27)+AF27 | AH27: =AG27*$AH$4*(1-$B27)+AG27 | AI27: =AH27*$AI$4*(1-$B27)+AH27 | AJ27: =AI27*$AJ$4*(1-$B27)+AI27 | AK27: =AJ27*$AK$4*(1-$B27)+AJ27 | AL27: =AK27*$AL$4*(1-$B27)+AK27 | AM27: =AL27*$AM$4*(1-$B27)+AL27 | AN27: =AM27*$AN$4*(1-$B27)+AM27 | AO27: =AN27*$AO$4*(1-$B27)+AN27 | AP27: =AO27*$AP$4*(1-$B27)+AO27 | AQ27: =AP27*$AQ$4*(1-$B27)+AP27 | AR27: =AQ27*$AR$4*(1-$B27)+AQ27 | AS27: =AR27*$AS$4*(1-$B27)+AR27 | AT27: =AS27*$AT$4*(1-$B27)+AS27 | AU27: =AT27*$AU$4*(1-$B27)+AT27-(AT27*$AU$4*(1-$B27)+AT27) | AV27: =AU27*$AV$4*(1-$B27)+AU27 | AW27: =AV27*$AW$4*(1-$B27)+AV27 | AX27: =AW27*$AX$4*(1-$B27)+AW27 | AY27: =AX27*$AY$4*(1-$B27)+AX27 | AZ27: =AY27*$AZ$4*(1-$B27)+AY27 | BA27: =AZ27*$BA$4*(1-$B27)+AZ27 | BB27: =BA27*BB$4*(1-$B27)+BA27+SUMIFS(Investments!$D:$D,Investments!$B:$B,$A27,Investments!$C:$C,"BTC",Investments!$A:$A,BB$8) | BC27: =BB27*BC$4*(1-$B27)+BB27+SUMIFS(Investments!$D:$D,Investments!$B:$B,$A27,Investments!$C:$C,"BTC",Investments!$A:$A,BC$8) | BD27: =BC27*BD$4*(1-$B27)+BC27+SUMIFS(Investments!$D:$D,Investments!$B:$B,$A27,Investments!$C:$C,"BTC",Investments!$A:$A,BD$8) | BE27: =BD27*BE$4*(1-$B27)+BD27+SUMIFS(Investments!$D:$D,Investments!$B:$B,$A27,Investments!$C:$C,"BTC",Investments!$A:$A,BE$8) | BF27: =BE27*BF$4*(1-$B27)+BE27+SUMIFS(Investments!$D:$D,Investments!$B:$B,$A27,Investments!$C:$C,"BTC",Investments!$A:$A,BF$8)
A28: Total AUM | E28: =SUM(E9:E27) | F28: =SUM(F9:F27) | G28: =SUM(G9:G27) | H28: =SUM(H9:H27) | I28: =SUM(I9:I27) | J28: =SUM(J9:J27) | K28: =SUM(K9:K27) | L28: =SUM(L9:L27) | ... BF28: =SUM(BF9:BF27)
A30: Indigo Fees | B30: 0 | E30: =IFERROR(E9/E$28,"") | F30: =IFERROR(F9/F$28,"") | G30: =IFERROR(G9/G$28,"") | H30: =IFERROR(H9/H$28,"") | I30: =IFERROR(I9/I$28,"") | J30: =IFERROR(J9/J$28,"") | K30: =IFERROR(K9/K$28,"") | L30: =IFERROR(L9/L$28,"") | ... BF30: =IFERROR(BF9/BF$28,"")
A31: Jose Molla | B31: 0.2 | E31: =IFERROR(E10/E$28,"") | F31: =IFERROR(F10/F$28,"") | G31: =IFERROR(G10/G$28,"") | H31: =IFERROR(H10/H$28,"") | I31: =IFERROR(I10/I$28,"") | J31: =IFERROR(J10/J$28,"") | K31: =IFERROR(K10/K$28,"") | L31: =IFERROR(L10/L$28,"") | ... BF31: =IFERROR(BF10/BF$28,"")
A32: Kyle Gulamerian | B32: 0.15 | E32: =IFERROR(E11/E$28,"") | F32: =IFERROR(F11/F$28,"") | G32: =IFERROR(G11/G$28,"") | H32: =IFERROR(H11/H$28,"") | I32: =IFERROR(I11/I$28,"") | J32: =IFERROR(J11/J$28,"") | K32: =IFERROR(K11/K$28,"") | L32: =IFERROR(L11/L$28,"") | ... BF32: =IFERROR(BF11/BF$28,"")
A33: Matthias Reiser | B33: 0.1 | E33: =IFERROR(E12/E$28,"") | F33: =IFERROR(F12/F$28,"") | G33: =IFERROR(G12/G$28,"") | H33: =IFERROR(H12/H$28,"") | I33: =IFERROR(I12/I$28,"") | J33: =IFERROR(J12/J$28,"") | K33: =IFERROR(K12/K$28,"") | L33: =IFERROR(L12/L$28,"") | ... BF33: =IFERROR(BF12/BF$28,"")
A34: Thomas Puech | B34: 0 | E34: =IFERROR(E13/E$28,"") | F34: =IFERROR(F13/F$28,"") | G34: =IFERROR(G13/G$28,"") | H34: =IFERROR(H13/H$28,"") | I34: =IFERROR(I13/I$28,"") | J34: =IFERROR(J13/J$28,"") | K34: =IFERROR(K13/K$28,"") | L34: =IFERROR(L13/L$28,"") | ... BF34: =IFERROR(BF13/BF$28,"")
A35: Danielle Richetta | B35: 0.1 | E35: =IFERROR(E14/E$28,"") | F35: =IFERROR(F14/F$28,"") | G35: =IFERROR(G14/G$28,"") | H35: =IFERROR(H14/H$28,"") | I35: =IFERROR(I14/I$28,"") | J35: =IFERROR(J14/J$28,"") | K35: =IFERROR(K14/K$28,"") | L35: =IFERROR(L14/L$28,"") | ... BF35: =IFERROR(BF14/BF$28,"")
A36: Kabbaj | B36: 0.2 | E36: =IFERROR(E15/E$28,"") | F36: =IFERROR(F15/F$28,"") | G36: =IFERROR(G15/G$28,"") | H36: =IFERROR(H15/H$28,"") | I36: =IFERROR(I15/I$28,"") | J36: =IFERROR(J15/J$28,"") | K36: =IFERROR(K15/K$28,"") | L36: =IFERROR(L15/L$28,"") | ... BF36: =IFERROR(BF15/BF$28,"")
A37: Victoria Pariente-Cohen | B37: 0 | E37: =IFERROR(E16/E$28,"") | F37: =IFERROR(F16/F$28,"") | G37: =IFERROR(G16/G$28,"") | H37: =IFERROR(H16/H$28,"") | I37: =IFERROR(I16/I$28,"") | J37: =IFERROR(J16/J$28,"") | K37: =IFERROR(K16/K$28,"") | L37: =IFERROR(L16/L$28,"") | ... BF37: =IFERROR(BF16/BF$28,"")
A38: Nathanaël Cohen | B38: 0 | E38: =IFERROR(E17/E$28,"") | F38: =IFERROR(F17/F$28,"") | G38: =IFERROR(G17/G$28,"") | H38: =IFERROR(H17/H$28,"") | I38: =IFERROR(I17/I$28,"") | J38: =IFERROR(J17/J$28,"") | K38: =IFERROR(K17/K$28,"") | L38: =IFERROR(L17/L$28,"") | ... BF38: =IFERROR(BF17/BF$28,"")
A39: Blondish | B39: 0 | E39: =IFERROR(E18/E$28,"") | F39: =IFERROR(F18/F$28,"") | G39: =IFERROR(G18/G$28,"") | H39: =IFERROR(H18/H$28,"") | I39: =IFERROR(I18/I$28,"") | J39: =IFERROR(J18/J$28,"") | K39: =IFERROR(K18/K$28,"") | L39: =IFERROR(L18/L$28,"") | ... BF39: =IFERROR(BF18/BF$28,"")
A40: Oliver Loisel | B40: 0.1 | E40: =IFERROR(E19/E$28,"") | F40: =IFERROR(F19/F$28,"") | G40: =IFERROR(G19/G$28,"") | H40: =IFERROR(H19/H$28,"") | I40: =IFERROR(I19/I$28,"") | J40: =IFERROR(J19/J$28,"") | K40: =IFERROR(K19/K$28,"") | L40: =IFERROR(L19/L$28,"") | ... BF40: =IFERROR(BF19/BF$28,"")
A41: Paul Johnson | B41: 0.135 | C41: 0.015 | E41: =IFERROR(E20/E$28,"") | F41: =IFERROR(F20/F$28,"") | G41: =IFERROR(G20/G$28,"") | H41: =IFERROR(H20/H$28,"") | I41: =IFERROR(I20/I$28,"") | J41: =IFERROR(J20/J$28,"") | K41: =IFERROR(K20/K$28,"") | L41: =IFERROR(L20/L$28,"") | ... BF41: =IFERROR(BF20/BF$28,"")
A42: Alex Jacobs | B42: 0.2 | E42: =IFERROR(E21/E$28,"") | F42: =IFERROR(F21/F$28,"") | G42: =IFERROR(G21/G$28,"") | H42: =IFERROR(H21/H$28,"") | I42: =IFERROR(I21/I$28,"") | J42: =IFERROR(J21/J$28,"") | K42: =IFERROR(K21/K$28,"") | L42: =IFERROR(L21/L$28,"") | ... BF42: =IFERROR(BF21/BF$28,"")
A43: Sam Johnson | B43: 0.18 | C43: 0.015 | E43: =IFERROR(E22/E$28,"") | F43: =IFERROR(F22/F$28,"") | G43: =IFERROR(G22/G$28,"") | H43: =IFERROR(H22/H$28,"") | I43: =IFERROR(I22/I$28,"") | J43: =IFERROR(J22/J$28,"") | K43: =IFERROR(K22/K$28,"") | L43: =IFERROR(L22/L$28,"") | ... BF43: =IFERROR(BF22/BF$28,"")
A44: Ryan Van Der Wall | B44: 0.2 | E44: =IFERROR(E23/E$28,"") | F44: =IFERROR(F23/F$28,"") | G44: =IFERROR(G23/G$28,"") | H44: =IFERROR(H23/H$28,"") | I44: =IFERROR(I23/I$28,"") | J44: =IFERROR(J23/J$28,"") | K44: =IFERROR(K23/K$28,"") | L44: =IFERROR(L23/L$28,"") | ... BF44: =IFERROR(BF23/BF$28,"")
A45: Nath & Thomas | B45: 0 | E45: =IFERROR(E24/E$28,"") | F45: =IFERROR(F24/F$28,"") | G45: =IFERROR(G24/G$28,"") | H45: =IFERROR(H24/H$28,"") | I45: =IFERROR(I24/I$28,"") | J45: =IFERROR(J24/J$28,"") | K45: =IFERROR(K24/K$28,"") | L45: =IFERROR(L24/L$28,"") | ... BF45: =IFERROR(BF24/BF$28,"")
A46: Vivie & Liana | B46: 0 | E46: =IFERROR(E25/E$28,"") | F46: =IFERROR(F25/F$28,"") | G46: =IFERROR(G25/G$28,"") | H46: =IFERROR(H25/H$28,"") | I46: =IFERROR(I25/I$28,"") | J46: =IFERROR(J25/J$28,"") | K46: =IFERROR(K25/K$28,"") | L46: =IFERROR(L25/L$28,"") | ... BF46: =IFERROR(BF25/BF$28,"")
A47: NSVO Holdings | B47: 0.2 | E47: =IFERROR(E26/E$28,"") | F47: =IFERROR(F26/F$28,"") | G47: =IFERROR(G26/G$28,"") | H47: =IFERROR(H26/H$28,"") | I47: =IFERROR(I26/I$28,"") | J47: =IFERROR(J26/J$28,"") | K47: =IFERROR(K26/K$28,"") | L47: =IFERROR(L26/L$28,"") | ... BF47: =IFERROR(BF26/BF$28,"")
A48: ALOK PAVAN BATRA | B48: 0.2 | E48: =IFERROR(E27/E$28,"") | F48: =IFERROR(F27/F$28,"") | G48: =IFERROR(G27/G$28,"") | H48: =IFERROR(H27/H$28,"") | I48: =IFERROR(I27/I$28,"") | J48: =IFERROR(J27/J$28,"") | K48: =IFERROR(K27/K$28,"") | L48: =IFERROR(L27/L$28,"") | ... BF48: =IFERROR(BF27/BF$28,"")
A49: Total AUM | E49: =SUM(E30:E48) | F49: =SUM(F30:F48) | G49: =SUM(G30:G48) | H49: =SUM(H30:H48) | I49: =SUM(I30:I48) | J49: =SUM(J30:J48) | K49: =SUM(K30:K48) | L49: =SUM(L30:L48) | ... BF49: =SUM(BF30:BF48)

Sheet ETH Yield Fund
A1: AUM Before | D1: 0 | E1: 202.23 | F1: 239.44 | G1: =242.88-0.14 | H1: 454.82 | I1: =I3-I2 | J1: 311.09 | K1: 311.59 | L1: 322.45 | M1: 327.13 | N1: 340.32 | O1: 404.05 | P1: 404.25 | Q1: 392.9 | R1: 403.4 | S1: 471.52 | T1: 474.62 | U1: 481.89 | V1: 490.71 | W1: 490.73 | X1: 499.296 | Y1: 506.41 | Z1: 502.11 | AA1: 512.9 | AB1: 597.88 | AC1: 634.2 | AD1: 667.56 | AE1: 676.95 | AF1: 708.83 | AG1: 743.66 | AH1: 778.93 | AI1: 778.93 | AJ1: 583.34 | AK1: 596.03 | AL1: 623.12 | AM1: 624.18 | AN1: 775.01 | AO1: 772.37
A2: Top Up / Withdrawals | D2: 202.01 | E2: 35.2966 | F2: 2 | G2: =62.6261+26.6797+0.898+119.7862 | H2: 32 | I2: -178.37 | J2: 0 | K2: 10.44 | L2: 4.6327 | M2: =8.96+3.35 | N2: 63.1 | O2: 0 | P2: -12 | Q2: 10.051 | R2: =64.27+3.75 | S2: 3.1 | T2: 6.5417 | U2: =1.2+6.4 | V2: 0 | W2: 8.404 | X2: 6.9519 | Y2: =7.6215-12.22 | Z2: 10.224 | AA2: =6.234+78 | AB2: 35 | AC2: 33 | AD2: 9.143 | AE2: 31.37 | AF2: 34 | AG2: 32.5 | AH2: 0 | AI2: =-213.73+18 | AJ2: =SUMIFS(Investments!$D:$D,Investments!$C:$C,"eth",Investments!$A:$A,AJ$8) | AK2: =SUMIFS(Investments!$D:$D,Investments!$C:$C,"eth",Investments!$A:$A,AK$8) | AL2: =SUMIFS(Investments!$D:$D,Investments!$C:$C,"eth",Investments!$A:$A,AL$8) | AM2: =SUMIFS(Investments!$D:$D,Investments!$C:$C,"eth",Investments!$A:$A,AM$8) | AN2: =SUMIFS(Investments!$D:$D,Investments!$C:$C,"eth",Investments!$A:$A,AN$8) | AO2: =SUMIFS(Investments!$D:$D,Investments!$C:$C,"eth",Investments!$A:$A,AO$8)
A3: AUM After | D3: =SUM(D1:D2) | E3: =SUM(E1:E2) | F3: =F1+F2 | G3: =G1+G2 | H3: =H1+H2 | I3: =H3-(G12*$H$4*(1-$B12)+G12) | J3: =J1+J2 | K3: =K1+K2 | L3: =L1+L2 | M3: =M1+M2 | N3: =N1+N2 | O3: =O1+O2 | P3: =P1+P2 | Q3: =Q1+Q2 | ... AO3: =AO1+AO2
A4: Gross Performance | D4: 1 | E4: =(E1*$D$4/D3)-100% | F4: =(F1*$D$4/E3)-100% | G4: =(G1*$D$4/F3)-100% | H4: =(H1*$D$4/G3)-100% | I4: 0 | J4: =(J1*$D$4/I3)-100% | K4: =(K1*$D$4/J1)-100% | L4: =(L1*$D$4/K3)-100% | M4: =(M1*$D$4/L3)-100% | N4: =(N1*$D$4/M3)-100% | O4: =(O1*$D$4/N3)-100% | P4: =(P1*$D$4/O1)-100% | Q4: =(Q1*$D$4/P3)-100% | R4: =(R1*$D$4/Q3)-100% | S4: =(S1*$D$4/R3)-100% | T4: =(T1*$D$4/S3)-100% | U4: =(U1*$D$4/T3)-100% | V4: =(V1*$D$4/U3)-100% | W4: =(W1*$D$4/V1)-100% | X4: =(X1*$D$4/W3)-100% | Y4: =(Y1*$D$4/X3)-100% | Z4: =(Z1*$D$4/Y3)-100% | AA4: =(AA1*$D$4/Z3)-100% | AB4: =(AB1*$D$4/AA3)-100% | AC4: =(AC1*$D$4/AB3)-100% | AD4: =(AD1*$D$4/AC3)-100% | AE4: =(AE1*$D$4/AD3)-100% | ... AH4: =(AH1*$D$4/AG3)-100% | AI4: =(AI1*$D$4/AH1)-100% | AJ4: =(AJ1-AI3)/AI3 | AK4: =(AK1-AJ3)/AJ3 | AL4: =(AL1-AK3)/AK3 | AM4: =(AM1-AL3)/AL3 | AN4: =(AN1-AM3)/AM3 | AO4: =(AO1-AN3)/AN3
A5: Net Performance | E5: =E4*0.8 | F5: =F4*0.8 | G5: =G4*0.8 | H5: =H4*0.8 | I5: =I4*0.8 | J5: =J4*0.8 | K5: =K4*0.8 | L5: =L4*0.8 | ... AO5: =AO4*0.8
A6: Yearly APY | E6: =E4*12 | F6: =F4*12 | G6: =G4*12 | H6: =H4*12 | I6: =I4*12 | J6: =J4*12 | K6: =K4*12 | L6: =L4*12 | ... AO6: =AO4*12
A7: Comments | D7: Set up the fund - Invest : Babak : 27.01 Indigo Main Fund : 175 | E7: Top up from Babak: 32.25 ETH Top up from Nathanaël : 3.0466 ETH | F7: Top up from Nathanaël : 2 ETH | G7: Transfert from ETH TAC Program Jose Molla :62.6261 ETH Nathanael Cohen : 26.6797 ETH Indigo Fees : 0.8980 ETH Blondish : 119.7862 ETH | H7: Invest from Advantage Blockchain : 32 ETH | I7: Withdrawal from INDIGO LP : -178.37 ETH | K7: Paul Johnson invests 10.44 ETH | L7: Paul Johnson top up 4.6327 ETH | M7: Top up from : Paul Jaunson : 8.96 ETH Nathanaël Cohen : 3.35 ETH | N7: Tomer Zur Invest 63.1 ETH | P7: Withdrawal from : Paul Johnson: 12 ETH | Q7: Tomer Zur top up 10.051 ETH | R7: Tomer Zur top up 64.27 ETH Babak top up 3.75 ETH | S7: Babak top up 3.10 ETH | T7: Tomer Zur top up 6.5417 ETH | U7: Jose Molla ETH 1.20 Tomer Zur ETH 6.40 | W7: Refund Tea-Fi hack for 8.404 ETH Indigo : 0.0359 Jose : 2.5064 Nathanael : 1.0677 Blondish : 4.7940 | X7: Tomer Zur ETH 6.9519 | Y7: Tomer Zur ETH 7.6215 Paul Johnson ETH -12.22 (OUT) | Z7: Tomer Zur ETH 10.224 | AA7: Tomer Zur ETH 6.234 Sam Johnson ETH 78.00 | AB7: Sam Johnson ETH 35 | AC7: Sam Johnson ETH 33 | AD7: Tomer Zur ETH 9.143 | AE7: Brandon Hood ETH 31.37 | AF7: Sam Johnson ETH 34 | AG7: Sam Johnson ETH 32.5 | AI7: Advantage +18 Sam Johnson -213.73 | AJ7: Nathanaël Cohen ETH 11.84556 | AK7: Nick Smits van Oyen ETH 25.03 | AM7: Jose Molla ETH 47.32 ALOK PAVAN BATRA ETH 103.38 | AN7: Nathanaël Cohen ETH -3.47
A8: Investors | B8: Fees | C8: IB | D8: 45803 | E8: 45809 | F8: 45839 | G8: 45849 | H8: 45868 | I8: 45869 | J8: 45901 | K8: 45904 | L8: 45910 | M8: 45912 | N8: 45927 | O8: 45930 | P8: 45933 | Q8: 45938 | R8: 45944 | S8: 45947 | T8: 45950 | U8: 45953 | V8: 45961 | W8: 45964 | X8: 45965 | Y8: 45966 | Z8: 45968 | AA8: 45978 | AB8: 45986 | AC8: 45991 | AD8: 45993 | AE8: 45995 | AF8: 45999 | AG8: 46006 | AH8: 46023 | AI8: 46024 | AJ8: 46027 | AK8: 46035 | AL8: 46054 | AM8: 46065 | AN8: 46072 | AO8: 46081
A9: Indigo Fees | B9: 0 | D9: 0 | E9: =D9*$E$4*1+D9+(D10*$E$4*20%)+(D12*$E$4*$B$12)+(D13*$E$4*$B$13)+(D14*$E$4*$B$14) | F9: =E9*$F$4*1+E9+(E10*$F$4*20%)+(E12*$F$4*$B$12)+(E13*$F$4*$B$13)+(E14*$F$4*$B$14) | G9: =F9*$G$4*1+F9+(F10*$G$4*20%)+(F12*$G$4*$B$12)+(F13*$G$4*$B$13)+(F14*$G$4*$B$14)+0.898 | H9: =G9*$H$4*1+G9+(G10*$H$4*20%)+(G12*$H$4*$B$12)+(G13*$H$4*$B$13)+(G14*$H$4*$B$14)+(G15*$H$4*$B$15)+(G16*$H$4*$B$16)+(G17*$H$4*$B$17) | I9: =H9*$I$4*1+H9+(H10*$I$4*20%)+(H12*$I$4*$B$12)+(H13*$I$4*$B$13)+(H14*$I$4*$B$14)+(H15*$I$4*$B$15)+(H16*$I$4*$B$16)+(H17*$I$4*$B$17) | J9: =I9*$J$4*1+I9+(I10*$J$4*$B$10)+(I12*$J$4*$B$12)+(I13*$J$4*$B$13)+(I14*$J$4*$B$14)+(I15*$J$4*$B$15)+(I16*$J$4*$B$16)+(I17*$J$4*$B$17)+(I11*$J$4*$B$11) | K9: =J9*$K$4*1+J9+(J10*$K$4*$B$10)+(J12*$K$4*$B$12)+(J13*$K$4*$B$13)+(J14*$K$4*$B$14)+(J15*$K$4*$B$15)+(J16*$K$4*$B$16)+(J17*$K$4*$B$17)+(J11*$K$4*$B$11)+(J18*$K$4*$B$18)+(J19*$K$4*$B$19) | L9: =K9*$L$4*1+K9+(K10*$L$4*$B$10)+(K12*$L$4*$B$12)+(K13*$L$4*$B$13)+(K14*$L$4*$B$14)+(K15*$L$4*$B$15)+(K16*$L$4*$B$16)+(K17*$L$4*$B$17)+(K11*$L$4*$B$11)+(K18*$L$4*$B$18)+(K19*$L$4*$B$19) | M9: =L9*$M$4*1+L9+(L10*$M$4*$B$10)+(L12*$M$4*$B$12)+(L13*$M$4*$B$13)+(L14*$M$4*$B$14)+(L15*$M$4*$B$15)+(L16*$M$4*$B$16)+(L17*$M$4*$B$17)+(L11*$M$4*$B$11)+(L18*$M$4*$B$18)+(L19*$M$4*$B$19) | N9: =M9*$N$4*1+M9+(M10*$N$4*$B$10)+(M12*$N$4*$B$12)+(M13*$N$4*$B$13)+(M14*$N$4*$B$14)+(M15*$N$4*$B$15)+(M16*$N$4*$B$16)+(M17*$N$4*$B$17)+(M11*$N$4*$B$11)+(M18*$N$4*$B$18)+(M19*$N$4*$B$19)+(M20*$N$4*$B$20) | O9: =N9*$O$4*1+N9+(N10*$O$4*$B$10)+(N12*$O$4*$B$12)+(N13*$O$4*$B$13)+(N14*$O$4*$B$14)+(N15*$O$4*$B$15)+(N16*$O$4*$B$16)+(N17*$O$4*$B$17)+(N11*$O$4*$B$11)+(N18*$O$4*$B$18)+(N19*$O$4*$B$19)+(N20*$O$4*$B$20) | P9: =O9*$P$4*1+O9+(O10*$P$4*$B$10)+(O12*$P$4*$B$12)+(O13*$P$4*$B$13)+(O14*$P$4*$B$14)+(O15*$P$4*$B$15)+(O16*$P$4*$B$16)+(O17*$P$4*$B$17)+(O11*$P$4*$B$11)+(O18*$P$4*$B$18)+(O19*$P$4*$B$19)+(O20*$P$4*$B$20) | Q9: =P9*$Q$4*1+P9+(P10*$Q$4*$B$10)+(P12*$Q$4*$B$12)+(P13*$Q$4*$B$13)+(P14*$Q$4*$B$14)+(P15*$Q$4*$B$15)+(P16*$Q$4*$B$16)+(P17*$Q$4*$B$17)+(P11*$Q$4*$B$11)+(P18*$Q$4*$B$18)+(P19*$Q$4*$B$19)+(P20*$Q$4*$B$20) | R9: =Q9*$R$4*1+Q9+(Q10*$R$4*$B$10)+(Q12*$R$4*$B$12)+(Q13*$R$4*$B$13)+(Q14*$R$4*$B$14)+(Q15*$R$4*$B$15)+(Q16*$R$4*$B$16)+(Q17*$R$4*$B$17)+(Q11*$R$4*$B$11)+(Q18*$R$4*$B$18)+(Q19*$R$4*$B$19)+(Q20*$R$4*$B$20) | S9: =R9*$S$4*1+R9+(R10*$S$4*$B$10)+(R12*$S$4*$B$12)+(R13*$S$4*$B$13)+(R14*$S$4*$B$14)+(R15*$S$4*$B$15)+(R16*$S$4*$B$16)+(R17*$S$4*$B$17)+(R11*$S$4*$B$11)+(R18*$S$4*$B$18)+(R19*$S$4*$B$19)+(R20*$S$4*$B$20) | T9: =S9*$T$4*1+S9+(S10*$T$4*$B$10)+(S12*$T$4*$B$12)+(S13*$T$4*$B$13)+(S14*$T$4*$B$14)+(S15*$T$4*$B$15)+(S16*$T$4*$B$16)+(S17*$T$4*$B$17)+(S11*$T$4*$B$11)+(S18*$T$4*$B$18)+(S19*$T$4*$B$19)+(S20*$T$4*$B$20) | U9: =T9*$U$4*1+T9+(T10*$U$4*$B$10)+(T12*$U$4*$B$12)+(T13*$U$4*$B$13)+(T14*$U$4*$B$14)+(T15*$U$4*$B$15)+(T16*$U$4*$B$16)+(T17*$U$4*$B$17)+(T11*$U$4*$B$11)+(T18*$U$4*$B$18)+(T19*$U$4*$B$19)+(T20*$U$4*$B$20) | V9: =U9*$V$4*1+U9+(U10*$V$4*$B$10)+(U12*$V$4*$B$12)+(U13*$V$4*$B$13)+(U14*$V$4*$B$14)+(U15*$V$4*$B$15)+(U16*$V$4*$B$16)+(U17*$V$4*$B$17)+(U11*$V$4*$B$11)+(U18*$V$4*$B$18)+(U19*$V$4*$B$19)+(U20*$V$4*$B$20) | W9: =V9*$W$4*1+V9+(V10*$W$4*$B$10)+(V12*$W$4*$B$12)+(V13*$W$4*$B$13)+(V14*$W$4*$B$14)+(V15*$W$4*$B$15)+(V16*$W$4*$B$16)+(V17*$W$4*$B$17)+(V11*$W$4*$B$11)+(V18*$W$4*$B$18)+(V19*$W$4*$B$19)+(V20*$W$4*$B$20)+0.0359 | X9: =W9*$X$4*1+W9+(W10*$X$4*$B$10)+(W12*$X$4*$B$12)+(W13*$X$4*$B$13)+(W14*$X$4*$B$14)+(W15*$X$4*$B$15)+(W16*$X$4*$B$16)+(W17*$X$4*$B$17)+(W11*$X$4*$B$11)+(W18*$X$4*$B$18)+(W19*$X$4*$B$19)+(W20*$X$4*$B$20) | Y9: =X9*$Y$4*1+X9+(X10*$Y$4*$B$10)+(X12*$Y$4*$B$12)+(X13*$Y$4*$B$13)+(X14*$Y$4*$B$14)+(X15*$Y$4*$B$15)+(X16*$Y$4*$B$16)+(X17*$Y$4*$B$17)+(X11*$Y$4*$B$11)+(X18*$Y$4*$B$18)+(X19*$Y$4*$B$19)+(X20*$Y$4*$B$20)+(X18*$Y$4*(1-$B18-$C18)+X18)-12.22 | Z9: =Y9*$Z$4*1+Y9+(Y10*$Z$4*$B$10)+(Y12*$Z$4*$B$12)+(Y13*$Z$4*$B$13)+(Y14*$Z$4*$B$14)+(Y15*$Z$4*$B$15)+(Y16*$Z$4*$B$16)+(Y17*$Z$4*$B$17)+(Y11*$Z$4*$B$11)+(Y18*$Z$4*$B$18)+(Y19*$Z$4*$B$19)+(Y20*$Z$4*$B$20)+(Y21*$Z$4*$B$21) | AA9: =Z9*$AA$4*1+Z9+(Z10*$AA$4*$B$10)+(Z12*$AA$4*$B$12)+(Z13*$AA$4*$B$13)+(Z14*$AA$4*$B$14)+(Z15*$AA$4*$B$15)+(Z16*$AA$4*$B$16)+(Z17*$AA$4*$B$17)+(Z11*$AA$4*$B$11)+(Z18*$AA$4*$B$18)+(Z19*$AA$4*$B$19)+(Z20*$AA$4*$B$20)+(Z21*$AA$4*$B$21) | AB9: =AA9*$AB$4*1+AA9+(AA10*$AB$4*$B$10)+(AA12*$AB$4*$B$12)+(AA13*$AB$4*$B$13)+(AA14*$AB$4*$B$14)+(AA15*$AB$4*$B$15)+(AA16*$AB$4*$B$16)+(AA17*$AB$4*$B$17)+(AA11*$AB$4*$B$11)+(AA18*$AB$4*$B$18)+(AA19*$AB$4*$B$19)+(AA20*$AB$4*$B$20)+(AA21*$AB$4*$B$21)+(AA22*$AB$4*$B$22) | AC9: =AB9*$AC$4*1+AB9+(AB10*$AC$4*$B$10)+(AB12*$AC$4*$B$12)+(AB13*$AC$4*$B$13)+(AB14*$AC$4*$B$14)+(AB15*$AC$4*$B$15)+(AB16*$AC$4*$B$16)+(AB17*$AC$4*$B$17)+(AB11*$AC$4*$B$11)+(AB18*$AC$4*$B$18)+(AB19*$AC$4*$B$19)+(AB20*$AC$4*$B$20)+(AB21*$AC$4*$B$21)+(AB22*$AC$4*$B$22) | AD9: =AC9*$AD$4*1+AC9+(AC10*$AD$4*$B$10)+(AC12*$AD$4*$B$12)+(AC13*$AD$4*$B$13)+(AC14*$AD$4*$B$14)+(AC15*$AD$4*$B$15)+(AC16*$AD$4*$B$16)+(AC17*$AD$4*$B$17)+(AC11*$AD$4*$B$11)+(AC18*$AD$4*$B$18)+(AC19*$AD$4*$B$19)+(AC20*$AD$4*$B$20)+(AC21*$AD$4*$B$21)+(AC22*$AD$4*$B$22)+(AC23*$AD$4*$B$23) | AE9: =AD9*$AE$4*1+AD9+(AD10*$AE$4*$B$10)+(AD12*$AE$4*$B$12)+(AD13*$AE$4*$B$13)+(AD14*$AE$4*$B$14)+(AD15*$AE$4*$B$15)+(AD16*$AE$4*$B$16)+(AD17*$AE$4*$B$17)+(AD11*$AE$4*$B$11)+(AD18*$AE$4*$B$18)+(AD19*$AE$4*$B$19)+(AD20*$AE$4*$B$20)+(AD21*$AE$4*$B$21)+(AD22*$AE$4*$B$22)+(AD23*$AE$4*$B$23) | AF9: =AE9*$AF$4*1+AE9+(AE10*$AF$4*$B$10)+(AE12*$AF$4*$B$12)+(AE13*$AF$4*$B$13)+(AE14*$AF$4*$B$14)+(AE15*$AF$4*$B$15)+(AE16*$AF$4*$B$16)+(AE17*$AF$4*$B$17)+(AE11*$AF$4*$B$11)+(AE18*$AF$4*$B$18)+(AE19*$AF$4*$B$19)+(AE20*$AF$4*$B$20)+(AE21*$AF$4*$B$21)+(AE22*$AF$4*$B$22)+(AE23*$AF$4*$B$23) | AG9: =AF9*$AG$4*1+AF9+(AF10*$AG$4*$B$10)+(AF12*$AG$4*$B$12)+(AF13*$AG$4*$B$13)+(AF14*$AG$4*$B$14)+(AF15*$AG$4*$B$15)+(AF16*$AG$4*$B$16)+(AF17*$AG$4*$B$17)+(AF11*$AG$4*$B$11)+(AF18*$AG$4*$B$18)+(AF19*$AG$4*$B$19)+(AF20*$AG$4*$B$20)+(AF21*$AG$4*$B$21)+(AF22*$AG$4*$B$22)+(AF23*$AG$4*$B$23) | AH9: =AG9*$AH$4*1+AG9+(AG10*$AH$4*$B$10)+(AG12*$AH$4*$B$12)+(AG13*$AH$4*$B$13)+(AG14*$AH$4*$B$14)+(AG15*$AH$4*$B$15)+(AG16*$AH$4*$B$16)+(AG17*$AH$4*$B$17)+(AG11*$AH$4*$B$11)+(AG18*$AH$4*$B$18)+(AG19*$AH$4*$B$19)+(AG20*$AH$4*$B$20)+(AG21*$AH$4*$B$21)+(AG22*$AH$4*$B$22)+(AG23*$AH$4*$B$23) | AI9: =AH9*$AI$4*1+AH9+(AH10*$AI$4*$B$10)+(AH12*$AI$4*$B$12)+(AH13*$AI$4*$B$13)+(AH14*$AI$4*$B$14)+(AH15*$AI$4*$B$15)+(AH16*$AI$4*$B$16)+(AH17*$AI$4*$B$17)+(AH11*$AI$4*$B$11)+(AH18*$AI$4*$B$18)+(AH19*$AI$4*$B$19)+(AH20*$AI$4*$B$20)+(AH21*$AI$4*$B$21)+(AH22*$AI$4*$B$22)+(AH23*$AI$4*$B$23)-213.73+(AH21*$AI$4*(1-$B21-$C21)+AH21) | AJ9: =AI9*AJ$4*1+AI9+(AI10*AJ$4*$B$10)+(AI12*AJ$4*$B$12)+(AI13*AJ$4*$B$13)+(AI14*AJ$4*$B$14)+(AI15*AJ$4*$B$15)+(AI16*AJ$4*$B$16)+(AI17*AJ$4*$B$17)+(AI11*AJ$4*$B$11)+(AI18*AJ$4*$B$18)+(AI19*AJ$4*$B$19)+(AI20*AJ$4*$B$20)+(AI21*AJ$4*$B$21)+(AI22*AJ$4*$B$22)+(AI23*AJ$4*$B$23)+SUMIFS(Investments!$D:$D,Investments!$B:$B,$A9,Investments!$C:$C,"ETH",Investments!$A:$A,AJ$8) | AK9: =AJ9*AK$4*1+AJ9+(AJ10*AK$4*$B$10)+(AJ12*AK$4*$B$12)+(AJ13*AK$4*$B$13)+(AJ14*AK$4*$B$14)+(AJ15*AK$4*$B$15)+(AJ16*AK$4*$B$16)+(AJ17*AK$4*$B$17)+(AJ11*AK$4*$B$11)+(AJ18*AK$4*$B$18)+(AJ19*AK$4*$B$19)+(AJ20*AK$4*$B$20)+(AJ21*AK$4*$B$21)+(AJ22*AK$4*$B$22)+(AJ23*AK$4*$B$23)+SUMIFS(Investments!$D:$D,Investments!$B:$B,$A9,Investments!$C:$C,"ETH",Investments!$A:$A,AK$8) | AL9: =AK9*AL$4*1+AK9+(AK10*AL$4*$B$10)+(AK12*AL$4*$B$12)+(AK13*AL$4*$B$13)+(AK14*AL$4*$B$14)+(AK15*AL$4*$B$15)+(AK16*AL$4*$B$16)+(AK17*AL$4*$B$17)+(AK11*AL$4*$B$11)+(AK18*AL$4*$B$18)+(AK19*AL$4*$B$19)+(AK20*AL$4*$B$20)+(AK21*AL$4*$B$21)+(AK22*AL$4*$B$22)+(AK23*AL$4*$B$23)+(AK24*AL$4*$B$24)+SUMIFS(Investments!$D:$D,Investments!$B:$B,$A9,Investments!$C:$C,"ETH",Investments!$A:$A,AL$8) | AM9: =AL9*AM$4*1+AL9+(AL10*AM$4*$B$10)+(AL12*AM$4*$B$12)+(AL13*AM$4*$B$13)+(AL14*AM$4*$B$14)+(AL15*AM$4*$B$15)+(AL16*AM$4*$B$16)+(AL17*AM$4*$B$17)+(AL11*AM$4*$B$11)+(AL18*AM$4*$B$18)+(AL19*AM$4*$B$19)+(AL20*AM$4*$B$20)+(AL21*AM$4*$B$21)+(AL22*AM$4*$B$22)+(AL23*AM$4*$B$23)+(AL24*AM$4*$B$24)+SUMIFS(Investments!$D:$D,Investments!$B:$B,$A9,Investments!$C:$C,"ETH",Investments!$A:$A,AM$8) | AN9: =AM9*AN$4*1+AM9+(AM10*AN$4*$B$10)+(AM12*AN$4*$B$12)+(AM13*AN$4*$B$13)+(AM14*AN$4*$B$14)+(AM15*AN$4*$B$15)+(AM16*AN$4*$B$16)+(AM17*AN$4*$B$17)+(AM11*AN$4*$B$11)+(AM18*AN$4*$B$18)+(AM19*AN$4*$B$19)+(AM20*AN$4*$B$20)+(AM21*AN$4*$B$21)+(AM22*AN$4*$B$22)+(AM23*AN$4*$B$23)+(AM24*AN$4*$B$24)+(AM25*AN$4*$B$25)+SUMIFS(Investments!$D:$D,Investments!$B:$B,$A9,Investments!$C:$C,"ETH",Investments!$A:$A,AN$8) | AO9: =AN9*AO$4*1+AN9+(AN10*AO$4*$B$10)+(AN12*AO$4*$B$12)+(AN13*AO$4*$B$13)+(AN14*AO$4*$B$14)+(AN15*AO$4*$B$15)+(AN16*AO$4*$B$16)+(AN17*AO$4*$B$17)+(AN11*AO$4*$B$11)+(AN18*AO$4*$B$18)+(AN19*AO$4*$B$19)+(AN20*AO$4*$B$20)+(AN21*AO$4*$B$21)+(AN22*AO$4*$B$22)+(AN23*AO$4*$B$23)+(AN24*AO$4*$B$24)+(AN25*AO$4*$B$25)+SUMIFS(Investments!$D:$D,Investments!$B:$B,$A9,Investments!$C:$C,"ETH",Investments!$A:$A,AO$8)
A10: Babak Eftekhari | B10: 0.18 | C10: 0.02 | D10: 27.01 | E10: =59.2835323003812 | F10: 59.66558 | G10: 59.922589 | H10: 60.143892 | I10: 60.143892 | J10: =I10*$J$4*(1-$B10-$C10)+I10 | K10: =J10*$K$4*(1-$B10-$C10)+J10 | L10: =K10*$L$4*(1-$B10-$C10)+K10 | M10: =L10*$M$4*(1-$B10-$C10)+L10 | N10: =M10*$N$4*(1-$B10-$C10)+M10 | O10: =N10*$O$4*(1-$B10-$C10)+N10 | P10: =O10*$P$4*(1-$B10-$C10)+O10 | Q10: =P10*$Q$4*(1-$B10-$C10)+P10 | R10: =Q10*$R$4*(1-$B10-$C10)+Q10+3.75 | S10: =R10*$S$4*(1-$B10-$C10)+R10+3.1 | T10: =S10*$T$4*(1-$B10-$C10)+S10 | U10: =T10*$U$4*(1-$B10-$C10)+T10 | V10: =U10*$V$4*(1-$B10-$C10)+U10 | W10: =V10*$W$4*(1-$B10-$C10)+V10 | X10: =W10*$X$4*(1-$B10-$C10)+W10 | Y10: =X10*$Y$4*(1-$B10-$C10)+X10 | Z10: =Y10*$Z$4*(1-$B10-$C10)+Y10 | AA10: =Z10*$AA$4*(1-$B10-$C10)+Z10 | AB10: =AA10*$AB$4*(1-$B10-$C10)+AA10 | AC10: =AB10*$AC$4*(1-$B10-$C10)+AB10 | AD10: =AC10*$AD$4*(1-$B10-$C10)+AC10 | AE10: =AD10*$AE$4*(1-$B10-$C10)+AD10 | AF10: =AE10*$AF$4*(1-$B10-$C10)+AE10 | AG10: =AF10*$AG$4*(1-$B10-$C10)+AF10 | AH10: =AG10*$AH$4*(1-$B10-$C10)+AG10 | AI10: =AH10*$AI$4*(1-$B10-$C10)+AH10 | AJ10: =AI10*AJ$4*(1-$B10-$C10)+AI10+SUMIFS(Investments!$D:$D,Investments!$B:$B,$A10,Investments!$C:$C,"ETH",Investments!$A:$A,AJ$8) | AK10: =AJ10*AK$4*(1-$B10-$C10)+AJ10+SUMIFS(Investments!$D:$D,Investments!$B:$B,$A10,Investments!$C:$C,"ETH",Investments!$A:$A,AK$8) | AL10: =AK10*AL$4*(1-$B10-$C10)+AK10+SUMIFS(Investments!$D:$D,Investments!$B:$B,$A10,Investments!$C:$C,"ETH",Investments!$A:$A,AL$8) | AM10: =AL10*AM$4*(1-$B10-$C10)+AL10+SUMIFS(Investments!$D:$D,Investments!$B:$B,$A10,Investments!$C:$C,"ETH",Investments!$A:$A,AM$8) | AN10: =AM10*AN$4*(1-$B10-$C10)+AM10+SUMIFS(Investments!$D:$D,Investments!$B:$B,$A10,Investments!$C:$C,"ETH",Investments!$A:$A,AN$8) | AO10: =AN10*AO$4*(1-$B10-$C10)+AN10+SUMIFS(Investments!$D:$D,Investments!$B:$B,$A10,Investments!$C:$C,"ETH",Investments!$A:$A,AO$8)
A11: Lars Ahlgreen | B11: 0.2 | D11: 0 | E11: =D11*$E$4*(1-$B11)+D11 | F11: =E11*$F$4*(1-$B11)+E11 | G11: =F11*$G$4*(1-$B11)+F11 | H11: =(G11*$H$4*(1-$B11)+G11)+(G17*$H$4*$C$16) | I11: =(H11*$I$4*(1-$B11)+H11)+(H17*$I$4*$C$16) | J11: =(I11*$J$4*(1-$B11)+I11)+(I10*$J$4*$C$10) | K11: =(J11*$K$4*(1-$B11)+J11)+(J10*$K$4*$C$10) | L11: =(K11*$L$4*(1-$B11)+K11)+(K10*$L$4*$C$10) | M11: =(L11*$M$4*(1-$B11)+L11)+(L10*$M$4*$C$10) | N11: =(M11*$N$4*(1-$B11)+M11)+(M10*$N$4*$C$10) | O11: =(N11*$O$4*(1-$B11)+N11)+(N10*$O$4*$C$10) | P11: =(O11*$P$4*(1-$B11)+O11)+(O10*$P$4*$C$10) | Q11: =(P11*$Q$4*(1-$B11)+P11)+(P10*$Q$4*$C$10) | R11: =(Q11*$R$4*(1-$B11)+Q11)+(Q10*$R$4*$C$10) | S11: =(R11*$S$4*(1-$B11)+R11)+(R10*$S$4*$C$10) | T11: =(S11*$T$4*(1-$B11)+S11)+(S10*$T$4*$C$10) | U11: =(T11*$U$4*(1-$B11)+T11)+(T10*$U$4*$C$10) | V11: =(U11*$V$4*(1-$B11)+U11)+(U10*$V$4*$C$10) | W11: =(V11*$W$4*(1-$B11)+V11)+(V10*$W$4*$C$10) | X11: =(W11*$X$4*(1-$B11)+W11)+(W10*$X$4*$C$10) | Y11: =(X11*$Y$4*(1-$B11)+X11)+(X10*$Y$4*$C$10) | Z11: =(Y11*$Z$4*(1-$B11)+Y11)+(Y10*$Z$4*$C$10) | AA11: =(Z11*$AA$4*(1-$B11)+Z11)+(Z10*$AA$4*$C$10) | AB11: =(AA11*$AB$4*(1-$B11)+AA11)+(AA10*$AB$4*$C$10) | AC11: =(AB11*$AC$4*(1-$B11)+AB11)+(AB10*$AC$4*$C$10) | AD11: =(AC11*$AD$4*(1-$B11)+AC11)+(AC10*$AD$4*$C$10) | AE11: =(AD11*$AE$4*(1-$B11)+AD11)+(AD10*$AE$4*$C$10) | AF11: =(AE11*$AF$4*(1-$B11)+AE11)+(AE10*$AF$4*$C$10) | AG11: =(AF11*$AG$4*(1-$B11)+AF11)+(AF10*$AG$4*$C$10) | AH11: =(AG11*$AH$4*(1-$B11)+AG11)+(AG10*$AH$4*$C$10) | AI11: =(AH11*$AI$4*(1-$B11)+AH11)+(AH10*$AI$4*$C$10) | AJ11: =(AI11*AJ$4*(1-$B11)+AI11)+(AI10*AJ$4*$C$10)+SUMIFS(Investments!$D:$D,Investments!$B:$B,$A11,Investments!$C:$C,"ETH",Investments!$A:$A,AJ$8) | AK11: =(AJ11*AK$4*(1-$B11)+AJ11)+(AJ10*AK$4*$C$10)+SUMIFS(Investments!$D:$D,Investments!$B:$B,$A11,Investments!$C:$C,"ETH",Investments!$A:$A,AK$8) | AL11: =(AK11*AL$4*(1-$B11)+AK11)+(AK10*AL$4*$C$10)+SUMIFS(Investments!$D:$D,Investments!$B:$B,$A11,Investments!$C:$C,"ETH",Investments!$A:$A,AL$8) | AM11: =(AL11*AM$4*(1-$B11)+AL11)+(AL10*AM$4*$C$10)+SUMIFS(Investments!$D:$D,Investments!$B:$B,$A11,Investments!$C:$C,"ETH",Investments!$A:$A,AM$8) | AN11: =(AM11*AN$4*(1-$B11)+AM11)+(AM10*AN$4*$C$10)+SUMIFS(Investments!$D:$D,Investments!$B:$B,$A11,Investments!$C:$C,"ETH",Investments!$A:$A,AN$8) | AO11: =(AN11*AO$4*(1-$B11)+AN11)+(AN10*AO$4*$C$10)+SUMIFS(Investments!$D:$D,Investments!$B:$B,$A11,Investments!$C:$C,"ETH",Investments!$A:$A,AO$8)
A12: INDIGO DIGITAL ASSET FUND LP | B12: 0 | D12: 175 | E12: =D12*$E$4*(1-$B12)+D12 | F12: =E12*$F$4*(1-$B12)+E12 | G12: =F12*$G$4*(1-$B12)+F12 | H12: =(G12*$H$4*(1-$B12)+G12) | I12: =(H12*$I$4*(1-$B12)+H12)-(H12*$I$4*(1-$B12)+H12) | J12: =(I12*$J$4*(1-$B12)+I12)-(I12*$J$4*(1-$B12)+I12) | K12: =(J12*$K$4*(1-$B12)+J12)-(J12*$K$4*(1-$B12)+J12) | L12: =(K12*$L$4*(1-$B12)+K12)-(K12*$L$4*(1-$B12)+K12) | M12: =(L12*$M$4*(1-$B12)+L12)-(L12*$M$4*(1-$B12)+L12) | N12: =(M12*$N$4*(1-$B12)+M12)-(M12*$N$4*(1-$B12)+M12) | O12: =(N12*$O$4*(1-$B12)+N12)-(N12*$O$4*(1-$B12)+N12) | P12: =(O12*$P$4*(1-$B12)+O12)-(O12*$P$4*(1-$B12)+O12) | Q12: =(P12*$Q$4*(1-$B12)+P12)-(P12*$Q$4*(1-$B12)+P12) | R12: =(Q12*$R$4*(1-$B12)+Q12)-(Q12*$R$4*(1-$B12)+Q12) | S12: =(R12*$S$4*(1-$B12)+R12)-(R12*$S$4*(1-$B12)+R12) | T12: =(S12*$T$4*(1-$B12)+S12)-(S12*$T$4*(1-$B12)+S12) | U12: =(T12*$U$4*(1-$B12)+T12)-(T12*$U$4*(1-$B12)+T12) | V12: =(U12*$V$4*(1-$B12)+U12)-(U12*$V$4*(1-$B12)+U12) | W12: =(V12*$W$4*(1-$B12)+V12)-(V12*$W$4*(1-$B12)+V12) | X12: =(W12*$X$4*(1-$B12)+W12)-(W12*$X$4*(1-$B12)+W12) | Y12: =(X12*$Y$4*(1-$B12)+X12)-(X12*$Y$4*(1-$B12)+X12) | Z12: =(Y12*$Z$4*(1-$B12)+Y12) | AA12: =(Z12*$AA$4*(1-$B12)+Z12) | AB12: =(AA12*$AB$4*(1-$B12)+AA12) | AC12: =(AB12*$AC$4*(1-$B12)+AB12) | AD12: =(AC12*$AD$4*(1-$B12)+AC12) | AE12: =(AD12*$AE$4*(1-$B12)+AD12) | AF12: =(AE12*$AF$4*(1-$B12)+AE12) | AG12: =(AF12*$AG$4*(1-$B12)+AF12) | AH12: =(AG12*$AH$4*(1-$B12)+AG12) | AI12: =(AH12*$AI$4*(1-$B12)+AH12) | AJ12: =(AI12*AJ$4*(1-$B12)+AI12)+SUMIFS(Investments!$D:$D,Investments!$B:$B,$A12,Investments!$C:$C,"ETH",Investments!$A:$A,AJ$8) | AK12: =(AJ12*AK$4*(1-$B12)+AJ12)+SUMIFS(Investments!$D:$D,Investments!$B:$B,$A12,Investments!$C:$C,"ETH",Investments!$A:$A,AK$8) | AL12: =(AK12*AL$4*(1-$B12)+AK12)+SUMIFS(Investments!$D:$D,Investments!$B:$B,$A12,Investments!$C:$C,"ETH",Investments!$A:$A,AL$8) | AM12: =(AL12*AM$4*(1-$B12)+AL12)+SUMIFS(Investments!$D:$D,Investments!$B:$B,$A12,Investments!$C:$C,"ETH",Investments!$A:$A,AM$8) | AN12: =(AM12*AN$4*(1-$B12)+AM12)+SUMIFS(Investments!$D:$D,Investments!$B:$B,$A12,Investments!$C:$C,"ETH",Investments!$A:$A,AN$8) | AO12: =(AN12*AO$4*(1-$B12)+AN12)+SUMIFS(Investments!$D:$D,Investments!$B:$B,$A12,Investments!$C:$C,"ETH",Investments!$A:$A,AO$8)
A13: Nathanaël Cohen | B13: 0 | D13: 0 | E13: =D13*$E$4*(1-$B13)+D13+3.0466 | F13: =E13*$F$4*(1-$B13)+E13+2 | G13: =F13*$G$4*(1-$B13)+F13+26.6797 | H13: =G13*$H$4*(1-$B13)+G13 | I13: =H13*$I$4*(1-$B13)+H13 | J13: =I13*$J$4*(1-$B13)+I13 | K13: =J13*$K$4*(1-$B13)+J13 | L13: =K13*$L$4*(1-$B13)+K13 | M13: =L13*$M$4*(1-$B13)+L13+3.35 | N13: =M13*$N$4*(1-$B13)+M13 | O13: =N13*$O$4*(1-$B13)+N13 | P13: =O13*$P$4*(1-$B13)+O13 | Q13: =P13*$Q$4*(1-$B13)+P13 | R13: =Q13*$R$4*(1-$B13)+Q13 | S13: =R13*$S$4*(1-$B13)+R13 | T13: =S13*$T$4*(1-$B13)+S13 | U13: =T13*$U$4*(1-$B13)+T13 | V13: =U13*$V$4*(1-$B13)+U13 | W13: =V13*$W$4*(1-$B13)+V13+1.0677 | X13: =W13*$X$4*(1-$B13)+W13 | Y13: =X13*$Y$4*(1-$B13)+X13 | Z13: =Y13*$Z$4*(1-$B13)+Y13 | AA13: =Z13*$AA$4*(1-$B13)+Z13 | AB13: =AA13*$AB$4*(1-$B13)+AA13 | AC13: =AB13*$AC$4*(1-$B13)+AB13 | AD13: =AC13*$AD$4*(1-$B13)+AC13 | AE13: =AD13*$AE$4*(1-$B13)+AD13 | AF13: =AE13*$AF$4*(1-$B13)+AE13 | AG13: =AF13*$AG$4*(1-$B13)+AF13 | AH13: =AG13*$AH$4*(1-$B13)+AG13 | AI13: =AH13*$AI$4*(1-$B13)+AH13 | AJ13: =AI13*AJ$4*(1-$B13)+AI13+SUMIFS(Investments!$D:$D,Investments!$B:$B,$A13,Investments!$C:$C,"ETH",Investments!$A:$A,AJ$8) | AK13: =AJ13*AK$4*(1-$B13)+AJ13+SUMIFS(Investments!$D:$D,Investments!$B:$B,$A13,Investments!$C:$C,"ETH",Investments!$A:$A,AK$8) | AL13: =AK13*AL$4*(1-$B13)+AK13+SUMIFS(Investments!$D:$D,Investments!$B:$B,$A13,Investments!$C:$C,"ETH",Investments!$A:$A,AL$8) | AM13: =AL13*AM$4*(1-$B13)+AL13+SUMIFS(Investments!$D:$D,Investments!$B:$B,$A13,Investments!$C:$C,"ETH",Investments!$A:$A,AM$8) | AN13: =AM13*AN$4*(1-$B13)+AM13+SUMIFS(Investments!$D:$D,Investments!$B:$B,$A13,Investments!$C:$C,"ETH",Investments!$A:$A,AN$8) | AO13: =AN13*AO$4*(1-$B13)+AN13+SUMIFS(Investments!$D:$D,Investments!$B:$B,$A13,Investments!$C:$C,"ETH",Investments!$A:$A,AO$8)
A14: Jose Molla | B14: 0.15 | D14: 0 | E14: =D14*$E$4*(1-$B14)+D14 | F14: =E14*$F$4*(1-$B14)+E14 | G14: =F14*$G$4*(1-$B14)+F14+62.6261 | H14: =G14*$H$4*(1-$B14)+G14 | I14: =H14*$I$4*(1-$B14)+H14 | J14: =I14*$J$4*(1-$B14)+I14 | K14: =J14*$K$4*(1-$B14)+J14 | L14: =K14*$L$4*(1-$B14)+K14 | M14: =L14*$M$4*(1-$B14)+L14 | N14: =M14*$N$4*(1-$B14)+M14 | O14: =N14*$O$4*(1-$B14)+N14 | P14: =O14*$P$4*(1-$B14)+O14 | Q14: =P14*$Q$4*(1-$B14)+P14 | R14: =Q14*$R$4*(1-$B14)+Q14 | S14: =R14*$S$4*(1-$B14)+R14 | T14: =S14*$T$4*(1-$B14)+S14 | U14: =T14*$U$4*(1-$B14)+T14+1.2 | V14: =U14*$V$4*(1-$B14)+U14 | W14: =V14*$W$4*(1-$B14)+V14+2.5064 | X14: =W14*$X$4*(1-$B14)+W14 | Y14: =X14*$Y$4*(1-$B14)+X14 | Z14: =Y14*$Z$4*(1-$B14)+Y14 | AA14: =Z14*$AA$4*(1-$B14)+Z14 | AB14: =AA14*$AB$4*(1-$B14)+AA14 | AC14: =AB14*$AC$4*(1-$B14)+AB14 | AD14: =AC14*$AD$4*(1-$B14)+AC14 | AE14: =AD14*$AE$4*(1-$B14)+AD14 | AF14: =AE14*$AF$4*(1-$B14)+AE14 | AG14: =AF14*$AG$4*(1-$B14)+AF14 | AH14: =AG14*$AH$4*(1-$B14)+AG14 | AI14: =AH14*$AI$4*(1-$B14)+AH14 | AJ14: =AI14*AJ$4*(1-$B14)+AI14+SUMIFS(Investments!$D:$D,Investments!$B:$B,$A14,Investments!$C:$C,"ETH",Investments!$A:$A,AJ$8) | AK14: =AJ14*AK$4*(1-$B14)+AJ14+SUMIFS(Investments!$D:$D,Investments!$B:$B,$A14,Investments!$C:$C,"ETH",Investments!$A:$A,AK$8) | AL14: =AK14*AL$4*(1-$B14)+AK14+SUMIFS(Investments!$D:$D,Investments!$B:$B,$A14,Investments!$C:$C,"ETH",Investments!$A:$A,AL$8) | AM14: =AL14*AM$4*(1-$B14)+AL14+SUMIFS(Investments!$D:$D,Investments!$B:$B,$A14,Investments!$C:$C,"ETH",Investments!$A:$A,AM$8) | AN14: =AM14*AN$4*(1-$B14)+AM14+SUMIFS(Investments!$D:$D,Investments!$B:$B,$A14,Investments!$C:$C,"ETH",Investments!$A:$A,AN$8) | AO14: =AN14*AO$4*(1-$B14)+AN14+SUMIFS(Investments!$D:$D,Investments!$B:$B,$A14,Investments!$C:$C,"ETH",Investments!$A:$A,AO$8)
A15: Blondish | B15: 0 | D15: 0 | E15: =D15*$E$4*(1-$B15)+D15 | F15: =E15*$F$4*(1-$B15)+E15 | G15: =F15*$G$4*(1-$B15)+F15+119.7862 | H15: =G15*$H$4*(1-$B15)+G15 | I15: =H15*$I$4*(1-$B15)+H15 | J15: =I15*$J$4*(1-$B15)+I15 | K15: =J15*$K$4*(1-$B15)+J15 | L15: =K15*$L$4*(1-$B15)+K15 | M15: =L15*$M$4*(1-$B15)+L15 | N15: =M15*$N$4*(1-$B15)+M15 | O15: =N15*$O$4*(1-$B15)+N15 | P15: =O15*$P$4*(1-$B15)+O15 | Q15: =P15*$Q$4*(1-$B15)+P15 | R15: =Q15*$R$4*(1-$B15)+Q15 | S15: =R15*$S$4*(1-$B15)+R15 | T15: =S15*$T$4*(1-$B15)+S15 | U15: =T15*$U$4*(1-$B15)+T15 | V15: =U15*$V$4*(1-$B15)+U15 | W15: =V15*$W$4*(1-$B15)+V15+4.794 | X15: =W15*$X$4*(1-$B15)+W15 | Y15: =X15*$Y$4*(1-$B15)+X15 | Z15: =Y15*$Z$4*(1-$B15)+Y15 | AA15: =Z15*$AA$4*(1-$B15)+Z15 | AB15: =AA15*$AB$4*(1-$B15)+AA15 | AC15: =AB15*$AC$4*(1-$B15)+AB15 | AD15: =AC15*$AD$4*(1-$B15)+AC15 | AE15: =AD15*$AE$4*(1-$B15)+AD15 | AF15: =AE15*$AF$4*(1-$B15)+AE15 | AG15: =AF15*$AG$4*(1-$B15)+AF15 | AH15: =AG15*$AH$4*(1-$B15)+AG15 | AI15: =AH15*$AI$4*(1-$B15)+AH15 | AJ15: =AI15*AJ$4*(1-$B15)+AI15+SUMIFS(Investments!$D:$D,Investments!$B:$B,$A15,Investments!$C:$C,"ETH",Investments!$A:$A,AJ$8) | AK15: =AJ15*AK$4*(1-$B15)+AJ15+SUMIFS(Investments!$D:$D,Investments!$B:$B,$A15,Investments!$C:$C,"ETH",Investments!$A:$A,AK$8) | AL15: =AK15*AL$4*(1-$B15)+AK15+SUMIFS(Investments!$D:$D,Investments!$B:$B,$A15,Investments!$C:$C,"ETH",Investments!$A:$A,AL$8) | AM15: =AL15*AM$4*(1-$B15)+AL15+SUMIFS(Investments!$D:$D,Investments!$B:$B,$A15,Investments!$C:$C,"ETH",Investments!$A:$A,AM$8) | AN15: =AM15*AN$4*(1-$B15)+AM15+SUMIFS(Investments!$D:$D,Investments!$B:$B,$A15,Investments!$C:$C,"ETH",Investments!$A:$A,AN$8) | AO15: =AN15*AO$4*(1-$B15)+AN15+SUMIFS(Investments!$D:$D,Investments!$B:$B,$A15,Investments!$C:$C,"ETH",Investments!$A:$A,AO$8)
A16: Advantage Blockchain | B16: 0.18 | C16: 0.02 | D16: 0 | E16: =D16*$E$4*(1-$B16)+D16 | F16: =E16*$F$4*(1-$B16)+E16 | G16: =F16*$G$4*(1-$B16)+F16 | H16: =G16*$H$4*(1-($B16+$C16))+G16+32 | I16: =H16*$I$4*(1-($B16+$C16))+H16 | J16: =I16*$J$4*(1-($B16+$C16))+I16 | K16: =J16*$K$4*(1-($B16+$C16))+J16 | L16: =K16*$L$4*(1-($B16+$C16))+K16 | M16: =L16*$M$4*(1-($B16+$C16))+L16 | N16: =M16*$N$4*(1-($B16+$C16))+M16 | O16: =N16*$O$4*(1-($B16+$C16))+N16 | P16: =O16*$P$4*(1-($B16+$C16))+O16 | Q16: =P16*$Q$4*(1-($B16+$C16))+P16 | R16: =Q16*$R$4*(1-($B16+$C16))+Q16 | S16: =R16*$S$4*(1-($B16+$C16))+R16 | T16: =S16*$T$4*(1-($B16+$C16))+S16 | U16: =T16*$U$4*(1-($B16+$C16))+T16 | V16: =U16*$V$4*(1-($B16+$C16))+U16 | W16: =V16*$W$4*(1-($B16+$C16))+V16 | X16: =W16*$X$4*(1-($B16+$C16))+W16 | Y16: =X16*$Y$4*(1-($B16+$C16))+X16 | Z16: =Y16*$Z$4*(1-($B16+$C16))+Y16 | AA16: =Z16*$AA$4*(1-($B16+$C16))+Z16 | AB16: =AA16*$AB$4*(1-($B16+$C16))+AA16 | AC16: =AB16*$AC$4*(1-($B16+$C16))+AB16 | AD16: =AC16*$AD$4*(1-($B16+$C16))+AC16 | AE16: =AD16*$AE$4*(1-($B16+$C16))+AD16 | AF16: =AE16*$AF$4*(1-($B16+$C16))+AE16 | AG16: =AF16*$AG$4*(1-($B16+$C16))+AF16 | AH16: =AG16*$AH$4*(1-($B16+$C16))+AG16 | AI16: =AH16*$AI$4*(1-($B16+$C16))+AH16+18 | AJ16: =AI16*AJ$4*(1-($B16+$C16))+AI16+SUMIFS(Investments!$D:$D,Investments!$B:$B,$A16,Investments!$C:$C,"ETH",Investments!$A:$A,AJ$8) | AK16: =AJ16*AK$4*(1-($B16+$C16))+AJ16+SUMIFS(Investments!$D:$D,Investments!$B:$B,$A16,Investments!$C:$C,"ETH",Investments!$A:$A,AK$8) | AL16: =AK16*AL$4*(1-($B16+$C16))+AK16+SUMIFS(Investments!$D:$D,Investments!$B:$B,$A16,Investments!$C:$C,"ETH",Investments!$A:$A,AL$8) | AM16: =AL16*AM$4*(1-($B16+$C16))+AL16+SUMIFS(Investments!$D:$D,Investments!$B:$B,$A16,Investments!$C:$C,"ETH",Investments!$A:$A,AM$8) | AN16: =AM16*AN$4*(1-($B16+$C16))+AM16+SUMIFS(Investments!$D:$D,Investments!$B:$B,$A16,Investments!$C:$C,"ETH",Investments!$A:$A,AN$8) | AO16: =AN16*AO$4*(1-($B16+$C16))+AN16+SUMIFS(Investments!$D:$D,Investments!$B:$B,$A16,Investments!$C:$C,"ETH",Investments!$A:$A,AO$8)
A17: Alec Beckman | B17: 0.2 | D17: 0 | E17: =D17*$E$4*(1-$B17)+D17 | F17: =E17*$F$4*(1-$B17)+E17 | G17: =F17*$G$4*(1-$B17)+F17 | H17: =(G17*$H$4*(1-$B17)+G17)+(G16*$H$4*$C$16) | I17: =(H17*$I$4*(1-$B17)+H17)+(H16*$I$4*$C$16) | J17: =(I17*$J$4*(1-$B17)+I17)+(I16*$J$4*$C$16) | K17: =(J17*$K$4*(1-$B17)+J17)+(J16*$K$4*$C$16) | L17: =(K17*$L$4*(1-$B17)+K17)+(K16*$L$4*$C$16) | M17: =(L17*$M$4*(1-$B17)+L17)+(L16*$M$4*$C$16) | N17: =(M17*$N$4*(1-$B17)+M17)+(M16*$N$4*$C$16) | O17: =(N17*$O$4*(1-$B17)+N17)+(N16*$O$4*$C$16) | P17: =(O17*$P$4*(1-$B17)+O17)+(O16*$P$4*$C$16) | Q17: =(P17*$Q$4*(1-$B17)+P17)+(P16*$Q$4*$C$16) | R17: =(Q17*$R$4*(1-$B17)+Q17)+(Q16*$R$4*$C$16) | S17: =(R17*$S$4*(1-$B17)+R17)+(R16*$S$4*$C$16) | T17: =(S17*$T$4*(1-$B17)+S17)+(S16*$T$4*$C$16) | U17: =(T17*$U$4*(1-$B17)+T17)+(T16*$U$4*$C$16) | V17: =(U17*$V$4*(1-$B17)+U17)+(U16*$V$4*$C$16) | W17: =(V17*$W$4*(1-$B17)+V17)+(V16*$W$4*$C$16) | X17: =(W17*$X$4*(1-$B17)+W17)+(W16*$X$4*$C$16) | Y17: =(X17*$Y$4*(1-$B17)+X17)+(X16*$Y$4*$C$16) | Z17: =(Y17*$Z$4*(1-$B17)+Y17)+(Y16*$Z$4*$C$16) | AA17: =(Z17*$AA$4*(1-$B17)+Z17)+(Z16*$AA$4*$C$16) | AB17: =(AA17*$AB$4*(1-$B17)+AA17)+(AA16*$AB$4*$C$16) | AC17: =(AB17*$AC$4*(1-$B17)+AB17)+(AB16*$AC$4*$C$16) | AD17: =(AC17*$AD$4*(1-$B17)+AC17)+(AC16*$AD$4*$C$16) | AE17: =(AD17*$AE$4*(1-$B17)+AD17)+(AD16*$AE$4*$C$16) | AF17: =(AE17*$AF$4*(1-$B17)+AE17)+(AE16*$AF$4*$C$16) | AG17: =(AF17*$AG$4*(1-$B17)+AF17)+(AF16*$AG$4*$C$16) | AH17: =(AG17*$AH$4*(1-$B17)+AG17)+(AG16*$AH$4*$C$16) | AI17: =(AH17*$AI$4*(1-$B17)+AH17)+(AH16*$AI$4*$C$16) | AJ17: =(AI17*AJ$4*(1-$B17)+AI17)+(AI16*AJ$4*$C$16)+SUMIFS(Investments!$D:$D,Investments!$B:$B,$A17,Investments!$C:$C,"ETH",Investments!$A:$A,AJ$8) | AK17: =(AJ17*AK$4*(1-$B17)+AJ17)+(AJ16*AK$4*$C$16)+SUMIFS(Investments!$D:$D,Investments!$B:$B,$A17,Investments!$C:$C,"ETH",Investments!$A:$A,AK$8) | AL17: =(AK17*AL$4*(1-$B17)+AK17)+(AK16*AL$4*$C$16)+SUMIFS(Investments!$D:$D,Investments!$B:$B,$A17,Investments!$C:$C,"ETH",Investments!$A:$A,AL$8) | AM17: =(AL17*AM$4*(1-$B17)+AL17)+(AL16*AM$4*$C$16)+SUMIFS(Investments!$D:$D,Investments!$B:$B,$A17,Investments!$C:$C,"ETH",Investments!$A:$A,AM$8) | AN17: =(AM17*AN$4*(1-$B17)+AM17)+(AM16*AN$4*$C$16)+SUMIFS(Investments!$D:$D,Investments!$B:$B,$A17,Investments!$C:$C,"ETH",Investments!$A:$A,AN$8) | AO17: =(AN17*AO$4*(1-$B17)+AN17)+(AN16*AO$4*$C$16)+SUMIFS(Investments!$D:$D,Investments!$B:$B,$A17,Investments!$C:$C,"ETH",Investments!$A:$A,AO$8)
A18: Paul Johnson | B18: 0.135 | C18: 0.015 | D18: 0 | E18: =D18*$E$4*(1-$B18)+D18 | F18: =E18*$F$4*(1-$B18)+E18 | G18: =F18*$G$4*(1-$B18)+F18 | H18: =(G18*$H$4*(1-$B18)+G18)+(G11*$H$4*$C$16) | I18: =(H18*$I$4*(1-$B18)+H18)+(H11*$I$4*$C$16) | J18: =(I18*$I$4*(1-$B18)+I18)+(I11*$I$4*$C$16) | K18: =J18*$K$4*(1-$B18-$C18)+J18+10.44 | L18: =K18*$L$4*(1-$B18-$C18)+K18+4.6327 | M18: =L18*$M$4*(1-$B18-$C18)+L18+8.96 | N18: =M18*$N$4*(1-$B18-$C18)+M18 | O18: =N18*$O$4*(1-$B18-$C18)+N18 | P18: =O18*$P$4*(1-$B18-$C18)+O18-12 | Q18: =P18*$Q$4*(1-$B18-$C18)+P18 | R18: =Q18*$R$4*(1-$B18-$C18)+Q18 | S18: =R18*$S$4*(1-$B18-$C18)+R18 | T18: =S18*$T$4*(1-$B18-$C18)+S18 | U18: =T18*$U$4*(1-$B18-$C18)+T18 | V18: =U18*$V$4*(1-$B18-$C18)+U18 | W18: =V18*$W$4*(1-$B18-$C18)+V18 | X18: =W18*$X$4*(1-$B18-$C18)+W18 | Y18: =X18*$Y$4*(1-$B18-$C18)+X18-(X18*$Y$4*(1-$B18-$C18)+X18) | Z18: =Y18*$Z$4*(1-$B18-$C18)+Y18-(Y18*$Z$4*(1-$B18-$C18)+Y18) | AA18: =Z18*$AA$4*(1-$B18-$C18)+Z18 | AB18: =AA18*$AB$4*(1-$B18-$C18)+AA18 | AC18: =AB18*$AC$4*(1-$B18-$C18)+AB18 | AD18: =AC18*$AD$4*(1-$B18-$C18)+AC18 | AE18: =AD18*$AE$4*(1-$B18-$C18)+AD18 | AF18: =AE18*$AF$4*(1-$B18-$C18)+AE18 | AG18: =AF18*$AG$4*(1-$B18-$C18)+AF18 | AH18: =AG18*$AH$4*(1-$B18-$C18)+AG18 | AI18: =AH18*$AI$4*(1-$B18-$C18)+AH18 | AJ18: =AI18*AJ$4*(1-$B18-$C18)+AI18+SUMIFS(Investments!$D:$D,Investments!$B:$B,$A18,Investments!$C:$C,"ETH",Investments!$A:$A,AJ$8) | AK18: =AJ18*AK$4*(1-$B18-$C18)+AJ18+SUMIFS(Investments!$D:$D,Investments!$B:$B,$A18,Investments!$C:$C,"ETH",Investments!$A:$A,AK$8) | AL18: =AK18*AL$4*(1-$B18-$C18)+AK18+SUMIFS(Investments!$D:$D,Investments!$B:$B,$A18,Investments!$C:$C,"ETH",Investments!$A:$A,AL$8) | AM18: =AL18*AM$4*(1-$B18-$C18)+AL18+SUMIFS(Investments!$D:$D,Investments!$B:$B,$A18,Investments!$C:$C,"ETH",Investments!$A:$A,AM$8) | AN18: =AM18*AN$4*(1-$B18-$C18)+AM18+SUMIFS(Investments!$D:$D,Investments!$B:$B,$A18,Investments!$C:$C,"ETH",Investments!$A:$A,AN$8) | AO18: =AN18*AO$4*(1-$B18-$C18)+AN18+SUMIFS(Investments!$D:$D,Investments!$B:$B,$A18,Investments!$C:$C,"ETH",Investments!$A:$A,AO$8)
A19: Alex Jacobs | B19: 0.2 | D19: 0 | E19: =D19*$E$4*(1-$B19)+D19 | F19: =E19*$F$4*(1-$B19)+E19 | G19: =F19*$G$4*(1-$B19)+F19 | H19: =(G19*$H$4*(1-$B19)+G19)+(G18*$H$4*$C$16) | I19: =(H19*$I$4*(1-$B19)+H19)+(H18*$I$4*$C$16) | J19: =(I19*$I$4*(1-$B19)+I19)+(I18*$I$4*$C$16) | K19: =(J19*$K$4*(1-$B19)+J19)+(J18*$K$4*$C$18) | L19: =(K19*$L$4*(1-$B19)+K19)+(K18*$L$4*$C$18) | M19: =(L19*$M$4*(1-$B19)+L19)+(L18*$M$4*$C$18) | N19: =(M19*$N$4*(1-$B19)+M19)+(M18*$N$4*$C$18) | O19: =(N19*$O$4*(1-$B19)+N19)+(N18*$O$4*$C$18) | P19: =(O19*$P$4*(1-$B19)+O19)+(O18*$P$4*$C$18) | Q19: =(P19*$Q$4*(1-$B19)+P19)+(P18*$Q$4*$C$18) | R19: =(Q19*$R$4*(1-$B19)+Q19)+(Q18*$R$4*$C$18) | S19: =(R19*$S$4*(1-$B19)+R19)+(R18*$S$4*$C$18) | T19: =(S19*$T$4*(1-$B19)+S19)+(S18*$T$4*$C$18) | U19: =(T19*$U$4*(1-$B19)+T19)+(T18*$U$4*$C$18) | V19: =(U19*$V$4*(1-$B19)+U19)+(U18*$V$4*$C$18) | W19: =(V19*$W$4*(1-$B19)+V19)+(V18*$W$4*$C$18) | X19: =(W19*$X$4*(1-$B19)+W19)+(W18*$X$4*$C$18) | Y19: =(X19*$Y$4*(1-$B19)+X19)+(X18*$Y$4*$C$18) | Z19: =(Y19*$Z$4*(1-$B19)+Y19)+(Y18*$Z$4*$C$18) | AA19: =(Z19*$AA$4*(1-$B19)+Z19)+(Z18*$AA$4*$C$18) | AB19: =(AA19*$AB$4*(1-$B19)+AA19)+(AA18*$AB$4*$C$18) | AC19: =(AB19*$AC$4*(1-$B19)+AB19)+(AB18*$AC$4*$C$18) | AD19: =(AC19*$AD$4*(1-$B19)+AC19)+(AC18*$AD$4*$C$18) | AE19: =(AD19*$AE$4*(1-$B19)+AD19)+(AD18*$AE$4*$C$18) | AF19: =(AE19*$AF$4*(1-$B19)+AE19)+(AE18*$AF$4*$C$18) | AG19: =(AF19*$AG$4*(1-$B19)+AF19)+(AF18*$AG$4*$C$18) | AH19: =(AG19*$AH$4*(1-$B19)+AG19)+(AG18*$AH$4*$C$18) | AI19: =(AH19*$AI$4*(1-$B19)+AH19)+(AH18*$AI$4*$C$18) | AJ19: =(AI19*AJ$4*(1-$B19)+AI19)+(AI18*AJ$4*$C$18)+SUMIFS(Investments!$D:$D,Investments!$B:$B,$A19,Investments!$C:$C,"ETH",Investments!$A:$A,AJ$8) | AK19: =(AJ19*AK$4*(1-$B19)+AJ19)+(AJ18*AK$4*$C$18)+SUMIFS(Investments!$D:$D,Investments!$B:$B,$A19,Investments!$C:$C,"ETH",Investments!$A:$A,AK$8) | AL19: =(AK19*AL$4*(1-$B19)+AK19)+(AK18*AL$4*$C$18)+SUMIFS(Investments!$D:$D,Investments!$B:$B,$A19,Investments!$C:$C,"ETH",Investments!$A:$A,AL$8) | AM19: =(AL19*AM$4*(1-$B19)+AL19)+(AL18*AM$4*$C$18)+SUMIFS(Investments!$D:$D,Investments!$B:$B,$A19,Investments!$C:$C,"ETH",Investments!$A:$A,AM$8) | AN19: =(AM19*AN$4*(1-$B19)+AM19)+(AM18*AN$4*$C$18)+SUMIFS(Investments!$D:$D,Investments!$B:$B,$A19,Investments!$C:$C,"ETH",Investments!$A:$A,AN$8) | AO19: =(AN19*AO$4*(1-$B19)+AN19)+(AN18*AO$4*$C$18)+SUMIFS(Investments!$D:$D,Investments!$B:$B,$A19,Investments!$C:$C,"ETH",Investments!$A:$A,AO$8)
A20: Tomer Zur | B20: 0.2 | D20: 0 | E20: =D20*$E$4*(1-$B20)+D20 | F20: =E20*$F$4*(1-$B20)+E20 | G20: =F20*$G$4*(1-$B20)+F20 | H20: =G20*$H$4*(1-$B20)+G20 | I20: =H20*$I$4*(1-$B20)+H20 | J20: =I20*$J$4*(1-$B20)+I20 | K20: =J20*$K$4*(1-$B20)+J20 | L20: =K20*$L$4*(1-$B20)+K20 | M20: =L20*$M$4*(1-$B20)+L20 | N20: =M20*$N$4*(1-$B20)+M20+63.1 | O20: =N20*$O$4*(1-$B20)+N20 | P20: =O20*$P$4*(1-$B20)+O20 | Q20: =P20*$Q$4*(1-$B20)+P20+10.051 | R20: =Q20*$R$4*(1-$B20)+Q20+64.27 | S20: =R20*$S$4*(1-$B20)+R20 | T20: =S20*$T$4*(1-$B20)+S20+6.5417 | U20: =T20*$U$4*(1-$B20)+T20+6.4 | V20: =U20*$V$4*(1-$B20)+U20 | W20: =V20*$W$4*(1-$B20)+V20 | X20: =W20*$X$4*(1-$B20)+W20+6.9519 | Y20: =X20*$Y$4*(1-$B20)+X20+7.6215 | Z20: =Y20*$Z$4*(1-$B20)+Y20+10.224 | AA20: =Z20*$AA$4*(1-$B20)+Z20+6.234 | AB20: =AA20*$AB$4*(1-$B20)+AA20 | AC20: =AB20*$AC$4*(1-$B20)+AB20 | AD20: =AC20*$AD$4*(1-$B20)+AC20+9.143 | AE20: =AD20*$AE$4*(1-$B20)+AD20 | AF20: =AE20*$AF$4*(1-$B20)+AE20 | AG20: =AF20*$AG$4*(1-$B20)+AF20 | AH20: =AG20*$AH$4*(1-$B20)+AG20 | AI20: =AH20*$AI$4*(1-$B20)+AH20 | AJ20: =AI20*AJ$4*(1-$B20)+AI20+SUMIFS(Investments!$D:$D,Investments!$B:$B,$A20,Investments!$C:$C,"ETH",Investments!$A:$A,AJ$8) | AK20: =AJ20*AK$4*(1-$B20)+AJ20+SUMIFS(Investments!$D:$D,Investments!$B:$B,$A20,Investments!$C:$C,"ETH",Investments!$A:$A,AK$8) | AL20: =AK20*AL$4*(1-$B20)+AK20+SUMIFS(Investments!$D:$D,Investments!$B:$B,$A20,Investments!$C:$C,"ETH",Investments!$A:$A,AL$8) | AM20: =AL20*AM$4*(1-$B20)+AL20+SUMIFS(Investments!$D:$D,Investments!$B:$B,$A20,Investments!$C:$C,"ETH",Investments!$A:$A,AM$8) | AN20: =AM20*AN$4*(1-$B20)+AM20+SUMIFS(Investments!$D:$D,Investments!$B:$B,$A20,Investments!$C:$C,"ETH",Investments!$A:$A,AN$8) | AO20: =AN20*AO$4*(1-$B20)+AN20+SUMIFS(Investments!$D:$D,Investments!$B:$B,$A20,Investments!$C:$C,"ETH",Investments!$A:$A,AO$8)
A21: Sam Johnson | B21: 0.16 | C21: 0.04 | D21: 0 | E21: =D21*$E$4*(1-$B21)+D21 | F21: =E21*$F$4*(1-$B21)+E21 | G21: =F21*$G$4*(1-$B21)+F21 | H21: =G21*$H$4*(1-$B21)+G21 | I21: =H21*$I$4*(1-$B21)+H21 | J21: =I21*$J$4*(1-$B21)+I21 | K21: =J21*$K$4*(1-$B21)+J21 | L21: =K21*$L$4*(1-$B21)+K21 | M21: =L21*$M$4*(1-$B21)+L21 | N21: =M21*$N$4*(1-$B21)+M21 | O21: =N21*$O$4*(1-$B21)+N21 | P21: =O21*$P$4*(1-$B21)+O21 | Q21: =P21*$Q$4*(1-$B21)+P21 | R21: =Q21*$R$4*(1-$B21)+Q21 | S21: =R21*$S$4*(1-$B21)+R21 | T21: =S21*$T$4*(1-$B21)+S21 | U21: =T21*$U$4*(1-$B21)+T21 | V21: =U21*$V$4*(1-$B21)+U21 | W21: =V21*$W$4*(1-$B21)+V21 | X21: =W21*$X$4*(1-$B21)+W21 | Y21: =X21*$Y$4*(1-$B21)+X21 | Z21: =Y21*$Z$4*(1-$B21)+Y21 | AA21: =Z21*$AA$4*(1-$B21-$C21)+Z21+78 | AB21: =AA21*$AB$4*(1-$B21-$C21)+AA21+35 | AC21: =AB21*$AC$4*(1-$B21-$C21)+AB21+33 | AD21: =AC21*$AD$4*(1-$B21-$C21)+AC21 | AE21: =AD21*$AE$4*(1-$B21-$C21)+AD21 | AF21: =AE21*$AF$4*(1-$B21-$C21)+AE21+34 | AG21: =AF21*$AG$4*(1-$B21-$C21)+AF21+32.5 | AH21: =AG21*$AH$4*(1-$B21-$C21)+AG21 | AI21: =AH21*$AI$4*(1-$B21-$C21)+AH21-(AH21*$AI$4*(1-$B21-$C21)+AH21) | AJ21: =AI21*AJ$4*(1-$B21-$C21)+AI21+SUMIFS(Investments!$D:$D,Investments!$B:$B,$A21,Investments!$C:$C,"ETH",Investments!$A:$A,AJ$8) | AK21: =AJ21*AK$4*(1-$B21-$C21)+AJ21+SUMIFS(Investments!$D:$D,Investments!$B:$B,$A21,Investments!$C:$C,"ETH",Investments!$A:$A,AK$8) | AL21: =AK21*AL$4*(1-$B21-$C21)+AK21+SUMIFS(Investments!$D:$D,Investments!$B:$B,$A21,Investments!$C:$C,"ETH",Investments!$A:$A,AL$8) | AM21: =AL21*AM$4*(1-$B21-$C21)+AL21+SUMIFS(Investments!$D:$D,Investments!$B:$B,$A21,Investments!$C:$C,"ETH",Investments!$A:$A,AM$8) | AN21: =AM21*AN$4*(1-$B21-$C21)+AM21+SUMIFS(Investments!$D:$D,Investments!$B:$B,$A21,Investments!$C:$C,"ETH",Investments!$A:$A,AN$8) | AO21: =AN21*AO$4*(1-$B21-$C21)+AN21+SUMIFS(Investments!$D:$D,Investments!$B:$B,$A21,Investments!$C:$C,"ETH",Investments!$A:$A,AO$8)
A22: Ryan Van Der Wall | B22: 0.2 | D22: 0 | E22: =D22*$E$4*(1-$B22)+D22 | F22: =E22*$F$4*(1-$B22)+E22 | G22: =F22*$G$4*(1-$B22)+F22 | H22: =(G22*$H$4*(1-$B22)+G22)+(G21*$H$4*$C$16) | I22: =(H22*$I$4*(1-$B22)+H22)+(H21*$I$4*$C$16) | J22: =(I22*$I$4*(1-$B22)+I22)+(I21*$I$4*$C$16) | K22: =(J22*$K$4*(1-$B22)+J22)+(J21*$K$4*$C$21) | L22: =(K22*$L$4*(1-$B22)+K22)+(K21*$L$4*$C$21) | M22: =(L22*$M$4*(1-$B22)+L22)+(L21*$M$4*$C$21) | N22: =(M22*$N$4*(1-$B22)+M22)+(M21*$N$4*$C$21) | O22: =(N22*$O$4*(1-$B22)+N22)+(N21*$O$4*$C$21) | P22: =(O22*$P$4*(1-$B22)+O22)+(O21*$P$4*$C$21) | Q22: =(P22*$Q$4*(1-$B22)+P22)+(P21*$Q$4*$C$21) | R22: =(Q22*$R$4*(1-$B22)+Q22)+(Q21*$R$4*$C$21) | S22: =(R22*$S$4*(1-$B22)+R22)+(R21*$S$4*$C$21) | T22: =(S22*$T$4*(1-$B22)+S22)+(S21*$T$4*$C$21) | U22: =(T22*$U$4*(1-$B22)+T22)+(T21*$U$4*$C$21) | V22: =(U22*$V$4*(1-$B22)+U22)+(U21*$V$4*$C$21) | W22: =(V22*$W$4*(1-$B22)+V22)+(V21*$W$4*$C$21) | X22: =(W22*$X$4*(1-$B22)+W22)+(W21*$X$4*$C$21) | Y22: =(X22*$Y$4*(1-$B22)+X22)+(X21*$Y$4*$C$21) | Z22: =(Y22*$Z$4*(1-$B22)+Y22)+(Y21*$Z$4*$C$21) | AA22: =(Z22*$AA$4*(1-$B22)+Z22)+(Z21*$AA$4*$C$21) | AB22: =(AA22*$AB$4*(1-$B22)+AA22)+(AA21*$AB$4*$C$21) | AC22: =(AB22*$AC$4*(1-$B22)+AB22)+(AB21*$AC$4*$C$21) | AD22: =(AC22*$AD$4*(1-$B22)+AC22)+(AC21*$AD$4*$C$21) | AE22: =(AD22*$AE$4*(1-$B22)+AD22)+(AD21*$AE$4*$C$21) | AF22: =(AE22*$AF$4*(1-$B22)+AE22)+(AE21*$AF$4*$C$21) | AG22: =(AF22*$AG$4*(1-$B22)+AF22)+(AF21*$AG$4*$C$21) | AH22: =(AG22*$AH$4*(1-$B22)+AG22)+(AG21*$AH$4*$C$21) | AI22: =(AH22*$AI$4*(1-$B22)+AH22)+(AH21*$AI$4*$C$21) | AJ22: =(AI22*AJ$4*(1-$B22)+AI22)+(AI21*AJ$4*$C$21)+SUMIFS(Investments!$D:$D,Investments!$B:$B,$A22,Investments!$C:$C,"ETH",Investments!$A:$A,AJ$8) | AK22: =(AJ22*AK$4*(1-$B22)+AJ22)+(AJ21*AK$4*$C$21)+SUMIFS(Investments!$D:$D,Investments!$B:$B,$A22,Investments!$C:$C,"ETH",Investments!$A:$A,AK$8) | AL22: =(AK22*AL$4*(1-$B22)+AK22)+(AK21*AL$4*$C$21)+SUMIFS(Investments!$D:$D,Investments!$B:$B,$A22,Investments!$C:$C,"ETH",Investments!$A:$A,AL$8) | AM22: =(AL22*AM$4*(1-$B22)+AL22)+(AL21*AM$4*$C$21)+SUMIFS(Investments!$D:$D,Investments!$B:$B,$A22,Investments!$C:$C,"ETH",Investments!$A:$A,AM$8) | AN22: =(AM22*AN$4*(1-$B22)+AM22)+(AM21*AN$4*$C$21)+SUMIFS(Investments!$D:$D,Investments!$B:$B,$A22,Investments!$C:$C,"ETH",Investments!$A:$A,AN$8) | AO22: =(AN22*AO$4*(1-$B22)+AN22)+(AN21*AO$4*$C$21)+SUMIFS(Investments!$D:$D,Investments!$B:$B,$A22,Investments!$C:$C,"ETH",Investments!$A:$A,AO$8)
A23: Brandon Hood | B23: 0.2 | D23: 0 | E23: =D23*$E$4*(1-$B23)+D23 | F23: =E23*$F$4*(1-$B23)+E23 | G23: =F23*$G$4*(1-$B23)+F23 | H23: =G23*$H$4*(1-$B23)+G23 | I23: =H23*$I$4*(1-$B23)+H23 | J23: =I23*$J$4*(1-$B23)+I23 | K23: =J23*$K$4*(1-$B23)+J23 | L23: =K23*$L$4*(1-$B23)+K23 | M23: =L23*$M$4*(1-$B23)+L23 | N23: =M23*$N$4*(1-$B23)+M23 | O23: =N23*$O$4*(1-$B23)+N23 | P23: =O23*$P$4*(1-$B23)+O23 | Q23: =P23*$Q$4*(1-$B23)+P23 | R23: =Q23*$R$4*(1-$B23)+Q23 | S23: =R23*$S$4*(1-$B23)+R23 | T23: =S23*$T$4*(1-$B23)+S23 | U23: =T23*$U$4*(1-$B23)+T23 | V23: =U23*$V$4*(1-$B23)+U23 | W23: =V23*$W$4*(1-$B23)+V23 | X23: =W23*$X$4*(1-$B23)+W23 | Y23: =X23*$Y$4*(1-$B23)+X23 | Z23: =Y23*$Z$4*(1-$B23)+Y23 | AA23: =Z23*$AA$4*(1-$B23)+Z23 | AB23: =AA23*$AB$4*(1-$B23)+AA23 | AC23: =AB23*$AC$4*(1-$B23)+AB23 | AD23: =AC23*$AD$4*(1-$B23)+AC23 | AE23: =AD23*$AE$4*(1-$B23)+AD23+31.37 | AF23: =AE23*$AF$4*(1-$B23)+AE23 | AG23: =AF23*$AG$4*(1-$B23)+AF23 | AH23: =AG23*$AH$4*(1-$B23)+AG23 | AI23: =AH23*$AI$4*(1-$B23)+AH23 | AJ23: =AI23*AJ$4*(1-$B23)+AI23+SUMIFS(Investments!$D:$D,Investments!$B:$B,$A23,Investments!$C:$C,"ETH",Investments!$A:$A,AJ$8) | AK23: =AJ23*AK$4*(1-$B23)+AJ23+SUMIFS(Investments!$D:$D,Investments!$B:$B,$A23,Investments!$C:$C,"ETH",Investments!$A:$A,AK$8) | AL23: =AK23*AL$4*(1-$B23)+AK23+SUMIFS(Investments!$D:$D,Investments!$B:$B,$A23,Investments!$C:$C,"ETH",Investments!$A:$A,AL$8) | AM23: =AL23*AM$4*(1-$B23)+AL23+SUMIFS(Investments!$D:$D,Investments!$B:$B,$A23,Investments!$C:$C,"ETH",Investments!$A:$A,AM$8) | AN23: =AM23*AN$4*(1-$B23)+AM23+SUMIFS(Investments!$D:$D,Investments!$B:$B,$A23,Investments!$C:$C,"ETH",Investments!$A:$A,AN$8) | AO23: =AN23*AO$4*(1-$B23)+AN23+SUMIFS(Investments!$D:$D,Investments!$B:$B,$A23,Investments!$C:$C,"ETH",Investments!$A:$A,AO$8)
A24: NSVO Holdings | B24: 0.2 | D24: 0 | E24: =D24*$E$4*(1-$B24)+D24 | F24: =E24*$F$4*(1-$B24)+E24 | G24: =F24*$G$4*(1-$B24)+F24 | H24: =G24*$H$4*(1-$B24)+G24 | I24: =H24*$I$4*(1-$B24)+H24 | J24: =I24*$J$4*(1-$B24)+I24 | K24: =J24*$K$4*(1-$B24)+J24 | L24: =K24*$L$4*(1-$B24)+K24 | M24: =L24*$M$4*(1-$B24)+L24 | N24: =M24*$N$4*(1-$B24)+M24 | O24: =N24*$O$4*(1-$B24)+N24 | P24: =O24*$P$4*(1-$B24)+O24 | Q24: =P24*$Q$4*(1-$B24)+P24 | R24: =Q24*$R$4*(1-$B24)+Q24 | S24: =R24*$S$4*(1-$B24)+R24 | T24: =S24*$T$4*(1-$B24)+S24 | U24: =T24*$U$4*(1-$B24)+T24 | V24: =U24*$V$4*(1-$B24)+U24 | W24: =V24*$W$4*(1-$B24)+V24 | X24: =W24*$X$4*(1-$B24)+W24 | Y24: =X24*$Y$4*(1-$B24)+X24 | Z24: =Y24*$Z$4*(1-$B24)+Y24 | AA24: =Z24*$AA$4*(1-$B24)+Z24 | AB24: =AA24*$AB$4*(1-$B24)+AA24 | AC24: =AB24*$AC$4*(1-$B24)+AB24 | AD24: =AC24*$AD$4*(1-$B24)+AC24 | AE24: =AD24*$AE$4*(1-$B24)+AD24 | AF24: =AE24*$AF$4*(1-$B24)+AE24 | AG24: =AF24*$AG$4*(1-$B24)+AF24 | AH24: =AG24*$AH$4*(1-$B24)+AG24 | AI24: =AH24*$AI$4*(1-$B24)+AH24 | AJ24: =AI24*AJ$4*(1-$B24)+AI24+SUMIFS(Investments!$D:$D,Investments!$B:$B,$A24,Investments!$C:$C,"ETH",Investments!$A:$A,AJ$8) | AK24: =AJ24*AK$4*(1-$B24)+AJ24+SUMIFS(Investments!$D:$D,Investments!$B:$B,$A24,Investments!$C:$C,"ETH",Investments!$A:$A,AK$8) | AL24: =AK24*AL$4*(1-$B24)+AK24+SUMIFS(Investments!$D:$D,Investments!$B:$B,$A24,Investments!$C:$C,"ETH",Investments!$A:$A,AL$8) | AM24: =AL24*AM$4*(1-$B24)+AL24+SUMIFS(Investments!$D:$D,Investments!$B:$B,$A24,Investments!$C:$C,"ETH",Investments!$A:$A,AM$8) | AN24: =AM24*AN$4*(1-$B24)+AM24+SUMIFS(Investments!$D:$D,Investments!$B:$B,$A24,Investments!$C:$C,"ETH",Investments!$A:$A,AN$8) | AO24: =AN24*AO$4*(1-$B24)+AN24+SUMIFS(Investments!$D:$D,Investments!$B:$B,$A24,Investments!$C:$C,"ETH",Investments!$A:$A,AO$8)
A25: ALOK PAVAN BATRA | B25: 0.2 | D25: 0 | E25: =D25*$E$4*(1-$B25)+D25 | F25: =E25*$F$4*(1-$B25)+E25 | G25: =F25*$G$4*(1-$B25)+F25 | H25: =G25*$H$4*(1-$B25)+G25 | I25: =H25*$I$4*(1-$B25)+H25 | J25: =I25*$J$4*(1-$B25)+I25 | K25: =J25*$K$4*(1-$B25)+J25 | L25: =K25*$L$4*(1-$B25)+K25 | M25: =L25*$M$4*(1-$B25)+L25 | N25: =M25*$N$4*(1-$B25)+M25 | O25: =N25*$O$4*(1-$B25)+N25 | P25: =O25*$P$4*(1-$B25)+O25 | Q25: =P25*$Q$4*(1-$B25)+P25 | R25: =Q25*$R$4*(1-$B25)+Q25 | S25: =R25*$S$4*(1-$B25)+R25 | T25: =S25*$T$4*(1-$B25)+S25 | U25: =T25*$U$4*(1-$B25)+T25 | V25: =U25*$V$4*(1-$B25)+U25 | W25: =V25*$W$4*(1-$B25)+V25 | X25: =W25*$X$4*(1-$B25)+W25 | Y25: =X25*$Y$4*(1-$B25)+X25 | Z25: =Y25*$Z$4*(1-$B25)+Y25 | AA25: =Z25*$AA$4*(1-$B25)+Z25 | AB25: =AA25*$AB$4*(1-$B25)+AA25 | AC25: =AB25*$AC$4*(1-$B25)+AB25 | AD25: =AC25*$AD$4*(1-$B25)+AC25 | AE25: =AD25*$AE$4*(1-$B25)+AD25 | AF25: =AE25*$AF$4*(1-$B25)+AE25 | AG25: =AF25*$AG$4*(1-$B25)+AF25 | AH25: =AG25*$AH$4*(1-$B25)+AG25 | AI25: =AH25*$AI$4*(1-$B25)+AH25 | AJ25: =AI25*AJ$4*(1-$B25)+AI25+SUMIFS(Investments!$D:$D,Investments!$B:$B,$A25,Investments!$C:$C,"ETH",Investments!$A:$A,AJ$8) | AK25: =AJ25*AK$4*(1-$B25)+AJ25+SUMIFS(Investments!$D:$D,Investments!$B:$B,$A25,Investments!$C:$C,"ETH",Investments!$A:$A,AK$8) | AL25: =AK25*AL$4*(1-$B25)+AK25+SUMIFS(Investments!$D:$D,Investments!$B:$B,$A25,Investments!$C:$C,"ETH",Investments!$A:$A,AL$8) | AM25: =AL25*AM$4*(1-$B25)+AL25+SUMIFS(Investments!$D:$D,Investments!$B:$B,$A25,Investments!$C:$C,"ETH",Investments!$A:$A,AM$8) | AN25: =AM25*AN$4*(1-$B25)+AM25+SUMIFS(Investments!$D:$D,Investments!$B:$B,$A25,Investments!$C:$C,"ETH",Investments!$A:$A,AN$8) | AO25: =AN25*AO$4*(1-$B25)+AN25+SUMIFS(Investments!$D:$D,Investments!$B:$B,$A25,Investments!$C:$C,"ETH",Investments!$A:$A,AO$8)
A26: Total AUM | D26: =SUM(D9:D25) | E26: =SUM(E9:E25) | F26: =SUM(F9:F25) | G26: =SUM(G9:G25) | H26: =SUM(H9:H25) | I26: =SUM(I9:I25) | J26: =SUM(J9:J25) | K26: =SUM(K9:K25) | ... AO26: =SUM(AO9:AO25)
A28: Indigo fees | D28: =IFERROR(D9/D$26,"") | E28: =IFERROR(E9/E$26,"") | F28: =IFERROR(F9/F$26,"") | G28: =IFERROR(G9/G$26,"") | H28: =IFERROR(H9/H$26,"") | I28: =IFERROR(I9/I$26,"") | J28: =IFERROR(J9/J$26,"") | K28: =IFERROR(K9/K$26,"") | ... AO28: =IFERROR(AO9/AO$26,"")
A29: Babak Eftekhari | D29: =IFERROR(D10/D$26,"") | E29: =IFERROR(E10/E$26,"") | F29: =IFERROR(F10/F$26,"") | G29: =IFERROR(G10/G$26,"") | H29: =IFERROR(H10/H$26,"") | I29: =IFERROR(I10/I$26,"") | J29: =IFERROR(J10/J$26,"") | K29: =IFERROR(K10/K$26,"") | ... AO29: =IFERROR(AO10/AO$26,"")
A30: Lars Ahlgreen | D30: =IFERROR(D11/D$26,"") | E30: =IFERROR(E11/E$26,"") | F30: =IFERROR(F11/F$26,"") | G30: =IFERROR(G11/G$26,"") | H30: =IFERROR(H11/H$26,"") | I30: =IFERROR(I11/I$26,"") | J30: =IFERROR(J11/J$26,"") | K30: =IFERROR(K11/K$26,"") | ... AO30: =IFERROR(AO11/AO$26,"")
A31: Indigo Main Fund | D31: =IFERROR(D12/D$26,"") | E31: =IFERROR(E12/E$26,"") | F31: =IFERROR(F12/F$26,"") | G31: =IFERROR(G12/G$26,"") | H31: =IFERROR(H12/H$26,"") | I31: =IFERROR(I12/I$26,"") | J31: =IFERROR(J12/J$26,"") | K31: =IFERROR(K12/K$26,"") | ... AO31: =IFERROR(AO12/AO$26,"")
A32: Nathanael Cohen | D32: =IFERROR(D13/D$26,"") | E32: =IFERROR(E13/E$26,"") | F32: =IFERROR(F13/F$26,"") | G32: =IFERROR(G13/G$26,"") | H32: =IFERROR(H13/H$26,"") | I32: =IFERROR(I13/I$26,"") | J32: =IFERROR(J13/J$26,"") | K32: =IFERROR(K13/K$26,"") | ... AO32: =IFERROR(AO13/AO$26,"")
A33: Jose Molla | D33: =IFERROR(D14/D$26,"") | E33: =IFERROR(E14/E$26,"") | F33: =IFERROR(F14/F$26,"") | G33: =IFERROR(G14/G$26,"") | H33: =IFERROR(H14/H$26,"") | I33: =IFERROR(I14/I$26,"") | J33: =IFERROR(J14/J$26,"") | K33: =IFERROR(K14/K$26,"") | ... AO33: =IFERROR(AO14/AO$26,"")
A34: Blondish | D34: =IFERROR(D15/D$26,"") | E34: =IFERROR(E15/E$26,"") | F34: =IFERROR(F15/F$26,"") | G34: =IFERROR(G15/G$26,"") | H34: =IFERROR(H15/H$26,"") | I34: =IFERROR(I15/I$26,"") | J34: =IFERROR(J15/J$26,"") | K34: =IFERROR(K15/K$26,"") | ... AO34: =IFERROR(AO15/AO$26,"")
A35: Advantage Blockchain | D35: =IFERROR(D16/D$26,"") | E35: =IFERROR(E16/E$26,"") | F35: =IFERROR(F16/F$26,"") | G35: =IFERROR(G16/G$26,"") | H35: =IFERROR(H16/H$26,"") | I35: =IFERROR(I16/I$26,"") | J35: =IFERROR(J16/J$26,"") | K35: =IFERROR(K16/K$26,"") | ... AO35: =IFERROR(AO16/AO$26,"")
A36: Alec Beckman | D36: =IFERROR(D17/D$26,"") | E36: =IFERROR(E17/E$26,"") | F36: =IFERROR(F17/F$26,"") | G36: =IFERROR(G17/G$26,"") | H36: =IFERROR(H17/H$26,"") | I36: =IFERROR(I17/I$26,"") | J36: =IFERROR(J17/J$26,"") | K36: =IFERROR(K17/K$26,"") | ... AO36: =IFERROR(AO17/AO$26,"")
A37: Paul Johnson | D37: =IFERROR(D18/D$26,"") | E37: =IFERROR(E18/E$26,"") | F37: =IFERROR(F18/F$26,"") | G37: =IFERROR(G18/G$26,"") | H37: =IFERROR(H18/H$26,"") | I37: =IFERROR(I18/I$26,"") | J37: =IFERROR(J18/J$26,"") | K37: =IFERROR(K18/K$26,"") | ... AO37: =IFERROR(AO18/AO$26,"")
A38: Alex Jacobs | D38: =IFERROR(D19/D$26,"") | E38: =IFERROR(E19/E$26,"") | F38: =IFERROR(F19/F$26,"") | G38: =IFERROR(G19/G$26,"") | H38: =IFERROR(H19/H$26,"") | I38: =IFERROR(I19/I$26,"") | J38: =IFERROR(J19/J$26,"") | K38: =IFERROR(K19/K$26,"") | ... AO38: =IFERROR(AO19/AO$26,"")
A39: Tomer Zur | D39: =IFERROR(D20/D$26,"") | E39: =IFERROR(E20/E$26,"") | F39: =IFERROR(F20/F$26,"") | G39: =IFERROR(G20/G$26,"") | H39: =IFERROR(H20/H$26,"") | I39: =IFERROR(I20/I$26,"") | J39: =IFERROR(J20/J$26,"") | K39: =IFERROR(K20/K$26,"") | ... AO39: =IFERROR(AO20/AO$26,"")
... A44: ALOK PAVAN BATRA | D44: =IFERROR(D25/D$26,"") | E44: =IFERROR(E25/E$26,"") | F44: =IFERROR(F25/F$26,"") | G44: =IFERROR(G25/G$26,"") | H44: =IFERROR(H25/H$26,"") | I44: =IFERROR(I25/I$26,"") | J44: =IFERROR(J25/J$26,"") | K44: =IFERROR(K25/K$26,"") | ... AO44: =IFERROR(AO25/AO$26,"")
A45: Total AUM | D45: =SUM(D28:D44) | E45: =SUM(E28:E44) | F45: =SUM(F28:F44) | G45: =SUM(G28:G44) | H45: =SUM(H28:H44) | I45: =SUM(I28:I44) | J45: =SUM(J28:J44) | K45: =SUM(K28:K44) | ... AO45: =SUM(AO28:AO44)

Sheet USDT Yield Fund
A1: AUM Before | D1: 0 | E1: =(D3*8.5%/12/30*14)+D3 | F1: 136384.9 | G1: 995679.39 | H1: 1243863 | I1: 1827189 | J1: 1828196 | K1: 1975715 | L1: 2004890 | M1: 2124583 | N1: 2138665 | O1: 2153219 | P1: 2155208 | Q1: 2159126 | R1: 2181753 | S1: 2156595 | T1: 2259974 | U1: 2374584 | V1: 2375129 | W1: 2261906 | X1: 2300362 | Y1: 3141094 | Z1: 3096047 | AA1: 3402181 | AB1: 3357086 | AC1: 3407816 | AD1: 3337879 | AE1: 3444580 | AF1: 3448495 | AG1: 3302426 | AH1: 3307337 | AI1: 3194608 | AJ1: 7402657 | AK1: 8003972 | AL1: 8420322 | AM1: 8420322 | AN1: 9133049 | AO1: 9113619 | AP1: 9672597 | AQ1: 9801255 | AR1: 10325522 | AS1: 10336447 | AT1: 10436447
A2: Top Up / Withdrawals | D2: =SUMIFS(Investments!$D:$D,Investments!$C:$C,"USDT",Investments!$A:$A,D$8) | E2: =SUMIFS(Investments!$D:$D,Investments!$C:$C,"USDT",Investments!$A:$A,E$8) | F2: =SUMIFS(Investments!$D:$D,Investments!$C:$C,"USDT",Investments!$A:$A,F$8) | G2: =SUMIFS(Investments!$D:$D,Investments!$C:$C,"USDT",Investments!$A:$A,G$8) | H2: =SUMIFS(Investments!$D:$D,Investments!$C:$C,"USDT",Investments!$A:$A,H$8) | I2: =SUMIFS(Investments!$D:$D,Investments!$C:$C,"USDT",Investments!$A:$A,I$8) | J2: =SUMIFS(Investments!$D:$D,Investments!$C:$C,"USDT",Investments!$A:$A,J$8) | K2: =SUMIFS(Investments!$D:$D,Investments!$C:$C,"USDT",Investments!$A:$A,K$8) | ... AT2: =SUMIFS(Investments!$D:$D,Investments!$C:$C,"USDT",Investments!$A:$A,AT$8)
A3: AUM After | D3: =D1+D2 | E3: =E1+E2 | F3: =F1+F2 | G3: =G1+G2 | H3: =H1+H2 | I3: =I1+I2 | J3: =J1+J2 | K3: =K1+K2 | ... AT3: =AT1+AT2
A4: Gross Performance | D4: 1 | E4: =(E1*$D$4/D3)-100% | F4: =(F1*$D$4/E1)-100% | G4: =(G1*$D$4/F3)-100% | H4: =(H1*$D$4/G3)-100% | I4: =(I1*$D$4/H3)-100% | J4: =(J1*$D$4/I1)-100% | K4: =(K1*$D$4/J3)-100% | L4: =(L1*$D$4/K3)-100% | M4: =(M1*$D$4/L3)-100% | N4: =(N1*$D$4/M1)-100% | O4: =(O1*$D$4/N3)-100% | P4: =(P1*$D$4/O1)-100% | Q4: =(Q1*$D$4/P3)-100% | R4: =(R1*$D$4/Q3)-100% | S4: =(S1*$D$4/R3)-100% | T4: =(T1*$D$4/S3)-100% | U4: =(U1*$D$4/T3)-100% | V4: =(V1*$D$4/U1)-100% | W4: =(W1*$D$4/V3)-100% | X4: =(X1*$D$4/W3)-100% | Y4: =(Y1*$D$4/X3)-100% | Z4: =(Z1*$D$4/Y3)-100% | AA4: =(AA1*$D$4/Z3)-100% | AB4: =(AB1*$D$4/AA3)-100% | AC4: =(AC1*$D$4/AB3)-100% | AD4: =(AD1*$D$4/AC3)-100% | AE4: =(AE1*$D$4/AD3)-100% | AF4: =(AF1*$D$4/AE1)-100% | AG4: =(AG1*$D$4/AF3)-100% | AH4: =(AH1-AG3)/AG3 | AI4: =(AI1-AH3)/AH3 | AJ4: =(AJ1-AI3)/AI3 | AK4: =(AK1-AJ3)/AJ3 | AL4: =(AL1-AK3)/AK3 | AM4: =(AM1-AL3)/AL3 | AN4: =(AN1-AM3)/AM3 | AO4: =(AO1-AN3)/AN3 | ... AT4: =(AT1-AS3)/AS3
A5: Net Performance | E5: =E4*0.8 | F5: =F4*0.8 | G5: =G4*0.8 | H5: =H4*0.8 | I5: =I4*0.8 | J5: =J4*0.8 | K5: =K4*0.8 | L5: =L4*0.8 | ... AT5: =AT4*0.8
A6: Yearly APY | E6: =E4*12 | F6: =F4*12 | G6: =G4*12 | H6: =H4*12 | I6: =I4*12 | J6: =J4*12 | K6: =K4*12 | L6: =L4*12 | ... AT6: =AT4*12
A7: Comments | D7: Babak invest 135,726.75 | F7: julien grunebaum : 109392 daniele francilia : 109776 pierre bezencon : 109333 matthew beatty : 255504 bo kriek : 273807 | G7: Dario: 199,659.72 Babak: 46,955.28 | H7: alain bensimon : 136737 anne cecile noique : 222687 terance chen : 219747 | J7: INDIGO Ventures: $130,000 Babak top-up: $10,000 | K7: Matthew Beatty: +25,900 USDC | L7: INDIGO Main Fund: +$111,370 | N7: Babak top-up: $10,000 | P7: INDIGO Ventures: $-100,000 Sacha Oshry: +$100,000 | Q7: Babak top-up: $20,000 | R7: Ventures withdrawal : $32,594.55 Ventures Top-up : $5,000 Total : - $27,594.55 | S7: Invest HALLEY86 : $99,990 | T7: Jose Molla USDT 97,695.00 Babak Eftekhari USDT 10,450.00 | V7: INDIGO LP Account worth : 113 867.78 Withdraw INDIGO LP : 113 841.65 INDIGO take the delta : 26.13 | W7: Matthew Beatty USDT 35,300.00 | X7: Monica Levy Chicheportiche USDT 840,168.03 | Y7: Jose Molla USDT -50000 | Z7: Nath & Thomas USDT 299,915.77 | AA7: Jose Molla USDT -47,908.00 | AB7: Valeria Cruz USDT 50000 | AC7: Matthew Beatty USDT 18000 Nath & Thomas USDT -87,937.00 | AD7: Rabih Mokbel USDT 100,000.00 | AF7: Nath & Thomas withdrawal : -213,501.60 Thomas Puech investment : 106,750.80 | AH7: INDIGO Ventures : -5,115.04 Daniele Francilla : -114,867.59 | AI7: Sam Johnson USDT 4,200,000.00 | AJ7: Sam Johnson USDT 600,000.00 | AK7: Sam Johnson USDT 400,000.00 | AM7: Sam Johnson USDT 750,000.00 Thomas Puech USDT -47,373.77 | AN7: Indigo Fees USDT -20,000.00 | AO7: Sam Johnson USDT 550,000.00 | AQ7: Sam Johnson USDT 500,000.00
A8: Investors | B8: Fees | C8: IB | D8: 45824 | E8: 45839 | F8: 45852 | G8: 45857 | H8: 45861 | I8: 45869 | J8: 45873 | K8: 45883 | L8: 45888 | M8: 45901 | N8: 45924 | O8: 45930 | P8: 45936 | Q8: 45939 | R8: 45943 | S8: 45945 | T8: 45953 | U8: 45961 | V8: 45964 | W8: 45965 | X8: 45968 | Y8: 45969 | Z8: 45974 | AA8: 45982 | AB8: 45986 | AC8: 45987 | AD8: 45988 | AE8: 45991 | AF8: 45999 | AG8: 46023 | AH8: 46030 | AI8: 46041 | AJ8: 46048 | AK8: 46050 | AL8: 46054 | AM8: 46055 | AN8: 46059 | AO8: 46061 | AP8: 46066 | AQ8: 46076 | AR8: 46081 | AS8: 46086 | AT8: 46089
A9: Indigo Fees | B9: 0 | D9: 0 | E9: =D9*$E$4*1+D9+(D12*$E$4*$B$12)+(D13*$E$4*$B$13) | F9: =E9*$F$4*1+E9+(E10*$F$4*B10)+(E12*$F$4*$B$12)+(E13*$F$4*$B$13)+(E14*$F$4*$B$14)+(E15*$F$4*$B$15)+(E16*$F$4*$B$16)+(E11*$F$4*$B$11) | G9: =F9*$G$4*1+F9+(F10*$G$4*B10)+(F12*$G$4*$B$12)+(F13*$G$4*$B$13)+(F14*$G$4*$B$14)+(F15*$G$4*$B$15)+(F16*$G$4*$B$16)+(F17*$G$4*$B$17)+(F11*$G$4*$B$11) | H9: =G9*$H$4*1+G9+(G10*$H$4*B10)+(G12*$H$4*$B$12)+(G13*$H$4*$B$13)+(G14*$H$4*$B$14)+(G15*$H$4*$B$15)+(G16*$H$4*$B$16)+(G17*$H$4*$B$17)+(G18*$H$4*$B$18)+(G19*$H$4*$B$19)+(G20*$H$4*$B$20)+(G11*$H$4*$B$11) | I9: =H9*$I$4*1+H9+(H10*$I$4*B10)+(H12*$I$4*$B$12)+(H13*$I$4*$B$13)+(H14*$I$4*$B$14)+(H15*$I$4*$B$15)+(H16*$I$4*$B$16)+(H17*$I$4*$B$17)+(H18*$I$4*$B$18)+(H19*$I$4*$B$19)+(H20*$I$4*$B$20)+(H11*$I$4*$B$11) | J9: =I9*$J$4*1+I9+(I10*$J$4*$B$10)+(I12*$J$4*$B$12)+(I13*$J$4*$B$13)+(I14*$J$4*$B$14)+(I15*$J$4*$B$15)+(I16*$J$4*$B$16)+(I17*$J$4*$B$17)+(I18*$J$4*$B$18)+(I19*$J$4*$B$19)+(I20*$J$4*$B$20)+(I11*$J$4*$B$11) | K9: =J9*$K$4*1+J9+(J10*$K$4*$B$10)+(J12*$K$4*$B$12)+(J13*$K$4*$B$13)+(J14*$K$4*$B$14)+(J15*$K$4*$B$15)+(J16*$K$4*$B$16)+(J17*$K$4*$B$17)+(J18*$K$4*$B$18)+(J19*$K$4*$B$19)+(J20*$K$4*$B$20)+(J11*$K$4*$B$11) | L9: =K9*$L$4*1+K9+(K10*$L$4*$B$10)+(K12*$L$4*$B$12)+(K13*$L$4*$B$13)+(K14*$L$4*$B$14)+(K15*$L$4*$B$15)+(K16*$L$4*$B$16)+(K17*$L$4*$B$17)+(K18*$L$4*$B$18)+(K19*$L$4*$B$19)+(K20*$L$4*$B$20)+(K21*$L$4*$B$21)+(K22*$L$4*$B$22)+(K11*$L$4*$B$11) | M9: =L9*$M$4*1+L9+(L10*$M$4*$B$10)+(L12*$M$4*$B$12)+(L13*$M$4*$B$13)+(L14*$M$4*$B$14)+(L15*$M$4*$B$15)+(L16*$M$4*$B$16)+(L17*$M$4*$B$17)+(L18*$M$4*$B$18)+(L19*$M$4*$B$19)+(L20*$M$4*$B$20)+(L21*$M$4*$B$21)+(L22*$M$4*$B$22)+(L11*$M$4*$B$11) | N9: =M9*$N$4*1+M9+(M10*$N$4*$B$10)+(M12*$N$4*$B$12)+(M13*$N$4*$B$13)+(M14*$N$4*$B$14)+(M15*$N$4*$B$15)+(M16*$N$4*$B$16)+(M17*$N$4*$B$17)+(M18*$N$4*$B$18)+(M19*$N$4*$B$19)+(M20*$N$4*$B$20)+(M21*$N$4*$B$21)+(M22*$N$4*$B$22)+(M11*$N$4*$B$11) | O9: =N9*$O$4*1+N9+(N10*$O$4*$B$10)+(N12*$O$4*$B$12)+(N13*$O$4*$B$13)+(N14*$O$4*$B$14)+(N15*$O$4*$B$15)+(N16*$O$4*$B$16)+(N17*$O$4*$B$17)+(N18*$O$4*$B$18)+(N19*$O$4*$B$19)+(N20*$O$4*$B$20)+(N21*$O$4*$B$21)+(N22*$O$4*$B$22)+(N11*$O$4*$B$11) | P9: =O9*$P$4*1+O9+(O10*$P$4*$B$10)+(O12*$P$4*$B$12)+(O13*$P$4*$B$13)+(O14*$P$4*$B$14)+(O15*$P$4*$B$15)+(O16*$P$4*$B$16)+(O17*$P$4*$B$17)+(O18*$P$4*$B$18)+(O19*$P$4*$B$19)+(O20*$P$4*$B$20)+(O21*$P$4*$B$21)+(O22*$P$4*$B$22)+(O11*$P$4*$B$11) | Q9: =P9*$Q$4*1+P9+(P10*$Q$4*$B$10)+(P12*$Q$4*$B$12)+(P13*$Q$4*$B$13)+(P14*$Q$4*$B$14)+(P15*$Q$4*$B$15)+(P16*$Q$4*$B$16)+(P17*$Q$4*$B$17)+(P18*$Q$4*$B$18)+(P19*$Q$4*$B$19)+(P20*$Q$4*$B$20)+(P21*$Q$4*$B$21)+(P22*$Q$4*$B$22)+(P11*$Q$4*$B$11)+(P23*$Q$4*$B$23) | R9: =Q9*$R$4*1+Q9+(Q10*$R$4*$B$10)+(Q12*$R$4*$B$12)+(Q13*$R$4*$B$13)+(Q14*$R$4*$B$14)+(Q15*$R$4*$B$15)+(Q16*$R$4*$B$16)+(Q17*$R$4*$B$17)+(Q18*$R$4*$B$18)+(Q19*$R$4*$B$19)+(Q20*$R$4*$B$20)+(Q21*$R$4*$B$21)+(Q22*$R$4*$B$22)+(Q11*$R$4*$B$11)+(Q23*$R$4*$B$23) | S9: =R9*$S$4*1+R9+(R10*$S$4*$B$10)+(R12*$S$4*$B$12)+(R13*$S$4*$B$13)+(R14*$S$4*$B$14)+(R15*$S$4*$B$15)+(R16*$S$4*$B$16)+(R17*$S$4*$B$17)+(R18*$S$4*$B$18)+(R19*$S$4*$B$19)+(R20*$S$4*$B$20)+(R21*$S$4*$B$21)+(R22*$S$4*$B$22)+(R11*$S$4*$B$11)+(R23*$S$4*$B$23)+(R24*$S$4*$B$24) | T9: =S9*$T$4*1+S9+(S10*$T$4*$B$10)+(S12*$T$4*$B$12)+(S13*$T$4*$B$13)+(S14*$T$4*$B$14)+(S15*$T$4*$B$15)+(S16*$T$4*$B$16)+(S17*$T$4*$B$17)+(S18*$T$4*$B$18)+(S19*$T$4*$B$19)+(S20*$T$4*$B$20)+(S21*$T$4*$B$21)+(S22*$T$4*$B$22)+(S11*$T$4*$B$11)+(S23*$T$4*$B$23)+(S24*$T$4*$B$24) | U9: =T9*$U$4*1+T9+(T10*$U$4*$B$10)+(T12*$U$4*$B$12)+(T13*$U$4*$B$13)+(T14*$U$4*$B$14)+(T15*$U$4*$B$15)+(T16*$U$4*$B$16)+(T17*$U$4*$B$17)+(T18*$U$4*$B$18)+(T19*$U$4*$B$19)+(T20*$U$4*$B$20)+(T21*$U$4*$B$21)+(T22*$U$4*$B$22)+(T11*$U$4*$B$11)+(T23*$U$4*$B$23)+(T24*$U$4*$B$24)+(T25*$U$4*$B$25) | V9: =U9*$V$4*1+U9+(U10*$V$4*$B$10)+(U12*$V$4*$B$12)+(U13*$V$4*$B$13)+(U14*$V$4*$B$14)+(U15*$V$4*$B$15)+(U16*$V$4*$B$16)+(U17*$V$4*$B$17)+(U18*$V$4*$B$18)+(U19*$V$4*$B$19)+(U20*$V$4*$B$20)+(U21*$V$4*$B$21)+(U22*$V$4*$B$22)+(U11*$V$4*$B$11)+(U23*$V$4*$B$23)+(U24*$V$4*$B$24)+(U25*$V$4*$B$25)+(U22*$V$4*(1-$B22)+U22)-113841.65 | W9: =V9*$W$4*1+V9+(V10*$W$4*$B$10)+(V12*$W$4*$B$12)+(V13*$W$4*$B$13)+(V14*$W$4*$B$14)+(V15*$W$4*$B$15)+(V16*$W$4*$B$16)+(V17*$W$4*$B$17)+(V18*$W$4*$B$18)+(V19*$W$4*$B$19)+(V20*$W$4*$B$20)+(V21*$W$4*$B$21)+(V22*$W$4*$B$22)+(V11*$W$4*$B$11)+(V23*$W$4*$B$23)+(V24*$W$4*$B$24)+(V25*$W$4*$B$25) | X9: =W9*$X$4*1+W9+(W10*$X$4*$B$10)+(W12*$X$4*$B$12)+(W13*$X$4*$B$13)+(W14*$X$4*$B$14)+(W15*$X$4*$B$15)+(W16*$X$4*$B$16)+(W17*$X$4*$B$17)+(W18*$X$4*$B$18)+(W19*$X$4*$B$19)+(W20*$X$4*$B$20)+(W21*$X$4*$B$21)+(W22*$X$4*$B$22)+(W11*$X$4*$B$11)+(W23*$X$4*$B$23)+(W24*$X$4*$B$24)+(W25*$X$4*$B$25)+(W26*$X$4*$B$26) | Y9: =X9*$Y$4*1+X9+(X10*$Y$4*$B$10)+(X12*$Y$4*$B$12)+(X13*$Y$4*$B$13)+(X14*$Y$4*$B$14)+(X15*$Y$4*$B$15)+(X16*$Y$4*$B$16)+(X17*$Y$4*$B$17)+(X18*$Y$4*$B$18)+(X19*$Y$4*$B$19)+(X20*$Y$4*$B$20)+(X21*$Y$4*$B$21)+(X22*$Y$4*$B$22)+(X11*$Y$4*$B$11)+(X23*$Y$4*$B$23)+(X24*$Y$4*$B$24)+(X25*$Y$4*$B$25)+(X26*$Y$4*$B$26) | Z9: =Y9*$Z$4*1+Y9+(Y10*$Z$4*$B$10)+(Y12*$Z$4*$B$12)+(Y13*$Z$4*$B$13)+(Y14*$Z$4*$B$14)+(Y15*$Z$4*$B$15)+(Y16*$Z$4*$B$16)+(Y17*$Z$4*$B$17)+(Y18*$Z$4*$B$18)+(Y19*$Z$4*$B$19)+(Y20*$Z$4*$B$20)+(Y21*$Z$4*$B$21)+(Y22*$Z$4*$B$22)+(Y11*$Z$4*$B$11)+(Y23*$Z$4*$B$23)+(Y24*$Z$4*$B$24)+(Y25*$Z$4*$B$25)+(Y26*$Z$4*$B$26)+(Y27*$Z$4*$B$27)+(Y28*$Z$4*$B$28) | AA9: =Z9*$AA$4*1+Z9+(Z10*$AA$4*$B$10)+(Z12*$AA$4*$B$12)+(Z13*$AA$4*$B$13)+(Z14*$AA$4*$B$14)+(Z15*$AA$4*$B$15)+(Z16*$AA$4*$B$16)+(Z17*$AA$4*$B$17)+(Z18*$AA$4*$B$18)+(Z19*$AA$4*$B$19)+(Z20*$AA$4*$B$20)+(Z21*$AA$4*$B$21)+(Z22*$AA$4*$B$22)+(Z11*$AA$4*$B$11)+(Z23*$AA$4*$B$23)+(Z24*$AA$4*$B$24)+(Z25*$AA$4*$B$25)+(Z26*$AA$4*$B$26)+(Z27*$AA$4*$B$27)+(Z28*$AA$4*$B$28)+(Z29*$AA$4*$B$29)+(Z30*$AA$4*$B$30) | AB9: =AA9*$AB$4*1+AA9+(AA10*$AB$4*$B$10)+(AA12*$AB$4*$B$12)+(AA13*$AB$4*$B$13)+(AA14*$AB$4*$B$14)+(AA15*$AB$4*$B$15)+(AA16*$AB$4*$B$16)+(AA17*$AB$4*$B$17)+(AA18*$AB$4*$B$18)+(AA19*$AB$4*$B$19)+(AA20*$AB$4*$B$20)+(AA21*$AB$4*$B$21)+(AA22*$AB$4*$B$22)+(AA11*$AB$4*$B$11)+(AA23*$AB$4*$B$23)+(AA24*$AB$4*$B$24)+(AA25*$AB$4*$B$25)+(AA26*$AB$4*$B$26)+(AA27*$AB$4*$B$27)+(AA28*$AB$4*$B$28)+(AA29*$AB$4*$B$29)+(AA30*$AB$4*$B$30) | AC9: =AB9*$AC$4*1+AB9+(AB10*$AC$4*$B$10)+(AB12*$AC$4*$B$12)+(AB13*$AC$4*$B$13)+(AB14*$AC$4*$B$14)+(AB15*$AC$4*$B$15)+(AB16*$AC$4*$B$16)+(AB17*$AC$4*$B$17)+(AB18*$AC$4*$B$18)+(AB19*$AC$4*$B$19)+(AB20*$AC$4*$B$20)+(AB21*$AC$4*$B$21)+(AB22*$AC$4*$B$22)+(AB11*$AC$4*$B$11)+(AB23*$AC$4*$B$23)+(AB24*$AC$4*$B$24)+(AB25*$AC$4*$B$25)+(AB26*$AC$4*$B$26)+(AB27*$AC$4*$B$27)+(AB28*$AC$4*$B$28)+(AB29*$AC$4*$B$29)+(AB30*$AC$4*$B$30)+(AB31*$AC$4*$B$31)+(AB32*$AC$4*$B$32) | AD9: =AC9*$AD$4*1+AC9+(AC10*$AD$4*$B$10)+(AC12*$AD$4*$B$12)+(AC13*$AD$4*$B$13)+(AC14*$AD$4*$B$14)+(AC15*$AD$4*$B$15)+(AC16*$AD$4*$B$16)+(AC17*$AD$4*$B$17)+(AC18*$AD$4*$B$18)+(AC19*$AD$4*$B$19)+(AC20*$AD$4*$B$20)+(AC21*$AD$4*$B$21)+(AC22*$AD$4*$B$22)+(AC11*$AD$4*$B$11)+(AC23*$AD$4*$B$23)+(AC24*$AD$4*$B$24)+(AC25*$AD$4*$B$25)+(AC26*$AD$4*$B$26)+(AC27*$AD$4*$B$27)+(AC28*$AD$4*$B$28)+(AC29*$AD$4*$B$29)+(AC30*$AD$4*$B$30)+(AC31*$AD$4*$B$31)+(AC32*$AD$4*$B$32) | AE9: =AD9*$AE$4*1+AD9+(AD10*$AE$4*$B$10)+(AD12*$AE$4*$B$12)+(AD13*$AE$4*$B$13)+(AD14*$AE$4*$B$14)+(AD15*$AE$4*$B$15)+(AD16*$AE$4*$B$16)+(AD17*$AE$4*$B$17)+(AD18*$AE$4*$B$18)+(AD19*$AE$4*$B$19)+(AD20*$AE$4*$B$20)+(AD21*$AE$4*$B$21)+(AD22*$AE$4*$B$22)+(AD11*$AE$4*$B$11)+(AD23*$AE$4*$B$23)+(AD24*$AE$4*$B$24)+(AD25*$AE$4*$B$25)+(AD26*$AE$4*$B$26)+(AD27*$AE$4*$B$27)+(AD28*$AE$4*$B$28)+(AD29*$AE$4*$B$29)+(AD30*$AE$4*$B$30)+(AD31*$AE$4*$B$31)+(AD32*$AE$4*$B$32) | AF9: =AE9*$AF$4*1+AE9+(AE10*$AF$4*$B$10)+(AE12*$AF$4*$B$12)+(AE13*$AF$4*$B$13)+(AE14*$AF$4*$B$14)+(AE15*$AF$4*$B$15)+(AE16*$AF$4*$B$16)+(AE17*$AF$4*$B$17)+(AE18*$AF$4*$B$18)+(AE19*$AF$4*$B$19)+(AE20*$AF$4*$B$20)+(AE21*$AF$4*$B$21)+(AE22*$AF$4*$B$22)+(AE11*$AF$4*$B$11)+(AE23*$AF$4*$B$23)+(AE24*$AF$4*$B$24)+(AE25*$AF$4*$B$25)+(AE26*$AF$4*$B$26)+(AE27*$AF$4*$B$27)+(AE28*$AF$4*$B$28)+(AE29*$AF$4*$B$29)+(AE30*$AF$4*$B$30)+(AE31*$AF$4*$B$31)+(AE32*$AF$4*$B$32)+(AE33*$AF$4*$B$33)+(AE27*$AF$4*(1-$B27)+AE27)-213501.6 | AG9: =AF9*$AG$4*1+AF9+(AF10*$AG$4*$B$10)+(AF12*$AG$4*$B$12)+(AF13*$AG$4*$B$13)+(AF14*$AG$4*$B$14)+(AF15*$AG$4*$B$15)+(AF16*$AG$4*$B$16)+(AF17*$AG$4*$B$17)+(AF18*$AG$4*$B$18)+(AF19*$AG$4*$B$19)+(AF20*$AG$4*$B$20)+(AF21*$AG$4*$B$21)+(AF22*$AG$4*$B$22)+(AF11*$AG$4*$B$11)+(AF23*$AG$4*$B$23)+(AF24*$AG$4*$B$24)+(AF25*$AG$4*$B$25)+(AF26*$AG$4*$B$26)+(AF27*$AG$4*$B$27)+(AF28*$AG$4*$B$28)+(AF29*$AG$4*$B$29)+(AF30*$AG$4*$B$30)+(AF31*$AG$4*$B$31)+(AF32*$AG$4*$B$32)+(AF33*$AG$4*$B$33) | AH9: =AG9*AH$4*1+AG9+(AG10*AH$4*$B$10)+(AG12*AH$4*$B$12)+(AG13*AH$4*$B$13)+(AG14*AH$4*$B$14)+(AG15*AH$4*$B$15)+(AG16*AH$4*$B$16)+(AG17*AH$4*$B$17)+(AG18*AH$4*$B$18)+(AG19*AH$4*$B$19)+(AG20*AH$4*$B$20)+(AG21*AH$4*$B$21)+(AG22*AH$4*$B$22)+(AG11*AH$4*$B$11)+(AG23*AH$4*$B$23)+(AG24*AH$4*$B$24)+(AG25*AH$4*$B$25)+(AG26*AH$4*$B$26)+(AG27*AH$4*$B$27)+(AG28*AH$4*$B$28)+(AG29*AH$4*$B$29)+(AG30*AH$4*$B$30)+(AG31*AH$4*$B$31)+(AG32*AH$4*$B$32)+(AG33*AH$4*$B$33)+SUMIFS(Investments!$D:$D,Investments!$B:$B,$A9,Investments!$C:$C,"USDT",Investments!$A:$A,AH$8)+AG13*AH$4*(1-$B13)+AG13-114867.59+AG21*AH$4*(1-$B21)+AG21-5115.04 | AI9: =AH9*AI$4*1+AH9+(AH10*AI$4*$B$10)+(AH12*AI$4*$B$12)+(AH13*AI$4*$B$13)+(AH14*AI$4*$B$14)+(AH15*AI$4*$B$15)+(AH16*AI$4*$B$16)+(AH17*AI$4*$B$17)+(AH18*AI$4*$B$18)+(AH19*AI$4*$B$19)+(AH20*AI$4*$B$20)+(AH21*AI$4*$B$21)+(AH22*AI$4*$B$22)+(AH11*AI$4*$B$11)+(AH23*AI$4*$B$23)+(AH24*AI$4*$B$24)+(AH25*AI$4*$B$25)+(AH26*AI$4*$B$26)+(AH27*AI$4*$B$27)+(AH28*AI$4*$B$28)+(AH29*AI$4*$B$29)+(AH30*AI$4*$B$30)+(AH31*AI$4*$B$31)+(AH32*AI$4*$B$32)+(AH33*AI$4*$B$33)+SUMIFS(Investments!$D:$D,Investments!$B:$B,$A9,Investments!$C:$C,"USDT",Investments!$A:$A,AI$8) | AJ9: =AI9*AJ$4*1+AI9+(AI10*AJ$4*$B$10)+(AI12*AJ$4*$B$12)+(AI13*AJ$4*$B$13)+(AI14*AJ$4*$B$14)+(AI15*AJ$4*$B$15)+(AI16*AJ$4*$B$16)+(AI17*AJ$4*$B$17)+(AI18*AJ$4*$B$18)+(AI19*AJ$4*$B$19)+(AI20*AJ$4*$B$20)+(AI21*AJ$4*$B$21)+(AI22*AJ$4*$B$22)+(AI11*AJ$4*$B$11)+(AI23*AJ$4*$B$23)+(AI24*AJ$4*$B$24)+(AI25*AJ$4*$B$25)+(AI26*AJ$4*$B$26)+(AI27*AJ$4*$B$27)+(AI28*AJ$4*$B$28)+(AI29*AJ$4*$B$29)+(AI30*AJ$4*$B$30)+(AI31*AJ$4*$B$31)+(AI32*AJ$4*$B$32)+(AI33*AJ$4*$B$33)+SUMIFS(Investments!$D:$D,Investments!$B:$B,$A9,Investments!$C:$C,"USDT",Investments!$A:$A,AJ$8) | AK9: =AJ9*AK$4*1+AJ9+(AJ10*AK$4*$B$10)+(AJ12*AK$4*$B$12)+(AJ13*AK$4*$B$13)+(AJ14*AK$4*$B$14)+(AJ15*AK$4*$B$15)+(AJ16*AK$4*$B$16)+(AJ17*AK$4*$B$17)+(AJ18*AK$4*$B$18)+(AJ19*AK$4*$B$19)+(AJ20*AK$4*$B$20)+(AJ21*AK$4*$B$21)+(AJ22*AK$4*$B$22)+(AJ11*AK$4*$B$11)+(AJ23*AK$4*$B$23)+(AJ24*AK$4*$B$24)+(AJ25*AK$4*$B$25)+(AJ26*AK$4*$B$26)+(AJ27*AK$4*$B$27)+(AJ28*AK$4*$B$28)+(AJ29*AK$4*$B$29)+(AJ30*AK$4*$B$30)+(AJ31*AK$4*$B$31)+(AJ32*AK$4*$B$32)+(AJ33*AK$4*$B$33)+SUMIFS(Investments!$D:$D,Investments!$B:$B,$A9,Investments!$C:$C,"USDT",Investments!$A:$A,AK$8) | AL9: =AK9*AL$4*1+AK9+(AK10*AL$4*$B$10)+(AK12*AL$4*$B$12)+(AK13*AL$4*$B$13)+(AK14*AL$4*$B$14)+(AK15*AL$4*$B$15)+(AK16*AL$4*$B$16)+(AK17*AL$4*$B$17)+(AK18*AL$4*$B$18)+(AK19*AL$4*$B$19)+(AK20*AL$4*$B$20)+(AK21*AL$4*$B$21)+(AK22*AL$4*$B$22)+(AK11*AL$4*$B$11)+(AK23*AL$4*$B$23)+(AK24*AL$4*$B$24)+(AK25*AL$4*$B$25)+(AK26*AL$4*$B$26)+(AK27*AL$4*$B$27)+(AK28*AL$4*$B$28)+(AK29*AL$4*$B$29)+(AK30*AL$4*$B$30)+(AK31*AL$4*$B$31)+(AK32*AL$4*$B$32)+(AK33*AL$4*$B$33)+SUMIFS(Investments!$D:$D,Investments!$B:$B,$A9,Investments!$C:$C,"USDT",Investments!$A:$A,AL$8) | AM9: =AL9*AM$4*1+AL9+(AL10*AM$4*$B$10)+(AL12*AM$4*$B$12)+(AL13*AM$4*$B$13)+(AL14*AM$4*$B$14)+(AL15*AM$4*$B$15)+(AL16*AM$4*$B$16)+(AL17*AM$4*$B$17)+(AL18*AM$4*$B$18)+(AL19*AM$4*$B$19)+(AL20*AM$4*$B$20)+(AL21*AM$4*$B$21)+(AL22*AM$4*$B$22)+(AL11*AM$4*$B$11)+(AL23*AM$4*$B$23)+(AL24*AM$4*$B$24)+(AL25*AM$4*$B$25)+(AL26*AM$4*$B$26)+(AL27*AM$4*$B$27)+(AL28*AM$4*$B$28)+(AL29*AM$4*$B$29)+(AL30*AM$4*$B$30)+(AL31*AM$4*$B$31)+(AL32*AM$4*$B$32)+(AL33*AM$4*$B$33)+(AL33*AM$4*(1-$B33)+AL33)-47373.77+SUMIFS(Investments!$D:$D,Investments!$B:$B,$A9,Investments!$C:$C,"USDT",Investments!$A:$A,AM$8) | AN9: =AM9*AN$4*1+AM9+(AM10*AN$4*$B$10)+(AM12*AN$4*$B$12)+(AM13*AN$4*$B$13)+(AM14*AN$4*$B$14)+(AM15*AN$4*$B$15)+(AM16*AN$4*$B$16)+(AM17*AN$4*$B$17)+(AM18*AN$4*$B$18)+(AM19*AN$4*$B$19)+(AM20*AN$4*$B$20)+(AM21*AN$4*$B$21)+(AM22*AN$4*$B$22)+(AM11*AN$4*$B$11)+(AM23*AN$4*$B$23)+(AM24*AN$4*$B$24)+(AM25*AN$4*$B$25)+(AM26*AN$4*$B$26)+(AM27*AN$4*$B$27)+(AM28*AN$4*$B$28)+(AM29*AN$4*$B$29)+(AM30*AN$4*$B$30)+(AM31*AN$4*$B$31)+(AM32*AN$4*$B$32)+(AM33*AN$4*$B$33)+SUMIFS(Investments!$D:$D,Investments!$B:$B,$A9,Investments!$C:$C,"USDT",Investments!$A:$A,AN$8) | AO9: =AN9*AO$4*1+AN9+(AN10*AO$4*$B$10)+(AN12*AO$4*$B$12)+(AN13*AO$4*$B$13)+(AN14*AO$4*$B$14)+(AN15*AO$4*$B$15)+(AN16*AO$4*$B$16)+(AN17*AO$4*$B$17)+(AN18*AO$4*$B$18)+(AN19*AO$4*$B$19)+(AN20*AO$4*$B$20)+(AN21*AO$4*$B$21)+(AN22*AO$4*$B$22)+(AN11*AO$4*$B$11)+(AN23*AO$4*$B$23)+(AN24*AO$4*$B$24)+(AN25*AO$4*$B$25)+(AN26*AO$4*$B$26)+(AN27*AO$4*$B$27)+(AN28*AO$4*$B$28)+(AN29*AO$4*$B$29)+(AN30*AO$4*$B$30)+(AN31*AO$4*$B$31)+(AN32*AO$4*$B$32)+(AN33*AO$4*$B$33)+SUMIFS(Investments!$D:$D,Investments!$B:$B,$A9,Investments!$C:$C,"USDT",Investments!$A:$A,AO$8) | AP9: =AO9*AP$4*1+AO9+(AO10*AP$4*$B$10)+(AO12*AP$4*$B$12)+(AO13*AP$4*$B$13)+(AO14*AP$4*$B$14)+(AO15*AP$4*$B$15)+(AO16*AP$4*$B$16)+(AO17*AP$4*$B$17)+(AO18*AP$4*$B$18)+(AO19*AP$4*$B$19)+(AO20*AP$4*$B$20)+(AO21*AP$4*$B$21)+(AO22*AP$4*$B$22)+(AO11*AP$4*$B$11)+(AO23*AP$4*$B$23)+(AO24*AP$4*$B$24)+(AO25*AP$4*$B$25)+(AO26*AP$4*$B$26)+(AO27*AP$4*$B$27)+(AO28*AP$4*$B$28)+(AO29*AP$4*$B$29)+(AO30*AP$4*$B$30)+(AO31*AP$4*$B$31)+(AO32*AP$4*$B$32)+(AO33*AP$4*$B$33)+SUMIFS(Investments!$D:$D,Investments!$B:$B,$A9,Investments!$C:$C,"USDT",Investments!$A:$A,AP$8) | AQ9: =AP9*AQ$4*1+AP9+(AP10*AQ$4*$B$10)+(AP12*AQ$4*$B$12)+(AP13*AQ$4*$B$13)+(AP14*AQ$4*$B$14)+(AP15*AQ$4*$B$15)+(AP16*AQ$4*$B$16)+(AP17*AQ$4*$B$17)+(AP18*AQ$4*$B$18)+(AP19*AQ$4*$B$19)+(AP20*AQ$4*$B$20)+(AP21*AQ$4*$B$21)+(AP22*AQ$4*$B$22)+(AP11*AQ$4*$B$11)+(AP23*AQ$4*$B$23)+(AP24*AQ$4*$B$24)+(AP25*AQ$4*$B$25)+(AP26*AQ$4*$B$26)+(AP27*AQ$4*$B$27)+(AP28*AQ$4*$B$28)+(AP29*AQ$4*$B$29)+(AP30*AQ$4*$B$30)+(AP31*AQ$4*$B$31)+(AP32*AQ$4*$B$32)+(AP33*AQ$4*$B$33)+SUMIFS(Investments!$D:$D,Investments!$B:$B,$A9,Investments!$C:$C,"USDT",Investments!$A:$A,AQ$8) | AR9: =AQ9*AR$4*1+AQ9+(AQ10*AR$4*$B$10)+(AQ12*AR$4*$B$12)+(AQ13*AR$4*$B$13)+(AQ14*AR$4*$B$14)+(AQ15*AR$4*$B$15)+(AQ16*AR$4*$B$16)+(AQ17*AR$4*$B$17)+(AQ18*AR$4*$B$18)+(AQ19*AR$4*$B$19)+(AQ20*AR$4*$B$20)+(AQ21*AR$4*$B$21)+(AQ22*AR$4*$B$22)+(AQ11*AR$4*$B$11)+(AQ23*AR$4*$B$23)+(AQ24*AR$4*$B$24)+(AQ25*AR$4*$B$25)+(AQ26*AR$4*$B$26)+(AQ27*AR$4*$B$27)+(AQ28*AR$4*$B$28)+(AQ29*AR$4*$B$29)+(AQ30*AR$4*$B$30)+(AQ31*AR$4*$B$31)+(AQ32*AR$4*$B$32)+(AQ33*AR$4*$B$33)+SUMIFS(Investments!$D:$D,Investments!$B:$B,$A9,Investments!$C:$C,"USDT",Investments!$A:$A,AR$8) | AS9: =AR9*AS$4*1+AR9+(AR10*AS$4*$B$10)+(AR12*AS$4*$B$12)+(AR13*AS$4*$B$13)+(AR14*AS$4*$B$14)+(AR15*AS$4*$B$15)+(AR16*AS$4*$B$16)+(AR17*AS$4*$B$17)+(AR18*AS$4*$B$18)+(AR19*AS$4*$B$19)+(AR20*AS$4*$B$20)+(AR21*AS$4*$B$21)+(AR22*AS$4*$B$22)+(AR11*AS$4*$B$11)+(AR23*AS$4*$B$23)+(AR24*AS$4*$B$24)+(AR25*AS$4*$B$25)+(AR26*AS$4*$B$26)+(AR27*AS$4*$B$27)+(AR28*AS$4*$B$28)+(AR29*AS$4*$B$29)+(AR30*AS$4*$B$30)+(AR31*AS$4*$B$31)+(AR32*AS$4*$B$32)+(AR33*AS$4*$B$33)+SUMIFS(Investments!$D:$D,Investments!$B:$B,$A9,Investments!$C:$C,"USDT",Investments!$A:$A,AS$8) | AT9: =AS9*AT$4*1+AS9+(AS10*AT$4*$B$10)+(AS12*AT$4*$B$12)+(AS13*AT$4*$B$13)+(AS14*AT$4*$B$14)+(AS15*AT$4*$B$15)+(AS16*AT$4*$B$16)+(AS17*AT$4*$B$17)+(AS18*AT$4*$B$18)+(AS19*AT$4*$B$19)+(AS20*AT$4*$B$20)+(AS21*AT$4*$B$21)+(AS22*AT$4*$B$22)+(AS11*AT$4*$B$11)+(AS23*AT$4*$B$23)+(AS24*AT$4*$B$24)+(AS25*AT$4*$B$25)+(AS26*AT$4*$B$26)+(AS27*AT$4*$B$27)+(AS28*AT$4*$B$28)+(AS29*AT$4*$B$29)+(AS30*AT$4*$B$30)+(AS31*AT$4*$B$31)+(AS32*AT$4*$B$32)+(AS33*AT$4*$B$33)+SUMIFS(Investments!$D:$D,Investments!$B:$B,$A9,Investments!$C:$C,"USDT",Investments!$A:$A,AT$8)+(AS28*AT$4*(1-$B28-$C28)+AS28)-7045353.8
A10: Babak Eftekhari | B10: 0.18 | C10: 0.02 | D10: =134026.75+1700 | E10: =D10*$E$4+D10 | F10: =E10*$F$4*(1-B10-C10)+E10 | G10: =F10*$G$4*(1-B10-C10)+F10+46955.28 | H10: =G10*$H$4*(1-B10-C10)+G10 | I10: =H10*$I$4*(1-B10-C10)+H10 | J10: =I10*$J$4*(1-$B10-$C10)+I10+10000 | K10: =J10*$K$4*(1-$B10-$C10)+J10 | L10: =K10*$L$4*(1-$B10-$C10)+K10 | M10: =L10*$M$4*(1-$B10-$C10)+L10 | N10: =M10*$N$4*(1-$B10-$C10)+M10+10000 | O10: =N10*$O$4*(1-$B10-$C10)+N10 | P10: =O10*$P$4*(1-$B10-$C10)+O10 | Q10: =P10*$Q$4*(1-$B10-$C10)+P10+20000 | R10: =Q10*$R$4*(1-$B10-$C10)+Q10 | S10: =R10*$S$4*(1-$B10-$C10)+R10 | T10: =S10*$T$4*(1-$B10-$C10)+S10+10450 | U10: =T10*$U$4*(1-$B10-$C10)+T10 | V10: =U10*$V$4*(1-$B10-$C10)+U10 | W10: =V10*$W$4*(1-$B10-$C10)+V10 | X10: =W10*$X$4*(1-$B10-$C10)+W10 | Y10: =X10*$Y$4*(1-$B10-$C10)+X10 | Z10: =Y10*$Z$4*(1-$B10-$C10)+Y10 | AA10: =Z10*$AA$4*(1-$B10-$C10)+Z10 | AB10: =AA10*$AB$4*(1-$B10-$C10)+AA10 | AC10: =AB10*$AC$4*(1-$B10-$C10)+AB10 | AD10: =AC10*$AD$4*(1-$B10-$C10)+AC10 | AE10: =AD10*$AE$4*(1-$B10-$C10)+AD10 | AF10: =AE10*$AF$4*(1-$B10-$C10)+AE10 | AG10: =AF10*$AG$4*(1-$B10-$C10)+AF10 | AH10: =AG10*AH$4*(1-$B10-$C10)+AG10+SUMIFS(Investments!$D:$D,Investments!$B:$B,$A10,Investments!$C:$C,"USDT",Investments!$A:$A,AH$8) | AI10: =AH10*AI$4*(1-$B10-$C10)+AH10+SUMIFS(Investments!$D:$D,Investments!$B:$B,$A10,Investments!$C:$C,"USDT",Investments!$A:$A,AI$8) | AJ10: =AI10*AJ$4*(1-$B10-$C10)+AI10+SUMIFS(Investments!$D:$D,Investments!$B:$B,$A10,Investments!$C:$C,"USDT",Investments!$A:$A,AJ$8) | AK10: =AJ10*AK$4*(1-$B10-$C10)+AJ10+SUMIFS(Investments!$D:$D,Investments!$B:$B,$A10,Investments!$C:$C,"USDT",Investments!$A:$A,AK$8) | AL10: =AK10*AL$4*(1-$B10-$C10)+AK10+SUMIFS(Investments!$D:$D,Investments!$B:$B,$A10,Investments!$C:$C,"USDT",Investments!$A:$A,AL$8) | AM10: =AL10*AM$4*(1-$B10-$C10)+AL10+SUMIFS(Investments!$D:$D,Investments!$B:$B,$A10,Investments!$C:$C,"USDT",Investments!$A:$A,AM$8) | AN10: =AM10*AN$4*(1-$B10-$C10)+AM10+SUMIFS(Investments!$D:$D,Investments!$B:$B,$A10,Investments!$C:$C,"USDT",Investments!$A:$A,AN$8) | AO10: =AN10*AO$4*(1-$B10-$C10)+AN10+SUMIFS(Investments!$D:$D,Investments!$B:$B,$A10,Investments!$C:$C,"USDT",Investments!$A:$A,AO$8) | ... AT10: =AS10*AT$4*(1-$B10-$C10)+AS10+SUMIFS(Investments!$D:$D,Investments!$B:$B,$A10,Investments!$C:$C,"USDT",Investments!$A:$A,AT$8)
A11: Lars Ahlgreen | B11: 0.2 | D11: 0 | E11: =D11*$E$4*(1-$B11)+D11 | F11: =E11*$F$4*(1-$B11)+E11+(E10*$F$4*$C$10) | G11: =F11*$G$4*(1-$B11)+F11+(F10*$G$4*$C$10) | H11: =G11*$H$4*(1-$B11)+G11+(G10*$H$4*$C$10) | I11: =H11*$I$4*(1-$B11)+H11+(H10*$I$4*$C$10) | J11: =(I11*$J$4*(1-$B11)+I11)+(I10*$J$4*$C$10) | K11: =(J11*$K$4*(1-$B11)+J11)+(J10*$K$4*$C$10) | L11: =(K11*$L$4*(1-$B11)+K11)+(K10*$L$4*$C$10) | M11: =(L11*$M$4*(1-$B11)+L11)+(L10*$M$4*$C$10) | N11: =(M11*$N$4*(1-$B11)+M11)+(M10*$N$4*$C$10) | O11: =(N11*$O$4*(1-$B11)+N11)+(N10*$O$4*$C$10) | P11: =(O11*$P$4*(1-$B11)+O11)+(O10*$P$4*$C$10) | Q11: =(P11*$Q$4*(1-$B11)+P11)+(P10*$Q$4*$C$10) | R11: =(Q11*$R$4*(1-$B11)+Q11)+(Q10*$R$4*$C$10) | S11: =(R11*$S$4*(1-$B11)+R11)+(R10*$S$4*$C$10) | T11: =(S11*$T$4*(1-$B11)+S11)+(S10*$T$4*$C$10) | U11: =(T11*$U$4*(1-$B11)+T11)+(T10*$U$4*$C$10) | V11: =(U11*$V$4*(1-$B11)+U11)+(U10*$V$4*$C$10) | W11: =(V11*$W$4*(1-$B11)+V11)+(V10*$W$4*$C$10) | X11: =(W11*$X$4*(1-$B11)+W11)+(W10*$X$4*$C$10) | Y11: =(X11*$Y$4*(1-$B11)+X11)+(X10*$Y$4*$C$10) | Z11: =(Y11*$Z$4*(1-$B11)+Y11)+(Y10*$Z$4*$C$10) | AA11: =(Z11*$AA$4*(1-$B11)+Z11)+(Z10*$AA$4*$C$10) | AB11: =(AA11*$AB$4*(1-$B11)+AA11)+(AA10*$AB$4*$C$10) | AC11: =(AB11*$AC$4*(1-$B11)+AB11)+(AB10*$AC$4*$C$10) | AD11: =(AC11*$AD$4*(1-$B11)+AC11)+(AC10*$AD$4*$C$10) | AE11: =(AD11*$AE$4*(1-$B11)+AD11)+(AD10*$AE$4*$C$10) | AF11: =(AE11*$AF$4*(1-$B11)+AE11)+(AE10*$AF$4*$C$10) | AG11: =(AF11*$AG$4*(1-$B11)+AF11)+(AF10*$AG$4*$C$10) | AH11: =(AG11*AH$4*(1-$B11)+AG11)+(AG10*AH$4*$C$10) | AI11: =(AH11*AI$4*(1-$B11)+AH11)+(AH10*AI$4*$C$10) | AJ11: =(AI11*AJ$4*(1-$B11)+AI11)+(AI10*AJ$4*$C$10) | AK11: =(AJ11*AK$4*(1-$B11)+AJ11)+(AJ10*AK$4*$C$10) | AL11: =(AK11*AL$4*(1-$B11)+AK11)+(AK10*AL$4*$C$10) | AM11: =(AL11*AM$4*(1-$B11)+AL11)+(AL10*AM$4*$C$10) | AN11: =(AM11*AN$4*(1-$B11)+AM11)+(AM10*AN$4*$C$10) | AO11: =(AN11*AO$4*(1-$B11)+AN11)+(AN10*AO$4*$C$10) | ... AT11: =(AS11*AT$4*(1-$B11)+AS11)+(AS10*AT$4*$C$10)
A12: Julien Grunebaum | B12: 0.1 | D12: 0 | E12: =D12*$E$4*(1-$B12)+D12 | F12: =E12*$F$4*(1-$B12)+E12+109392 | G12: =F12*$G$4*(1-$B12)+F12 | H12: =G12*$H$4*(1-$B12)+G12 | I12: =H12*$I$4*(1-$B12)+H12 | J12: =I12*$J$4*(1-$B12)+I12 | K12: =J12*$K$4*(1-$B12)+J12 | L12: =K12*$L$4*(1-$B12)+K12 | M12: =L12*$M$4*(1-$B12)+L12 | N12: =M12*$N$4*(1-$B12)+M12 | O12: =N12*$O$4*(1-$B12)+N12 | P12: =O12*$P$4*(1-$B12)+O12 | Q12: =P12*$Q$4*(1-$B12)+P12 | R12: =Q12*$R$4*(1-$B12)+Q12 | S12: =R12*$S$4*(1-$B12)+R12 | T12: =S12*$T$4*(1-$B12)+S12 | U12: =T12*$U$4*(1-$B12)+T12 | V12: =U12*$V$4*(1-$B12)+U12 | W12: =V12*$W$4*(1-$B12)+V12 | X12: =W12*$X$4*(1-$B12)+W12 | Y12: =X12*$Y$4*(1-$B12)+X12 | Z12: =Y12*$Z$4*(1-$B12)+Y12 | AA12: =Z12*$AA$4*(1-$B12)+Z12 | AB12: =AA12*$AB$4*(1-$B12)+AA12 | AC12: =AB12*$AC$4*(1-$B12)+AB12 | AD12: =AC12*$AD$4*(1-$B12)+AC12 | AE12: =AD12*$AE$4*(1-$B12)+AD12 | AF12: =AE12*$AF$4*(1-$B12)+AE12 | AG12: =AF12*$AG$4*(1-$B12)+AF12 | AH12: =AG12*AH$4*(1-$B12)+AG12+SUMIFS(Investments!$D:$D,Investments!$B:$B,$A12,Investments!$C:$C,"USDT",Investments!$A:$A,AH$8) | AI12: =AH12*AI$4*(1-$B12)+AH12+SUMIFS(Investments!$D:$D,Investments!$B:$B,$A12,Investments!$C:$C,"USDT",Investments!$A:$A,AI$8) | AJ12: =AI12*AJ$4*(1-$B12)+AI12+SUMIFS(Investments!$D:$D,Investments!$B:$B,$A12,Investments!$C:$C,"USDT",Investments!$A:$A,AJ$8) | AK12: =AJ12*AK$4*(1-$B12)+AJ12+SUMIFS(Investments!$D:$D,Investments!$B:$B,$A12,Investments!$C:$C,"USDT",Investments!$A:$A,AK$8) | AL12: =AK12*AL$4*(1-$B12)+AK12+SUMIFS(Investments!$D:$D,Investments!$B:$B,$A12,Investments!$C:$C,"USDT",Investments!$A:$A,AL$8) | AM12: =AL12*AM$4*(1-$B12)+AL12+SUMIFS(Investments!$D:$D,Investments!$B:$B,$A12,Investments!$C:$C,"USDT",Investments!$A:$A,AM$8) | AN12: =AM12*AN$4*(1-$B12)+AM12+SUMIFS(Investments!$D:$D,Investments!$B:$B,$A12,Investments!$C:$C,"USDT",Investments!$A:$A,AN$8) | AO12: =AN12*AO$4*(1-$B12)+AN12+SUMIFS(Investments!$D:$D,Investments!$B:$B,$A12,Investments!$C:$C,"USDT",Investments!$A:$A,AO$8) | ... AT12: =AS12*AT$4*(1-$B12)+AS12+SUMIFS(Investments!$D:$D,Investments!$B:$B,$A12,Investments!$C:$C,"USDT",Investments!$A:$A,AT$8)
A13: Daniele Francilia | B13: 0.1 | D13: 0 | E13: =D13*$E$4*(1-$B13)+D13 | F13: =E13*$F$4*(1-$B13)+E13+109776 | G13: =F13*$G$4*(1-$B13)+F13 | H13: =G13*$H$4*(1-$B13)+G13 | I13: =H13*$I$4*(1-$B13)+H13 | J13: =I13*$J$4*(1-$B13)+I13 | K13: =J13*$K$4*(1-$B13)+J13 | L13: =K13*$L$4*(1-$B13)+K13 | M13: =L13*$M$4*(1-$B13)+L13 | N13: =M13*$N$4*(1-$B13)+M13 | O13: =N13*$O$4*(1-$B13)+N13 | P13: =O13*$P$4*(1-$B13)+O13 | Q13: =P13*$Q$4*(1-$B13)+P13 | R13: =Q13*$R$4*(1-$B13)+Q13 | S13: =R13*$S$4*(1-$B13)+R13 | T13: =S13*$T$4*(1-$B13)+S13 | U13: =T13*$U$4*(1-$B13)+T13 | V13: =U13*$V$4*(1-$B13)+U13 | W13: =V13*$W$4*(1-$B13)+V13 | X13: =W13*$X$4*(1-$B13)+W13 | Y13: =X13*$Y$4*(1-$B13)+X13 | Z13: =Y13*$Z$4*(1-$B13)+Y13 | AA13: =Z13*$AA$4*(1-$B13)+Z13 | AB13: =AA13*$AB$4*(1-$B13)+AA13 | AC13: =AB13*$AC$4*(1-$B13)+AB13 | AD13: =AC13*$AD$4*(1-$B13)+AC13 | AE13: =AD13*$AE$4*(1-$B13)+AD13 | AF13: =AE13*$AF$4*(1-$B13)+AE13 | AG13: =AF13*$AG$4*(1-$B13)+AF13 | AH13: =AG13*AH$4*(1-$B13)+AG13-(AG13*AH$4*(1-$B13)+AG13) | AI13: =AH13*AI$4*(1-$B13)+AH13-(AH13*AI$4*(1-$B13)+AH13) | AJ13: =AI13*AJ$4*(1-$B13)+AI13-(AI13*AJ$4*(1-$B13)+AI13) | AK13: =AJ13*AK$4*(1-$B13)+AJ13-(AJ13*AK$4*(1-$B13)+AJ13) | AL13: =AK13*AL$4*(1-$B13)+AK13-(AK13*AL$4*(1-$B13)+AK13) | AM13: =AL13*AM$4*(1-$B13)+AL13-(AL13*AM$4*(1-$B13)+AL13) | AN13: =AM13*AN$4*(1-$B13)+AM13-(AM13*AN$4*(1-$B13)+AM13) | AO13: =AN13*AO$4*(1-$B13)+AN13-(AN13*AO$4*(1-$B13)+AN13) | ... AT13: =AS13*AT$4*(1-$B13)+AS13-(AS13*AT$4*(1-$B13)+AS13)
A14: Pierre Bezençon | B14: 0.1 | D14: 0 | E14: =D14*$E$4*(1-$B14)+D14 | F14: =E14*$F$4*(1-$B14)+E14+109333 | G14: =F14*$G$4*(1-$B14)+F14 | H14: =G14*$H$4*(1-$B14)+G14 | I14: =H14*$I$4*(1-$B14)+H14 | J14: =I14*$J$4*(1-$B14)+I14 | K14: =J14*$K$4*(1-$B14)+J14 | L14: =K14*$L$4*(1-$B14)+K14 | M14: =L14*$M$4*(1-$B14)+L14 | N14: =M14*$N$4*(1-$B14)+M14 | O14: =N14*$O$4*(1-$B14)+N14 | P14: =O14*$P$4*(1-$B14)+O14 | Q14: =P14*$Q$4*(1-$B14)+P14 | R14: =Q14*$R$4*(1-$B14)+Q14 | S14: =R14*$S$4*(1-$B14)+R14 | T14: =S14*$T$4*(1-$B14)+S14 | U14: =T14*$U$4*(1-$B14)+T14 | V14: =U14*$V$4*(1-$B14)+U14 | W14: =V14*$W$4*(1-$B14)+V14 | X14: =W14*$X$4*(1-$B14)+W14 | Y14: =X14*$Y$4*(1-$B14)+X14 | Z14: =Y14*$Z$4*(1-$B14)+Y14 | AA14: =Z14*$AA$4*(1-$B14)+Z14 | AB14: =AA14*$AB$4*(1-$B14)+AA14 | AC14: =AB14*$AC$4*(1-$B14)+AB14 | AD14: =AC14*$AD$4*(1-$B14)+AC14 | AE14: =AD14*$AE$4*(1-$B14)+AD14 | AF14: =AE14*$AF$4*(1-$B14)+AE14 | AG14: =AF14*$AG$4*(1-$B14)+AF14 | AH14: =AG14*AH$4*(1-$B14)+AG14+SUMIFS(Investments!$D:$D,Investments!$B:$B,$A14,Investments!$C:$C,"USDT",Investments!$A:$A,AH$8) | AI14: =AH14*AI$4*(1-$B14)+AH14+SUMIFS(Investments!$D:$D,Investments!$B:$B,$A14,Investments!$C:$C,"USDT",Investments!$A:$A,AI$8) | AJ14: =AI14*AJ$4*(1-$B14)+AI14+SUMIFS(Investments!$D:$D,Investments!$B:$B,$A14,Investments!$C:$C,"USDT",Investments!$A:$A,AJ$8) | AK14: =AJ14*AK$4*(1-$B14)+AJ14+SUMIFS(Investments!$D:$D,Investments!$B:$B,$A14,Investments!$C:$C,"USDT",Investments!$A:$A,AK$8) | AL14: =AK14*AL$4*(1-$B14)+AK14+SUMIFS(Investments!$D:$D,Investments!$B:$B,$A14,Investments!$C:$C,"USDT",Investments!$A:$A,AL$8) | AM14: =AL14*AM$4*(1-$B14)+AL14+SUMIFS(Investments!$D:$D,Investments!$B:$B,$A14,Investments!$C:$C,"USDT",Investments!$A:$A,AM$8) | AN14: =AM14*AN$4*(1-$B14)+AM14+SUMIFS(Investments!$D:$D,Investments!$B:$B,$A14,Investments!$C:$C,"USDT",Investments!$A:$A,AN$8) | AO14: =AN14*AO$4*(1-$B14)+AN14+SUMIFS(Investments!$D:$D,Investments!$B:$B,$A14,Investments!$C:$C,"USDT",Investments!$A:$A,AO$8) | ... AT14: =AS14*AT$4*(1-$B14)+AS14+SUMIFS(Investments!$D:$D,Investments!$B:$B,$A14,Investments!$C:$C,"USDT",Investments!$A:$A,AT$8)
A15: Matthew Beatty | B15: 0.1 | D15: 0 | E15: =D15*$E$4*(1-$B15)+D15 | F15: =E15*$F$4*(1-$B15)+E15+255504 | G15: =F15*$G$4*(1-$B15)+F15 | H15: =G15*$H$4*(1-$B15)+G15 | I15: =H15*$I$4*(1-$B15)+H15 | J15: =I15*$J$4*(1-$B15)+I15 | K15: =J15*$K$4*(1-$B15)+J15+25900 | L15: =K15*$L$4*(1-$B15)+K15 | M15: =L15*$M$4*(1-$B15)+L15 | N15: =M15*$N$4*(1-$B15)+M15 | O15: =N15*$O$4*(1-$B15)+N15 | P15: =O15*$P$4*(1-$B15)+O15 | Q15: =P15*$Q$4*(1-$B15)+P15 | R15: =Q15*$R$4*(1-$B15)+Q15 | S15: =R15*$S$4*(1-$B15)+R15 | T15: =S15*$T$4*(1-$B15)+S15 | U15: =T15*$U$4*(1-$B15)+T15 | V15: =U15*$V$4*(1-$B15)+U15 | W15: =V15*$W$4*(1-$B15)+V15+35300 | X15: =W15*$X$4*(1-$B15)+W15 | Y15: =X15*$Y$4*(1-$B15)+X15 | Z15: =Y15*$Z$4*(1-$B15)+Y15 | AA15: =Z15*$AA$4*(1-$B15)+Z15 | AB15: =AA15*$AB$4*(1-$B15)+AA15 | AC15: =AB15*$AC$4*(1-$B15)+AB15+18000 | AD15: =AC15*$AD$4*(1-$B15)+AC15 | AE15: =AD15*$AE$4*(1-$B15)+AD15 | AF15: =AE15*$AF$4*(1-$B15)+AE15 | AG15: =AF15*$AG$4*(1-$B15)+AF15 | AH15: =AG15*AH$4*(1-$B15)+AG15+SUMIFS(Investments!$D:$D,Investments!$B:$B,$A15,Investments!$C:$C,"USDT",Investments!$A:$A,AH$8) | AI15: =AH15*AI$4*(1-$B15)+AH15+SUMIFS(Investments!$D:$D,Investments!$B:$B,$A15,Investments!$C:$C,"USDT",Investments!$A:$A,AI$8) | AJ15: =AI15*AJ$4*(1-$B15)+AI15+SUMIFS(Investments!$D:$D,Investments!$B:$B,$A15,Investments!$C:$C,"USDT",Investments!$A:$A,AJ$8) | AK15: =AJ15*AK$4*(1-$B15)+AJ15+SUMIFS(Investments!$D:$D,Investments!$B:$B,$A15,Investments!$C:$C,"USDT",Investments!$A:$A,AK$8) | AL15: =AK15*AL$4*(1-$B15)+AK15+SUMIFS(Investments!$D:$D,Investments!$B:$B,$A15,Investments!$C:$C,"USDT",Investments!$A:$A,AL$8) | AM15: =AL15*AM$4*(1-$B15)+AL15+SUMIFS(Investments!$D:$D,Investments!$B:$B,$A15,Investments!$C:$C,"USDT",Investments!$A:$A,AM$8) | AN15: =AM15*AN$4*(1-$B15)+AM15+SUMIFS(Investments!$D:$D,Investments!$B:$B,$A15,Investments!$C:$C,"USDT",Investments!$A:$A,AN$8) | AO15: =AN15*AO$4*(1-$B15)+AN15+SUMIFS(Investments!$D:$D,Investments!$B:$B,$A15,Investments!$C:$C,"USDT",Investments!$A:$A,AO$8) | ... AT15: =AS15*AT$4*(1-$B15)+AS15+SUMIFS(Investments!$D:$D,Investments!$B:$B,$A15,Investments!$C:$C,"USDT",Investments!$A:$A,AT$8)
A16: Bo De kriek | B16: 0.1 | D16: 0 | E16: =D16*$E$4*(1-$B16)+D16 | F16: =E16*$F$4*(1-$B16)+E16+273807 | G16: =F16*$G$4*(1-$B16)+F16 | H16: =G16*$H$4*(1-$B16)+G16 | I16: =H16*$I$4*(1-$B16)+H16 | J16: =I16*$J$4*(1-$B16)+I16 | K16: =J16*$K$4*(1-$B16)+J16 | L16: =K16*$L$4*(1-$B16)+K16 | M16: =L16*$M$4*(1-$B16)+L16 | N16: =M16*$N$4*(1-$B16)+M16 | O16: =N16*$O$4*(1-$B16)+N16 | P16: =O16*$P$4*(1-$B16)+O16 | Q16: =P16*$Q$4*(1-$B16)+P16 | R16: =Q16*$R$4*(1-$B16)+Q16 | S16: =R16*$S$4*(1-$B16)+R16 | T16: =S16*$T$4*(1-$B16)+S16 | U16: =T16*$U$4*(1-$B16)+T16 | V16: =U16*$V$4*(1-$B16)+U16 | W16: =V16*$W$4*(1-$B16)+V16 | X16: =W16*$X$4*(1-$B16)+W16 | Y16: =X16*$Y$4*(1-$B16)+X16 | Z16: =Y16*$Z$4*(1-$B16)+Y16 | AA16: =Z16*$AA$4*(1-$B16)+Z16 | AB16: =AA16*$AB$4*(1-$B16)+AA16 | AC16: =AB16*$AC$4*(1-$B16)+AB16 | AD16: =AC16*$AD$4*(1-$B16)+AC16 | AE16: =AD16*$AE$4*(1-$B16)+AD16 | AF16: =AE16*$AF$4*(1-$B16)+AE16 | AG16: =AF16*$AG$4*(1-$B16)+AF16 | AH16: =AG16*AH$4*(1-$B16)+AG16+SUMIFS(Investments!$D:$D,Investments!$B:$B,$A16,Investments!$C:$C,"USDT",Investments!$A:$A,AH$8) | AI16: =AH16*AI$4*(1-$B16)+AH16+SUMIFS(Investments!$D:$D,Investments!$B:$B,$A16,Investments!$C:$C,"USDT",Investments!$A:$A,AI$8) | AJ16: =AI16*AJ$4*(1-$B16)+AI16+SUMIFS(Investments!$D:$D,Investments!$B:$B,$A16,Investments!$C:$C,"USDT",Investments!$A:$A,AJ$8) | AK16: =AJ16*AK$4*(1-$B16)+AJ16+SUMIFS(Investments!$D:$D,Investments!$B:$B,$A16,Investments!$C:$C,"USDT",Investments!$A:$A,AK$8) | AL16: =AK16*AL$4*(1-$B16)+AK16+SUMIFS(Investments!$D:$D,Investments!$B:$B,$A16,Investments!$C:$C,"USDT",Investments!$A:$A,AL$8) | AM16: =AL16*AM$4*(1-$B16)+AL16+SUMIFS(Investments!$D:$D,Investments!$B:$B,$A16,Investments!$C:$C,"USDT",Investments!$A:$A,AM$8) | AN16: =AM16*AN$4*(1-$B16)+AM16+SUMIFS(Investments!$D:$D,Investments!$B:$B,$A16,Investments!$C:$C,"USDT",Investments!$A:$A,AN$8) | AO16: =AN16*AO$4*(1-$B16)+AN16+SUMIFS(Investments!$D:$D,Investments!$B:$B,$A16,Investments!$C:$C,"USDT",Investments!$A:$A,AO$8) | ... AT16: =AS16*AT$4*(1-$B16)+AS16+SUMIFS(Investments!$D:$D,Investments!$B:$B,$A16,Investments!$C:$C,"USDT",Investments!$A:$A,AT$8)
A17: Dario Deiana | B17: 0.2 | D17: 0 | E17: =D17*$E$4*(1-$B17)+D17 | F17: =E17*$F$4*(1-$B17)+E17 | G17: =F17*$G$4*(1-$B17)+F17+199659.72 | H17: =G17*$H$4*(1-$B17)+G17 | I17: =H17*$I$4*(1-$B17)+H17 | J17: =I17*$J$4*(1-$B17)+I17 | K17: =J17*$K$4*(1-$B17)+J17 | L17: =K17*$L$4*(1-$B17)+K17 | M17: =L17*$M$4*(1-$B17)+L17 | N17: =M17*$N$4*(1-$B17)+M17 | O17: =N17*$O$4*(1-$B17)+N17 | P17: =O17*$P$4*(1-$B17)+O17 | Q17: =P17*$Q$4*(1-$B17)+P17 | R17: =Q17*$R$4*(1-$B17)+Q17 | S17: =R17*$S$4*(1-$B17)+R17 | T17: =S17*$T$4*(1-$B17)+S17 | U17: =T17*$U$4*(1-$B17)+T17 | V17: =U17*$V$4*(1-$B17)+U17 | W17: =V17*$W$4*(1-$B17)+V17 | X17: =W17*$X$4*(1-$B17)+W17 | Y17: =X17*$Y$4*(1-$B17)+X17 | Z17: =Y17*$Z$4*(1-$B17)+Y17 | AA17: =Z17*$AA$4*(1-$B17)+Z17 | AB17: =AA17*$AB$4*(1-$B17)+AA17 | AC17: =AB17*$AC$4*(1-$B17)+AB17 | AD17: =AC17*$AD$4*(1-$B17)+AC17 | AE17: =AD17*$AE$4*(1-$B17)+AD17 | AF17: =AE17*$AF$4*(1-$B17)+AE17 | AG17: =AF17*$AG$4*(1-$B17)+AF17 | AH17: =AG17*AH$4*(1-$B17)+AG17+SUMIFS(Investments!$D:$D,Investments!$B:$B,$A17,Investments!$C:$C,"USDT",Investments!$A:$A,AH$8) | AI17: =AH17*AI$4*(1-$B17)+AH17+SUMIFS(Investments!$D:$D,Investments!$B:$B,$A17,Investments!$C:$C,"USDT",Investments!$A:$A,AI$8) | AJ17: =AI17*AJ$4*(1-$B17)+AI17+SUMIFS(Investments!$D:$D,Investments!$B:$B,$A17,Investments!$C:$C,"USDT",Investments!$A:$A,AJ$8) | AK17: =AJ17*AK$4*(1-$B17)+AJ17+SUMIFS(Investments!$D:$D,Investments!$B:$B,$A17,Investments!$C:$C,"USDT",Investments!$A:$A,AK$8) | AL17: =AK17*AL$4*(1-$B17)+AK17+SUMIFS(Investments!$D:$D,Investments!$B:$B,$A17,Investments!$C:$C,"USDT",Investments!$A:$A,AL$8) | AM17: =AL17*AM$4*(1-$B17)+AL17+SUMIFS(Investments!$D:$D,Investments!$B:$B,$A17,Investments!$C:$C,"USDT",Investments!$A:$A,AM$8) | AN17: =AM17*AN$4*(1-$B17)+AM17+SUMIFS(Investments!$D:$D,Investments!$B:$B,$A17,Investments!$C:$C,"USDT",Investments!$A:$A,AN$8) | AO17: =AN17*AO$4*(1-$B17)+AN17+SUMIFS(Investments!$D:$D,Investments!$B:$B,$A17,Investments!$C:$C,"USDT",Investments!$A:$A,AO$8) | ... AT17: =AS17*AT$4*(1-$B17)+AS17+SUMIFS(Investments!$D:$D,Investments!$B:$B,$A17,Investments!$C:$C,"USDT",Investments!$A:$A,AT$8)
A18: Alain Bensimon | B18: 0.1 | D18: 0 | E18: =D18*$E$4*(1-$B18)+D18 | F18: =E18*$F$4*(1-$B18)+E18 | G18: =F18*$G$4*(1-$B18)+F18 | H18: =G18*$H$4*(1-$B18)+G18+136737 | I18: =H18*$I$4*(1-$B18)+H18 | J18: =I18*$J$4*(1-$B18)+I18 | K18: =J18*$K$4*(1-$B18)+J18 | L18: =K18*$L$4*(1-$B18)+K18 | M18: =L18*$M$4*(1-$B18)+L18 | N18: =M18*$N$4*(1-$B18)+M18 | O18: =N18*$O$4*(1-$B18)+N18 | P18: =O18*$P$4*(1-$B18)+O18 | Q18: =P18*$Q$4*(1-$B18)+P18 | R18: =Q18*$R$4*(1-$B18)+Q18 | S18: =R18*$S$4*(1-$B18)+R18 | T18: =S18*$T$4*(1-$B18)+S18 | U18: =T18*$U$4*(1-$B18)+T18 | V18: =U18*$V$4*(1-$B18)+U18 | W18: =V18*$W$4*(1-$B18)+V18 | X18: =W18*$X$4*(1-$B18)+W18 | Y18: =X18*$Y$4*(1-$B18)+X18 | Z18: =Y18*$Z$4*(1-$B18)+Y18 | AA18: =Z18*$AA$4*(1-$B18)+Z18 | AB18: =AA18*$AB$4*(1-$B18)+AA18 | AC18: =AB18*$AC$4*(1-$B18)+AB18 | AD18: =AC18*$AD$4*(1-$B18)+AC18 | AE18: =AD18*$AE$4*(1-$B18)+AD18 | AF18: =AE18*$AF$4*(1-$B18)+AE18 | AG18: =AF18*$AG$4*(1-$B18)+AF18 | AH18: =AG18*AH$4*(1-$B18)+AG18+SUMIFS(Investments!$D:$D,Investments!$B:$B,$A18,Investments!$C:$C,"USDT",Investments!$A:$A,AH$8) | AI18: =AH18*AI$4*(1-$B18)+AH18+SUMIFS(Investments!$D:$D,Investments!$B:$B,$A18,Investments!$C:$C,"USDT",Investments!$A:$A,AI$8) | AJ18: =AI18*AJ$4*(1-$B18)+AI18+SUMIFS(Investments!$D:$D,Investments!$B:$B,$A18,Investments!$C:$C,"USDT",Investments!$A:$A,AJ$8) | AK18: =AJ18*AK$4*(1-$B18)+AJ18+SUMIFS(Investments!$D:$D,Investments!$B:$B,$A18,Investments!$C:$C,"USDT",Investments!$A:$A,AK$8) | AL18: =AK18*AL$4*(1-$B18)+AK18+SUMIFS(Investments!$D:$D,Investments!$B:$B,$A18,Investments!$C:$C,"USDT",Investments!$A:$A,AL$8) | AM18: =AL18*AM$4*(1-$B18)+AL18+SUMIFS(Investments!$D:$D,Investments!$B:$B,$A18,Investments!$C:$C,"USDT",Investments!$A:$A,AM$8) | AN18: =AM18*AN$4*(1-$B18)+AM18+SUMIFS(Investments!$D:$D,Investments!$B:$B,$A18,Investments!$C:$C,"USDT",Investments!$A:$A,AN$8) | AO18: =AN18*AO$4*(1-$B18)+AN18+SUMIFS(Investments!$D:$D,Investments!$B:$B,$A18,Investments!$C:$C,"USDT",Investments!$A:$A,AO$8) | ... AT18: =AS18*AT$4*(1-$B18)+AS18+SUMIFS(Investments!$D:$D,Investments!$B:$B,$A18,Investments!$C:$C,"USDT",Investments!$A:$A,AT$8)
A19: Anne Cecile Noique | B19: 0.1 | D19: 0 | E19: =D19*$E$4*(1-$B19)+D19 | F19: =E19*$F$4*(1-$B19)+E19 | G19: =F19*$G$4*(1-$B19)+F19 | H19: =G19*$H$4*(1-$B19)+G19+222687 | I19: =H19*$I$4*(1-$B19)+H19 | J19: =I19*$J$4*(1-$B19)+I19 | K19: =J19*$K$4*(1-$B19)+J19 | L19: =K19*$L$4*(1-$B19)+K19 | M19: =L19*$M$4*(1-$B19)+L19 | N19: =M19*$N$4*(1-$B19)+M19 | O19: =N19*$O$4*(1-$B19)+N19 | P19: =O19*$P$4*(1-$B19)+O19 | Q19: =P19*$Q$4*(1-$B19)+P19 | R19: =Q19*$R$4*(1-$B19)+Q19 | S19: =R19*$S$4*(1-$B19)+R19 | T19: =S19*$T$4*(1-$B19)+S19 | U19: =T19*$U$4*(1-$B19)+T19 | V19: =U19*$V$4*(1-$B19)+U19 | W19: =V19*$W$4*(1-$B19)+V19 | X19: =W19*$X$4*(1-$B19)+W19 | Y19: =X19*$Y$4*(1-$B19)+X19 | Z19: =Y19*$Z$4*(1-$B19)+Y19 | AA19: =Z19*$AA$4*(1-$B19)+Z19 | AB19: =AA19*$AB$4*(1-$B19)+AA19 | AC19: =AB19*$AC$4*(1-$B19)+AB19 | AD19: =AC19*$AD$4*(1-$B19)+AC19 | AE19: =AD19*$AE$4*(1-$B19)+AD19 | AF19: =AE19*$AF$4*(1-$B19)+AE19 | AG19: =AF19*$AG$4*(1-$B19)+AF19 | AH19: =AG19*AH$4*(1-$B19)+AG19+SUMIFS(Investments!$D:$D,Investments!$B:$B,$A19,Investments!$C:$C,"USDT",Investments!$A:$A,AH$8) | AI19: =AH19*AI$4*(1-$B19)+AH19+SUMIFS(Investments!$D:$D,Investments!$B:$B,$A19,Investments!$C:$C,"USDT",Investments!$A:$A,AI$8) | AJ19: =AI19*AJ$4*(1-$B19)+AI19+SUMIFS(Investments!$D:$D,Investments!$B:$B,$A19,Investments!$C:$C,"USDT",Investments!$A:$A,AJ$8) | AK19: =AJ19*AK$4*(1-$B19)+AJ19+SUMIFS(Investments!$D:$D,Investments!$B:$B,$A19,Investments!$C:$C,"USDT",Investments!$A:$A,AK$8) | AL19: =AK19*AL$4*(1-$B19)+AK19+SUMIFS(Investments!$D:$D,Investments!$B:$B,$A19,Investments!$C:$C,"USDT",Investments!$A:$A,AL$8) | AM19: =AL19*AM$4*(1-$B19)+AL19+SUMIFS(Investments!$D:$D,Investments!$B:$B,$A19,Investments!$C:$C,"USDT",Investments!$A:$A,AM$8) | AN19: =AM19*AN$4*(1-$B19)+AM19+SUMIFS(Investments!$D:$D,Investments!$B:$B,$A19,Investments!$C:$C,"USDT",Investments!$A:$A,AN$8) | AO19: =AN19*AO$4*(1-$B19)+AN19+SUMIFS(Investments!$D:$D,Investments!$B:$B,$A19,Investments!$C:$C,"USDT",Investments!$A:$A,AO$8) | ... AT19: =AS19*AT$4*(1-$B19)+AS19+SUMIFS(Investments!$D:$D,Investments!$B:$B,$A19,Investments!$C:$C,"USDT",Investments!$A:$A,AT$8)
A20: Terance Chen | B20: 0.1 | D20: 0 | E20: =D20*$E$4*(1-$B20)+D20 | F20: =E20*$F$4*(1-$B20)+E20 | G20: =F20*$G$4*(1-$B20)+F20 | H20: =G20*$H$4*(1-$B20)+G20+219747 | I20: =H20*$I$4*(1-$B20)+H20 | J20: =I20*$J$4*(1-$B20)+I20 | K20: =J20*$K$4*(1-$B20)+J20 | L20: =K20*$L$4*(1-$B20)+K20 | M20: =L20*$M$4*(1-$B20)+L20 | N20: =M20*$N$4*(1-$B20)+M20 | O20: =N20*$O$4*(1-$B20)+N20 | P20: =O20*$P$4*(1-$B20)+O20 | Q20: =P20*$Q$4*(1-$B20)+P20 | R20: =Q20*$R$4*(1-$B20)+Q20 | S20: =R20*$S$4*(1-$B20)+R20 | T20: =S20*$T$4*(1-$B20)+S20 | U20: =T20*$U$4*(1-$B20)+T20 | V20: =U20*$V$4*(1-$B20)+U20 | W20: =V20*$W$4*(1-$B20)+V20 | X20: =W20*$X$4*(1-$B20)+W20 | Y20: =X20*$Y$4*(1-$B20)+X20 | Z20: =Y20*$Z$4*(1-$B20)+Y20 | AA20: =Z20*$AA$4*(1-$B20)+Z20 | AB20: =AA20*$AB$4*(1-$B20)+AA20 | AC20: =AB20*$AC$4*(1-$B20)+AB20 | AD20: =AC20*$AD$4*(1-$B20)+AC20 | AE20: =AD20*$AE$4*(1-$B20)+AD20 | AF20: =AE20*$AF$4*(1-$B20)+AE20 | AG20: =AF20*$AG$4*(1-$B20)+AF20 | AH20: =AG20*AH$4*(1-$B20)+AG20+SUMIFS(Investments!$D:$D,Investments!$B:$B,$A20,Investments!$C:$C,"USDT",Investments!$A:$A,AH$8) | AI20: =AH20*AI$4*(1-$B20)+AH20+SUMIFS(Investments!$D:$D,Investments!$B:$B,$A20,Investments!$C:$C,"USDT",Investments!$A:$A,AI$8) | AJ20: =AI20*AJ$4*(1-$B20)+AI20+SUMIFS(Investments!$D:$D,Investments!$B:$B,$A20,Investments!$C:$C,"USDT",Investments!$A:$A,AJ$8) | AK20: =AJ20*AK$4*(1-$B20)+AJ20+SUMIFS(Investments!$D:$D,Investments!$B:$B,$A20,Investments!$C:$C,"USDT",Investments!$A:$A,AK$8) | AL20: =AK20*AL$4*(1-$B20)+AK20+SUMIFS(Investments!$D:$D,Investments!$B:$B,$A20,Investments!$C:$C,"USDT",Investments!$A:$A,AL$8) | AM20: =AL20*AM$4*(1-$B20)+AL20+SUMIFS(Investments!$D:$D,Investments!$B:$B,$A20,Investments!$C:$C,"USDT",Investments!$A:$A,AM$8) | AN20: =AM20*AN$4*(1-$B20)+AM20+SUMIFS(Investments!$D:$D,Investments!$B:$B,$A20,Investments!$C:$C,"USDT",Investments!$A:$A,AN$8) | AO20: =AN20*AO$4*(1-$B20)+AN20+SUMIFS(Investments!$D:$D,Investments!$B:$B,$A20,Investments!$C:$C,"USDT",Investments!$A:$A,AO$8) | ... AT20: =AS20*AT$4*(1-$B20)+AS20+SUMIFS(Investments!$D:$D,Investments!$B:$B,$A20,Investments!$C:$C,"USDT",Investments!$A:$A,AT$8)
A21: INDIGO Ventures | B21: 0 | D21: 0 | E21: =D21*$E$4*(1-$B21)+D21 | F21: =E21*$F$4*(1-$B21)+E21 | G21: =F21*$G$4*(1-$B21)+F21 | H21: =G21*$H$4*(1-$B21)+G21 | I21: =H21*$I$4*(1-$B21)+H21 | J21: =I21*$J$4*(1-$B21)+I21+130000 | K21: =J21*$K$4*(1-$B21)+J21 | L21: =K21*$L$4*(1-$B21)+K21 | M21: =L21*$M$4*(1-$B21)+L21 | N21: =M21*$N$4*(1-$B21)+M21 | O21: =N21*$O$4*(1-$B21)+N21 | P21: =O21*$P$4*(1-$B21)+O21-100000 | Q21: =P21*$Q$4*(1-$B21)+P21 | R21: =Q21*$R$4*(1-$B21)+Q21-32594.55+5000 | S21: =R21*$S$4*(1-$B21)+R21 | T21: =S21*$T$4*(1-$B21)+S21 | U21: =T21*$U$4*(1-$B21)+T21 | V21: =U21*$V$4*(1-$B21)+U21 | W21: =V21*$W$4*(1-$B21)+V21 | X21: =W21*$X$4*(1-$B21)+W21 | Y21: =X21*$Y$4*(1-$B21)+X21 | Z21: =Y21*$Z$4*(1-$B21)+Y21 | AA21: =Z21*$AA$4*(1-$B21)+Z21 | AB21: =AA21*$AB$4*(1-$B21)+AA21 | AC21: =AB21*$AC$4*(1-$B21)+AB21 | AD21: =AC21*$AD$4*(1-$B21)+AC21 | AE21: =AD21*$AE$4*(1-$B21)+AD21 | AF21: =AE21*$AF$4*(1-$B21)+AE21 | AG21: =AF21*$AG$4*(1-$B21)+AF21 | AH21: =AG21*AH$4*(1-$B21)+AG21-(AG21*AH$4*(1-$B21)+AG21) | AI21: =AH21*AI$4*(1-$B21)+AH21-(AH21*AI$4*(1-$B21)+AH21) | AJ21: =AI21*AJ$4*(1-$B21)+AI21-(AI21*AJ$4*(1-$B21)+AI21) | AK21: =AJ21*AK$4*(1-$B21)+AJ21-(AJ21*AK$4*(1-$B21)+AJ21) | AL21: =AK21*AL$4*(1-$B21)+AK21-(AK21*AL$4*(1-$B21)+AK21) | AM21: =AL21*AM$4*(1-$B21)+AL21-(AL21*AM$4*(1-$B21)+AL21) | AN21: =AM21*AN$4*(1-$B21)+AM21-(AM21*AN$4*(1-$B21)+AM21) | AO21: =AN21*AO$4*(1-$B21)+AN21-(AN21*AO$4*(1-$B21)+AN21) | ... AT21: =AS21*AT$4*(1-$B21)+AS21-(AS21*AT$4*(1-$B21)+AS21)
A22: INDIGO DIGITAL ASSET FUND LP | B22: 0 | D22: 0 | E22: =D22*$E$4*(1-$B22)+D22 | F22: =E22*$F$4*(1-$B22)+E22 | G22: =F22*$G$4*(1-$B22)+F22 | H22: =G22*$H$4*(1-$B22)+G22 | I22: =H22*$I$4*(1-$B22)+H22 | J22: =I22*$J$4*(1-$B22)+I22 | K22: =J22*$K$4*(1-$B22)+J22 | L22: =K22*$L$4*(1-$B22)+K22+111370 | M22: =L22*$M$4*(1-$B22)+L22 | N22: =M22*$N$4*(1-$B22)+M22 | O22: =N22*$O$4*(1-$B22)+N22 | P22: =O22*$P$4*(1-$B22)+O22 | Q22: =P22*$Q$4*(1-$B22)+P22 | R22: =Q22*$R$4*(1-$B22)+Q22 | S22: =R22*$S$4*(1-$B22)+R22 | T22: =S22*$T$4*(1-$B22)+S22 | U22: =T22*$U$4*(1-$B22)+T22 | V22: =U22*$V$4*(1-$B22)+U22-(U22*$V$4*(1-$B22)+U22) | W22: =V22*$W$4*(1-$B22)+V22 | X22: =W22*$X$4*(1-$B22)+W22 | Y22: =X22*$Y$4*(1-$B22)+X22 | Z22: =Y22*$Z$4*(1-$B22)+Y22 | AA22: =Z22*$AA$4*(1-$B22)+Z22 | AB22: =AA22*$AB$4*(1-$B22)+AA22 | AC22: =AB22*$AC$4*(1-$B22)+AB22 | AD22: =AC22*$AD$4*(1-$B22)+AC22 | AE22: =AD22*$AE$4*(1-$B22)+AD22 | AF22: =AE22*$AF$4*(1-$B22)+AE22 | AG22: =AF22*$AG$4*(1-$B22)+AF22 | AH22: =AG22*AH$4*(1-$B22)+AG22+SUMIFS(Investments!$D:$D,Investments!$B:$B,$A22,Investments!$C:$C,"USDT",Investments!$A:$A,AH$8) | AI22: =AH22*AI$4*(1-$B22)+AH22+SUMIFS(Investments!$D:$D,Investments!$B:$B,$A22,Investments!$C:$C,"USDT",Investments!$A:$A,AI$8) | AJ22: =AI22*AJ$4*(1-$B22)+AI22+SUMIFS(Investments!$D:$D,Investments!$B:$B,$A22,Investments!$C:$C,"USDT",Investments!$A:$A,AJ$8) | AK22: =AJ22*AK$4*(1-$B22)+AJ22+SUMIFS(Investments!$D:$D,Investments!$B:$B,$A22,Investments!$C:$C,"USDT",Investments!$A:$A,AK$8) | AL22: =AK22*AL$4*(1-$B22)+AK22+SUMIFS(Investments!$D:$D,Investments!$B:$B,$A22,Investments!$C:$C,"USDT",Investments!$A:$A,AL$8) | AM22: =AL22*AM$4*(1-$B22)+AL22+SUMIFS(Investments!$D:$D,Investments!$B:$B,$A22,Investments!$C:$C,"USDT",Investments!$A:$A,AM$8) | AN22: =AM22*AN$4*(1-$B22)+AM22+SUMIFS(Investments!$D:$D,Investments!$B:$B,$A22,Investments!$C:$C,"USDT",Investments!$A:$A,AN$8) | AO22: =AN22*AO$4*(1-$B22)+AN22+SUMIFS(Investments!$D:$D,Investments!$B:$B,$A22,Investments!$C:$C,"USDT",Investments!$A:$A,AO$8) | ... AT22: =AS22*AT$4*(1-$B22)+AS22+SUMIFS(Investments!$D:$D,Investments!$B:$B,$A22,Investments!$C:$C,"USDT",Investments!$A:$A,AT$8)
A23: Sacha Oshry | B23: 0.15 | D23: 0 | E23: =D23*$E$4*(1-$B23)+D23 | F23: =E23*$F$4*(1-$B23)+E23 | G23: =F23*$G$4*(1-$B23)+F23 | H23: =G23*$H$4*(1-$B23)+G23 | I23: =H23*$I$4*(1-$B23)+H23 | J23: =(I23*$J$4*(1-$B23)+I23) | K23: =(J23*$K$4*(1-$B23)+J23) | L23: =(K23*$L$4*(1-$B23)+K23) | M23: =(L23*$M$4*(1-$B23)+L23) | N23: =(M23*$N$4*(1-$B23)+M23) | O23: =(N23*$O$4*(1-$B23)+N23) | P23: =(O23*$P$4*(1-$B23)+O23)+100000 | Q23: =(P23*$Q$4*(1-$B23)+P23) | R23: =(Q23*$R$4*(1-$B23)+Q23) | S23: =(R23*$S$4*(1-$B23)+R23) | T23: =(S23*$T$4*(1-$B23)+S23) | U23: =(T23*$U$4*(1-$B23)+T23) | V23: =(U23*$V$4*(1-$B23)+U23) | W23: =(V23*$W$4*(1-$B23)+V23) | X23: =(W23*$X$4*(1-$B23)+W23) | Y23: =(X23*$Y$4*(1-$B23)+X23) | Z23: =(Y23*$Z$4*(1-$B23)+Y23) | AA23: =(Z23*$AA$4*(1-$B23)+Z23) | AB23: =(AA23*$AB$4*(1-$B23)+AA23) | AC23: =(AB23*$AC$4*(1-$B23)+AB23) | AD23: =(AC23*$AD$4*(1-$B23)+AC23) | AE23: =(AD23*$AE$4*(1-$B23)+AD23) | AF23: =(AE23*$AF$4*(1-$B23)+AE23) | AG23: =(AF23*$AG$4*(1-$B23)+AF23) | AH23: =(AG23*AH$4*(1-$B23)+AG23)+SUMIFS(Investments!$D:$D,Investments!$B:$B,$A23,Investments!$C:$C,"USDT",Investments!$A:$A,AH$8) | AI23: =(AH23*AI$4*(1-$B23)+AH23)+SUMIFS(Investments!$D:$D,Investments!$B:$B,$A23,Investments!$C:$C,"USDT",Investments!$A:$A,AI$8) | AJ23: =(AI23*AJ$4*(1-$B23)+AI23)+SUMIFS(Investments!$D:$D,Investments!$B:$B,$A23,Investments!$C:$C,"USDT",Investments!$A:$A,AJ$8) | AK23: =(AJ23*AK$4*(1-$B23)+AJ23)+SUMIFS(Investments!$D:$D,Investments!$B:$B,$A23,Investments!$C:$C,"USDT",Investments!$A:$A,AK$8) | AL23: =(AK23*AL$4*(1-$B23)+AK23)+SUMIFS(Investments!$D:$D,Investments!$B:$B,$A23,Investments!$C:$C,"USDT",Investments!$A:$A,AL$8) | AM23: =(AL23*AM$4*(1-$B23)+AL23)+SUMIFS(Investments!$D:$D,Investments!$B:$B,$A23,Investments!$C:$C,"USDT",Investments!$A:$A,AM$8) | AN23: =(AM23*AN$4*(1-$B23)+AM23)+SUMIFS(Investments!$D:$D,Investments!$B:$B,$A23,Investments!$C:$C,"USDT",Investments!$A:$A,AN$8) | AO23: =(AN23*AO$4*(1-$B23)+AN23)+SUMIFS(Investments!$D:$D,Investments!$B:$B,$A23,Investments!$C:$C,"USDT",Investments!$A:$A,AO$8) | ... AT23: =(AS23*AT$4*(1-$B23)+AS23)+SUMIFS(Investments!$D:$D,Investments!$B:$B,$A23,Investments!$C:$C,"USDT",Investments!$A:$A,AT$8)
A24: HALLEY86 | B24: 0.2 | D24: 0 | E24: =D24*$E$4*(1-$B24)+D24 | F24: =E24*$F$4*(1-$B24)+E24 | G24: =F24*$G$4*(1-$B24)+F24 | H24: =G24*$H$4*(1-$B24)+G24 | I24: =H24*$I$4*(1-$B24)+H24 | J24: =(I24*$J$4*(1-$B24)+I24) | K24: =(J24*$K$4*(1-$B24)+J24) | L24: =(K24*$L$4*(1-$B24)+K24) | M24: =(L24*$M$4*(1-$B24)+L24) | N24: =(M24*$N$4*(1-$B24)+M24) | O24: =(N24*$O$4*(1-$B24)+N24) | P24: =(O24*$P$4*(1-$B24)+O24) | Q24: =(P24*$Q$4*(1-$B24)+P24) | R24: =(Q24*$R$4*(1-$B24)+Q24) | S24: =(R24*$S$4*(1-$B24)+R24)+99990 | T24: =(S24*$T$4*(1-$B24)+S24) | U24: =(T24*$U$4*(1-$B24)+T24) | V24: =(U24*$V$4*(1-$B24)+U24) | W24: =(V24*$W$4*(1-$B24)+V24) | X24: =(W24*$X$4*(1-$B24)+W24) | Y24: =(X24*$Y$4*(1-$B24)+X24) | Z24: =(Y24*$Z$4*(1-$B24)+Y24) | AA24: =(Z24*$AA$4*(1-$B24)+Z24) | AB24: =(AA24*$AB$4*(1-$B24)+AA24) | AC24: =(AB24*$AC$4*(1-$B24)+AB24) | AD24: =(AC24*$AD$4*(1-$B24)+AC24) | AE24: =(AD24*$AE$4*(1-$B24)+AD24) | AF24: =(AE24*$AF$4*(1-$B24)+AE24) | AG24: =(AF24*$AG$4*(1-$B24)+AF24) | AH24: =(AG24*AH$4*(1-$B24)+AG24)+SUMIFS(Investments!$D:$D,Investments!$B:$B,$A24,Investments!$C:$C,"USDT",Investments!$A:$A,AH$8) | AI24: =(AH24*AI$4*(1-$B24)+AH24)+SUMIFS(Investments!$D:$D,Investments!$B:$B,$A24,Investments!$C:$C,"USDT",Investments!$A:$A,AI$8) | AJ24: =(AI24*AJ$4*(1-$B24)+AI24)+SUMIFS(Investments!$D:$D,Investments!$B:$B,$A24,Investments!$C:$C,"USDT",Investments!$A:$A,AJ$8) | AK24: =(AJ24*AK$4*(1-$B24)+AJ24)+SUMIFS(Investments!$D:$D,Investments!$B:$B,$A24,Investments!$C:$C,"USDT",Investments!$A:$A,AK$8) | AL24: =(AK24*AL$4*(1-$B24)+AK24)+SUMIFS(Investments!$D:$D,Investments!$B:$B,$A24,Investments!$C:$C,"USDT",Investments!$A:$A,AL$8) | AM24: =(AL24*AM$4*(1-$B24)+AL24)+SUMIFS(Investments!$D:$D,Investments!$B:$B,$A24,Investments!$C:$C,"USDT",Investments!$A:$A,AM$8) | AN24: =(AM24*AN$4*(1-$B24)+AM24)+SUMIFS(Investments!$D:$D,Investments!$B:$B,$A24,Investments!$C:$C,"USDT",Investments!$A:$A,AN$8) | AO24: =(AN24*AO$4*(1-$B24)+AN24)+SUMIFS(Investments!$D:$D,Investments!$B:$B,$A24,Investments!$C:$C,"USDT",Investments!$A:$A,AO$8) | ... AT24: =(AS24*AT$4*(1-$B24)+AS24)+SUMIFS(Investments!$D:$D,Investments!$B:$B,$A24,Investments!$C:$C,"USDT",Investments!$A:$A,AT$8)
A25: Jose Molla | B25: 0.15 | D25: 0 | E25: =D25*$E$4*(1-$B25)+D25 | F25: =E25*$F$4*(1-$B25)+E25 | G25: =F25*$G$4*(1-$B25)+F25 | H25: =G25*$H$4*(1-$B25)+G25 | I25: =H25*$I$4*(1-$B25)+H25 | J25: =(I25*$J$4*(1-$B25)+I25) | K25: =(J25*$K$4*(1-$B25)+J25) | L25: =(K25*$L$4*(1-$B25)+K25) | M25: =(L25*$M$4*(1-$B25)+L25) | N25: =(M25*$N$4*(1-$B25)+M25) | O25: =(N25*$O$4*(1-$B25)+N25) | P25: =(O25*$P$4*(1-$B25)+O25) | Q25: =(P25*$Q$4*(1-$B25)+P25) | R25: =(Q25*$R$4*(1-$B25)+Q25) | S25: =(R25*$S$4*(1-$B25)+R25) | T25: =(S25*$T$4*(1-$B25)+S25)+97695 | U25: =(T25*$U$4*(1-$B25)+T25) | V25: =(U25*$V$4*(1-$B25)+U25) | W25: =(V25*$W$4*(1-$B25)+V25) | X25: =(W25*$X$4*(1-$B25)+W25) | Y25: =(X25*$Y$4*(1-$B25)+X25)-50000 | Z25: =(Y25*$Z$4*(1-$B25)+Y25) | AA25: =(Z25*$AA$4*(1-$B25)+Z25)-47908 | AB25: =(AA25*$AB$4*(1-$B25)+AA25) | AC25: =(AB25*$AC$4*(1-$B25)+AB25) | AD25: =(AC25*$AD$4*(1-$B25)+AC25) | AE25: =(AD25*$AE$4*(1-$B25)+AD25) | AF25: =(AE25*$AF$4*(1-$B25)+AE25) | AG25: =(AF25*$AG$4*(1-$B25)+AF25) | AH25: =(AG25*AH$4*(1-$B25)+AG25)+SUMIFS(Investments!$D:$D,Investments!$B:$B,$A25,Investments!$C:$C,"USDT",Investments!$A:$A,AH$8) | AI25: =(AH25*AI$4*(1-$B25)+AH25)+SUMIFS(Investments!$D:$D,Investments!$B:$B,$A25,Investments!$C:$C,"USDT",Investments!$A:$A,AI$8) | AJ25: =(AI25*AJ$4*(1-$B25)+AI25)+SUMIFS(Investments!$D:$D,Investments!$B:$B,$A25,Investments!$C:$C,"USDT",Investments!$A:$A,AJ$8) | AK25: =(AJ25*AK$4*(1-$B25)+AJ25)+SUMIFS(Investments!$D:$D,Investments!$B:$B,$A25,Investments!$C:$C,"USDT",Investments!$A:$A,AK$8) | AL25: =(AK25*AL$4*(1-$B25)+AK25)+SUMIFS(Investments!$D:$D,Investments!$B:$B,$A25,Investments!$C:$C,"USDT",Investments!$A:$A,AL$8) | AM25: =(AL25*AM$4*(1-$B25)+AL25)+SUMIFS(Investments!$D:$D,Investments!$B:$B,$A25,Investments!$C:$C,"USDT",Investments!$A:$A,AM$8) | AN25: =(AM25*AN$4*(1-$B25)+AM25)+SUMIFS(Investments!$D:$D,Investments!$B:$B,$A25,Investments!$C:$C,"USDT",Investments!$A:$A,AN$8) | AO25: =(AN25*AO$4*(1-$B25)+AN25)+SUMIFS(Investments!$D:$D,Investments!$B:$B,$A25,Investments!$C:$C,"USDT",Investments!$A:$A,AO$8) | ... AT25: =(AS25*AT$4*(1-$B25)+AS25)+SUMIFS(Investments!$D:$D,Investments!$B:$B,$A25,Investments!$C:$C,"USDT",Investments!$A:$A,AT$8)
A26: Monica Levy Chicheportiche | B26: 0.2 | D26: 0 | E26: =D26*$E$4*(1-$B26)+D26 | F26: =E26*$F$4*(1-$B26)+E26 | G26: =F26*$G$4*(1-$B26)+F26 | H26: =G26*$H$4*(1-$B26)+G26 | I26: =H26*$I$4*(1-$B26)+H26 | J26: =(I26*$J$4*(1-$B26)+I26) | K26: =(J26*$K$4*(1-$B26)+J26) | L26: =(K26*$L$4*(1-$B26)+K26) | M26: =(L26*$M$4*(1-$B26)+L26) | N26: =(M26*$N$4*(1-$B26)+M26) | O26: =(N26*$O$4*(1-$B26)+N26) | P26: =(O26*$P$4*(1-$B26)+O26) | Q26: =(P26*$Q$4*(1-$B26)+P26) | R26: =(Q26*$R$4*(1-$B26)+Q26) | S26: =(R26*$S$4*(1-$B26)+R26) | T26: =(S26*$T$4*(1-$B26)+S26) | U26: =(T26*$U$4*(1-$B26)+T26) | V26: =(U26*$V$4*(1-$B26)+U26) | W26: =(V26*$W$4*(1-$B26)+V26) | X26: =(W26*$X$4*(1-$B26)+W26)+840168.03 | Y26: =(X26*$Y$4*(1-$B26)+X26) | Z26: =(Y26*$Z$4*(1-$B26)+Y26) | AA26: =(Z26*$AA$4*(1-$B26)+Z26) | AB26: =(AA26*$AB$4*(1-$B26)+AA26) | AC26: =(AB26*$AC$4*(1-$B26)+AB26) | AD26: =(AC26*$AD$4*(1-$B26)+AC26) | AE26: =(AD26*$AE$4*(1-$B26)+AD26) | AF26: =(AE26*$AF$4*(1-$B26)+AE26) | AG26: =(AF26*$AG$4*(1-$B26)+AF26) | AH26: =(AG26*AH$4*(1-$B26)+AG26)+SUMIFS(Investments!$D:$D,Investments!$B:$B,$A26,Investments!$C:$C,"USDT",Investments!$A:$A,AH$8) | AI26: =(AH26*AI$4*(1-$B26)+AH26)+SUMIFS(Investments!$D:$D,Investments!$B:$B,$A26,Investments!$C:$C,"USDT",Investments!$A:$A,AI$8) | AJ26: =(AI26*AJ$4*(1-$B26)+AI26)+SUMIFS(Investments!$D:$D,Investments!$B:$B,$A26,Investments!$C:$C,"USDT",Investments!$A:$A,AJ$8) | AK26: =(AJ26*AK$4*(1-$B26)+AJ26)+SUMIFS(Investments!$D:$D,Investments!$B:$B,$A26,Investments!$C:$C,"USDT",Investments!$A:$A,AK$8) | AL26: =(AK26*AL$4*(1-$B26)+AK26)+SUMIFS(Investments!$D:$D,Investments!$B:$B,$A26,Investments!$C:$C,"USDT",Investments!$A:$A,AL$8) | AM26: =(AL26*AM$4*(1-$B26)+AL26)+SUMIFS(Investments!$D:$D,Investments!$B:$B,$A26,Investments!$C:$C,"USDT",Investments!$A:$A,AM$8) | AN26: =(AM26*AN$4*(1-$B26)+AM26)+SUMIFS(Investments!$D:$D,Investments!$B:$B,$A26,Investments!$C:$C,"USDT",Investments!$A:$A,AN$8) | AO26: =(AN26*AO$4*(1-$B26)+AN26)+SUMIFS(Investments!$D:$D,Investments!$B:$B,$A26,Investments!$C:$C,"USDT",Investments!$A:$A,AO$8) | ... AT26: =(AS26*AT$4*(1-$B26)+AS26)+SUMIFS(Investments!$D:$D,Investments!$B:$B,$A26,Investments!$C:$C,"USDT",Investments!$A:$A,AT$8)
A27: Nath & Thomas | B27: 0 | D27: 0 | E27: =D27*$E$4*(1-$B27)+D27 | F27: =E27*$F$4*(1-$B27)+E27 | G27: =F27*$G$4*(1-$B27)+F27 | H27: =G27*$H$4*(1-$B27)+G27 | I27: =H27*$I$4*(1-$B27)+H27 | J27: =(I27*$J$4*(1-$B27)+I27) | K27: =(J27*$K$4*(1-$B27)+J27) | L27: =(K27*$L$4*(1-$B27)+K27) | M27: =(L27*$M$4*(1-$B27)+L27) | N27: =(M27*$N$4*(1-$B27)+M27) | O27: =(N27*$O$4*(1-$B27)+N27) | P27: =(O27*$P$4*(1-$B27)+O27) | Q27: =(P27*$Q$4*(1-$B27)+P27) | R27: =(Q27*$R$4*(1-$B27)+Q27) | S27: =(R27*$S$4*(1-$B27)+R27) | T27: =(S27*$T$4*(1-$B27)+S27) | U27: =(T27*$U$4*(1-$B27)+T27) | V27: =(U27*$V$4*(1-$B27)+U27) | W27: =(V27*$W$4*(1-$B27)+V27) | X27: =(W27*$X$4*(1-$B27)+W27) | Y27: =(X27*$Y$4*(1-$B27)+X27) | Z27: =(Y27*$Z$4*(1-$B27)+Y27)+299915.77 | AA27: =(Z27*$AA$4*(1-$B27)+Z27) | AB27: =(AA27*$AB$4*(1-$B27)+AA27) | AC27: =(AB27*$AC$4*(1-$B27)+AB27)-87937 | AD27: =(AC27*$AD$4*(1-$B27)+AC27) | AE27: =(AD27*$AE$4*(1-$B27)+AD27) | AF27: =(AE27*$AF$4*(1-$B27)+AE27)-(AE27*$AF$4*(1-$B27)+AE27) | AG27: =(AF27*$AG$4*(1-$B27)+AF27) | AH27: =(AG27*AH$4*(1-$B27)+AG27)+SUMIFS(Investments!$D:$D,Investments!$B:$B,$A27,Investments!$C:$C,"USDT",Investments!$A:$A,AH$8) | AI27: =(AH27*AI$4*(1-$B27)+AH27)+SUMIFS(Investments!$D:$D,Investments!$B:$B,$A27,Investments!$C:$C,"USDT",Investments!$A:$A,AI$8) | AJ27: =(AI27*AJ$4*(1-$B27)+AI27)+SUMIFS(Investments!$D:$D,Investments!$B:$B,$A27,Investments!$C:$C,"USDT",Investments!$A:$A,AJ$8) | AK27: =(AJ27*AK$4*(1-$B27)+AJ27)+SUMIFS(Investments!$D:$D,Investments!$B:$B,$A27,Investments!$C:$C,"USDT",Investments!$A:$A,AK$8) | AL27: =(AK27*AL$4*(1-$B27)+AK27)+SUMIFS(Investments!$D:$D,Investments!$B:$B,$A27,Investments!$C:$C,"USDT",Investments!$A:$A,AL$8) | AM27: =(AL27*AM$4*(1-$B27)+AL27)+SUMIFS(Investments!$D:$D,Investments!$B:$B,$A27,Investments!$C:$C,"USDT",Investments!$A:$A,AM$8) | AN27: =(AM27*AN$4*(1-$B27)+AM27)+SUMIFS(Investments!$D:$D,Investments!$B:$B,$A27,Investments!$C:$C,"USDT",Investments!$A:$A,AN$8) | AO27: =(AN27*AO$4*(1-$B27)+AN27)+SUMIFS(Investments!$D:$D,Investments!$B:$B,$A27,Investments!$C:$C,"USDT",Investments!$A:$A,AO$8) | ... AT27: =(AS27*AT$4*(1-$B27)+AS27)+SUMIFS(Investments!$D:$D,Investments!$B:$B,$A27,Investments!$C:$C,"USDT",Investments!$A:$A,AT$8)
A28: Sam Johnson | B28: 0.16 | C28: 0.04 | D28: 0 | E28: =D28*$E$4*(1-$B28)+D28 | F28: =E28*$F$4*(1-$B28)+E28 | G28: =F28*$G$4*(1-$B28)+F28 | H28: =G28*$H$4*(1-$B28)+G28 | I28: =H28*$I$4*(1-$B28)+H28 | J28: =(I28*$J$4*(1-$B28)+I28) | K28: =(J28*$K$4*(1-$B28)+J28) | L28: =(K28*$L$4*(1-$B28)+K28) | M28: =(L28*$M$4*(1-$B28)+L28) | N28: =(M28*$N$4*(1-$B28)+M28) | O28: =(N28*$O$4*(1-$B28)+N28) | P28: =(O28*$P$4*(1-$B28)+O28) | Q28: =(P28*$Q$4*(1-$B28)+P28) | R28: =(Q28*$R$4*(1-$B28)+Q28) | S28: =(R28*$S$4*(1-$B28)+R28) | T28: =(S28*$T$4*(1-$B28)+S28) | U28: =(T28*$U$4*(1-$B28)+T28) | V28: =(U28*$V$4*(1-$B28)+U28) | W28: =(V28*$W$4*(1-$B28)+V28) | X28: =(W28*$X$4*(1-$B28)+W28) | Y28: =(X28*$Y$4*(1-$B28)+X28) | Z28: =(Y28*$Z$4*(1-$B28)+Y28) | AA28: =(Z28*$AA$4*(1-$B28-$C28)+Z28) | AB28: =(AA28*$AB$4*(1-$B28-$C28)+AA28) | AC28: =(AB28*$AC$4*(1-$B28-$C28)+AB28) | AD28: =(AC28*$AD$4*(1-$B28-$C28)+AC28) | AE28: =(AD28*$AE$4*(1-$B28-$C28)+AD28) | AF28: =(AE28*$AF$4*(1-$B28-$C28)+AE28) | AG28: =(AF28*$AG$4*(1-$B28-$C28)+AF28) | AH28: =(AG28*AH$4*(1-$B28-$C28)+AG28)+SUMIFS(Investments!$D:$D,Investments!$B:$B,$A28,Investments!$C:$C,"USDT",Investments!$A:$A,AH$8) | AI28: =(AH28*AI$4*(1-$B28-$C28)+AH28)+SUMIFS(Investments!$D:$D,Investments!$B:$B,$A28,Investments!$C:$C,"USDT",Investments!$A:$A,AI$8) | AJ28: =(AI28*AJ$4*(1-$B28-$C28)+AI28)+SUMIFS(Investments!$D:$D,Investments!$B:$B,$A28,Investments!$C:$C,"USDT",Investments!$A:$A,AJ$8) | AK28: =(AJ28*AK$4*(1-$B28-$C28)+AJ28)+SUMIFS(Investments!$D:$D,Investments!$B:$B,$A28,Investments!$C:$C,"USDT",Investments!$A:$A,AK$8) | AL28: =(AK28*AL$4*(1-$B28-$C28)+AK28)+SUMIFS(Investments!$D:$D,Investments!$B:$B,$A28,Investments!$C:$C,"USDT",Investments!$A:$A,AL$8) | AM28: =(AL28*AM$4*(1-$B28-$C28)+AL28)+SUMIFS(Investments!$D:$D,Investments!$B:$B,$A28,Investments!$C:$C,"USDT",Investments!$A:$A,AM$8) | AN28: =(AM28*AN$4*(1-$B28-$C28)+AM28)+SUMIFS(Investments!$D:$D,Investments!$B:$B,$A28,Investments!$C:$C,"USDT",Investments!$A:$A,AN$8) | AO28: =(AN28*AO$4*(1-$B28-$C28)+AN28)+SUMIFS(Investments!$D:$D,Investments!$B:$B,$A28,Investments!$C:$C,"USDT",Investments!$A:$A,AO$8) | ... AS28: =(AR28*AS$4*(1-$B28-$C28)+AR28)+SUMIFS(Investments!$D:$D,Investments!$B:$B,$A28,Investments!$C:$C,"USDT",Investments!$A:$A,AS$8) | AT28: =(AS28*AT$4*(1-$B28-$C28)+AS28)-(AS28*AT$4*(1-$B28-$C28)+AS28)
A29: Ryan Van Der Wall | B29: 0.2 | D29: 0 | E29: =D29*$E$4*(1-$B29)+D29 | F29: =E29*$F$4*(1-$B29)+E29 | G29: =F29*$G$4*(1-$B29)+F29 | H29: =G29*$H$4*(1-$B29)+G29 | I29: =H29*$P$4*(1-$B29)+H29 | J29: =(I29*$J$4*(1-$B29)+I29)+(I28*$J$4*$C28) | K29: =(J29*$K$4*(1-$B29)+J29)+(J28*$K$4*$C28) | L29: =(K29*$L$4*(1-$B29)+K29)+(K28*$L$4*$C28) | M29: =(L29*$M$4*(1-$B29)+L29)+(L28*$M$4*$C28) | N29: =(M29*$N$4*(1-$B29)+M29)+(M28*$N$4*$C28) | O29: =(N29*$O$4*(1-$B29)+N29)+(N28*$O$4*$C28) | P29: =(O29*$P$4*(1-$B29)+O29)+(O28*$P$4*$C28) | Q29: =(P29*$Q$4*(1-$B29)+P29)+(P28*$Q$4*$C28) | R29: =(Q29*$R$4*(1-$B29)+Q29)+(Q28*$R$4*$C28) | S29: =(R29*$S$4*(1-$B29)+R29)+(R28*$S$4*$C28) | T29: =(S29*$T$4*(1-$B29)+S29)+(S28*$T$4*$C28) | U29: =(T29*$U$4*(1-$B29)+T29)+(T28*$U$4*$C28) | V29: =(U29*$V$4*(1-$B29)+U29)+(U28*$V$4*$C28) | W29: =(V29*$W$4*(1-$B29)+V29)+(V28*$W$4*$C28) | X29: =(W29*$X$4*(1-$B29)+W29)+(W28*$X$4*$C28) | Y29: =(X29*$Y$4*(1-$B29)+X29)+(X28*$Y$4*$C28) | Z29: =(Y29*$Z$4*(1-$B29)+Y29)+(Y28*$Z$4*$C28) | AA29: =(Z29*$AA$4*(1-$B29)+Z29)+(Z28*$AA$4*$C28) | AB29: =(AA29*$AB$4*(1-$B29)+AA29)+(AA28*$AB$4*$C28) | AC29: =(AB29*$AC$4*(1-$B29)+AB29)+(AB28*$AC$4*$C28) | AD29: =(AC29*$AD$4*(1-$B29)+AC29)+(AC28*$AD$4*$C28) | AE29: =(AD29*$AE$4*(1-$B29)+AD29)+(AD28*$AE$4*$C28) | AF29: =(AE29*$AF$4*(1-$B29)+AE29)+(AE28*$AF$4*$C28) | AG29: =(AF29*$AG$4*(1-$B29)+AF29)+(AF28*$AG$4*$C28) | AH29: =(AG29*AH$4*(1-$B29)+AG29)+(AG28*AH$4*$C28)+SUMIFS(Investments!$D:$D,Investments!$B:$B,$A29,Investments!$C:$C,"USDT",Investments!$A:$A,AH$8) | AI29: =(AH29*AI$4*(1-$B29)+AH29)+(AH28*AI$4*$C28)+SUMIFS(Investments!$D:$D,Investments!$B:$B,$A29,Investments!$C:$C,"USDT",Investments!$A:$A,AI$8) | AJ29: =(AI29*AJ$4*(1-$B29)+AI29)+(AI28*AJ$4*$C28)+SUMIFS(Investments!$D:$D,Investments!$B:$B,$A29,Investments!$C:$C,"USDT",Investments!$A:$A,AJ$8) | AK29: =(AJ29*AK$4*(1-$B29)+AJ29)+(AJ28*AK$4*$C28)+SUMIFS(Investments!$D:$D,Investments!$B:$B,$A29,Investments!$C:$C,"USDT",Investments!$A:$A,AK$8) | AL29: =(AK29*AL$4*(1-$B29)+AK29)+(AK28*AL$4*$C28)+SUMIFS(Investments!$D:$D,Investments!$B:$B,$A29,Investments!$C:$C,"USDT",Investments!$A:$A,AL$8) | AM29: =(AL29*AM$4*(1-$B29)+AL29)+(AL28*AM$4*$C28)+SUMIFS(Investments!$D:$D,Investments!$B:$B,$A29,Investments!$C:$C,"USDT",Investments!$A:$A,AM$8) | AN29: =(AM29*AN$4*(1-$B29)+AM29)+(AM28*AN$4*$C28)+SUMIFS(Investments!$D:$D,Investments!$B:$B,$A29,Investments!$C:$C,"USDT",Investments!$A:$A,AN$8) | AO29: =(AN29*AO$4*(1-$B29)+AN29)+(AN28*AO$4*$C28)+SUMIFS(Investments!$D:$D,Investments!$B:$B,$A29,Investments!$C:$C,"USDT",Investments!$A:$A,AO$8) | ... AT29: =(AS29*AT$4*(1-$B29)+AS29)+(AS28*AT$4*$C28)+SUMIFS(Investments!$D:$D,Investments!$B:$B,$A29,Investments!$C:$C,"USDT",Investments!$A:$A,AT$8)
A30: Valeria Cruz | B30: 0.2 | D30: 0 | E30: =D30*$E$4*(1-$B30)+D30 | F30: =E30*$F$4*(1-$B30)+E30 | G30: =F30*$G$4*(1-$B30)+F30 | H30: =G30*$H$4*(1-$B30)+G30 | I30: =H30*$I$4*(1-$B30)+H30 | J30: =(I30*$J$4*(1-$B30)+I30) | K30: =(J30*$K$4*(1-$B30)+J30) | L30: =(K30*$L$4*(1-$B30)+K30) | M30: =(L30*$M$4*(1-$B30)+L30) | N30: =(M30*$N$4*(1-$B30)+M30) | O30: =(N30*$O$4*(1-$B30)+N30) | P30: =(O30*$P$4*(1-$B30)+O30) | Q30: =(P30*$Q$4*(1-$B30)+P30) | R30: =(Q30*$R$4*(1-$B30)+Q30) | S30: =(R30*$S$4*(1-$B30)+R30) | T30: =(S30*$T$4*(1-$B30)+S30) | U30: =(T30*$U$4*(1-$B30)+T30) | V30: =(U30*$V$4*(1-$B30)+U30) | W30: =(V30*$W$4*(1-$B30)+V30) | X30: =(W30*$X$4*(1-$B30)+W30) | Y30: =(X30*$Y$4*(1-$B30)+X30) | Z30: =(Y30*$Z$4*(1-$B30)+Y30) | AA30: =(Z30*$AA$4*(1-$B30)+Z30) | AB30: =(AA30*$AB$4*(1-$B30)+AA30)+50000 | AC30: =(AB30*$AC$4*(1-$B30)+AB30) | AD30: =(AC30*$AD$4*(1-$B30)+AC30) | AE30: =(AD30*$AE$4*(1-$B30)+AD30) | AF30: =(AE30*$AF$4*(1-$B30)+AE30) | AG30: =(AF30*$AG$4*(1-$B30)+AF30) | AH30: =(AG30*AH$4*(1-$B30)+AG30)+SUMIFS(Investments!$D:$D,Investments!$B:$B,$A30,Investments!$C:$C,"USDT",Investments!$A:$A,AH$8) | AI30: =(AH30*AI$4*(1-$B30)+AH30)+SUMIFS(Investments!$D:$D,Investments!$B:$B,$A30,Investments!$C:$C,"USDT",Investments!$A:$A,AI$8) | AJ30: =(AI30*AJ$4*(1-$B30)+AI30)+SUMIFS(Investments!$D:$D,Investments!$B:$B,$A30,Investments!$C:$C,"USDT",Investments!$A:$A,AJ$8) | AK30: =(AJ30*AK$4*(1-$B30)+AJ30)+SUMIFS(Investments!$D:$D,Investments!$B:$B,$A30,Investments!$C:$C,"USDT",Investments!$A:$A,AK$8) | AL30: =(AK30*AL$4*(1-$B30)+AK30)+SUMIFS(Investments!$D:$D,Investments!$B:$B,$A30,Investments!$C:$C,"USDT",Investments!$A:$A,AL$8) | AM30: =(AL30*AM$4*(1-$B30)+AL30)+SUMIFS(Investments!$D:$D,Investments!$B:$B,$A30,Investments!$C:$C,"USDT",Investments!$A:$A,AM$8) | AN30: =(AM30*AN$4*(1-$B30)+AM30)+SUMIFS(Investments!$D:$D,Investments!$B:$B,$A30,Investments!$C:$C,"USDT",Investments!$A:$A,AN$8) | AO30: =(AN30*AO$4*(1-$B30)+AN30)+SUMIFS(Investments!$D:$D,Investments!$B:$B,$A30,Investments!$C:$C,"USDT",Investments!$A:$A,AO$8) | ... AT30: =(AS30*AT$4*(1-$B30)+AS30)+SUMIFS(Investments!$D:$D,Investments!$B:$B,$A30,Investments!$C:$C,"USDT",Investments!$A:$A,AT$8)
A31: Ventures Life Style | B31: 0.16 | C31: 0.04 | D31: 0 | E31: =D31*$E$4*(1-$B31)+D31 | F31: =E31*$F$4*(1-$B31)+E31 | G31: =F31*$G$4*(1-$B31)+F31 | H31: =G31*$H$4*(1-$B31)+G31 | I31: =H31*$I$4*(1-$B31)+H31 | J31: =(I31*$J$4*(1-$B31)+I31) | K31: =(J31*$K$4*(1-$B31)+J31) | L31: =(K31*$L$4*(1-$B31)+K31) | M31: =(L31*$M$4*(1-$B31)+L31) | N31: =(M31*$N$4*(1-$B31)+M31) | O31: =(N31*$O$4*(1-$B31)+N31) | P31: =(O31*$P$4*(1-$B31)+O31) | Q31: =(P31*$Q$4*(1-$B31)+P31) | R31: =(Q31*$R$4*(1-$B31)+Q31) | S31: =(R31*$S$4*(1-$B31)+R31) | T31: =(S31*$T$4*(1-$B31)+S31) | U31: =(T31*$U$4*(1-$B31)+T31) | V31: =(U31*$V$4*(1-$B31)+U31) | W31: =(V31*$W$4*(1-$B31)+V31) | X31: =(W31*$X$4*(1-$B31)+W31) | Y31: =(X31*$Y$4*(1-$B31)+X31) | Z31: =(Y31*$Z$4*(1-$B31)+Y31) | AA31: =(Z31*$AA$4*(1-$B31-$C31)+Z31) | AB31: =(AA31*$AB$4*(1-$B31-$C31)+AA31) | AC31: =(AB31*$AC$4*(1-$B31-$C31)+AB31) | AD31: =(AC31*$AD$4*(1-$B31-$C31)+AC31)+100000 | AE31: =(AD31*$AE$4*(1-$B31-$C31)+AD31) | AF31: =(AE31*$AF$4*(1-$B31-$C31)+AE31) | AG31: =(AF31*$AG$4*(1-$B31-$C31)+AF31) | AH31: =(AG31*AH$4*(1-$B31-$C31)+AG31)+SUMIFS(Investments!$D:$D,Investments!$B:$B,$A31,Investments!$C:$C,"USDT",Investments!$A:$A,AH$8) | AI31: =(AH31*AI$4*(1-$B31-$C31)+AH31)+SUMIFS(Investments!$D:$D,Investments!$B:$B,$A31,Investments!$C:$C,"USDT",Investments!$A:$A,AI$8) | AJ31: =(AI31*AJ$4*(1-$B31-$C31)+AI31)+SUMIFS(Investments!$D:$D,Investments!$B:$B,$A31,Investments!$C:$C,"USDT",Investments!$A:$A,AJ$8) | AK31: =(AJ31*AK$4*(1-$B31-$C31)+AJ31)+SUMIFS(Investments!$D:$D,Investments!$B:$B,$A31,Investments!$C:$C,"USDT",Investments!$A:$A,AK$8) | AL31: =(AK31*AL$4*(1-$B31-$C31)+AK31)+SUMIFS(Investments!$D:$D,Investments!$B:$B,$A31,Investments!$C:$C,"USDT",Investments!$A:$A,AL$8) | AM31: =(AL31*AM$4*(1-$B31-$C31)+AL31)+SUMIFS(Investments!$D:$D,Investments!$B:$B,$A31,Investments!$C:$C,"USDT",Investments!$A:$A,AM$8) | AN31: =(AM31*AN$4*(1-$B31-$C31)+AM31)+SUMIFS(Investments!$D:$D,Investments!$B:$B,$A31,Investments!$C:$C,"USDT",Investments!$A:$A,AN$8) | AO31: =(AN31*AO$4*(1-$B31-$C31)+AN31)+SUMIFS(Investments!$D:$D,Investments!$B:$B,$A31,Investments!$C:$C,"USDT",Investments!$A:$A,AO$8) | ... AT31: =(AS31*AT$4*(1-$B31-$C31)+AS31)+SUMIFS(Investments!$D:$D,Investments!$B:$B,$A31,Investments!$C:$C,"USDT",Investments!$A:$A,AT$8)
