Workbook

Sheet DONE - BTC Boosted Program
A1: Date | B1: AUM | C1: Gross Performance (%) | D1: Gross Performance (BTC) | E1: Net Performance | F1: Yearly APY | G1: Comments | I1: Investors | J1: Fees | K1: 45640 | L1: 45658 | M1: 45689 | N1: 45717 | O1: 45748 | P1: 45763
A2: 45640 | B2: 11.5681 | C2: 1 | G2: Création du fond | I2: Indigo | J2: 0 | K2: 0 | L2: =K2*$C$3*1+K2+(K3*$C$3*0.15)+(K4*$C$3*0.1)+(K5*$C$3*0.1) -> 0.004558288 | M2: =L2*$C$4*1+L2+(L3*$C$4*0.15)+(L4*$C$4*0.1)+(L5*$C$4*0.1) -> 0.017654882 | N2: =M2*$C$5*1+M2+(M3*$C$5*0.15)+(M4*$C$5*0.1)+(M5*$C$5*0.1) -> 0.029768747 | O2: =N2*$C$6*1+N2+(N3*$C$6*0.15)+(N4*$C$6*0.1)+(N5*$C$6*0.1) -> 0.041981173 | P2: =O2*$C$7*1+O2+(O3*$C$7*0.15)+(O4*$C$7*0.1)+(O5*$C$7*0.1) -> 0.049814796
A3: 45658 | B3: 11.61 | C3: =(B3*$C$2/B2)-100% -> 0.0036220295 | D3: =B3-B2 -> 0.0419 | E3: =C3*0.8 -> 0.0028976236 | F3: =C3*12 -> 0.043464355 | I3: Kyle Gulamerian | J3: 0.15 | K3: 2.0336 | L3: =K3*$C$3*0.85+K3 -> 2.0398609 | M3: =L3*$C$4*0.85+L3 -> 2.0577822 | N3: =M3*$C$5*0.85+M3 -> 2.0741848 | O3: =N3*$C$6*0.85+N3 -> 2.0905645 | P3: =O3*$C$7*0.85+O3 -> 2.1009736
A4: 45689 | B4: 11.73 | C4: =(B4*$C$2/B3)-100% -> 0.010335917 | D4: =B4-B3 -> 0.12 | E4: =C4*0.8 -> 0.0082687338 | F4: =C4*12 -> 0.12403101 | I4: Matthias Reiser | J4: 0.1 | K4: 4.6717 | L4: =K4*$C$3*0.9+K4 -> 4.6869289 | M4: =L4*$C$4*0.9+L4 -> 4.7305283 | N4: =M4*$C$5*0.9+M4 -> 4.7704534 | O4: =N4*$C$6*0.9+N4 -> 4.8103415 | P4: =O4*$C$7*0.9+O4 -> 4.8357015
A5: 45717 | B5: 11.84 | C5: =(B5*$C$2/B4)-100% -> 0.0093776641 | D5: =B5-B4 -> 0.11 | E5: =C5*0.8 -> 0.0075021313 | F5: =C5*12 -> 0.11253197 | I5: Danielle Richetta | J5: 0.1 | K5: 4.8628 | L5: =K5*$C$3*0.9+K5 -> 4.8786519 | M5: =L5*$C$4*0.9+L5 -> 4.9240347 | N5: =M5*$C$5*0.9+M5 -> 4.965593 | O5: =N5*$C$6*0.9+N5 -> 5.0071128 | P5: =O5*$C$7*0.9+O5 -> 5.0335101
A6: 45747 | B6: 11.95 | C6: =(B6*$C$2/B5)-100% -> 0.0092905405 | D6: =B6-B5 -> 0.11 | E6: =C6*0.8 -> 0.0074324324 | F6: =C6*12 -> 0.11148649 | I6: Total AUM | K6: =SUM(K2:K5) -> 11.5681 | L6: =SUM(L2:L5) -> 11.61 | M6: =SUM(M2:M5) -> 11.73 | N6: =SUM(N2:N5) -> 11.84 | O6: =SUM(O2:O5) -> 11.95 | P6: =SUM(P2:P5) -> 12.02
A7: 45763 | B7: 12.02 | C7: =(B7*$C$2/B6)-100% -> 0.0058577406 | D7: =B7-B6 -> 0.07 | E7: =C7*0.8 -> 0.0046861925 | F7: =C7*12 -> 0.070292887
A8: Closing the fond + transfert the assets in BTC Yield Fund | I8: Indigo | K8: =IFERROR(K2/K$6,"") -> 0 | L8: =IFERROR(L2/L$6,"") -> 0.0003926174 | M8: =IFERROR(M2/M$6,"") -> 0.0015051051 | N8: =IFERROR(N2/N$6,"") -> 0.0025142523 | O8: =IFERROR(O2/O$6,"") -> 0.0035130689 | P8: =IFERROR(P2/P$6,"") -> 0.0041443258
I9: Kyle | K9: =IFERROR(K3/K$6,"") -> 0.17579378 | L9: =IFERROR(L3/L$6,"") -> 0.17569861 | M9: =IFERROR(M3/M$6,"") -> 0.175429 | N9: =IFERROR(N3/N$6,"") -> 0.17518452 | O9: =IFERROR(O3/O$6,"") -> 0.17494264 | P9: =IFERROR(P3/P$6,"") -> 0.17478982
A10: Total | B10: 4 Months | C10: =(B7-B2)/B2 -> 0.039064323 | D10: =B7-B2 -> 0.4519 | E10: =C10*0.8 -> 0.031251459 | F10: =E10/4*12 -> 0.093754376 | I10: Mathias | K10: =IFERROR(K4/K$6,"") -> 0.40384333 | L10: =IFERROR(L4/L$6,"") -> 0.40369758 | M10: =IFERROR(M4/M$6,"") -> 0.40328459 | N10: =IFERROR(N4/N$6,"") -> 0.40290992 | O10: =IFERROR(O4/O$6,"") -> 0.40253904 | P10: =IFERROR(P4/P$6,"") -> 0.40230462
I11: Danielle Richetta | K11: =IFERROR(K5/K$6,"") -> 0.42036289 | L11: =IFERROR(L5/L$6,"") -> 0.42021119 | M11: =IFERROR(M5/M$6,"") -> 0.4197813 | N11: =IFERROR(N5/N$6,"") -> 0.4193913 | O11: =IFERROR(O5/O$6,"") -> 0.41900525 | P11: =IFERROR(P5/P$6,"") -> 0.41876124
I12: Total AUM | K12: =SUM(K8:K11) -> 1 | L12: =SUM(L8:L11) -> 1 | M12: =SUM(M8:M11) -> 1 | N12: =SUM(N8:N11) -> 1 | O12: =SUM(O8:O11) -> 1 | P12: =SUM(P8:P11) -> 1

Sheet DONE - BTC TAC Program
A1: Date | B1: AUM | C1: Gross Performance (%) | D1: Gross Performance (BTC) | E1: Net Performance | F1: Yearly APY | G1: Comments | I1: Investors | J1: Fees | K1: 45748 | L1: 45778 | M1: 45809 | N1: 45839 | O1: 45849
A2: 45748 | B2: 11.4434 | C2: 1 | G2: Création du fond | I2: Indigo | J2: 0 | K2: 0 | L2: =K2*$C$3*1+K2+(K3*$C$3*$J$3)+(K4*$C$3*$J$4)+(K5*$C$3*$J$5)+(K6*$C$3*$J$6) -> 0 | M2: =L2*$C$4*1+L2+(L3*$C$4*$J$3)+(L4*$C$4*$J$4)+(L5*$C$4*$J$5)+(L6*$C$4*$J$6) -> 0 | N2: =M2*$C$5*1+M2+(M3*$C$5*$J$3)+(M4*$C$5*$J$4)+(M5*$C$5*$J$5)+(M6*$C$5*$J$6) -> 0 | O2: =N2*$C$5*1+N2+(N3*$C$5*$J$3)+(N4*$C$5*$J$4)+(N5*$C$5*$J$5)+(N6*$C$5*$J$6) -> 0
A3: 45778 | B3: 11.394 | C3: =(B3*$C$2/B2)-100% -> -0.0043168988 | D3: =B3-B2 -> -0.0494 | E3: =C3*0.8 -> -0.0034535191 | F3: =C3*12 -> -0.051802786 | I3: Victoria | J3: 0 | K3: 0.1492 | L3: =K3*$C$3*(1-$J3)+K3 -> 0.14855592 | M3: =L3*$C$4*(1-$J3)+L3 -> 0.14855983 | N3: =M3*$C$5*(1-$J3)+M3 -> 0.14855983 | O3: =N3*$C$6*(1-$J3)+N3 -> 0.14842554
A4: 45807 | B4: 11.3943 | C4: =(B4*$C$2/B3)-100% -> 2.6329647e-05 | D4: =B4-B3 -> 0.0003 | E4: =C4*0.8 -> 2.1063718e-05 | F4: =C4*12 -> 0.00031595577 | I4: Nathanael Cohen | J4: 0 | K4: 0.4483 | L4: =K4*$C$3*(1-$J4)+K4 -> 0.44636473 | M4: =L4*$C$4*(1-$J4)+L4 -> 0.44637649 | N4: =M4*$C$5*(1-$J4)+M4 -> 0.44637649 | O4: =N4*$C$6*(1-$J4)+N4 -> 0.44597298
A5: 45838 | B5: 11.3943 | C5: =(B5*$C$2/B4)-100% -> 0 | D5: =B5-B4 -> 0 | E5: =C5*0.8 -> 0 | F5: =C5*12 -> 0 | I5: Thomas Puech | J5: 0 | K5: 6.7249 | L5: =K5*$C$3*(1-$J5)+K5 -> 6.6958693 | M5: =L5*$C$4*(1-$J5)+L5 -> 6.6960456 | N5: =M5*$C$5*(1-$J5)+M5 -> 6.6960456 | O5: =N5*$C$6*(1-$J5)+N5 -> 6.6899926
A6: 45849 | B6: 11.384 | C6: =(B6*$C$2/B5)-100% -> -0.00090396075 | D6: =B6-B5 -> -0.0103 | E6: =C6*0.8 -> -0.0007231686 | F6: =C6*12 -> -0.010847529 | G6: End of fund and transfert to BTC Yield Fund | I6: Blondish | J6: 0 | K6: 4.121 | L6: =K6*$C$3*(1-$J6)+K6 -> 4.1032101 | M6: =L6*$C$4*(1-$J6)+L6 -> 4.1033181 | N6: =M6*$C$5*(1-$J6)+M6 -> 4.1033181 | O6: =N6*$C$6*(1-$J6)+N6 -> 4.0996089
A7: Closing the fond + transfert the assets in BTC Yield Fund | I7: Total | K7: =SUM(K2:K6) -> 11.4434 | L7: =SUM(L2:L6) -> 11.394 | M7: =SUM(M2:M6) -> 11.3943 | N7: =SUM(N2:N6) -> 11.3943 | O7: =SUM(O2:O6) -> 11.384
A9: Total | B9: 3.5 Months | C9: =(B6-B2)/B2 -> -0.005190765 | D9: =B6-B2 -> -0.0594 | E9: =C9*0.8 -> -0.004152612 | F9: =E9/3.5*12 -> -0.014237527 | I9: Indigo | K9: =IFERROR(K2/K$7,"") -> 0 | L9: =IFERROR(L2/L$7,"") -> 0 | M9: =IFERROR(M2/M$7,"") -> 0 | N9: =IFERROR(N2/N$7,"") -> 0 | O9: =IFERROR(O2/O$7,"") -> 0
I10: Maman | K10: =IFERROR(K3/K$7,"") -> 0.013038083 | L10: =IFERROR(L3/L$7,"") -> 0.013038083 | M10: =IFERROR(M3/M$7,"") -> 0.013038083 | N10: =IFERROR(N3/N$7,"") -> 0.013038083 | O10: =IFERROR(O3/O$7,"") -> 0.013038083
I11: Nathanael | K11: =IFERROR(K4/K$7,"") -> 0.03917542 | L11: =IFERROR(L4/L$7,"") -> 0.03917542 | M11: =IFERROR(M4/M$7,"") -> 0.03917542 | N11: =IFERROR(N4/N$7,"") -> 0.03917542 | O11: =IFERROR(O4/O$7,"") -> 0.03917542
I12: Thomas | K12: =IFERROR(K5/K$7,"") -> 0.58766625 | L12: =IFERROR(L5/L$7,"") -> 0.58766625 | M12: =IFERROR(M5/M$7,"") -> 0.58766625 | N12: =IFERROR(N5/N$7,"") -> 0.58766625 | O12: =IFERROR(O5/O$7,"") -> 0.58766625
I13: Vivie | K13: =IFERROR(K6/K$7,"") -> 0.36012024 | L13: =IFERROR(L6/L$7,"") -> 0.36012024 | M13: =IFERROR(M6/M$7,"") -> 0.36012024 | N13: =IFERROR(N6/N$7,"") -> 0.36012024 | O13: =IFERROR(O6/O$7,"") -> 0.36012024
I14: Total AUM | K14: =SUM(K9:K13) -> 1 | L14: =SUM(L9:L13) -> 1 | M14: =SUM(M9:M13) -> 1 | N14: =SUM(N9:N13) -> 1 | O14: =SUM(O9:O13) -> 1

Sheet Done - ETH TAC Program
A1: Date | B1: AUM | C1: Gross Performance (%) | D1: Gross Performance (ETH) | E1: Net Performance | F1: Yearly APY | G1: Comments | I1: Investors | J1: Fees | K1: 45505 | L1: 45536 | M1: 45566 | N1: 45589 | O1: 45597 | P1: 45627 | Q1: 45658 | R1: 45689 | S1: 45717 | T1: 45748 | U1: 45778 | V1: 45809 | W1: 45839 | X1: 45849
A2: 45474 | B2: 61.5 | C2: 1 | G2: Creation du fond | I2: Indigo | J2: 0 | K2: =B2*C3*0.2 -> 0.154 | L2: =K2*$C$4*1+K2+(K3*$C$4*0.2) -> 0.26508816 | M2: =L2*$C$5*1+L2+(L3*$C$5*0.2) -> 0.36880985 | N2: =M2*$C$7*1+M2+(M3*$C$7*0.2) -> 0.43173539 | O2: =N2*$C$9*1+N2+(N3*$C$9*0.2) -> 0.43173539 | P2: =O2*$C$10*1+O2+(O3*$C$10*0.2) -> 0.43173539 | Q2: =P2*$C$11*1+P2+(P3*$C$11*0.2) -> 0.43173539 | R2: =Q2*$C$12*1+Q2+(Q3*$C$12*0.2) -> 0.50513683 | S2: =R2*$C$13*1+R2+(R3*$C$13*0.2) -> 0.66886119 | T2: =S2*$C$15*1+S2+(S3*$C$15*0.2) -> 0.7072813 | U2: =T2*$C$17*1+T2+(T3*$C$17*0.2) -> 0.86944735 | V2: =U2*$C$18*1+U2+(U3*$C$18*0.2) -> 0.90224763 | W2: =V2*$C$19*1+V2+(V3*$C$19*0.2) -> 0.9337404 | X2: =W2*$C$20*1+W2 -> 0.89796587
A3: 45505 | B3: 62.27 | C3: =(B3*$C$2/B2)-100% -> 0.012520325 | D3: =B3-B2 -> 0.77 | E3: =C3*0.8 -> 0.01001626 | F3: =C3*12 -> 0.1502439 | I3: Jose Molla | J3: 0.2 | K3: =B2*C3*0.8+B2 -> 62.116 | L3: =K3*$C$4*0.8+K3 -> 62.554912 | M3: =L3*$C$5*0.8+L3 -> 62.96119 | N3: =M3*$C$7*0.8+M3 -> 63.20573 | O3: =N3*$C$9*0.8+N3 -> 63.20573 | P3: =O3*$C$10*0.8+O3 -> 63.20573 | Q3: =P3*$C$11*0.8+P3 -> 63.20573 | R3: =Q3*$C$12*0.8+Q3 -> 63.489639 | S3: =R3*$C$13*0.8+R3 -> 64.119481 | T3: =S3*$C$15*0.8+S3 -> 64.265543 | U3: =T3*$C$17*0.8+T3 -> 64.880375 | V3: =U3*$C$18*0.8+U3 -> 65.003337 | W3: =V3*$C$19*0.8+V3 -> 65.121133 | X3: =W3*$C$20+W3 -> 62.626138
A4: 45537 | B4: 62.82 | C4: =(B4*$C$2/B3)-100% -> 0.0088325036 | D4: =B4-B3 -> 0.55 | E4: =C4*0.8 -> 0.0070660029 | F4: =C4*12 -> 0.10599004 | I4: Nathanael Cohen | J4: 0 | K4: 0 | L4: 0 | M4: 17 | N4: =M4*$C$7+M4 -> 17.082535 | O4: =N4*$C$9+N4 -> 17.082535 | P4: =O4*$C$10+O4 -> 17.082535 | Q4: =P4*$C$11+P4 -> 17.082535 | R4: =Q4*$C$12+Q4 -> 17.178449 | S4: =R4*$C$13+R4+4.608 -> 21.99947 | T4: =S4*$C$15+S4+5.226 -> 27.288113 | U4: =T4*$C$17+T4 -> 27.614446 | V4: =U4*$C$18+U4 -> 27.679865 | W4: =V4*$C$19+V4 -> 27.742566 | X4: =W4*$C$20+W4 -> 26.679661
A5: 45566 | B5: 63.33 | C5: =(B5/B4)-100% -> 0.0081184336 | D5: =B5-B4 -> 0.51 | E5: =C5*0.8 -> 0.0064947469 | F5: =C5*12 -> 0.097421203 | I5: Blondish | J5: 0 | K5: 0 | L5: 0 | M5: 0 | N5: 120 | O5: =N5*$C$9+N5 -> 120 | P5: =O5*$C$10+O5 -> 120 | Q5: =P5*$C$11+P5 -> 120 | R5: =Q5*$C$12+Q5 -> 120.67377 | S5: =R5*$C$13+R5 -> 122.17019 | T5: =S5*$C$15+S5 -> 122.51806 | U5: =T5*$C$17+T5 -> 123.98323 | V5: =U5*$C$18+U5 -> 124.27695 | W5: =V5*$C$19+V5 -> 124.55846 | X5: =W5*$C$20+W5 -> 119.78624
A6: 45565 | B6: =17+B5 -> 80.33 | C6: 1 | G6: Entrée de Nathanael avec 17 ETH | I6: Total AUM | K6: =SUM(K2:K5) -> 62.27 | L6: =SUM(L2:L5) -> 62.82 | M6: =SUM(M2:M5) -> 80.33 | N6: =SUM(N2:N5) -> 200.72 | O6: =SUM(O2:O5) -> 200.72 | P6: =SUM(P2:P5) -> 200.72 | Q6: =SUM(Q2:Q5) -> 200.72 | R6: =SUM(R2:R5) -> 201.847 | ... X6: =SUM(X2:X5) -> 209.99
A7: 45589 | B7: 80.72 | C7: =(B7/B6)-100% -> 0.0048549732 | D7: =B7-B6 -> 0.39 | E7: =C7*0.8 -> 0.0038839786 | F7: =C7*12 -> 0.058259679
A8: 45590 | B8: =B7+120 -> 200.72 | C8: 1 | G8: Entrée de Blondish avec 120 ETH | I8: Indigo | K8: =IFERROR(K2/K$6,"") -> 0.002473101 | L8: =IFERROR(L2/L$6,"") -> 0.0042198052 | M8: =IFERROR(M2/M$6,"") -> 0.0045911844 | N8: =IFERROR(N2/N$6,"") -> 0.0021509336 | O8: =IFERROR(O2/O$6,"") -> 0.0021509336 | P8: =IFERROR(P2/P$6,"") -> 0.0021509336 | Q8: =IFERROR(Q2/Q$6,"") -> 0.0021509336 | R8: =IFERROR(R2/R$6,"") -> 0.0025025729 | ... X8: =IFERROR(X2/X$6,"") -> 0.0042762316
A9: 45597 | B9: 200.72 | C9: =(B9/B8)-100% -> 0 | D9: =B9-B8 -> 0 | E9: =C9*0.8 -> 0 | F9: =C9*12 -> 0 | I9: Jose | K9: =IFERROR(K3/K$6,"") -> 0.9975269 | L9: =IFERROR(L3/L$6,"") -> 0.99578019 | M9: =IFERROR(M3/M$6,"") -> 0.78378178 | N9: =IFERROR(N3/N$6,"") -> 0.31489503 | O9: =IFERROR(O3/O$6,"") -> 0.31489503 | P9: =IFERROR(P3/P$6,"") -> 0.31489503 | Q9: =IFERROR(Q3/Q$6,"") -> 0.31489503 | R9: =IFERROR(R3/R$6,"") -> 0.31454339 | ... X9: =IFERROR(X3/X$6,"") -> 0.29823391
A10: 45627 | B10: 200.72 | C10: =(B10/B9)-100% -> 0 | D10: =B10-B9 -> 0 | E10: =C10*0.8 -> 0 | F10: =C10*12 -> 0 | I10: Nathanael | K10: =IFERROR(K4/K$6,"") -> 0 | L10: =IFERROR(L4/L$6,"") -> 0 | M10: =IFERROR(M4/M$6,"") -> 0.21162704 | N10: =IFERROR(N4/N$6,"") -> 0.08510629 | O10: =IFERROR(O4/O$6,"") -> 0.08510629 | P10: =IFERROR(P4/P$6,"") -> 0.08510629 | Q10: =IFERROR(Q4/Q$6,"") -> 0.08510629 | R10: =IFERROR(R4/R$6,"") -> 0.08510629 | ... X10: =IFERROR(X4/X$6,"") -> 0.12705205
A11: 45658 | B11: 200.72 | C11: =(B11/B10)-100% -> 0 | D11: =B11-B10 -> 0 | E11: =C11*0.8 -> 0 | F11: =C11*12 -> 0 | I11: Blondish | K11: =IFERROR(K5/K$6,"") -> 0 | L11: =IFERROR(L5/L$6,"") -> 0 | M11: =IFERROR(M5/M$6,"") -> 0 | N11: =IFERROR(N5/N$6,"") -> 0.59784775 | O11: =IFERROR(O5/O$6,"") -> 0.59784775 | P11: =IFERROR(P5/P$6,"") -> 0.59784775 | Q11: =IFERROR(Q5/Q$6,"") -> 0.59784775 | R11: =IFERROR(R5/R$6,"") -> 0.59784775 | ... X11: =IFERROR(X5/X$6,"") -> 0.57043781
A12: 45689 | B12: 201.847 | C12: =(B12/B11)-100% -> 0.0056147868 | D12: =B12-B11 -> 1.127 | E12: =C12*0.8 -> 0.0044918294 | F12: =C12*12 -> 0.067377441 | I12: Total AUM | K12: =SUM(K8:K11) -> 1 | L12: =SUM(L8:L11) -> 1 | M12: =SUM(M8:M11) -> 1 | N12: =SUM(N8:N11) -> 1 | O12: =SUM(O8:O11) -> 1 | P12: =SUM(P8:P11) -> 1 | Q12: =SUM(Q8:Q11) -> 1 | R12: =SUM(R8:R11) -> 1 | ... X12: =SUM(X8:X11) -> 1
A13: 45717 | B13: 204.35 | C13: =(B13/B12)-100% -> 0.012400482 | D13: =B13-B12 -> 2.503 | E13: =C13*0.8 -> 0.0099203852 | F13: =C13*12 -> 0.14880578
A14: 45717 | B14: =B13+4.608 -> 208.958 | C14: 1 | G14: Top up de Nathanael avec 4.608 ETH
A15: 45747 | B15: 209.553 | C15: =(B15/B14)-100% -> 0.0028474622 | D15: =B15-B14 -> 0.595 | E15: =C15*0.8 -> 0.0022779697 | F15: =C15*12 -> 0.034169546
A16: 45748 | B16: =B15+5.226 -> 214.779 | C16: 1 | G16: Top up de Nathanael avec 5.226 ETH
A17: 45778 | B17: 217.3475 | C17: =(B17/B16)-100% -> 0.011958804 | D17: =B17-B16 -> 2.5685 | E17: =C17*0.8 -> 0.0095670433 | F17: =C17*12 -> 0.14350565
A18: 45807 | B18: 217.8624 | C18: =(B18/B17)-100% -> 0.0023690174 | D18: =B18-B17 -> 0.5149 | E18: =C18*0.8 -> 0.0018952139 | F18: =C18*12 -> 0.028428208
A19: 45838 | B19: 218.3559 | C19: =(B19/B18)-100% -> 0.0022651912 | D19: =B19-B18 -> 0.4935 | E19: =C19*0.8 -> 0.001812153 | F19: =C19*12 -> 0.027182295
A20: 45849 | B20: =209.85+0.14 -> 209.99 | C20: =(B20/B19)-100% -> -0.038313139 | D20: =B20-B19 -> -8.3659 | E20: =C20*0.8 -> -0.030650511 | F20: =C20*12 -> -0.45975767 | G20: End of fund and transfert to ETH Yield Fund
A21: Closing the fond + transfert the assets in ETH Yield Fund
A23: Total | B23: 11.5 Months | C23: =(B20-(B2+17+120+4.608+5.226))/(B2+17+120+4.608+5.226) -> 0.0079487746 | D23: =B20-(B2+17+120+4.608+5.226) -> 1.656 | E23: =C23*0.8 -> 0.0063590197 | F23: =E23/11.5*12 -> 0.0066354988

Sheet Investments
A1: Investment Date | B1: Investor Name | C1: Currency | D1: Amount | E1: Email
A2: 45455 | B2: Jose Molla | C2: BTC | D2: 2.723
A3: 45455 | B3: Jose Molla | C3: ETH | D3: 52.4
A4: 45481 | B4: Jose Molla | C4: BTC | D4: 0.745
A5: 45481 | B5: Jose Molla | C5: ETH | D5: 9.1
A6: 45525 | B6: Kyle Gulamerian | C6: BTC | D6: 0.01
A7: 45525 | B7: Kyle Gulamerian | C7: BTC | D7: 1.99
A8: 45566 | B8: Matthias Reiser | C8: BTC | D8: 4.62 | E8: matthias@xventures.de
A9: 45566 | B9: Thomas Puech | C9: BTC | D9: 6.5193
A10: 45566 | B10: Danielle Richetta | C10: BTC | D10: 5.2 | E10: danielle@iamfashion-st.com
A11: 45566 | B11: Nathanaël Cohen | C11: ETH | D11: 17
A12: 45589 | B12: Blondish | C12: ETH | D12: 120
A13: 45605 | B13: Danielle Richetta | C13: BTC | D13: -0.27
A14: 45640 | B14: Danielle Richetta | C14: BTC | D14: -0.124
A15: 45717 | B15: Nathanaël Cohen | C15: ETH | D15: 4.608
A16: 45747 | B16: Nathanaël Cohen | C16: ETH | D16: 5.226
A17: 45748 | B17: Victoria | C17: BTC | D17: 0.1492 | E17: TAC Program
A18: 45748 | B18: Nathanaël Cohen | C18: BTC | D18: 0.4483 | E18: TAC Program
A19: 45748 | B19: Blondish | C19: BTC | D19: 4.121 | E19: TAC Program
A20: 45803 | B20: Babak Eftekhari | C20: ETH | D20: 27.01 | E20: Babak.eftekhari@gmail.com
A21: 45803 | B21: Indigo Main Fund | C21: ETH | D21: 175
A22: 45807 | B22: Nathanaël Cohen | C22: ETH | D22: 3.0466
A23: 45807 | B23: Babak Eftekhari | C23: ETH | D23: 32.25
A24: 45807 | B24: danielle Richetta | C24: BTC | D24: -0.13
A25: 45819 | B25: Kabbaj Fam | C25: BTC | D25: 2 | E25: H.kabbaj@sgtm-maroc.com | F25: Hicham.kabbaj@sgtm-maroc.com
A26: 45824 | B26: Babak Eftekhari | C26: USDT | D26: =134026.75+1700 -> 135726.75
A27: 45838 | B27: Nathanaël Cohen | C27: ETH | D27: 2 | E27: ETH Yield Fund
A28: 45848 | B28: julien grunebaum | C28: USDT | D28: 109392 | E28: julien.grunebaum@icloud.com
A29: 45848 | B29: daniele francilia | C29: USDT | D29: 109776 | E29: danielefrancilia@gmail.com
A30: 45848 | B30: pierre bezencon | C30: USDT | D30: 109333 | E30: pib@bruellan.ch
A31: 45848 | B31: matthew beatty | C31: USDT | D31: 255504 | E31: Matthew@beattyvermeiren.co.za
A32: 45849 | B32: Kabbaj Fam | C32: BTC | D32: 0.9914
A33: 45852 | B33: julien grunebaum | C33: USDT | D33: 109392
A34: 45852 | B34: Daniele Francilia | C34: USDT | D34: 109776
A35: 45852 | B35: Pierre Bezencon | C35: USDT | D35: 109333
A36: 45852 | B36: Matthew Beatty | C36: USDT | D36: 255504
A37: 45852 | B37: Bo Kriek | C37: USDT | D37: 273807 | E37: bokriek@hotmail.com
A38: 45855 | B38: Dario Deiana | C38: USDT | D38: 199659.72
A39: 45855 | B39: Babak Eftekhari | C39: USDT | D39: 46955.28
A40: 45861 | B40: Alain Bensimon | C40: USDT | D40: 136737
A41: 45861 | B41: Anne Cecile Noique | C41: USDT | D41: 222687
A42: 45861 | B42: Terance Chen | C42: USDT | D42: 219747
A43: 45862 | B43: Oliver Loisel | C43: BTC | D43: 2.115364
A44: 45863 | B44: Danielle Richetta | C44: BTC | D44: -0.26
A45: 45868 | B45: Advantage Blockchain | C45: ETH | D45: 32
A46: 45868 | B46: INDIGO Main Fund | C46: ETH | D46: -178.37
A47: 45869 | B47: Kabbaj Fam | C47: BTC | D47: 0.6
A48: 45873 | B48: INDIGO Venture | C48: USDT | D48: 130000
A49: 45873 | B49: Babak Eftekhari | C49: USDT | D49: 10000
... A52: 45889 | B52: Danielle Richetta | C52: BTC | D52: -0.11

Sheet BTC Yield Fund
A1: Date | B1: AUM | C1: Gross Performance (%) | D1: Gross Performance (BTC) | E1: Net Performance | F1: Yearly APY | G1: Commentaires | I1: Investors | J1: Fees | K1: 45505 | L1: 45526 | M1: 45536 | N1: 45566 | O1: 45597 | P1: 45605 | Q1: 45627 | R1: 45640 | S1: 45640 | T1: 45658 | U1: 45689 | V1: 45717 | W1: 45748 | X1: 45763 | Y1: 45778 | Z1: 45790 | AA1: 45809 | AB1: 45819 | AC1: 45839 | AD1: 45849 | AE1: 45862 | AF1: 45863 | AG1: 45869 | AH1: 45889 | AI1: 45894 | AJ1: 45901
A2: 45474 | B2: 3.468 | C2: 1 | G2: Set up the fund | I2: Indigo | J2: 0 | K2: =B2*C3*$J$3 -> 0.0044 | L2: =K2*$C$4*1+K2+(K3*$C$4*$J$3) -> 0.006410086 | M2: =L2*$C$6*1+L2+(L3*$C$6*$J$3)+(L4*$C$6*$J$4) -> 0.0082375915 | N2: =M2*$C$7*1+M2+(M3*$C$7*$J$3)+(M4*$C$7*$J$4) -> 0.013728166 | O2: =N2*$C$9*1+N2+(N3*$C$9*$J$3)+(N4*$C$9*$J$4)+(N5*$C$9*$J$5)+(N7*$C$9*$J$7) -> 0.023849164 | P2: =O2*$C$10*1+O2+(O3*$C$10*$J$3)+(O4*$C$10*$J$4)+(O5*$C$10*$J$5)+(O7*$C$10*$J$7) -> 0.026603734 | Q2: =P2*$C$12*1+P2+(P3*$C$12*$J$3)+(P4*$C$12*$J$4)+(P5*$C$12*$J$5)+(P7*$C$12*$J$7) -> 0.034867958 | R2: =Q2*$C$13*1+Q2+(Q3*$C$13*$J$3)+(Q4*$C$13*$J$4)+(Q5*$C$13*$J$5)+(Q7*$C$13*$J$7) -> 0.038553736 | S2: =R2 -> 0.038553736 | T2: =S2*$C$16*1+S2+(S3*$C$16*$J$3)+(S4*$C$16*$J$4)+(S5*$C$16*$J$5)+(S7*$C$16*$J$7) -> 0.042380616 | U2: =T2*$C$17*1+T2+(T3*$C$17*$J$3)+(T4*$C$17*$J$4)+(T5*$C$17*$J$5)+(T7*$C$17*$J$7) -> 0.046804784 | V2: =U2*$C$18*1+U2+(U3*$C$18*$J$3)+(U4*$C$18*$J$4)+(U5*$C$18*$J$5)+(U7*$C$18*$J$7) -> 0.049767204 | W2: =V2*$C$19*1+V2+(V3*$C$19*$J$3)+(V4*$C$19*$J$4)+(V5*$C$19*$J$5)+(V7*$C$19*$J$7) -> 0.052738229 | X2: =W2*$C$21*1+W2+(W3*$C$21*$J$3)+(W4*$C$21*$J$4)+(W5*$C$21*$J$5)+(W7*$C$21*$J$7)+0.0498 -> 0.1078056 | Y2: =X2*$C$23*1+X2+(X3*$C$23*$J$3)+(X4*$C$23*$J$4)+(X5*$C$23*$J$5)+(X7*$C$23*$J$7) -> 0.11596204 | Z2: =Y2*$C$24*1+Y2+(Y3*$C$24*$J$3)+(Y4*$C$24*$J$4)+(Y5*$C$24*$J$5)+(Y7*$C$24*$J$7) -> 0.11868927 | AA2: =Z2*$C$27*1+Z2+(Z3*$C$27*$J$3)+(Z4*$C$27*$J$4)+(Z5*$C$27*$J$5)+(Z7*$C$27*$J$7) -> 0.12730526 | AB2: =AA2*$C$29*1+AA2+(AA3*$C$29*$J$3)+(AA4*$C$29*$J$4)+(AA5*$C$29*$J$5)+(AA7*$C$29*$J$7) -> 0.13279661 | AC2: =AB2*$C$31*1+AB2+(AB3*$C$31*$J$3)+(AB4*$C$31*$J$4)+(AB5*$C$31*$J$5)+(AB7*$C$31*$J$7)+(AB8*$C$31*$J$8) -> 0.13468055 | AD2: =AC2*$C$32*1+AC2+(AC3*$C$32*$J$3)+(AC4*$C$32*$J$4)+(AC5*$C$32*$J$5)+(AC7*$C$32*$J$7)+(AC8*$C$32*$J$8) -> 0.14331502 | AE2: =AD2*$C$34*1+AD2+(AD3*$C$34*$J$3)+(AD4*$C$34*$J$4)+(AD5*$C$34*$J$5)+(AD6*$C$34*$J$6)+(AD7*$C$34*$J$7)+(AD8*$C$34*$J$8)+(AD9*$C$34*$J$9)+(AD10*$C$34*$J$10)+(AD11*$C$34*$J$11)+(AD12*$C$34*$J$12) -> 0.14398243 | AF2: =AE2*$C$36*1+AE2+(AE3*$C$36*$J$3)+(AE4*$C$36*$J$4)+(AE5*$C$36*$J$5)+(AE6*$C$36*$J$6)+(AE7*$C$36*$J$7)+(AE8*$C$36*$J$8)+(AE9*$C$36*$J$9)+(AE10*$C$36*$J$10)+(AE11*$C$36*$J$11)+(AE12*$C$36*$J$12) -> 0.14412752 | AG2: =AF2*$C$38*1+AF2+(AF3*$C$38*$J$3)+(AF4*$C$38*$J$4)+(AF5*$C$38*$J$5)+(AF6*$C$38*$J$6)+(AF7*$C$38*$J$7)+(AF8*$C$38*$J$8)+(AF9*$C$38*$J$9)+(AF10*$C$38*$J$10)+(AF11*$C$38*$J$11)+(AF12*$C$38*$J$12) -> 0.14589939 | AH2: =AG2*$C$40*1+AG2+(AG3*$C$40*$J$3)+(AG4*$C$40*$J$4)+(AG5*$C$40*$J$5)+(AG6*$C$40*$J$6)+(AG7*$C$40*$J$7)+(AG8*$C$40*$J$8)+(AG9*$C$40*$J$9)+(AG10*$C$40*$J$10)+(AG11*$C$40*$J$11)+(AG12*$C$40*$J$12) -> 0.15337434 | AI2: =AH2*$C$42*1+AH2+(AH3*$C$42*$J$3)+(AH4*$C$42*$J$4)+(AH5*$C$42*$J$5)+(AH6*$C$42*$J$6)+(AH7*$C$42*$J$7)+(AH8*$C$42*$J$8)+(AH9*$C$42*$J$9)+(AH10*$C$42*$J$10)+(AH11*$C$42*$J$11)+(AH12*$C$42*$J$12) -> 0.15473916 | AJ2: =AI2*$C$44*1+AI2+(AI3*$C$44*$J$3)+(AI4*$C$44*$J$4)+(AI5*$C$44*$J$5)+(AI6*$C$44*$J$6)+(AI7*$C$44*$J$7)+(AI8*$C$44*$J$8)+(AI9*$C$44*$J$9)+(AI10*$C$44*$J$10)+(AI11*$C$44*$J$11)+(AI12*$C$44*$J$12) -> 0.15613296
A3: 45505 | B3: 3.49 | C3: =(B3*$C$2/B2)-100% -> 0.006343714 | D3: =B3-B2 -> 0.022 | E3: =C3*0.8 -> 0.0050749712 | F3: =C3*12 -> 0.076124567 | I3: Jose Molla | J3: 0.2 | K3: =B2*C3*(1-$J3)+B2 -> 3.4856 | L3: =K3*C4*(1-$J3)+K3 -> 3.4935899 | M3: =L3*$C$6*(1-$J3)+L3 -> 3.4986715 | N3: =M3*$C$7*(1-$J3)+M3 -> 3.5139107 | O3: =N3*$C$9*(1-$J3)+N3 -> 3.5281338 | P3: =O3*$C$10*(1-$J3)+O3 -> 3.5319845 | Q3: =P3*$C$12*(1-$J3)+P3 -> 3.5436766 | R3: =Q3*$C$13*(1-$J3)+Q3 -> 3.5488688 | S3: =R3 -> 3.5488688 | T3: =S3*$C$16*(1-$J3)+S3 -> 3.5633876 | U3: =T3*$C$17*(1-$J3)+T3 -> 3.580091 | V3: =U3*$C$18*(1-$J3)+U3 -> 3.5912136 | W3: =V3*$C$19*(1-$J3)+V3 -> 3.6023276 | X3: =W3*$C$21*(1-$J3)+W3 -> 3.62196 | Y3: =X3*$C$23*(1-$J3)+X3 -> 3.6330335 | Z3: =Y3*$C$24*(1-$J3)+Y3 -> 3.6367219 | AA3: =Z3*$C$27*(1-$J3)+Z3 -> 3.650364 | AB3: =AA3*$C$29*(1-$J3)+AA3 -> 3.6590794 | AC3: =AB3*$C$31*(1-$J3)+AB3 -> 3.6615306 | AD3: =AC3*$C$32*(1-$J3)+AC3 -> 3.6727553 | AE3: =AD3*$C$34*(1-$J3)+AD3 -> 3.6735502 | AF3: =AE3*$C$36*(1-$J3)+AE3 -> 3.6737093 | AG3: =AF3*$C$38*(1-$J3)+AF3 -> 3.6756714 | AH3: =AG3*$C$40*(1-$J3)+AG3 -> 3.6835858 | AI3: =AH3*$C$42*(1-$J3)+AH3 -> 3.6850327 | AJ3: =AI3*$C$44*(1-$J3)+AI3 -> 3.6864189
A4: 45525 | B4: 3.5 | C4: =(B4*$C$2/B3)-100% -> 0.0028653295 | D4: =B4-B3 -> 0.01 | E4: =C4*0.8 -> 0.0022922636 | F4: =C4*12 -> 0.034383954 | I4: Kyle Gulamerian | J4: 0.15 | K4: 0 | L4: 2 | M4: =L4*$C$6*(1-$J4)+L4 -> 2.0030909 | N4: =M4*$C$7*(1-$J4)+M4 -> 2.0123611 | O4: =N4*$C$9*(1-$J4)+N4 -> 2.0210156 | P4: =O4*$C$10*(1-$J4)+O4 -> 2.0233592 | Q4: =P4*$C$12*(1-$J4)+P4 -> 2.0304758 | R4: =Q4*$C$13*(1-$J4)+Q4 -> 2.0336368 | S4: =R4-R4 -> 0 | T4: =S4*$C$16*(1-$J4)+S4 -> 0 | U4: =T4*$C$17*(1-$J4)+T4 -> 0 | V4: =U4*$C$18*(1-$J4)+U4 -> 0 | W4: =V4*$C$19*(1-$J4)+V4 -> 0 | X4: =W4*$C$21*(1-$J4)+W4+2.101 -> 2.101 | Y4: =X4*$C$23*(1-$J4)+X4 -> 2.1078249 | Z4: =Y4*$C$24*(1-$J4)+Y4-(Y4*$C$24*(1-$J4)+Y4) -> 0 | AA4: =Z4*$C$27*(1-$J4)+Z4-(Z4*$C$27*(1-$J4)+Z4) -> 0 | AB4: =AA4*$C$29*(1-$J4)+AA4-(AA4*$C$29*(1-$J4)+AA4) -> 0 | AC4: =AB4*$C$31*(1-$J4)+AB4-(AB4*$C$31*(1-$J4)+AB4) -> 0 | AD4: =AC4*$C$32*(1-$J4)+AC4-(AC4*$C$32*(1-$J4)+AC4) -> 0 | AE4: =AD4*$C$34*(1-$J4)+AD4-(AD4*$C$34*(1-$J4)+AD4) -> 0 | AF4: =AE4*$C$36*(1-$J4)+AE4-(AE4*$C$36*(1-$J4)+AE4) -> 0 | AG4: =AF4*$C$38*(1-$J4)+AF4-(AF4*$C$38*(1-$J4)+AF4) -> 0 | AH4: =AG4*$C$40*(1-$J4)+AG4-(AG4*$C$40*(1-$J4)+AG4) -> 0 | AI4: =AH4*$C$42*(1-$J4)+AH4-(AH4*$C$42*(1-$J4)+AH4) -> 0 | AJ4: =AI4*$C$44*(1-$J4)+AI4-(AI4*$C$44*(1-$J4)+AI4) -> 0
A5: 45526 | B5: =3.5+2 -> 5.5 | C5: 1 | G5: Invest of Kyle with 2 BTC | I5: Matthias Reiser | J5: 0.1 | K5: 0 | L5: 0 | M5: 0 | N5: 4.62 | O5: =N5*$C$9*(1-$J5)+N5 -> 4.6410377 | P5: =O5*$C$10*(1-$J5)+O5 -> 4.6467361 | Q5: =P5*$C$12*(1-$J5)+P5 -> 4.6640412 | R5: =Q5*$C$13*(1-$J5)+Q5 -> 4.6717292 | S5: =R5-R5 -> 0 | T5: =S5*$C$16*(1-$J5)+S5 -> 0 | U5: =T5*$C$17*(1-$J5)+T5 -> 0 | V5: =U5*$C$18*(1-$J5)+U5 -> 0 | W5: =V5*$C$19*(1-$J5)+V5 -> 0 | X5: =W5*$C$21*(1-$J5)+W5+4.8357 -> 4.8357 | Y5: =X5*$C$23*(1-$J5)+X5 -> 4.8523323 | Z5: =Y5*$C$24*(1-$J5)+Y5 -> 4.8578743 | AA5: =Z5*$C$27*(1-$J5)+Z5 -> 4.8783752 | AB5: =AA5*$C$29*(1-$J5)+AA5 -> 4.8914784 | AC5: =AB5*$C$31*(1-$J5)+AB5 -> 4.8951647 | AD5: =AC5*$C$32*(1-$J5)+AC5 -> 4.912047 | AE5: =AD5*$C$34*(1-$J5)+AD5 -> 4.913243 | AF5: =AE5*$C$36*(1-$J5)+AE5 -> 4.9134824 | AG5: =AF5*$C$38*(1-$J5)+AF5 -> 4.9164347 | AH5: =AG5*$C$40*(1-$J5)+AG5 -> 4.928344 | AI5: =AH5*$C$42*(1-$J5)+AH5 -> 4.9305218 | AJ5: =AI5*$C$44*(1-$J5)+AI5 -> 4.9326084
A6: 45536 | B6: 5.51 | C6: =(B6*$C$5/B5)-100% -> 0.0018181818 | D6: =B6-B5 -> 0.01 | E6: =C6*0.8 -> 0.0014545455 | F6: =C6*12 -> 0.021818182 | I6: Thomas Puech | J6: 0 | K6: 0 | L6: 0 | M6: 0 | N6: 6.5193 | O6: =N6*$C$9*(1-$J6)+N6 -> 6.5522849 | P6: =O6*$C$10*(1-$J6)+O6 -> 6.5612239 | Q6: =P6*$C$12*(1-$J6)+P6 -> 6.5883738 | R6: =Q6*$C$13*(1-$J6)+Q6 -> 6.6004404 | S6: =R6 -> 6.6004404 | T6: =S6*$C$16*(1-$J6)+S6 -> 6.6341945 | U6: =T6*$C$17*(1-$J6)+T6 -> 6.6730667 | V6: =U6*$C$18*(1-$J6)+U6 -> 6.6989815 | W6: =(V6*$C$19*(1-$J6)+V6)-(V6*$C$19*(1-$J6)+V6) -> 0 | X6: =W6*$C$21*(1-$J6)+W6 -> 0 | Y6: =X6*$C$23*(1-$J6)+X6 -> 0 | Z6: =Y6*$C$24*(1-$J6)+Y6 -> 0 | AA6: =Z6*$C$27*(1-$J6)+Z6 -> 0 | AB6: =AA6*$C$29*(1-$J6)+AA6 -> 0 | AC6: =AB6*$C$31*(1-$J6)+AB6 -> 0 | AD6: =AC6*$C$32*(1-$J6)+AC6+6.69 -> 6.69 | AE6: =AD6*$C$34*(1-$J6)+AD6 -> 6.6918098 | AF6: =AE6*$C$36*(1-$J6)+AE6 -> 6.6921722 | AG6: =AF6*$C$38*(1-$J6)+AF6 -> 6.6966399 | AH6: =AG6*$C$40*(1-$J6)+AG6 -> 6.7146639 | AI6: =AH6*$C$42*(1-$J6)+AH6 -> 6.7179608 | AJ6: =AI6*$C$44*(1-$J6)+AI6 -> 6.7211197
A7: 45565 | B7: 5.54 | C7: =(B7/B6)-100% -> 0.0054446461 | D7: =B7-B6 -> 0.03 | E7: =C7*0.8 -> 0.0043557169 | F7: =C7*12 -> 0.065335753 | I7: Danielle Richetta | J7: 0.1 | K7: 0 | L7: 0 | M7: 0 | N7: 5.2 | O7: =N7*$C$9*(1-$J7)+N7 -> 5.2236788 | P7: =O7*$C$10*(1-$J7)+O7-0.27 -> 4.9600926 | Q7: =P7*$C$12*(1-$J7)+P7 -> 4.9785647 | R7: =Q7*$C$13*(1-$J7)+Q7-0.124 -> 4.8627711 | S7: =R7-R7 -> 0 | T7: =S7*$C$16*(1-$J7)+S7 -> 0 | U7: =T7*$C$17*(1-$J7)+T7 -> 0 | V7: =U7*$C$18*(1-$J7)+U7 -> 0 | W7: =V7*$C$19*(1-$J7)+V7 -> 0 | X7: =W7*$C$21*(1-$J7)+W7+5.0335 -> 5.0335 | Y7: =X7*$C$23*(1-$J7)+X7 -> 5.0508127 | Z7: =Y7*$C$24*(1-$J7)+Y7 -> 5.0565814 | AA7: =Z7*$C$27*(1-$J7)+Z7-0.13 -> 4.9479208 | AB7: =AA7*$C$29*(1-$J7)+AA7 -> 4.9612108 | AC7: =AB7*$C$31*(1-$J7)+AB7 -> 4.9649496 | AD7: =AC7*$C$32*(1-$J7)+AC7 -> 4.9820726 | AE7: =AD7*$C$34*(1-$J7)+AD7 -> 4.9832857 | AF7: =AE7*$C$36*(1-$J7)+AE7-0.26 -> 4.7235285 | AG7: =AF7*$C$38*(1-$J7)+AF7 -> 4.7263666 | AH7: =AG7*$C$40*(1-$J7)+AG7-0.11 -> 4.6278155 | AI7: =AH7*$C$42*(1-$J7)+AH7 -> 4.6298606 | AJ7: =AI7*$C$44*(1-$J7)+AI7 -> 4.6318199
A8: 45566 | B8: =B7+4.62+6.5193+5.2 -> 21.8793 | C8: 1 | G8: Invest of Mathias / Thomas / Daniel with 16.3393 BTC | I8: Kabbaj Fam | J8: 0.2 | K8: 0 | L8: 0 | M8: 0 | N8: 0 | O8: 0 | P8: 0 | Q8: 0 | R8: 0 | S8: 0 | T8: 0 | U8: 0 | V8: 0 | W8: 0 | X8: 0 | Y8: 0 | Z8: 0 | AA8: 0 | AB8: 2 | AC8: =AB8*$C$31*(1-$J8)+AB8 -> 2.0013398 | AD8: =AC8*$C$32*(1-$J8)+AC8+0.9914 -> 2.998875 | AE8: =AD8*$C$34*(1-$J8)+AD8 -> 2.9995241 | AF8: =AE8*$C$36*(1-$J8)+AE8 -> 2.999654 | AG8: =AF8*$C$38*(1-$J8)+AF8+0.6 -> 3.6012561 | AH8: =AG8*$C$40*(1-$J8)+AG8 -> 3.6090103 | AI8: =AH8*$C$42*(1-$J8)+AH8+0.9102 -> 4.5206279 | AJ8: =AI8*$C$44*(1-$J8)+AI8 -> 4.5223284
A9: 45597 | B9: 21.99 | C9: =(B9/B8)-100% -> 0.0050595769 | D9: =B9-B8 -> 0.1107 | E9: =C9*0.8 -> 0.0040476615 | F9: =C9*12 -> 0.060714922 | I9: Victoria | J9: 0 | K9: 0 | L9: 0 | M9: 0 | N9: 0 | O9: 0 | P9: 0 | Q9: 0 | R9: 0 | S9: 0 | T9: 0 | U9: 0 | V9: 0 | W9: 0 | X9: 0 | Y9: 0 | Z9: 0 | AA9: 0 | AB9: 0 | AC9: 0 | AD9: =AC9*$C$32*(1-$J9)+AC9+0.1484 -> 0.1484 | AE9: =AD9*$C$34*(1-$J9)+AD9 -> 0.14844015 | AF9: =AE9*$C$36*(1-$J9)+AE9 -> 0.14844818 | AG9: =AF9*$C$38*(1-$J9)+AF9 -> 0.14854729 | AH9: =AG9*$C$40*(1-$J9)+AG9 -> 0.1489471 | AI9: =AH9*$C$42*(1-$J9)+AH9 -> 0.14902024 | AJ9: =AI9*$C$44*(1-$J9)+AI9 -> 0.14909031
A10: 45605 | B10: =22.02 -> 22.02 | C10: =(B10/B9)-100% -> 0.0013642565 | D10: =B10-B9 -> 0.03 | E10: =C10*0.8 -> 0.0010914052 | F10: =C10*12 -> 0.016371078 | I10: Nathanael Cohen | J10: 0 | K10: 0 | L10: 0 | M10: 0 | N10: 0 | O10: 0 | P10: 0 | Q10: 0 | R10: 0 | S10: 0 | T10: 0 | U10: 0 | V10: 0 | W10: 0 | X10: 0 | Y10: 0 | Z10: 0 | AA10: 0 | AB10: 0 | AC10: 0 | AD10: =AC10*$C$32*(1-$J10)+AC10+0.446 -> 0.446 | AE10: =AD10*$C$34*(1-$J10)+AD10 -> 0.44612066 | AF10: =AE10*$C$36*(1-$J10)+AE10 -> 0.44614481 | AG10: =AF10*$C$38*(1-$J10)+AF10 -> 0.44644266 | AH10: =AG10*$C$40*(1-$J10)+AG10 -> 0.44764426 | AI10: =AH10*$C$42*(1-$J10)+AH10 -> 0.44786406 | AJ10: =AI10*$C$44*(1-$J10)+AI10 -> 0.44807465
A11: 45605 | B11: =B10-0.27 -> 21.75 | C11: 1 | G11: Withdraw 0.27 from Danielle | I11: Blondish | J11: 0 | K11: 0 | L11: 0 | M11: 0 | N11: 0 | O11: 0 | P11: 0 | Q11: 0 | R11: 0 | S11: 0 | T11: 0 | U11: 0 | V11: 0 | W11: 0 | X11: 0 | Y11: 0 | Z11: 0 | AA11: 0 | AB11: 0 | AC11: 0 | AD11: =AC11*$C$32*(1-$J11)+AC11+4.0996 -> 4.0996 | AE11: =AD11*$C$34*(1-$J11)+AD11 -> 4.1007091 | AF11: =AE11*$C$36*(1-$J11)+AE11 -> 4.1009311 | AG11: =AF11*$C$38*(1-$J11)+AF11 -> 4.1036689 | AH11: =AG11*$C$40*(1-$J11)+AG11 -> 4.1147139 | AI11: =AH11*$C$42*(1-$J11)+AH11 -> 4.1167343 | AJ11: =AI11*$C$44*(1-$J11)+AI11 -> 4.11867
A12: 45627 | B12: 21.84 | C12: =(B12/B11)-100% -> 0.004137931 | D12: =B12-B11 -> 0.09 | E12: =C12*0.8 -> 0.0033103448 | F12: =C12*12 -> 0.049655172 | I12: Oliver Loisel | J12: 0.1 | K12: 0 | L12: 0 | M12: 0 | N12: 0 | O12: 0 | P12: 0 | Q12: 0 | R12: 0 | S12: 0 | T12: 0 | U12: 0 | V12: 0 | W12: 0 | X12: 0 | Y12: 0 | Z12: 0 | AA12: 0 | AB12: 0 | AC12: 0 | AD12: 0 | AE12: =AD12*$C$34*(1-$J12)+AD12+2.115364 -> 2.115364 | AF12: =AE12*$C$36*(1-$J12)+AE12 -> 2.1154671 | AG12: =AF12*$C$38*(1-$J12)+AF12 -> 2.1167382 | AH12: =AG12*$C$40*(1-$J12)+AG12 -> 2.1218656 | AI12: =AH12*$C$42*(1-$J12)+AH12 -> 2.1228033 | AJ12: =AI12*$C$44*(1-$J12)+AI12 -> 2.1237016
A13: 45640 | B13: 21.88 | C13: =(B13/B12)-100% -> 0.0018315018 | D13: =B13-B12 -> 0.04 | E13: =C13*0.8 -> 0.0014652015 | F13: =C13*12 -> 0.021978022 | I13: Total AUM | K13: =SUM(K2:K12) -> 3.49 | L13: =SUM(L2:L12) -> 5.5 | M13: =SUM(M2:M12) -> 5.51 | N13: =SUM(N2:N12) -> 21.8793 | O13: =SUM(O2:O12) -> 21.99 | P13: =SUM(P2:P12) -> 21.75 | Q13: =SUM(Q2:Q12) -> 21.84 | R13: =SUM(R2:R12) -> 21.756 | ... AJ13: =SUM(AJ2:AJ12) -> 31.489965
A14: 45640 | B14: =21.88-0.124 -> 21.756 | C14: 1 | G14: Withdraw 0.124 from Danielle
A15: 45640 | B15: =21.88-0.124-11.5681 -> 10.1879 | C15: 1 | G15: Kyle / Mathias / Danielle go to Boosted Program with 11.5681 BTC | I15: Indigo | J15: 0 | K15: =IFERROR(K2/K$13,"") -> 0.001260745 | L15: =IFERROR(L2/L$13,"") -> 0.0011654702 | M15: =IFERROR(M2/M$13,"") -> 0.0014950257 | N15: =IFERROR(N2/N$13,"") -> 0.00062744997 | O15: =IFERROR(O2/O$13,"") -> 0.0010845459 | P15: =IFERROR(P2/P$13,"") -> 0.0012231602 | Q15: =IFERROR(Q2/Q$13,"") -> 0.0015965182 | R15: =IFERROR(R2/R$13,"") -> 0.0017720967 | ... AJ15: =IFERROR(AJ2/AJ$13,"") -> 0.0049581814
A16: 45658 | B16: 10.24 | C16: =(B16/B15)-100% -> 0.0051139096 | D16: =B16-B15 -> 0.0521 | E16: =C16*0.8 -> 0.0040911277 | F16: =C16*12 -> 0.061366916 | I16: Jose | J16: 0.2 | K16: =IFERROR(K3/K$13,"") -> 0.99873926 | L16: =IFERROR(L3/L$13,"") -> 0.63519817 | M16: =IFERROR(M3/M$13,"") -> 0.6349676 | N16: =IFERROR(N3/N$13,"") -> 0.16060435 | O16: =IFERROR(O3/O$13,"") -> 0.16044265 | P16: =IFERROR(P3/P$13,"") -> 0.16239009 | Q16: =IFERROR(Q3/Q$13,"") -> 0.16225625 | R16: =IFERROR(R3/R$13,"") -> 0.16312138 | ... AJ16: =IFERROR(AJ3/AJ$13,"") -> 0.11706647
A17: 45689 | B17: 10.3 | C17: =(B17/B16)-100% -> 0.005859375 | D17: =B17-B16 -> 0.06 | E17: =C17*0.8 -> 0.0046875 | F17: =C17*12 -> 0.0703125 | I17: Kyle | J17: 0.15 | K17: =IFERROR(K4/K$13,"") -> 0 | L17: =IFERROR(L4/L$13,"") -> 0.36363636 | M17: =IFERROR(M4/M$13,"") -> 0.36353737 | N17: =IFERROR(N4/N$13,"") -> 0.091975571 | O17: =IFERROR(O4/O$13,"") -> 0.091906119 | P17: =IFERROR(P4/P$13,"") -> 0.093028007 | Q17: =IFERROR(Q4/Q$13,"") -> 0.092970504 | R17: =IFERROR(R4/R$13,"") -> 0.093474756 | ... AJ17: =IFERROR(AJ4/AJ$13,"") -> 0
A18: 45717 | B18: 10.34 | C18: =(B18/B17)-100% -> 0.0038834951 | D18: =B18-B17 -> 0.04 | E18: =C18*0.8 -> 0.0031067961 | F18: =C18*12 -> 0.046601942 | I18: Mathias | J18: 0.1 | K18: =IFERROR(K5/K$13,"") -> 0 | L18: =IFERROR(L5/L$13,"") -> 0 | M18: =IFERROR(M5/M$13,"") -> 0 | N18: =IFERROR(N5/N$13,"") -> 0.21115849 | O18: =IFERROR(O5/O$13,"") -> 0.21105219 | P18: =IFERROR(P5/P$13,"") -> 0.21364304 | Q18: =IFERROR(Q5/Q$13,"") -> 0.213555 | R18: =IFERROR(R5/R$13,"") -> 0.21473291 | ... AJ18: =IFERROR(AJ5/AJ$13,"") -> 0.15664064
A19: 45747 | B19: 10.38 | C19: =(B19/B18)-100% -> 0.003868472 | D19: =B19-B18 -> 0.04 | E19: =C19*0.8 -> 0.0030947776 | F19: =C19*12 -> 0.046421663 | I19: Thomas Puech | J19: 0 | K19: =IFERROR(K6/K$13,"") -> 0 | L19: =IFERROR(L6/L$13,"") -> 0 | M19: =IFERROR(M6/M$13,"") -> 0 | N19: =IFERROR(N6/N$13,"") -> 0.29796657 | O19: =IFERROR(O6/O$13,"") -> 0.29796657 | P19: =IFERROR(P6/P$13,"") -> 0.30166547 | Q19: =IFERROR(Q6/Q$13,"") -> 0.30166547 | R19: =IFERROR(R6/R$13,"") -> 0.30338483 | ... AJ19: =IFERROR(AJ6/AJ$13,"") -> 0.21343687
A20: 45747 | B20: =B19-6.7249 -> 3.6551 | C20: 1 | G20: Thomas go to TAC Program with 6.7249 | I20: Danielle Richetta | J20: 0.1 | K20: =IFERROR(K7/K$13,"") -> 0 | L20: =IFERROR(L7/L$13,"") -> 0 | M20: =IFERROR(M7/M$13,"") -> 0 | N20: =IFERROR(N7/N$13,"") -> 0.23766757 | O20: =IFERROR(O7/O$13,"") -> 0.23754792 | P20: =IFERROR(P7/P$13,"") -> 0.22805024 | Q20: =IFERROR(Q7/Q$13,"") -> 0.22795626 | R20: =IFERROR(R7/R$13,"") -> 0.22351402 | ... AJ20: =IFERROR(AJ7/AJ$13,"") -> 0.14708876
A21: 45763 | B21: 3.68 | C21: =(B21/B20)-100% -> 0.0068123991 | D21: =B21-B20 -> 0.0249 | E21: =C21*0.8 -> 0.0054499193 | F21: =C21*12 -> 0.081748789 | I21: Kabbaj Fam | J21: 0.2 | K21: =IFERROR(K8/K$13,"") -> 0 | L21: =IFERROR(L8/L$13,"") -> 0 | M21: =IFERROR(M8/M$13,"") -> 0 | N21: =IFERROR(N8/N$13,"") -> 0 | O21: =IFERROR(O8/O$13,"") -> 0 | P21: =IFERROR(P8/P$13,"") -> 0 | Q21: =IFERROR(Q8/Q$13,"") -> 0 | R21: =IFERROR(R8/R$13,"") -> 0 | ... AJ21: =IFERROR(AJ8/AJ$13,"") -> 0.14361173
A22: 45763 | B22: =B21+12.02 -> 15.7 | C22: 1 | G22: Transfert of 12.02 BTC from boosted program for Kyle Gulamerian / Matthias Reiser / Danielle Richetta | I22: Victoria | J22: 0 | K22: =IFERROR(K9/K$13,"") -> 0 | L22: =IFERROR(L9/L$13,"") -> 0 | M22: =IFERROR(M9/M$13,"") -> 0 | N22: =IFERROR(N9/N$13,"") -> 0 | O22: =IFERROR(O9/O$13,"") -> 0 | P22: =IFERROR(P9/P$13,"") -> 0 | Q22: =IFERROR(Q9/Q$13,"") -> 0 | R22: =IFERROR(R9/R$13,"") -> 0 | ... AJ22: =IFERROR(AJ9/AJ$13,"") -> 0.004734534
A23: 45778 | B23: 15.76 | C23: =(B23/B22)-100% -> 0.0038216561 | D23: =B23-B22 -> 0.06 | E23: =C23*0.8 -> 0.0030573248 | F23: =C23*12 -> 0.045859873 | I23: Nathanael Cohen | J23: 0 | K23: =IFERROR(K10/K$13,"") -> 0 | L23: =IFERROR(L10/L$13,"") -> 0 | M23: =IFERROR(M10/M$13,"") -> 0 | N23: =IFERROR(N10/N$13,"") -> 0 | O23: =IFERROR(O10/O$13,"") -> 0 | P23: =IFERROR(P10/P$13,"") -> 0 | Q23: =IFERROR(Q10/Q$13,"") -> 0 | R23: =IFERROR(R10/R$13,"") -> 0 | ... AJ23: =IFERROR(AJ10/AJ$13,"") -> 0.014229125
A24: 45790 | B24: 15.78 | C24: =(B24/B23)-100% -> 0.0012690355 | D24: =B24-B23 -> 0.02 | E24: =C24*0.8 -> 0.0010152284 | F24: =C24*12 -> 0.015228426 | I24: Blondish | J24: 0 | K24: =IFERROR(K11/K$13,"") -> 0 | L24: =IFERROR(L11/L$13,"") -> 0 | M24: =IFERROR(M11/M$13,"") -> 0 | N24: =IFERROR(N11/N$13,"") -> 0 | O24: =IFERROR(O11/O$13,"") -> 0 | P24: =IFERROR(P11/P$13,"") -> 0 | Q24: =IFERROR(Q11/Q$13,"") -> 0 | R24: =IFERROR(R11/R$13,"") -> 0 | ... AJ24: =IFERROR(AJ11/AJ$13,"") -> 0.1307931
A25: 45790 | B25: =B24-0.1078 -> 15.6722 | C25: 1 | G25: Withdraw 0.1078 BTC from Kyle | I25: oliver loisel | J25: 0.1 | K25: =IFERROR(K12/K$13,"") -> 0 | L25: =IFERROR(L12/L$13,"") -> 0 | M25: =IFERROR(M12/M$13,"") -> 0 | N25: =IFERROR(N12/N$13,"") -> 0 | O25: =IFERROR(O12/O$13,"") -> 0 | P25: =IFERROR(P12/P$13,"") -> 0 | Q25: =IFERROR(Q12/Q$13,"") -> 0 | R25: =IFERROR(R12/R$13,"") -> 0 | ... AJ25: =IFERROR(AJ12/AJ$13,"") -> 0.067440585
A26: 45790 | B26: =B25-(Y4*$C$24*0.85+Y4-0.1078) -> 13.669901 | C26: 1 | G26: Withdraw 2.0023 BTC from Kyle (all his account) | I26: Total AUM | K26: =SUM(K15:K25) -> 1 | L26: =SUM(L15:L25) -> 1 | M26: =SUM(M15:M25) -> 1 | N26: =SUM(N15:N25) -> 1 | O26: =SUM(O15:O25) -> 1 | P26: =SUM(P15:P25) -> 1 | Q26: =SUM(Q15:Q25) -> 1 | R26: =SUM(R15:R25) -> 1 | ... AJ26: =SUM(AJ15:AJ25) -> 1
A27: 45807 | B27: =13.69+0.044 -> 13.734 | C27: =(B27/B26)-100% -> 0.0046890297 | D27: =B27-B26 -> 0.064098573 | E27: =C27*0.8 -> 0.0037512237 | F27: =C27*12 -> 0.056268356 | G27: +0.0044 BTC for Gas Fees that has been forgoten
A28: 45807 | B28: =B27-0.13 -> 13.604 | C28: 1 | G28: Withdraw 0.13 from Danielle Richetta
A29: 45819 | B29: 13.6446 | C29: =(B29/B28)-100% -> 0.0029844163 | D29: =B29-B28 -> 0.0406 | E29: =C29*0.8 -> 0.0023875331 | F29: =C29*12 -> 0.035812996
A30: 45819 | B30: =B29+2 -> 15.6446 | C30: 1 | G30: Kabbaj deposit 2 BTC
A31: 45838 | B31: 15.6577 | C31: =(B31/B30)-100% -> 0.00083734963 | D31: =B31-B30 -> 0.0131 | E31: =C31*0.8 -> 0.0006698797 | F31: =C31*12 -> 0.010048196
A32: 45849 | B32: 15.7177 | C32: =(B32/B31)-100% -> 0.0038319804 | D32: =B32-B31 -> 0.06 | E32: =C32*0.8 -> 0.0030655843 | F32: =C32*12 -> 0.045983765
A33: 45849 | B33: =B32+11.384+0.9914 -> 28.0931 | C33: 1 | G33: Top Up from Kabbaj : 0.9914 BTC Transfert from TAC Program Victoria :0.1484 BTC Nathanael Cohen : 0.4460 BTC Thomas Puech : 6.69 BTC Blondish : 4.0996 BTC
A34: 45862 | B34: 28.1007 | C34: =(B34/B33)-100% -> 0.00027052906 | D34: =B34-B33 -> 0.0076 | E34: =C34*0.8 -> 0.00021642325 | F34: =C34*12 -> 0.0032463487
A35: 45862 | B35: =B34+2.115364 -> 30.216064 | C35: 1 | G35: oliver loisel : 2.115364 BTC
A36: 45863 | B36: 30.2177 | C36: =(B36/B35)-100% -> 5.4143385e-05 | D36: =B36-B35 -> 0.001636 | E36: =C36*0.8 -> 4.3314708e-05 | F36: =C36*12 -> 0.00064972063
A37: 45863 | B37: =B36-0.26 -> 29.9577 | C37: 1 | G37: Withdrawal Danielle Richetta - 0.26 BTC
A38: 45869 | B38: 29.9777 | C38: =(B38/B37)-100% -> 0.00066760799 | D38: =B38-B37 -> 0.02 | E38: =C38*0.8 -> 0.0005340864 | F38: =C38*12 -> 0.0080112959
A39: 45869 | B39: =B38+0.6 -> 30.5777 | C39: 1 | G39: Kabbaj : 0.6 BTC
A40: 45889 | B40: 30.66 | C40: =(B40/B39)-100% -> 0.0026915039 | D40: =B40-B39 -> 0.0823 | E40: =C40*0.8 -> 0.0021532032 | F40: =C40*12 -> 0.032298047
A41: 45889 | B41: =B40-0.11 -> 30.55 | C41: 1 | G41: Withdrawal Danielle Richetta - 0.11 BTC
A42: 45894 | B42: 30.565 | C42: =(B42/B41)-100% -> 0.00049099836 | D42: =B42-B41 -> 0.015 | E42: =C42*0.8 -> 0.00039279869 | F42: =C42*12 -> 0.0058919804
A43: 45894 | B43: =B42+0.9102 -> 31.4752 | C43: 1 | G43: Top Up Kabbaj : 0.9102 BTC
A44: 45901 | B44: 31.49 | C44: =(B44/B43)-100% -> 0.00047021147 | D44: =B44-B43 -> 0.0148 | E44: =C44*0.8 -> 0.00037616917 | F44: =C44*12 -> 0.0056425376

Sheet ETH Yield Fund
A1: Date | B1: AUM | C1: Gross Performance (%) | D1: Gross Performance (USDT) | E1: Net Performance | F1: Yearly APY | G1: Comments | I1: Investors | J1: Fees | K1: IB | L1: 45803 | M1: 45809 | N1: 45839 | O1: 45849 | P1: 45868 | Q1: 45869 | R1: 45901
A2: 45803 | B2: 202.01 | C2: 1 | G2: Set up the fund | I2: Indigo | J2: 0 | L2: 0 | M2: =L2*$C$3*1+L2+(L3*$C$3*$J$3)+(L4*$C$3*$J$4)+(L5*$C$3*$J$5)+(L6*$C$3*$J$6) -> 0.0052947676 | N2: =M2*$C$5*1+M2+(M3*$C$5*$J$3)+(M4*$C$5*$J$4)+(M5*$C$5*$J$5)+(M6*$C$5*$J$6) -> 0.09129815 | O2: =N2*$C$7*1+N2+(N3*$C$7*$J$3)+(N4*$C$7*$J$4)+(N5*$C$7*$J$5)+(N6*$C$7*$J$6)+0.898 -> 1.0476167 | P2: =O2*$C$9*1+O2+(O3*$C$9*$J$3)+(O4*$C$9*$J$4)+(O5*$C$9*$J$5)+(O6*$C$9*$J$6)+(O7*$C$9*$J$7)+(O8*$C$9*$J$8)+(O9*$C$9*$J$9) -> 1.1600681 | Q2: =P2*$C$11*1+P2+(P3*$C$11*$J$3)+(P4*$C$11*$J$4)+(P5*$C$11*$J$5)+(P6*$C$11*$J$6)+(P7*$C$11*$J$7)+(P8*$C$11*$J$8)+(P9*$C$11*$J$9) -> 1.1600681 | R2: =Q2*$C$12*1+Q2+(Q3*$C$12*$J$3)+(Q4*$C$12*$J$4)+(Q5*$C$12*$J$5)+(Q6*$C$12*$J$6)+(Q7*$C$12*$J$7)+(Q8*$C$12*$J$8)+(Q9*$C$12*$J$9)+(Q10*$C$12*$J$10) -> 1.4197892
A3: 45807 | B3: 202.23 | C3: =(B3*$C$2/B2)-100% -> 0.001089055 | D3: =B3-B2 -> 0.22 | E3: =C3*0.8 -> 0.000871244 | F3: =C3*12 -> 0.01306866 | I3: Babak Eftekhari | J3: 0.18 | K3: 0.02 | L3: 27.01 | M3: 59.283532 | N3: 59.66558 | O3: 59.922589 | P3: 60.143892 | Q3: 60.143892 | R3: =Q3*$C$12*(1-$J3)+Q3 -> 60.566385
A4: 45807 | B4: =B3+32.25+3.0466 -> 237.5266 | C4: 1 | G4: Top up from Babak: 32.25 ETH Top up from Nathanaël : 3.0466 ETH | I4: INDIGO DIGITAL ASSET FUND LP | J4: 0 | L4: 175 | M4: =L4*$C$3*(1-$J4)+L4 -> 175.19058 | N4: =M4*$C$5*(1-$J4)+M4 -> 176.60184 | O4: =N4*$C$7*(1-$J4)+N4 -> 177.55272 | P4: =(O4*$C$9*(1-$J4)+O4) -> 178.37238 | Q4: =(P4*$C$11*(1-$J4)+P4)-(P4*$C$11*(1-$J4)+P4) -> 0 | R4: =(Q4*$C$12*(1-$J4)+Q4)-(Q4*$C$12*(1-$J4)+Q4) -> 0
A5: 45838 | B5: 239.44 | C5: =(B5*$C$2/B4)-100% -> 0.0080555188 | D5: =B5-B4 -> 1.9134 | E5: =C5*0.8 -> 0.0064444151 | F5: =C5*12 -> 0.096666226 | I5: Nathanael Cohen | J5: 0 | L5: 0 | M5: =L5*$C$3*(1-$J5)+L5+3.0466 -> 3.0466 | N5: =M5*$C$5*(1-$J5)+M5+2 -> 5.0711419 | O5: =N5*$C$7*(1-$J5)+N5+26.6797 -> 31.778147 | P5: =O5*$C$9*(1-$J5)+O5 -> 31.924849 | Q5: =P5*$C$11*(1-$J5)+P5 -> 31.924849 | R5: =Q5*$C$12*(1-$J5)+Q5 -> 32.19834
A6: 45838 | B6: =B5+2 -> 241.44 | C6: 1 | G6: Top up from Nathanaël : 2 ETH | I6: Jose Molla | J6: 0.2 | L6: 0 | M6: =L6*$C$3*(1-$J6)+L6 -> 0 | N6: =M6*$C$5*(1-$J6)+M6 -> 0 | O6: =N6*$C$7*(1-$J6)+N6+62.6261 -> 62.6261 | P6: =O6*$C$9*(1-$J6)+O6 -> 62.857388 | Q6: =P6*$C$11*(1-$J6)+P6 -> 62.857388 | R6: =Q6*$C$12*(1-$J6)+Q6 -> 63.288173
A7: 45849 | B7: =242.88-0.14 -> 242.74 | C7: =(B7*$C$2/B6)-100% -> 0.0053843605 | D7: =B7-B6 -> 1.3 | E7: =C7*0.8 -> 0.0043074884 | F7: =C7*12 -> 0.064612326 | I7: Blondish | J7: 0 | L7: 0 | M7: =L7*$C$3*(1-$J7)+L7 -> 0 | N7: =M7*$C$5*(1-$J7)+M7 -> 0 | O7: =N7*$C$7*(1-$J7)+N7+119.7862 -> 119.7862 | P7: =O7*$C$9*(1-$J7)+O7 -> 120.33919 | Q7: =P7*$C$11*(1-$J7)+P7 -> 120.33919 | R7: =Q7*$C$12*(1-$J7)+Q7 -> 121.3701
A8: 45849 | B8: =B7+209.99 -> 452.73 | C8: 1 | G8: Transfert from ETH TAC Program Jose Molla :62.6261 ETH Nathanael Cohen : 26.6797 ETH Indigo : 0.8980 ETH Blondish : 119.7862 ETH | I8: Advantage Blockchain | J8: 0.18 | K8: 0.02 | L8: 0 | M8: =L8*$C$3*(1-$J8)+L8 -> 0 | N8: =M8*$C$5*(1-$J8)+M8 -> 0 | O8: =N8*$C$7*(1-$J8)+N8 -> 0 | P8: =O8*$C$9*(1-($J8+$K8))+O8+32 -> 32 | Q8: =P8*$C$11*(1-($J8+$K8))+P8 -> 32 | R8: =Q8*$C$12*(1-($J8+$K8))+Q8 -> 32.219308
A9: 45868 | B9: 454.82 | C9: =(B9*$C$2/B8)-100% -> 0.0046164381 | D9: =B9-B8 -> 2.09 | E9: =C9*0.8 -> 0.0036931504 | F9: =C9*12 -> 0.055397257 | I9: Alec Beckman | J9: 0.2 | L9: 0 | M9: =L9*$C$3*(1-$J9)+L9 -> 0 | N9: =M9*$C$5*(1-$J9)+M9 -> 0 | O9: =N9*$C$7*(1-$J9)+N9 -> 0 | P9: =(O9*$C$9*(1-$J9)+O9)+(O8*$C$9*$K$8) -> 0 | Q9: =(P9*$C$11*(1-$J9)+P9)+(P8*$C$11*$K$8) -> 0 | R9: =(Q9*$C$12*(1-$J9)+Q9)+(Q8*$C$12*$K$8) -> 0.0054827017
A10: 45868 | B10: =B9+32 -> 486.82 | C10: 1 | G10: Invest from Advantage Blockchain : 32 ETH | I10: Lars Ahlgreen | J10: 0.2 | L10: 0 | M10: =L10*$C$3*(1-$J10)+L10 -> 0 | N10: =M10*$C$5*(1-$J10)+M10 -> 0 | O10: =N10*$C$7*(1-$J10)+N10 -> 0 | P10: =(O10*$C$9*(1-$J10)+O10)+(O9*$C$9*$K$8) -> 0 | Q10: =(P10*$C$11*(1-$J10)+P10)+(P9*$C$11*$K$8) -> 0 | R10: =(Q10*$C$12*(1-$J10)+Q10)+(Q3*$C$12*$K$3) -> 0.010304719
A11: 45869 | B11: =B10-(O4*$C$9*(1-$J4)+O4) -> 308.44762 | C11: 0 | G11: Withdrawal from INDIGO Main fund : -178.37 ETH | I11: Total | L11: =SUM(L2:L9) -> 202.01 | M11: =SUM(M2:M9) -> 237.52601 | N11: =SUM(N2:N9) -> 241.42986 | O11: =SUM(O2:O9) -> 452.71338 | P11: =SUM(P2:P9) -> 486.79777 | Q11: =SUM(Q2:Q9) -> 308.42538 | R11: =SUM(R2:R9) -> 311.06758
A12: 45901 | B12: 311.09 | C12: =(B12*$C$2/B11)-100% -> 0.0085667214 | D12: =B12-B11 -> 2.6423848 | E12: =C12*0.8 -> 0.0068533771 | F12: =C12*12 -> 0.10280066
I13: Indigo | L13: =IFERROR(L2/L$11,"") -> 0 | M13: =IFERROR(M2/M$11,"") -> 2.2291317e-05 | N13: =IFERROR(N2/N$11,"") -> 0.000378156 | O13: =IFERROR(O2/O$11,"") -> 0.0023140838 | P13: =IFERROR(P2/P$11,"") -> 0.0023830596 | Q13: =IFERROR(Q2/Q$11,"") -> 0.0037612601 | R13: =IFERROR(R2/R$11,"") -> 0.0045642468
I14: Babak Eftekhari | L14: =IFERROR(L3/L$11,"") -> 0.13370625 | M14: =IFERROR(M3/M$11,"") -> 0.24958754 | N14: =IFERROR(N3/N$11,"") -> 0.24713422 | O14: =IFERROR(O3/O$11,"") -> 0.13236319 | P14: =IFERROR(P3/P$11,"") -> 0.12355006 | Q14: =IFERROR(Q3/Q$11,"") -> 0.19500306 | R14: =IFERROR(R3/R$11,"") -> 0.19470491
I15: Indigo Main Fund | L15: =IFERROR(L4/L$11,"") -> 0.86629375 | M15: =IFERROR(M4/M$11,"") -> 0.73756379 | N15: =IFERROR(N4/N$11,"") -> 0.731483 | O15: =IFERROR(O4/O$11,"") -> 0.39219677 | P15: =IFERROR(P4/P$11,"") -> 0.36641989 | Q15: =IFERROR(Q4/Q$11,"") -> 0 | R15: =IFERROR(R4/R$11,"") -> 0
I16: Nathanael Cohen | L16: =IFERROR(L5/L$11,"") -> 0 | M16: =IFERROR(M5/M$11,"") -> 0.012826385 | N16: =IFERROR(N5/N$11,"") -> 0.021004618 | O16: =IFERROR(O5/O$11,"") -> 0.070194848 | P16: =IFERROR(P5/P$11,"") -> 0.065581338 | Q16: =IFERROR(Q5/Q$11,"") -> 0.10350915 | R16: =IFERROR(R5/R$11,"") -> 0.10350915
I17: Jose Molla | L17: =IFERROR(L6/L$11,"") -> 0 | M17: =IFERROR(M6/M$11,"") -> 0 | N17: =IFERROR(N6/N$11,"") -> 0 | O17: =IFERROR(O6/O$11,"") -> 0.13833499 | P17: =IFERROR(P6/P$11,"") -> 0.12912423 | Q17: =IFERROR(Q6/Q$11,"") -> 0.20380096 | R17: =IFERROR(R6/R$11,"") -> 0.20345474
I18: Blondish | L18: =IFERROR(L7/L$11,"") -> 0 | M18: =IFERROR(M7/M$11,"") -> 0 | N18: =IFERROR(N7/N$11,"") -> 0 | O18: =IFERROR(O7/O$11,"") -> 0.26459611 | P18: =IFERROR(P7/P$11,"") -> 0.24720571 | Q18: =IFERROR(Q7/Q$11,"") -> 0.39017277 | R18: =IFERROR(R7/R$11,"") -> 0.39017277
I19: Advantage Blockchain | L19: =IFERROR(L8/L$11,"") -> 0 | M19: =IFERROR(M8/M$11,"") -> 0 | N19: =IFERROR(N8/N$11,"") -> 0 | O19: =IFERROR(O8/O$11,"") -> 0 | P19: =IFERROR(P8/P$11,"") -> 0.065735717 | Q19: =IFERROR(Q8/Q$11,"") -> 0.10375281 | R19: =IFERROR(R8/R$11,"") -> 0.10357656
I20: Alec Beckman | L20: =IFERROR(L9/L$11,"") -> 0 | M20: =IFERROR(M9/M$11,"") -> 0 | N20: =IFERROR(N9/N$11,"") -> 0 | O20: =IFERROR(O9/O$11,"") -> 0 | P20: =IFERROR(P9/P$11,"") -> 0 | Q20: =IFERROR(Q9/Q$11,"") -> 0 | R20: =IFERROR(R9/R$11,"") -> 1.7625436e-05
I22: Total AUM | L22: =SUM(L13:L20) -> 1 | M22: =SUM(M13:M20) -> 1 | N22: =SUM(N13:N20) -> 1 | O22: =SUM(O13:O20) -> 1 | P22: =SUM(P13:P20) -> 1 | Q22: =SUM(Q13:Q20) -> 1 | R22: =SUM(R13:R20) -> 1

Sheet USDT Yield Fund
A1: Date | B1: AUM | C1: Gross Performance (%) | D1: Gross Performance (USDT) | E1: Net Performance | F1: Yearly APY | G1: Comments | I1: Investors | J1: Fees | K1: IB | L1: 45824 | M1: 45839 | N1: 45852 | O1: 45857 | P1: 45861 | Q1: 45869 | R1: 45873 | S1: 45883 | T1: 45888 | U1: 45901
A2: 45824 | B2: =134026.75+1700 -> 135726.75 | C2: 1 | G2: Babak invest 135,726.75 | I2: Indigo | J2: 0 | L2: 0 | M2: =L2*$C$3*1+L2+(L4*$C$3*$J$4)+(L5*$C$3*$J$5) -> 0 | N2: =M2*$C$4*1+M2+(M3*$C$4*20%)+(M4*$C$4*$J$4)+(M5*$C$4*$J$5)+(M6*$C$4*$J$6)+(M7*$C$4*$J$7)+(M8*$C$4*$J$8) -> 41.899538 | O2: =N2*$C$6*1+N2+(N3*$C$6*20%)+(N4*$C$6*$J$4)+(N5*$C$6*$J$5)+(N6*$C$6*$J$6)+(N7*$C$6*$J$7)+(N8*$C$6*$J$8)+(N9*$C$6*$J$9) -> 210.53546 | P2: =O2*$C$8*1+O2+(O3*$C$8*20%)+(O4*$C$8*$J$4)+(O5*$C$8*$J$5)+(O6*$C$8*$J$6)+(O7*$C$8*$J$7)+(O8*$C$8*$J$8)+(O9*$C$8*$J$9)+(O10*$C$8*$J$10)+(O11*$C$8*$J$11)+(O12*$C$8*$J$12) -> 416.01128 | Q2: =P2*$C$10*1+P2+(P3*$C$10*20%)+(P4*$C$10*$J$4)+(P5*$C$10*$J$5)+(P6*$C$10*$J$6)+(P7*$C$10*$J$7)+(P8*$C$10*$J$8)+(P9*$C$10*$J$9)+(P10*$C$10*$J$10)+(P11*$C$10*$J$11)+(P12*$C$10*$J$12) -> 919.77244 | R2: =Q2*$C$11*1+Q2+(Q3*$C$11*20%)+(Q4*$C$11*$J$4)+(Q5*$C$11*$J$5)+(Q6*$C$11*$J$6)+(Q7*$C$11*$J$7)+(Q8*$C$11*$J$8)+(Q9*$C$11*$J$9)+(Q10*$C$11*$J$10)+(Q11*$C$11*$J$11)+(Q12*$C$11*$J$12) -> 1042.1031 | S2: =R2*$C$13*1+R2+(R3*$C$13*20%)+(R4*$C$13*$J$4)+(R5*$C$13*$J$5)+(R6*$C$13*$J$6)+(R7*$C$13*$J$7)+(R8*$C$13*$J$8)+(R9*$C$13*$J$9)+(R10*$C$13*$J$10)+(R11*$C$13*$J$11)+(R12*$C$13*$J$12) -> 1898.5859 | T2: =S2*$C$15*1+S2+(S3*$C$15*20%)+(S4*$C$15*$J$4)+(S5*$C$15*$J$5)+(S6*$C$15*$J$6)+(S7*$C$15*$J$7)+(S8*$C$15*$J$8)+(S9*$C$15*$J$9)+(S10*$C$15*$J$10)+(S11*$C$15*$J$11)+(S12*$C$15*$J$12)+(S13*$C$15*$J$13)+(S14*$C$15*$J$14) -> 2272.2599 | U2: =T2*$C$17*1+T2+(T3*$C$17*$J$3)+(T4*$C$17*$J$4)+(T5*$C$17*$J$5)+(T6*$C$17*$J$6)+(T7*$C$17*$J$7)+(T8*$C$17*$J$8)+(T9*$C$17*$J$9)+(T10*$C$17*$J$10)+(T11*$C$17*$J$11)+(T12*$C$17*$J$12)+(T13*$C$17*$J$13)+(T14*$C$17*$J$14) -> 3157.862
A3: 45839 | B3: =(B2*8.5%/12/30*14)+B2 -> 136175.4 | C3: =(B3*$C$2/B2)-100% -> 0.0033055556 | D3: =B3-B2 -> 448.65231 | E3: =C3*0.8 -> 0.0026444444 | F3: =C3*12 -> 0.039666667 | I3: Babak Eftekhari | J3: 0.18 | K3: 0.02 | L3: =134026.75+1700 -> 135726.75 | M3: =L3*$C$3+L3 -> 136175.4 | N3: =M3*$C$4*(1-20%)+M3 -> 136343 | O3: =N3*$C$6*(1-20%)+N3+46955.28 -> 183460.93 | P3: =O3*$C$8*(1-20%)+O3 -> 183646.25 | Q3: =P3*$C$10*(1-20%)+P3 -> 183981.1 | R3: =Q3*$C$11*(1-$J3)+Q3+10000 -> 194064.24 | S3: =R3*$C$13*(1-$J3)+R3 -> 194672.17 | T3: =S3*$C$15*(1-$J3)+S3 -> 194933.35 | U3: =T3*$C$17*(1-$J3)+T3 -> 195562
A4: 45852 | B4: 136384.9 | C4: =(B4*$C$2/B3)-100% -> 0.00153844 | D4: =B4-B3 -> 209.49769 | E4: =C4*0.8 -> 0.001230752 | F4: =C4*12 -> 0.01846128 | I4: Julien Grunebaum | J4: 0.1 | L4: 0 | M4: =L4*$C$3*(1-$J4)+L4 -> 0 | N4: =M4*$C$4*(1-$J4)+M4+109392 -> 109392 | O4: =N4*$C$6*(1-$J4)+N4 -> 109538.81 | P4: =O4*$C$8*(1-$J4)+O4 -> 109663.29 | Q4: =P4*$C$10*(1-$J4)+P4 -> 109888.23 | R4: =Q4*$C$11*(1-$J4)+Q4 -> 109942.74 | S4: =R4*$C$13*(1-$J4)+R4 -> 110320.75 | T4: =S4*$C$15*(1-$J4)+S4 -> 110483.2 | U4: =T4*$C$17*(1-$J4)+T4 -> 110874.27
A5: 45852 | B5: =B4+109392+109776+109333+255504+273807 -> 994196.9 | C5: 1 | G5: julien grunebaum : 109392 daniele francilia : 109776 pierre bezencon : 109333 matthew beatty : 255504 bo kriek : 273807 | I5: Daniele Francilia | J5: 0.1 | L5: 0 | M5: =L5*$C$3*(1-$J5)+L5 -> 0 | N5: =M5*$C$4*(1-$J5)+M5+109776 -> 109776 | O5: =N5*$C$6*(1-$J5)+N5 -> 109923.32 | P5: =O5*$C$8*(1-$J5)+O5 -> 110048.24 | Q5: =P5*$C$10*(1-$J5)+P5 -> 110273.98 | R5: =Q5*$C$11*(1-$J5)+Q5 -> 110328.67 | S5: =R5*$C$13*(1-$J5)+R5 -> 110708.01 | T5: =S5*$C$15*(1-$J5)+S5 -> 110871.03 | U5: =T5*$C$17*(1-$J5)+T5 -> 111263.47
A6: 45857 | B6: 995679.39 | C6: =(B6*$C$2/B5)-100% -> 0.0014911433 | D6: =B6-B5 -> 1482.49 | E6: =C6*0.8 -> 0.0011929146 | F6: =C6*12 -> 0.017893719 | I6: Pierre Bezencon | J6: 0.1 | L6: 0 | M6: =L6*$C$3*(1-$J6)+L6 -> 0 | N6: =M6*$C$4*(1-$J6)+M6+109333 -> 109333 | O6: =N6*$C$6*(1-$J6)+N6 -> 109479.73 | P6: =O6*$C$8*(1-$J6)+O6 -> 109604.14 | Q6: =P6*$C$10*(1-$J6)+P6 -> 109828.97 | R6: =Q6*$C$11*(1-$J6)+Q6 -> 109883.44 | S6: =R6*$C$13*(1-$J6)+R6 -> 110261.25 | T6: =S6*$C$15*(1-$J6)+S6 -> 110423.61 | U6: =T6*$C$17*(1-$J6)+T6 -> 110814.47
A7: 45857 | B7: =B6+199659.72+46955.28 -> 1242294.4 | C7: 1 | G7: Dario: 199,659.72 Babak: 46,955.28 | I7: Matthew Beatty | J7: 0.1 | L7: 0 | M7: =L7*$C$3*(1-$J7)+L7 -> 0 | N7: =M7*$C$4*(1-$J7)+M7+255504 -> 255504 | O7: =N7*$C$6*(1-$J7)+N7 -> 255846.89 | P7: =O7*$C$8*(1-$J7)+O7 -> 256137.64 | Q7: =P7*$C$10*(1-$J7)+P7 -> 256663.04 | R7: =Q7*$C$11*(1-$J7)+Q7 -> 256790.35 | S7: =R7*$C$13*(1-$J7)+R7+25900 -> 283573.25 | T7: =S7*$C$15*(1-$J7)+S7 -> 283990.83 | U7: =T7*$C$17*(1-$J7)+T7 -> 284996.04
A8: 45861 | B8: 1243863 | C8: =(B8*$C$2/B7)-100% -> 0.0012626717 | D8: =B8-B7 -> 1568.61 | E8: =C8*0.8 -> 0.0010101374 | F8: =C8*12 -> 0.015152061 | I8: Bo Kriek | J8: 0.1 | L8: 0 | M8: =L8*$C$3*(1-$J8)+L8 -> 0 | N8: =M8*$C$4*(1-$J8)+M8+273807 -> 273807 | O8: =N8*$C$6*(1-$J8)+N8 -> 274174.46 | P8: =O8*$C$8*(1-$J8)+O8 -> 274486.03 | Q8: =P8*$C$10*(1-$J8)+P8 -> 275049.07 | R8: =Q8*$C$11*(1-$J8)+Q8 -> 275185.5 | S8: =R8*$C$13*(1-$J8)+R8 -> 276131.65 | T8: =S8*$C$15*(1-$J8)+S8 -> 276538.27 | U8: =T8*$C$17*(1-$J8)+T8 -> 277517.1
A9: 45861 | B9: =B8+579171 -> 1823034 | C9: 1 | G9: alain bensimon : 136737 anne cecile noique : 222687 terance chen : 219747 | I9: Dario Deiana | J9: 0.2 | L9: 0 | M9: =L9*$C$3*(1-$J9)+L9 -> 0 | N9: =M9*$C$4*(1-$J9)+M9 -> 0 | O9: =N9*$C$6*(1-$J9)+N9+199659.72 -> 199659.72 | P9: =O9*$C$8*(1-$J9)+O9 -> 199861.4 | Q9: =P9*$C$10*(1-$J9)+P9 -> 200225.82 | R9: =Q9*$C$11*(1-$J9)+Q9 -> 200314.1 | S9: =R9*$C$13*(1-$J9)+R9 -> 200926.3 | T9: =S9*$C$15*(1-$J9)+S9 -> 201189.3 | U9: =T9*$C$17*(1-$J9)+T9 -> 201822.3
A10: 45869 | B10: 1827189 | C10: =(B10*$C$2/B9)-100% -> 0.0022791676 | D10: =B10-B9 -> 4155 | E10: =C10*0.8 -> 0.0018233341 | F10: =C10*12 -> 0.027350011 | I10: Alain Bensimon | J10: 0.1 | L10: 0 | M10: =L10*$C$3*(1-$J10)+L10 -> 0 | N10: =M10*$C$4*(1-$J10)+M10 -> 0 | O10: =N10*$C$6*(1-$J10)+N10 -> 0 | P10: =O10*$C$8*(1-$J10)+O10+136737 -> 136737 | Q10: =P10*$C$10*(1-$J10)+P10 -> 137017.48 | R10: =Q10*$C$11*(1-$J10)+Q10 -> 137085.44 | S10: =R10*$C$13*(1-$J10)+R10 -> 137556.77 | T10: =S10*$C$15*(1-$J10)+S10 -> 137759.33 | U10: =T10*$C$17*(1-$J10)+T10 -> 138246.95
A11: 45873 | B11: 1828196 | C11: =(B11*$C$2/B10)-100% -> 0.00055111978 | D11: =B11-B10 -> 1007 | E11: =C11*0.8 -> 0.00044089582 | F11: =C11*12 -> 0.0066134374 | I11: Anne Cecile Noique | J11: 0.1 | L11: 0 | M11: =L11*$C$3*(1-$J11)+L11 -> 0 | N11: =M11*$C$4*(1-$J11)+M11 -> 0 | O11: =N11*$C$6*(1-$J11)+N11 -> 0 | P11: =O11*$C$8*(1-$J11)+O11+222687 -> 222687 | Q11: =P11*$C$10*(1-$J11)+P11 -> 223143.79 | R11: =Q11*$C$11*(1-$J11)+Q11 -> 223254.47 | S11: =R11*$C$13*(1-$J11)+R11 -> 224022.07 | T11: =S11*$C$15*(1-$J11)+S11 -> 224351.95 | U11: =T11*$C$17*(1-$J11)+T11 -> 225146.07
A12: 45873 | B12: =B11+130000+10000 -> 1968196 | C12: 1 | G12: INDIGO Ventures: $130,000 Babak top-up: $10,000 | I12: Terance Chen | J12: 0.1 | L12: 0 | M12: =L12*$C$3*(1-$J12)+L12 -> 0 | N12: =M12*$C$4*(1-$J12)+M12 -> 0 | O12: =N12*$C$6*(1-$J12)+N12 -> 0 | P12: =O12*$C$8*(1-$J12)+O12+219747 -> 219747 | Q12: =P12*$C$10*(1-$J12)+P12 -> 220197.76 | R12: =Q12*$C$11*(1-$J12)+Q12 -> 220306.98 | S12: =R12*$C$13*(1-$J12)+R12 -> 221064.44 | T12: =S12*$C$15*(1-$J12)+S12 -> 221389.97 | U12: =T12*$C$17*(1-$J12)+T12 -> 222173.6
A13: 45883 | B13: 1975715 | C13: =(B13*$C$2/B12)-100% -> 0.0038202496 | D13: =B13-B12 -> 7519 | E13: =C13*0.8 -> 0.0030561997 | F13: =C13*12 -> 0.045842995 | I13: INDIGO Ventures | J13: 0 | L13: 0 | M13: =L13*$C$3*(1-$J13)+L13 -> 0 | N13: =M13*$C$4*(1-$J13)+M13 -> 0 | O13: =N13*$C$6*(1-$J13)+N13 -> 0 | P13: =O13*$C$8*(1-$J13)+O13 -> 0 | Q13: =P13*$C$10*(1-$J13)+P13 -> 0 | R13: =Q13*$C$11*(1-$J13)+Q13+130000 -> 130000 | S13: =R13*$C$13*(1-$J13)+R13 -> 130496.63 | T13: =S13*$C$15*(1-$J13)+S13 -> 130710.15 | U13: =T13*$C$17*(1-$J13)+T13 -> 131224.22
A14: 45883 | B14: =B13+25900 -> 2001615 | C14: 1 | G14: Matthew Beatty: +25,900 USDC | I14: INDIGO DIGITAL ASSET FUND LP | J14: 0 | L14: 0 | M14: =L14*$C$3*(1-$J14)+L14 -> 0 | N14: =M14*$C$4*(1-$J14)+M14 -> 0 | O14: =N14*$C$6*(1-$J14)+N14 -> 0 | P14: =O14*$C$8*(1-$J14)+O14 -> 0 | Q14: =P14*$C$10*(1-$J14)+P14 -> 0 | R14: =Q14*$C$11*(1-$J14)+Q14 -> 0 | S14: =R14*$C$13*(1-$J14)+R14 -> 0 | T14: =S14*$C$15*(1-$J14)+S14+111370 -> 111370 | U14: =T14*$C$17*(1-$J14)+T14 -> 111808.01
A15: 45888 | B15: 2004890 | C15: =(B15*$C$2/B14)-100% -> 0.0016361788 | D15: =B15-B14 -> 3275 | E15: =C15*0.8 -> 0.001308943 | F15: =C15*12 -> 0.019634145 | I15: Lars Ahlgreen | J15: 0.2 | L15: 0 | M15: =L15*$C$3*(1-$J15)+L15 -> 0 | N15: =M15*$C$4*(1-$J15)+M15 -> 0 | O15: =N15*$C$6*(1-$J15)+N15 -> 0 | P15: =O15*$C$8*(1-$J15)+O15 -> 0 | Q15: =P15*$C$10*(1-$J15)+P15 -> 0 | R15: =Q15*$C$11*(1-$J15)+Q15 -> 0 | S15: =R15*$C$13*(1-$J15)+R15 -> 0 | T15: =S15*$C$15*(1-$J15)+S15 -> 0 | U15: =T15*$C$17*(1-$J15)+T15 -> 0
A16: 45888 | B16: =B15+111370 -> 2116260 | C16: 1 | G16: INDIGO Main Fund: +$111,370 | I16: Total | L16: =SUM(L2:L14) -> 135726.75 | M16: =SUM(M2:M14) -> 136175.4 | N16: =SUM(N2:N14) -> 994196.9 | O16: =SUM(O2:O14) -> 1242294.4 | P16: =SUM(P2:P14) -> 1823034 | Q16: =SUM(Q2:Q14) -> 1827189 | R16: =SUM(R2:R14) -> 1968198 | S16: =SUM(S2:S14) -> 2001631.9 | ... U16: =SUM(U2:U14) -> 2124606.4
A17: 45901 | B17: 2124583 | C17: =(B17*$C$2/B16)-100% -> 0.0039328816 | D17: =B17-B16 -> 8323 | E17: =C17*0.8 -> 0.0031463053 | F17: =C17*12 -> 0.047194579
I18: Indigo | L18: =IFERROR(L2/L$16,"") -> 0 | M18: =IFERROR(M2/M$16,"") -> 0 | N18: =IFERROR(N2/N$16,"") -> 4.2144104e-05 | O18: =IFERROR(O2/O$16,"") -> 0.00016947308 | P18: =IFERROR(P2/P$16,"") -> 0.00022819721 | Q18: =IFERROR(Q2/Q$16,"") -> 0.00050338112 | R18: =IFERROR(R2/R$16,"") -> 0.00052947063 | S18: =IFERROR(S2/S$16,"") -> 0.00094851904 | ... U18: =IFERROR(U2/U$16,"") -> 0.001486328
I19: Babak Eftekhari | L19: =IFERROR(L3/L$16,"") -> 1 | M19: =IFERROR(M3/M$16,"") -> 1 | N19: =IFERROR(N3/N$16,"") -> 0.13713883 | O19: =IFERROR(O3/O$16,"") -> 0.14767911 | P19: =IFERROR(P3/P$16,"") -> 0.1007366 | Q19: =IFERROR(Q3/Q$16,"") -> 0.10069079 | R19: =IFERROR(R3/R$16,"") -> 0.098599956 | S19: =IFERROR(S3/S$16,"") -> 0.097256728 | ... U19: =IFERROR(U3/U$16,"") -> 0.09204623
I20: julien grunebaum | L20: =IFERROR(L4/L$16,"") -> 0 | M20: =IFERROR(M4/M$16,"") -> 0 | N20: =IFERROR(N4/N$16,"") -> 0.11003052 | O20: =IFERROR(O4/O$16,"") -> 0.088174597 | P20: =IFERROR(P4/P$16,"") -> 0.060154274 | Q20: =IFERROR(Q4/Q$16,"") -> 0.060140595 | R20: =IFERROR(R4/R$16,"") -> 0.055859593 | S20: =IFERROR(S4/S$16,"") -> 0.055115404 | ... U20: =IFERROR(U4/U$16,"") -> 0.052185793
I21: daniele francilia | L21: =IFERROR(L5/L$16,"") -> 0 | M21: =IFERROR(M5/M$16,"") -> 0 | N21: =IFERROR(N5/N$16,"") -> 0.11041676 | O21: =IFERROR(O5/O$16,"") -> 0.088484117 | P21: =IFERROR(P5/P$16,"") -> 0.060365435 | Q21: =IFERROR(Q5/Q$16,"") -> 0.060351708 | R21: =IFERROR(R5/R$16,"") -> 0.056055677 | S21: =IFERROR(S5/S$16,"") -> 0.055308876 | ... U21: =IFERROR(U5/U$16,"") -> 0.052368981
I22: pierre bezencon | L22: =IFERROR(L6/L$16,"") -> 0 | M22: =IFERROR(M6/M$16,"") -> 0 | N22: =IFERROR(N6/N$16,"") -> 0.10997117 | O22: =IFERROR(O6/O$16,"") -> 0.088127041 | P22: =IFERROR(P6/P$16,"") -> 0.060121831 | Q22: =IFERROR(Q6/Q$16,"") -> 0.060108159 | R22: =IFERROR(R6/R$16,"") -> 0.055829465 | S22: =IFERROR(S6/S$16,"") -> 0.055085677 | ... U22: =IFERROR(U6/U$16,"") -> 0.052157647
I23: matthew beatty | L23: =IFERROR(L7/L$16,"") -> 0 | M23: =IFERROR(M7/M$16,"") -> 0 | N23: =IFERROR(N7/N$16,"") -> 0.25699537 | O23: =IFERROR(O7/O$16,"") -> 0.20594707 | P23: =IFERROR(P7/P$16,"") -> 0.14050075 | Q23: =IFERROR(Q7/Q$16,"") -> 0.1404688 | R23: =IFERROR(R7/R$16,"") -> 0.13046977 | S23: =IFERROR(S7/S$16,"") -> 0.14167103 | ... U23: =IFERROR(U7/U$16,"") -> 0.13414063
I24: bo kriek | L24: =IFERROR(L8/L$16,"") -> 0 | M24: =IFERROR(M8/M$16,"") -> 0 | N24: =IFERROR(N8/N$16,"") -> 0.2754052 | O24: =IFERROR(O8/O$16,"") -> 0.22070007 | P24: =IFERROR(P8/P$16,"") -> 0.1505655 | Q24: =IFERROR(Q8/Q$16,"") -> 0.15053126 | R24: =IFERROR(R8/R$16,"") -> 0.13981596 | S24: =IFERROR(S8/S$16,"") -> 0.13795326 | ... U24: =IFERROR(U8/U$16,"") -> 0.13062048
I25: Dario Deiana | L25: =IFERROR(L9/L$16,"") -> 0 | M25: =IFERROR(M9/M$16,"") -> 0 | N25: =IFERROR(N9/N$16,"") -> 0 | O25: =IFERROR(O9/O$16,"") -> 0.16071852 | P25: =IFERROR(P9/P$16,"") -> 0.1096312 | Q25: =IFERROR(Q9/Q$16,"") -> 0.10958134 | R25: =IFERROR(R9/R$16,"") -> 0.10177538 | S25: =IFERROR(S9/S$16,"") -> 0.10038124 | ... U25: =IFERROR(U9/U$16,"") -> 0.094992797
I26: alain bensimon | L26: =IFERROR(L10/L$16,"") -> 0 | M26: =IFERROR(M10/M$16,"") -> 0 | N26: =IFERROR(N10/N$16,"") -> 0 | O26: =IFERROR(O10/O$16,"") -> 0 | P26: =IFERROR(P10/P$16,"") -> 0.075005184 | Q26: =IFERROR(Q10/Q$16,"") -> 0.074988128 | R26: =IFERROR(R10/R$16,"") -> 0.069650229 | S26: =IFERROR(S10/S$16,"") -> 0.068722314 | ... U26: =IFERROR(U10/U$16,"") -> 0.065069441
I27: anne cecile noique | L27: =IFERROR(L11/L$16,"") -> 0 | M27: =IFERROR(M11/M$16,"") -> 0 | N27: =IFERROR(N11/N$16,"") -> 0 | O27: =IFERROR(O11/O$16,"") -> 0 | P27: =IFERROR(P11/P$16,"") -> 0.12215186 | Q27: =IFERROR(Q11/Q$16,"") -> 0.12212409 | R27: =IFERROR(R11/R$16,"") -> 0.1134309 | S27: =IFERROR(S11/S$16,"") -> 0.11191971 | ... U27: =IFERROR(U11/U$16,"") -> 0.10597072
I28: terance chen | L28: =IFERROR(L12/L$16,"") -> 0 | M28: =IFERROR(M12/M$16,"") -> 0 | N28: =IFERROR(N12/N$16,"") -> 0 | O28: =IFERROR(O12/O$16,"") -> 0 | P28: =IFERROR(P12/P$16,"") -> 0.12053917 | Q28: =IFERROR(Q12/Q$16,"") -> 0.12051176 | R28: =IFERROR(R12/R$16,"") -> 0.11193334 | S28: =IFERROR(S12/S$16,"") -> 0.11044211 | ... U28: =IFERROR(U12/U$16,"") -> 0.10457165
I29: INDIGO Ventures | L29: =IFERROR(L13/L$16,"") -> 0 | M29: =IFERROR(M13/M$16,"") -> 0 | N29: =IFERROR(N13/N$16,"") -> 0 | O29: =IFERROR(O13/O$16,"") -> 0 | P29: =IFERROR(P13/P$16,"") -> 0 | Q29: =IFERROR(Q13/Q$16,"") -> 0 | R29: =IFERROR(R13/R$16,"") -> 0.066050264 | S29: =IFERROR(S13/S$16,"") -> 0.065195121 | ... U29: =IFERROR(U13/U$16,"") -> 0.061764014
I30: Indigo Main Fund | L30: =IFERROR(L14/L$16,"") -> 0 | M30: =IFERROR(M14/M$16,"") -> 0 | N30: =IFERROR(N14/N$16,"") -> 0 | O30: =IFERROR(O14/O$16,"") -> 0 | P30: =IFERROR(P14/P$16,"") -> 0 | Q30: =IFERROR(Q14/Q$16,"") -> 0 | R30: =IFERROR(R14/R$16,"") -> 0 | S30: =IFERROR(S14/S$16,"") -> 0 | ... U30: =IFERROR(U14/U$16,"") -> 0.05262528
I31: Lars Ahlgreen
I32: Total AUM | L32: =SUM(L18:L30) -> 1 | M32: =SUM(M18:M30) -> 1 | N32: =SUM(N18:N30) -> 1 | O32: =SUM(O18:O30) -> 1 | P32: =SUM(P18:P30) -> 1 | Q32: =SUM(Q18:Q30) -> 1 | R32: =SUM(R18:R30) -> 1 | S32: =SUM(S18:S30) -> 1 | ... U32: =SUM(U18:U30) -> 1

Sheet Report
B1: BTC | C1: ETH | D1: USDT
A2: Month
A3: Quarter
A4: Year
A7: LUIS JOSE MOLLA TRUSTEE OF THE LUIS JOSE MOLLA REVOCABLE TRUST UAD 2/7/17 521 E DILIDO DR | G7: KYLE GULAMERIAN – 40 ST. DAVIDS SQUARE | M7: Matthias Reiser - Kard. -Dopfner-Str. | S7: Thomas Puech - 21 Brook Mews North | Y7: Danielle Richetta - Parnassusweg 7-2 | AE7: Nathanaël Cohen - 82 Amberley Road | AK7: Vivie-Ann Bakos - 2121 Biscayne Boulevard | AQ7: Victoria Pariente-Cohen | AW7: Flat 4, Westfield - 15 Kidderpore Avenue | BC7: Nathanael Cohen, Director - INDIGO DIGITAL ASSET FUND LP | BI7: HAMZA & HICHAM & MARYIAM & MOHAMED KABBAJ & FATIMA SAKI | BO7: Bo De kriek | BU7: Pierre Bezençon | CA7: Matthew Beatty | CG7: Julien Grunebaum | CM7: Daniele Francilia
A8: MIAMI BEACH, FL 33139 | G8: LONDON, E14 3WA – UNITED KINGDOM | M8: 80333 Munchen - Germany | S8: W2 3BW London - UK | Y8: 1077 DA Amsterdam - Netherlands | AE8: W9 2JY London - UK | AK8: 33137 Miami, FL - USA | AQ8: 129 Bd Diderot, 75012, Paris, France | AW8: NW3 7SF London - UK | BC8: 2121 BISCAYNE BLVD #1621 - MIAMI, FL 33137 - USA | BI8: 392 MARSA DUBAI - FLAT 4102 - 71893 Dubai, UAE | BO8: Czaar peterstraat 78, Amsterdam, Noord holland, 1018PR | BU8: Switzerland, Geneva, Geneva, Switzerland | CA8: Cape Town, South Africa | CG8: Hong Kong, Hong Kong | CM8: Dubai
A10: Jose MOLLA | G10: Kyle | M10: Matthias Reiser | S10: Thomas Puech | Y10: Danielle Richetta | AE10: Nathanaël Cohen | AK10: Blondish | AQ10: Victoria Pariente-Cohen | AW10: Babak Eftekhari | BC10: INDIGO DIGITAL ASSET FUND LP | BI10: Kabbaj | BO10: Bo De kriek | BU10: Pierre Bezençon | CA10: Matthew Beatty | CG10: Julien Grunebaum | CM10: Daniele Francilia | CS10: oliver loisel | CY10: Dario Deiana | DE10: alain bensimon | DK10: anne cecile noique | DQ10: terance chen | DW10: Advantage Blockchain | EC10: Alec Beckman | EI10: INDIGO Ventures | EO10: Lars Ahlgreen
G11: Out
A12: CAPITAL ACCOUNT SUMMARY FROM 08/2023 | G12: CAPITAL ACCOUNT SUMMARY | M12: CAPITAL ACCOUNT SUMMARY FROM 10/2024 | S12: CAPITAL ACCOUNT SUMMARY FROM 10/2024 | Y12: CAPITAL ACCOUNT SUMMARY FROM 10/2024 | AE12: CAPITAL ACCOUNT SUMMARY FROM 04/2025 | AK12: CAPITAL ACCOUNT SUMMARY FROM 04/2025 | AQ12: CAPITAL ACCOUNT SUMMARY FROM 04/2025 | BI12: CAPITAL ACCOUNT SUMMARY FROM 06/2025 | CS12: CAPITAL ACCOUNT SUMMARY FROM 07/2025
B13: MTD (BTC) | C13: QTD (BTC) | D13: YTD (BTC) | E13: ITD (BTC) | H13: MTD (BTC) | I13: QTD (BTC) | J13: YTD (BTC) | K13: ITD (BTC) | N13: MTD (BTC) | O13: QTD (BTC) | P13: YTD (BTC) | Q13: ITD (BTC) | T13: MTD (BTC) | U13: QTD (BTC) | V13: YTD (BTC) | W13: ITD (BTC) | Z13: MTD (BTC) | AA13: QTD (BTC) | AB13: YTD (BTC) | AC13: ITD (BTC) | AF13: MTD (BTC) | AG13: QTD (BTC) | AH13: YTD (BTC) | AI13: ITD (BTC) | AL13: MTD (BTC) | AM13: QTD (BTC) | AN13: YTD (BTC) | AO13: ITD (BTC) | AR13: MTD (BTC) | AS13: QTD (BTC) | AT13: YTD (BTC) | AU13: ITD (BTC) | BJ13: MTD (BTC) | BK13: QTD (BTC) | BL13: YTD (BTC) | BM13: ITD (BTC) | CT13: MTD (BTC) | CU13: QTD (BTC) | CV13: YTD (BTC) | CW13: ITD (BTC)
A14: Beginning Balance | B14: ='BTC Yield Fund'!AG3 -> 3.6756714 | C14: ='BTC Yield Fund'!AC3 -> 3.6615306 | D14: ='BTC Yield Fund'!T3 -> 3.5633876 | E14: ='BTC Yield Fund'!K3 -> 3.4856 | G14: Beginning Balance | H14: ='BTC Yield Fund'!AA4 -> 0 | I14: ='DONE - BTC Boosted Program'!O3 -> 2.0905645 | J14: ='DONE - BTC Boosted Program'!L3 -> 2.0398609 | M14: Beginning Balance | N14: ='BTC Yield Fund'!AG5 -> 4.9164347 | O14: ='BTC Yield Fund'!AC5 -> 4.8951647 | P14: ='DONE - BTC Boosted Program'!L4 -> 4.6869289 | Q14: ='BTC Yield Fund'!N5 -> 4.62 | S14: Beginning Balance | T14: ='BTC Yield Fund'!AG6 -> 6.6966399 | U14: ='DONE - BTC TAC Program'!N5 -> 6.6960456 | V14: ='BTC Yield Fund'!T6 -> 6.6341945 | W14: ='BTC Yield Fund'!N6 -> 6.5193 | Y14: Beginning Balance | Z14: ='BTC Yield Fund'!AG7 -> 4.7263666 | AA14: ='BTC Yield Fund'!AC7 -> 4.9649496 | AB14: ='DONE - BTC Boosted Program'!L5 -> 4.8786519 | AC14: ='BTC Yield Fund'!N7 -> 5.2 | AE14: Beginning Balance | AF14: ='BTC Yield Fund'!AG10 -> 0.44644266 | AG14: ='DONE - BTC TAC Program'!N4 -> 0.44637649 | AH14: ='DONE - BTC TAC Program'!K4 -> 0.4483 | AI14: ='DONE - BTC TAC Program'!K4 -> 0.4483 | AK14: Beginning Balance | AL14: ='BTC Yield Fund'!AG11 -> 4.1036689 | AM14: ='DONE - BTC TAC Program'!N6 -> 4.1033181 | AN14: ='DONE - BTC TAC Program'!K6 -> 4.121 | AO14: ='DONE - BTC TAC Program'!K6 -> 4.121 | AQ14: Beginning Balance | AR14: ='BTC Yield Fund'!AG9 -> 0.14854729 | AS14: ='DONE - BTC TAC Program'!N3 -> 0.14855983 | AT14: ='DONE - BTC TAC Program'!K3 -> 0.1492 | AU14: ='DONE - BTC TAC Program'!K3 -> 0.1492 | BI14: Beginning Balance | BJ14: ='BTC Yield Fund'!AG8 -> 3.6012561 | BK14: ='BTC Yield Fund'!AC8 -> 2.0013398 | BL14: ='BTC Yield Fund'!AB8 -> 2 | BM14: ='BTC Yield Fund'!AB8 -> 2 | CS14: Beginning Balance | CT14: ='BTC Yield Fund'!AG12 -> 2.1167382 | CU14: ='BTC Yield Fund'!AE12 -> 2.115364 | CV14: ='BTC Yield Fund'!AE12 -> 2.115364 | CW14: ='BTC Yield Fund'!AE12 -> 2.115364
A15: Additions | B15: 0 | C15: 0 | D15: 0 | E15: 0 | G15: Additions | H15: 0 | I15: 0 | J15: 0 | K15: 0 | M15: Additions | N15: 0 | O15: 0 | P15: 0 | Q15: 0 | S15: Additions | T15: 0 | U15: 0 | V15: 0 | W15: 0 | Y15: Additions | Z15: 0 | AA15: 0 | AB15: 0 | AC15: 0 | AE15: Additions | AF15: 0 | AG15: 0 | AH15: 0 | AI15: 0 | AK15: Additions | AL15: 0 | AM15: 0 | AN15: 0 | AO15: 0 | AQ15: Additions | AR15: 0 | AS15: 0 | AT15: 0 | AU15: 0 | BI15: Additions | BJ15: =0.9102 -> 0.9102 | BK15: =0.9914+0.6+0.9102 -> 2.5016 | BL15: =0.9914+0.6+0.9102 -> 2.5016 | BM15: =0.9914+0.6+0.9102 -> 2.5016 | CS15: Additions | CT15: 0 | CU15: 0 | CV15: 0 | CW15: 0
A16: Redemptions | B16: 0 | C16: 0 | D16: 0 | E16: 0 | G16: Redemptions | H16: 0 | I16: =2.0023+0.1078 -> 2.1101 | J16: =2.0023+0.1078 -> 2.1101 | K16: 0 | M16: Redemptions | N16: 0 | O16: 0 | P16: 0 | Q16: 0 | S16: Redemptions | T16: 0 | U16: 0 | V16: 0 | W16: 0 | Y16: Redemptions | Z16: 0.11 | AA16: =0.26+0.11 -> 0.37 | AB16: =0.39+0.11 -> 0.5 | AC16: =0.784+0.11 -> 0.894 | AE16: Redemptions | AF16: 0 | AG16: 0 | AH16: 0 | AI16: 0 | AK16: Redemptions | AL16: 0 | AM16: 0 | AN16: 0 | AO16: 0 | AQ16: Redemptions | AR16: 0 | AS16: 0 | AT16: 0 | AU16: 0 | BI16: Redemptions | BJ16: 0 | BK16: 0 | BL16: 0 | BM16: 0 | CS16: Redemptions | CT16: 0 | CU16: 0 | CV16: 0 | CW16: 0
A17: Net Income | B17: =B18-B14 -> 0.010747571 | C17: =C18-C14 -> 0.024888368 | D17: =D18-D14 -> 0.12303129 | E17: =E18-E14 -> 0.20081892 | G17: Net Income | H17: =H18-H14+H16 -> 0 | I17: =I18-I14+I16 -> 0.019535482 | J17: =J18-J14+J16 -> 0.070239105 | K17: =K18-K14-K15 -> 0 | M17: Net Income | N17: =N18-N14 -> 0.01617372 | O17: =O18-O14 -> 0.037443714 | P17: =P18-P14 -> 0.24567946 | Q17: =Q18-Q14-Q15 -> 0.31260839 | S17: Net Income | T17: =T18-T14 -> 0.024479784 | U17: =U18-U14 -> 0.025074101 | V17: =V18-V14 -> 0.086925225 | W17: =W18-W14-W15 -> 0.20181969 | Y17: Net Income | Z17: =Z18-Z14+Z16-Z15 -> 0.015453268 | AA17: =AA18-AA14+AA16-AA15 -> 0.036870264 | AB17: =AB18-AB14+AB16-AB15 -> 0.25316799 | AC17: =AC18-AC14+AC16-AC15 -> 0.32581988 | AE17: Net Income | AF17: =AF18-AF14 -> 0.0016319856 | AG17: =AG18-AG14 -> 0.001698159 | AH17: =AH18-AH14 -> -0.00022535412 | AI17: =AI18-AI14-AI15 -> -0.00022535412 | AK17: Net Income | AL17: =AL18-AL14 -> 0.015001094 | AM17: =AM18-AM14 -> 0.0153519 | AN17: =AN18-AN14 -> -0.0023300039 | AO17: =AO18-AO14-AO15 -> -0.0023300039 | AQ17: Net Income | AR17: =AR18-AR14 -> 0.00054301942 | AS17: =AS18-AS14 -> 0.00053047806 | AT17: =AT18-AT14 -> -0.00010969182 | AU17: =AU18-AU14-AU15 -> -0.00010969182 | BI17: Net Income | BJ17: =BJ18-BJ14-BJ15 -> 0.010872371 | BK17: =BK18-BK14-BK15 -> 0.019388671 | BL17: =BL18-BL14-BL15 -> 0.020728431 | BM17: =BM18-BM14-BM15 -> 0.020728431 | CS17: Net Income | CT17: =CT18-CT14 -> 0.0069634873 | CU17: =CU18-CU14 -> 0.0083376394 | CV17: =CV18-CV14 -> 0.0083376394 | CW17: =CW18-CW14-CW15 -> 0.0083376394
A18: Ending Balance | B18: ='BTC Yield Fund'!AJ3 -> 3.6864189 | C18: =B18 -> 3.6864189 | D18: =B18 -> 3.6864189 | E18: =B18 -> 3.6864189 | G18: Ending Balance | H18: ='BTC Yield Fund'!AC4 -> 0 | I18: =H18 -> 0 | J18: =H18 -> 0 | K18: =H18 -> 0 | M18: Ending Balance | N18: ='BTC Yield Fund'!AJ5 -> 4.9326084 | O18: =N18 -> 4.9326084 | P18: =N18 -> 4.9326084 | Q18: =N18 -> 4.9326084 | S18: Ending Balance | T18: ='BTC Yield Fund'!AJ6 -> 6.7211197 | U18: =T18 -> 6.7211197 | V18: =T18 -> 6.7211197 | W18: =T18 -> 6.7211197 | Y18: Ending Balance | Z18: ='BTC Yield Fund'!AJ7 -> 4.6318199 | AA18: =Z18 -> 4.6318199 | AB18: =Z18 -> 4.6318199 | AC18: =Z18 -> 4.6318199 | AE18: Ending Balance | AF18: ='BTC Yield Fund'!AJ10 -> 0.44807465 | AG18: =AF18 -> 0.44807465 | AH18: =AF18 -> 0.44807465 | AI18: =AF18 -> 0.44807465 | AK18: Ending Balance | AL18: ='BTC Yield Fund'!AJ11 -> 4.11867 | AM18: =AL18 -> 4.11867 | AN18: =AL18 -> 4.11867 | AO18: =AL18 -> 4.11867 | AQ18: Ending Balance | AR18: ='BTC Yield Fund'!AJ9 -> 0.14909031 | AS18: =AR18 -> 0.14909031 | AT18: =AR18 -> 0.14909031 | AU18: =AR18 -> 0.14909031 | BI18: Ending Balance | BJ18: ='BTC Yield Fund'!AJ8 -> 4.5223284 | BK18: =BJ18 -> 4.5223284 | BL18: =BJ18 -> 4.5223284 | BM18: =BJ18 -> 4.5223284 | CS18: Ending Balance | CT18: ='BTC Yield Fund'!AJ12 -> 2.1237016 | CU18: =CT18 -> 2.1237016 | CV18: =CT18 -> 2.1237016 | CW18: =CT18 -> 2.1237016
A19: Rate of Return | B19: =B17/B14 -> 0.0029239748 | C19: =C17/C14 -> 0.006797258 | D19: =D17/D14 -> 0.034526498 | E19: =E17/E14 -> 0.057613875 | G19: Rate of Return | H19: =H17/H14 -> #DIV/0! | I19: =I17/I14 -> 0.0093445964 | J19: =J17/J14 -> 0.034433282 | K19: =K17/K14 -> #DIV/0! | M19: Rate of Return | N19: =N17/N14 -> 0.0032897254 | O19: =O17/O14 -> 0.0076491224 | P19: =P17/P14 -> 0.052418004 | Q19: =Q17/Q14 -> 0.067664154 | S19: Rate of Return | T19: =T17/T14 -> 0.0036555324 | U19: =U17/U14 -> 0.0037446133 | V19: =V17/V14 -> 0.013102604 | W19: =W17/W14 -> 0.030957264 | Y19: Rate of Return | Z19: =Z17/Z14 -> 0.0032695872 | AA19: =AA17/AA14 -> 0.0074261105 | AB19: =AB17/AB14 -> 0.051893023 | AC19: =AC17/AC14 -> 0.062657669 | AE19: Rate of Return | AF19: =AF17/AF14 -> 0.0036555324 | AG19: =AG17/AG14 -> 0.00380432 | AH19: =AH17/AH14 -> -0.00050268597 | AI19: =AI17/AI14 -> -0.00050268597 | AK19: Rate of Return | AL19: =AL17/AL14 -> 0.0036555324 | AM19: =AM17/AM14 -> 0.003741338 | AN19: =AN17/AN14 -> -0.0005653977 | AO19: =AO17/AO14 -> -0.0005653977 | AQ19: Rate of Return | AR19: =AR17/AR14 -> 0.0036555324 | AS19: =AS17/AS14 -> 0.0035708042 | AT19: =AT17/AT14 -> -0.00073519986 | AU19: =AU17/AU14 -> -0.00073519986 | BI19: Rate of Return | BJ19: =BJ17/BJ14 -> 0.0030190498 | BK19: =BK17/BK14 -> 0.009687846 | BL19: =BL17/BL14 -> 0.010364215 | BM19: =BM17/BM14 -> 0.010364215 | CS19: Rate of Return | CT19: =CT17/CT14 -> 0.0032897254 | CU19: =CU17/CU14 -> 0.0039414679 | CV19: =CV17/CV14 -> 0.0039414679 | CW19: =CW17/CW14 -> 0.0039414679
BC20: Out
A21: CAPITAL ACCOUNT SUMMARY FROM 08/2023 | AE21: CAPITAL ACCOUNT SUMMARY FROM 10/2023 | AK21: CAPITAL ACCOUNT SUMMARY FROM 10/2023 | AW21: CAPITAL ACCOUNT SUMMARY FROM 05/2025 | BC21: CAPITAL ACCOUNT SUMMARY FROM 05/2025 | DW21: CAPITAL ACCOUNT SUMMARY FROM 08/2025 | EC21: CAPITAL ACCOUNT SUMMARY FROM 08/2025 | EO21: CAPITAL ACCOUNT SUMMARY FROM 08/2025
B22: MTD (ETH) | C22: QTD (ETH) | D22: YTD (ETH) | E22: ITD (ETH) | AF22: MTD (ETH) | AG22: QTD (ETH) | AH22: YTD (ETH) | AI22: ITD (ETH) | AL22: MTD (ETH) | AM22: QTD (ETH) | AN22: YTD (ETH) | AO22: ITD (ETH) | AX22: MTD (ETH) | AY22: QTD (ETH) | AZ22: YTD (ETH) | BA22: ITD (ETH) | BD22: MTD (ETH) | BE22: QTD (ETH) | BF22: YTD (ETH) | BG22: ITD (ETH) | DX22: MTD (ETH) | DY22: QTD (ETH) | DZ22: YTD (ETH) | EA22: ITD (ETH) | ED22: MTD (ETH) | EE22: QTD (ETH) | EF22: YTD (ETH) | EG22: ITD (ETH) | EP22: MTD (ETH) | EQ22: QTD (ETH) | ER22: YTD (ETH) | ES22: ITD (ETH)
A23: Beginning Balance | B23: ='ETH Yield Fund'!Q6 -> 62.857388 | C23: ='Done - ETH TAC Program'!W3 -> 65.121133 | D23: ='Done - ETH TAC Program'!Q3 -> 63.20573 | E23: ='Done - ETH TAC Program'!K3 -> 62.116 | AE23: Beginning Balance | AF23: ='ETH Yield Fund'!Q5 -> 31.924849 | AG23: ='Done - ETH TAC Program'!W4+'ETH Yield Fund'!N5 -> 32.813707 | AH23: ='Done - ETH TAC Program'!Q4 -> 17.082535 | AI23: ='Done - ETH TAC Program'!M4 -> 17 | AK23: Beginning Balance | AL23: ='ETH Yield Fund'!Q7 -> 120.33919 | AM23: ='Done - ETH TAC Program'!W5 -> 124.55846 | AN23: ='Done - ETH TAC Program'!Q5 -> 120 | AO23: ='Done - ETH TAC Program'!N5 -> 120 | AW23: Beginning Balance | AX23: ='ETH Yield Fund'!Q3 -> 60.143892 | AY23: ='ETH Yield Fund'!N3 -> 59.66558 | AZ23: ='ETH Yield Fund'!L3 -> 27.01 | BA23: ='ETH Yield Fund'!L3 -> 27.01 | BC23: Beginning Balance | BD23: ='ETH Yield Fund'!Q4 -> 0 | BE23: ='ETH Yield Fund'!N4 -> 176.60184 | BF23: ='ETH Yield Fund'!L4 -> 175 | BG23: ='ETH Yield Fund'!L4 -> 175 | DW23: Beginning Balance | DX23: ='ETH Yield Fund'!Q8 -> 32 | DY23: ='ETH Yield Fund'!P8 -> 32 | DZ23: ='ETH Yield Fund'!P8 -> 32 | EA23: ='ETH Yield Fund'!P8 -> 32 | EC23: Beginning Balance | ED23: ='ETH Yield Fund'!Q9 -> 0 | EE23: ='ETH Yield Fund'!Q9 -> 0 | EF23: ='ETH Yield Fund'!Q9 -> 0 | EG23: ='ETH Yield Fund'!Q9 -> 0 | EO23: Beginning Balance | EP23: ='ETH Yield Fund'!AC9 | EQ23: ='ETH Yield Fund'!AC9 | ER23: ='ETH Yield Fund'!AC9 | ES23: ='ETH Yield Fund'!AC9
A24: Additions | B24: 0 | C24: 0 | D24: 0 | E24: 0 | AE24: Additions | AF24: 0 | AG24: 0 | AH24: =4.608+5.226+3.0466+2 -> 14.8806 | AI24: 14.8806 | AK24: Additions | AL24: 0 | AM24: 0 | AN24: 0 | AO24: 0 | AW24: Additions | AX24: 0 | AY24: 0 | AZ24: 32.25 | BA24: 32.25 | BC24: Additions | BD24: 0 | BE24: 0 | BF24: 0 | BG24: 0 | DW24: Additions | DX24: 0 | DY24: 0 | DZ24: 0 | EA24: 0 | EC24: Additions | ED24: 0 | EE24: 0 | EF24: 0 | EG24: 0 | EO24: Additions | EP24: 0 | EQ24: 0 | ER24: 0 | ES24: 0
A25: Redemptions | B25: 0 | C25: 0 | D25: 0 | E25: 0 | AE25: Redemptions | AF25: 0 | AG25: 0 | AH25: 0 | AI25: 0 | AK25: Redemptions | AL25: 0 | AM25: 0 | AN25: 0 | AO25: 0 | AW25: Redemptions | AX25: 0 | AY25: 0 | AZ25: 0 | BA25: 0 | BC25: Redemptions | BD25: 0 | BE25: 0 | BF25: 0 | BG25: 0 | DW25: Redemptions | DX25: 0 | DY25: 0 | DZ25: 0 | EA25: 0 | EC25: Redemptions | ED25: 0 | EE25: 0 | EF25: 0 | EG25: 0 | EO25: Redemptions | EP25: 0 | EQ25: 0 | ER25: 0 | ES25: 0
A26: Net Income | B26: =B27-B23 -> 0.43078538 | C26: =C27-C23 -> -1.8329598 | D26: =D27-D23 -> 0.08244292 | E26: =E27-E23 -> 1.172173 | AE26: Net Income | AF26: =AF27-AF23-AF24 -> 0.27349128 | AG26: =AG27-AG23-AG24 -> -0.61536754 | AH26: =AH27-AH23-AH24 -> 0.23520538 | AI26: =AI27-AI23-AI24+AI25 -> 0.31773993 | AK26: Net Income | AL26: =AL27-AL23 -> 1.0309123 | AM26: =AM27-AM23 -> -3.1883635 | AN26: =AN27-AN23 -> 1.3700978 | AO26: =AO27-AO23-AO24 -> 1.3700978 | AW26: Net Income | AX26: =AX27-AX23-AX24 -> 0.42249349 | AY26: =AY27-AY23-AY24 -> 0.90080542 | AZ26: =AZ27-AZ23-AZ24 -> 1.3063854 | BA26: =BA27-BA23-BA24 -> 1.3063854 | BC26: Net Income | BD26: =BD27-BD23 -> 178.37238 | BE26: =BE27-BE23 -> 1.7705491 | BF26: =BF27-BF23 -> 3.3723848 | BG26: =BG27-BG23-BG24 -> 3.3723848 | DW26: Net Income | DX26: =DX27-DX23 -> 0.21930807 | DY26: =DY27-DY23 -> 0.21930807 | DZ26: =DZ27-DZ23 -> 0.21930807 | EA26: =EA27-EA23-EA24 -> 0.21930807 | EC26: Net Income | ED26: =ED27-ED23 -> 0.0054827017 | EE26: =EE27-EE23 -> 0.0054827017 | EF26: =EF27-EF23 -> 0.0054827017 | EG26: =EG27-EG23-EG24 -> 0.0054827017 | EO26: Net Income | EP26: =EP27-EP23 -> 0 | EQ26: =EQ27-EQ23 -> 0 | ER26: =ER27-ER23 -> 0 | ES26: =ES27-ES23-ES24 -> 0
A27: Ending Balance | B27: ='ETH Yield Fund'!R6 -> 63.288173 | C27: =B27 -> 63.288173 | D27: =B27 -> 63.288173 | E27: =B27 -> 63.288173 | AE27: Ending Balance | AF27: ='ETH Yield Fund'!R5 -> 32.19834 | AG27: =AF27 -> 32.19834 | AH27: =AG27 -> 32.19834 | AI27: =AF27 -> 32.19834 | AK27: Ending Balance | AL27: ='ETH Yield Fund'!R7 -> 121.3701 | AM27: =AL27 -> 121.3701 | AN27: =AM27 -> 121.3701 | AO27: =AL27 -> 121.3701 | AW27: Ending Balance | AX27: ='ETH Yield Fund'!R3 -> 60.566385 | AY27: =AX27 -> 60.566385 | AZ27: =AY27 -> 60.566385 | BA27: =AX27 -> 60.566385 | BC27: Ending Balance | BD27: ='ETH Yield Fund'!P4 -> 178.37238 | BE27: =BD27 -> 178.37238 | BF27: =BE27 -> 178.37238 | BG27: =BD27 -> 178.37238 | DW27: Ending Balance | DX27: ='ETH Yield Fund'!R8 -> 32.219308 | DY27: =DX27 -> 32.219308 | DZ27: =DY27 -> 32.219308 | EA27: =DX27 -> 32.219308 | EC27: Ending Balance | ED27: ='ETH Yield Fund'!R9 -> 0.0054827017 | EE27: =ED27 -> 0.0054827017 | EF27: =EE27 -> 0.0054827017 | EG27: =ED27 -> 0.0054827017 | EO27: Ending Balance | EP27: ='ETH Yield Fund'!AD9 | EQ27: =EP27 | ER27: =EQ27 | ES27: =EP27
A28: Rate of Return | B28: =B26/B23 -> 0.0068533771 | C28: =C26/C23 -> -0.028146927 | D28: =D26/D23 -> 0.0013043583 | E28: =E26/E23 -> 0.018870709 | AE28: Rate of Return | AF28: =AF26/AF23 -> 0.0085667214 | AG28: =AG26/AG23 -> -0.018753368 | AH28: =AH26/AH23 -> 0.013768764 | AI28: =AI26/AI23 -> 0.018690584 | AK28: Rate of Return | AL28: =AL26/AL23 -> 0.0085667214 | AM28: =AM26/AM23 -> -0.025597325 | AN28: =AN26/AN23 -> 0.011417482 | AO28: =AO26/AO23 -> 0.011417482 | AW28: Rate of Return | AX28: =AX26/AX23 -> 0.0070247115 | AY28: =AY26/AY23 -> 0.015097572 | AZ28: =AZ26/AZ23 -> 0.048366731 | BA28: =BA26/BA23 -> 0.048366731 | BC28: Rate of Return | BD28: =BD26/BD23 -> #DIV/0! | BE28: =BE26/BE23 -> 0.010025655 | BF28: =BF26/BF23 -> 0.01927077 | BG28: =BG26/BG23 -> 0.01927077 | DW28: Rate of Return | DX28: =DX26/DX23 -> 0.0068533771 | DY28: =DY26/DY23 -> 0.0068533771 | DZ28: =DZ26/DZ23 -> 0.0068533771 | EA28: =EA26/EA23 -> 0.0068533771 | EC28: Rate of Return | ED28: =IFERROR(ED26/ED23,"") | EE28: =IFERROR(EE26/EE23,"") | EF28: =IFERROR(EF26/EF23,"") | EG28: =IFERROR(EG26/EG23,"") | EO28: Rate of Return | EP28: =IFERROR(EP26/EP23,"") | EQ28: =IFERROR(EQ26/EQ23,"") | ER28: =IFERROR(ER26/ER23,"") | ES28: =IFERROR(ES26/ES23,"")
AW30: CAPITAL ACCOUNT SUMMARY FROM 06/2025 | BC30: CAPITAL ACCOUNT SUMMARY FROM 08/2025 | BO30: CAPITAL ACCOUNT SUMMARY FROM 07/2025 | BU30: CAPITAL ACCOUNT SUMMARY FROM 07/2025 | CA30: CAPITAL ACCOUNT SUMMARY FROM 07/2025 | CG30: CAPITAL ACCOUNT SUMMARY FROM 07/2025 | CM30: CAPITAL ACCOUNT SUMMARY FROM 07/2025 | CY30: CAPITAL ACCOUNT SUMMARY FROM 07/2025 | DE30: CAPITAL ACCOUNT SUMMARY FROM 07/2025 | DK30: CAPITAL ACCOUNT SUMMARY FROM 07/2025 | DQ30: CAPITAL ACCOUNT SUMMARY FROM 07/2025 | EI30: CAPITAL ACCOUNT SUMMARY FROM 08/2025 | EO30: CAPITAL ACCOUNT SUMMARY FROM 08/2025
AX31: MTD (USDT) | AY31: QTD (USDT) | AZ31: YTD (USDT) | BA31: ITD (USDT) | BD31: MTD (USDT) | BE31: QTD (USDT) | BF31: YTD (USDT) | BG31: ITD (USDT) | BP31: MTD (USDT) | BQ31: QTD (USDT) | BR31: YTD (USDT) | BS31: ITD (USDT) | BV31: MTD (USDT) | BW31: QTD (USDT) | BX31: YTD (USDT) | BY31: ITD (USDT) | CB31: MTD (USDT) | CC31: QTD (USDT) | CD31: YTD (USDT) | CE31: ITD (USDT) | CH31: MTD (USDT) | CI31: QTD (USDT) | CJ31: YTD (USDT) | CK31: ITD (USDT) | CN31: MTD (USDT) | CO31: QTD (USDT) | CP31: YTD (USDT) | CQ31: ITD (USDT) | CZ31: MTD (USDT) | DA31: QTD (USDT) | DB31: YTD (USDT) | DC31: ITD (USDT) | DF31: MTD (USDT) | DG31: QTD (USDT) | DH31: YTD (USDT) | DI31: ITD (USDT) | DL31: MTD (USDT) | DM31: QTD (USDT) | DN31: YTD (USDT) | DO31: ITD (USDT) | DR31: MTD (USDT) | DS31: QTD (USDT) | DT31: YTD (USDT) | DU31: ITD (USDT) | EJ31: MTD (USDT) | EK31: QTD (USDT) | EL31: YTD (USDT) | EM31: ITD (USDT) | EP31: MTD (ETH) | EQ31: QTD (ETH) | ER31: YTD (ETH) | ES31: ITD (ETH)
AW32: Beginning Balance | AX32: ='USDT Yield Fund'!Q3 -> 183981.1 | AY32: ='USDT Yield Fund'!M3 -> 136175.4 | AZ32: ='USDT Yield Fund'!L3 -> 135726.75 | BA32: ='USDT Yield Fund'!L3 -> 135726.75 | BC32: Beginning Balance | BD32: ='USDT Yield Fund'!T14 -> 111370 | BE32: ='USDT Yield Fund'!T14 -> 111370 | BF32: ='USDT Yield Fund'!T14 -> 111370 | BG32: ='USDT Yield Fund'!T14 -> 111370 | BO32: Beginning Balance | BP32: ='USDT Yield Fund'!Q8 -> 275049.07 | BQ32: ='USDT Yield Fund'!N8 -> 273807 | BR32: ='USDT Yield Fund'!N8 -> 273807 | BS32: ='USDT Yield Fund'!N8 -> 273807 | BU32: Beginning Balance | BV32: ='USDT Yield Fund'!Q6 -> 109828.97 | BW32: ='USDT Yield Fund'!N6 -> 109333 | BX32: ='USDT Yield Fund'!N6 -> 109333 | BY32: ='USDT Yield Fund'!N6 -> 109333 | CA32: Beginning Balance | CB32: ='USDT Yield Fund'!Q7 -> 256663.04 | CC32: ='USDT Yield Fund'!N7 -> 255504 | CD32: ='USDT Yield Fund'!N7 -> 255504 | CE32: ='USDT Yield Fund'!N7 -> 255504 | CG32: Beginning Balance | CH32: ='USDT Yield Fund'!Q4 -> 109888.23 | CI32: ='USDT Yield Fund'!N4 -> 109392 | CJ32: ='USDT Yield Fund'!N4 -> 109392 | CK32: ='USDT Yield Fund'!N4 -> 109392 | CM32: Beginning Balance | CN32: ='USDT Yield Fund'!Q5 -> 110273.98 | CO32: ='USDT Yield Fund'!N5 -> 109776 | CP32: ='USDT Yield Fund'!N5 -> 109776 | CQ32: ='USDT Yield Fund'!N5 -> 109776 | CY32: Beginning Balance | CZ32: ='USDT Yield Fund'!Q9 -> 200225.82 | DA32: ='USDT Yield Fund'!O9 -> 199659.72 | DB32: ='USDT Yield Fund'!O9 -> 199659.72 | DC32: ='USDT Yield Fund'!O9 -> 199659.72 | DE32: Beginning Balance | DF32: ='USDT Yield Fund'!Q10 -> 137017.48 | DG32: ='USDT Yield Fund'!P10 -> 136737 | DH32: ='USDT Yield Fund'!P10 -> 136737 | DI32: ='USDT Yield Fund'!P10 -> 136737 | DK32: Beginning Balance | DL32: ='USDT Yield Fund'!Q11 -> 223143.79 | DM32: ='USDT Yield Fund'!P11 -> 222687 | DN32: ='USDT Yield Fund'!P11 -> 222687 | DO32: ='USDT Yield Fund'!P11 -> 222687 | DQ32: Beginning Balance | DR32: ='USDT Yield Fund'!Q12 -> 220197.76 | DS32: ='USDT Yield Fund'!P12 -> 219747 | DT32: ='USDT Yield Fund'!P12 -> 219747 | DU32: ='USDT Yield Fund'!P12 -> 219747 | EI32: Beginning Balance | EJ32: ='USDT Yield Fund'!R13 -> 130000 | EK32: ='USDT Yield Fund'!R13 -> 130000 | EL32: ='USDT Yield Fund'!R13 -> 130000 | EM32: ='USDT Yield Fund'!R13 -> 130000 | EO32: Beginning Balance | EP32: ='ETH Yield Fund'!AC18 | EQ32: ='ETH Yield Fund'!AC18 | ER32: ='ETH Yield Fund'!AC18 | ES32: ='ETH Yield Fund'!AC18
AW33: Additions | AX33: 10000 | AY33: =46955.28+10000 -> 56955.28 | AZ33: =46955.28+10000 -> 56955.28 | BA33: =46955.28+10000 -> 56955.28 | BC33: Additions | BD33: 0 | BE33: 0 | BF33: 0 | BG33: 0 | BO33: Additions | BP33: 0 | BQ33: 0 | BR33: 0 | BS33: 0 | BU33: Additions | BV33: 0 | BW33: 0 | BX33: 0 | BY33: 0 | CA33: Additions | CB33: 25900 | CC33: 25900 | CD33: 25900 | CE33: 25900 | CG33: Additions | CH33: 0 | CI33: 0 | CJ33: 0 | CK33: 0 | CM33: Additions | CN33: 0 | CO33: 0 | CP33: 0 | CQ33: 0 | CY33: Additions | CZ33: 0 | DA33: 0 | DB33: 0 | DC33: 0 | DE33: Additions | DF33: 0 | DG33: 0 | DH33: 0 | DI33: 0 | DK33: Additions | DL33: 0 | DM33: 0 | DN33: 0 | DO33: 0 | DQ33: Additions | DR33: 0 | DS33: 0 | DT33: 0 | DU33: 0 | EI33: Additions | EJ33: 0 | EK33: 0 | EL33: 0 | EM33: 0 | EO33: Additions | EP33: 0 | EQ33: 0 | ER33: 0 | ES33: 0
AW34: Redemptions | AX34: 0 | AY34: 0 | AZ34: 0 | BA34: 0 | BC34: Redemptions | BD34: 0 | BE34: 0 | BF34: 0 | BG34: 0 | BO34: Redemptions | BP34: 0 | BQ34: 0 | BR34: 0 | BS34: 0 | BU34: Redemptions | BV34: 0 | BW34: 0 | BX34: 0 | BY34: 0 | CA34: Redemptions | CB34: 0 | CC34: 0 | CD34: 0 | CE34: 0 | CG34: Redemptions | CH34: 0 | CI34: 0 | CJ34: 0 | CK34: 0 | CM34: Redemptions | CN34: 0 | CO34: 0 | CP34: 0 | CQ34: 0 | CY34: Redemptions | CZ34: 0 | DA34: 0 | DB34: 0 | DC34: 0 | DE34: Redemptions | DF34: 0 | DG34: 0 | DH34: 0 | DI34: 0 | DK34: Redemptions | DL34: 0 | DM34: 0 | DN34: 0 | DO34: 0 | DQ34: Redemptions | DR34: 0 | DS34: 0 | DT34: 0 | DU34: 0 | EI34: Redemptions | EJ34: 0 | EK34: 0 | EL34: 0 | EM34: 0 | EO34: Redemptions | EP34: 0 | EQ34: 0 | ER34: 0 | ES34: 0
AW35: Net Income | AX35: =AX36-AX32-AX33 -> 1580.9089 | AY35: =AY36-AY32-AY33 -> 2431.3218 | AZ35: =AZ36-AZ32-AZ33 -> 2879.9741 | BA35: =BA36-BA32-BA33 -> 2879.9741 | BC35: Net Income | BD35: =BD36-BD32-BD33 -> 438.00502 | BE35: =BE36-BE32-BE33 -> 438.00502 | BF35: =BF36-BF32-BF33 -> 438.00502 | BG35: =BG36-BG32-BG33 -> 438.00502 | BO35: Net Income | BP35: =BP36-BP32 -> 2468.0297 | BQ35: =BQ36-BQ32 -> 3710.0995 | BR35: =BR36-BR32 -> 3710.0995 | BS35: =BS36-BS32-BS33 -> 3710.0995 | BU35: Net Income | BV35: =BV36-BV32 -> 985.50108 | BW35: =BW36-BW32 -> 1481.468 | BX35: =BX36-BX32 -> 1481.468 | BY35: =BY36-BY32-BY33 -> 1481.468 | CA35: Net Income | CB35: =CB36-CB32-CB33 -> 2433.0007 | CC35: =CC36-CC32-CC33 -> 3592.0426 | CD35: =CD36-CD32-CD33 -> 3592.0426 | CE35: =CE36-CE32-CE33 -> 3592.0426 | CG35: Net Income | CH35: =CH36-CH32 -> 986.0329 | CI35: =CI36-CI32 -> 1482.2674 | CJ35: =CJ36-CJ32 -> 1482.2674 | CK35: =CK36-CK32-CK33 -> 1482.2674 | CM35: Net Income | CN35: =CN36-CN32 -> 989.49418 | CO35: =CO36-CO32 -> 1487.4707 | CP35: =CP36-CP32 -> 1487.4707 | CQ35: =CQ36-CQ32-CQ33 -> 1487.4707 | CY35: Net Income | CZ35: =CZ36-CZ32 -> 1596.4826 | DA35: =DA36-DA32 -> 2162.5805 | DB35: =DB36-DB32 -> 2162.5805 | DC35: =DC36-DC32-DC33 -> 2162.5805 | DE35: Net Income | DF35: =DF36-DF32 -> 1229.4651 | DG35: =DG36-DG32 -> 1509.9469 | DH35: =DH36-DH32 -> 1509.9469 | DI35: =DI36-DI32-DI33 -> 1509.9469 | DK35: Net Income | DL35: =DL36-DL32 -> 2002.2809 | DM35: =DM36-DM32 -> 2459.0678 | DN35: =DN36-DN32 -> 2459.0678 | DO35: =DO36-DO32-DO33 -> 2459.0678 | DQ35: Net Income | DR35: =DR36-DR32 -> 1975.846 | DS35: =DS36-DS32 -> 2426.6022 | DT35: =DT36-DT32 -> 2426.6022 | DU35: =DU36-DU32-DU33 -> 2426.6022 | EI35: Net Income | EJ35: =EJ36-EJ32 -> 1224.2158 | EK35: =EK36-EK32 -> 1224.2158 | EL35: =EL36-EL32 -> 1224.2158 | EM35: =EM36-EM32-EM33 -> 1224.2158 | EO35: Net Income | EP35: =EP36-EP32 -> 0 | EQ35: =EQ36-EQ32 -> 0 | ER35: =ER36-ER32 -> 0 | ES35: =ES36-ES32-ES33 -> 0
AW36: Ending Balance | AX36: ='USDT Yield Fund'!U3 -> 195562 | AY36: =AX36 -> 195562 | AZ36: =AY36 -> 195562 | BA36: =AX36 -> 195562 | BC36: Ending Balance | BD36: ='USDT Yield Fund'!U14 -> 111808.01 | BE36: =BD36 -> 111808.01 | BF36: =BE36 -> 111808.01 | BG36: =BD36 -> 111808.01 | BO36: Ending Balance | BP36: ='USDT Yield Fund'!U8 -> 277517.1 | BQ36: =BP36 -> 277517.1 | BR36: =BQ36 -> 277517.1 | BS36: =BP36 -> 277517.1 | BU36: Ending Balance | BV36: ='USDT Yield Fund'!U6 -> 110814.47 | BW36: =BV36 -> 110814.47 | BX36: =BW36 -> 110814.47 | BY36: =BV36 -> 110814.47 | CA36: Ending Balance | CB36: ='USDT Yield Fund'!U7 -> 284996.04 | CC36: =CB36 -> 284996.04 | CD36: =CC36 -> 284996.04 | CE36: =CB36 -> 284996.04 | CG36: Ending Balance | CH36: ='USDT Yield Fund'!U4 -> 110874.27 | CI36: =CH36 -> 110874.27 | CJ36: =CI36 -> 110874.27 | CK36: =CH36 -> 110874.27 | CM36: Ending Balance | CN36: ='USDT Yield Fund'!U5 -> 111263.47 | CO36: =CN36 -> 111263.47 | CP36: =CO36 -> 111263.47 | CQ36: =CN36 -> 111263.47 | CY36: Ending Balance | CZ36: ='USDT Yield Fund'!U9 -> 201822.3 | DA36: =CZ36 -> 201822.3 | DB36: =DA36 -> 201822.3 | DC36: =CZ36 -> 201822.3 | DE36: Ending Balance | DF36: ='USDT Yield Fund'!U10 -> 138246.95 | DG36: =DF36 -> 138246.95 | DH36: =DG36 -> 138246.95 | DI36: =DF36 -> 138246.95 | DK36: Ending Balance | DL36: ='USDT Yield Fund'!U11 -> 225146.07 | DM36: =DL36 -> 225146.07 | DN36: =DM36 -> 225146.07 | DO36: =DL36 -> 225146.07 | DQ36: Ending Balance | DR36: ='USDT Yield Fund'!U12 -> 222173.6 | DS36: =DR36 -> 222173.6 | DT36: =DS36 -> 222173.6 | DU36: =DR36 -> 222173.6 | EI36: Ending Balance | EJ36: ='USDT Yield Fund'!U13 -> 131224.22 | EK36: =EJ36 -> 131224.22 | EL36: =EK36 -> 131224.22 | EM36: =EJ36 -> 131224.22 | EO36: Ending Balance | EP36: ='ETH Yield Fund'!AD18 | EQ36: =EP36 | ER36: =EQ36 | ES36: =EP36
AW37: Rate of Return | AX37: =AX35/AX32 -> 0.0085927792 | AY37: =AY35/AY32 -> 0.017854339 | AZ37: =AZ35/AZ32 -> 0.021218913 | BA37: =BA35/BA32 -> 0.021218913 | BC37: Rate of Return | BD37: =BD35/BD32 -> 0.0039328816 | BE37: =BE35/BE32 -> 0.0039328816 | BF37: =BF35/BF32 -> 0.0039328816 | BG37: =BG35/BG32 -> 0.0039328816 | BO37: Rate of Return | BP37: =BP35/BP32 -> 0.0089730525 | BQ37: =BQ35/BQ32 -> 0.013550053 | BR37: =BR35/BR32 -> 0.013550053 | BS37: =BS35/BS32 -> 0.013550053 | BU37: Rate of Return | BV37: =BV35/BV32 -> 0.0089730525 | BW37: =BW35/BW32 -> 0.013550053 | BX37: =BX35/BX32 -> 0.013550053 | BY37: =BY35/BY32 -> 0.013550053 | CA37: Rate of Return | CB37: =CB35/CB32 -> 0.0094793575 | CC37: =CC35/CC32 -> 0.014058655 | CD37: =CD35/CD32 -> 0.014058655 | CE37: =CE35/CE32 -> 0.014058655 | CG37: Rate of Return | CH37: =CH35/CH32 -> 0.0089730525 | CI37: =CI35/CI32 -> 0.013550053 | CJ37: =CJ35/CJ32 -> 0.013550053 | CK37: =CK35/CK32 -> 0.013550053 | CM37: Rate of Return | CN37: =CN35/CN32 -> 0.0089730525 | CO37: =CO35/CO32 -> 0.013550053 | CP37: =CP35/CP32 -> 0.013550053 | CQ37: =CQ35/CQ32 -> 0.013550053 | CY37: Rate of Return | CZ37: =CZ35/CZ32 -> 0.0079734105 | DA37: =DA35/DA32 -> 0.010831331 | DB37: =DB35/DB32 -> 0.010831331 | DC37: =DC35/DC32 -> 0.010831331 | DE37: Rate of Return | DF37: =DF35/DF32 -> 0.0089730525 | DG37: =DG35/DG32 -> 0.011042709 | DH37: =DH35/DH32 -> 0.011042709 | DI37: =DI35/DI32 -> 0.011042709 | DK37: Rate of Return | DL37: =DL35/DL32 -> 0.0089730525 | DM37: =DM35/DM32 -> 0.011042709 | DN37: =DN35/DN32 -> 0.011042709 | DO37: =DO35/DO32 -> 0.011042709 | DQ37: Rate of Return | DR37: =DR35/DR32 -> 0.0089730525 | DS37: =DS35/DS32 -> 0.011042709 | DT37: =DT35/DT32 -> 0.011042709 | DU37: =DU35/DU32 -> 0.011042709 | EI37: Rate of Return | EJ37: =EJ35/EJ32 -> 0.0094170447 | EK37: =EK35/EK32 -> 0.0094170447 | EL37: =EL35/EL32 -> 0.0094170447 | EM37: =EM35/EM32 -> 0.0094170447 | EO37: Rate of Return | EP37: =IFERROR(EP35/EP32,"") | EQ37: =IFERROR(EQ35/EQ32,"") | ER37: =IFERROR(ER35/ER32,"") | ES37: =IFERROR(ES35/ES32,"")

Sheet Performances
B1: Net Performance | F1: APY | J1: Indigo Fees | S1: Currency value to USD
B2: =3.5%/12 -> 0.0029166667 | C2: =7.5%/12 -> 0.00625 | D2: =7.75%/12 -> 0.0064583333 | J2: =SUM(J4:J996) -> 0.10631816 | K2: =SUM(K4:K996) -> 0.049814796 | L2: =SUM(L4:L996) -> 0 | M2: =SUM(M4:M996) -> 0.52182332 | N2: =SUM(N4:N996) -> 0.89796587 | O2: =SUM(O4:O996) -> 3157.862 | P2: =SUM(P4:P996) -> 22455.169 | Q2: =SUM(Q4:Q996) -> 26648.849 | S2: Yahoo Finance
B3: BTC | C3: ETH | D3: Stable | J3: BTC Yield Fund | K3: BTC BP | L3: BTC TAC | M3: ETH Yield Fund | N3: ETH TAC | O3: USDT Yield Fund | P3: End of month Value | Q3: Today Value | T3: BTC → USD | U3: ETH → USD
A4: 45504 | B4: ='BTC Yield Fund'!E3 -> 0.0050749712 | C4: ='Done - ETH TAC Program'!E3 -> 0.01001626 | D4: 0.0123 | J4: ='BTC Yield Fund'!K2 -> 0.0044 | K4: 0 | L4: 0 | M4: 0 | N4: ='Done - ETH TAC Program'!K2 -> 0.154 | O4: 0 | P4: =SUM(J4:L4)*T4+SUM(M4:N4)*U4+O4 -> 646.52962 | Q4: =SUM(J4:L4)*VLOOKUP(max($S$4:$S$996),$S$4:$T$996,2,FALSE)+SUM(M4:N4)*VLOOKUP(max($S$4:$S$996),$S$4:$U$996,3,FALSE)+O4 -> 1164.338 | S4: 45505 | T4: 58969.9 | U4: 2513.39
A5: 45535 | B5: =(1+'BTC Yield Fund'!E6)*(1+'BTC Yield Fund'!E4)-1 -> 0.0037501433 | C5: ='Done - ETH TAC Program'!E4 -> 0.0070660029 | D5: 0.0136 | J5: ='BTC Yield Fund'!M2-'BTC Yield Fund'!K2 -> 0.0038375915 | K5: 0 | L5: 0 | M5: 0 | N5: ='Done - ETH TAC Program'!L2-'Done - ETH TAC Program'!K2 -> 0.11108816 | O5: 0 | P5: =SUM(J5:L5)*T5+SUM(M5:N5)*U5+O5 -> 532.20191 | Q5: =SUM(J5:L5)*VLOOKUP(max($S$4:$S$996),$S$4:$T$996,2,FALSE)+SUM(M5:N5)*VLOOKUP(max($S$4:$S$996),$S$4:$U$996,3,FALSE)+O5 -> 913.15101 | S5: 45536 | T5: 63329.5 | U5: 2603.06
A6: 45565 | B6: ='BTC Yield Fund'!E7 -> 0.0043557169 | C6: ='Done - ETH TAC Program'!E5 -> 0.0064947469 | D6: 0.0128 | J6: ='BTC Yield Fund'!N2-'BTC Yield Fund'!M2 -> 0.0054905746 | K6: 0 | L6: 0 | M6: 0 | N6: ='Done - ETH TAC Program'!M2-'Done - ETH TAC Program'!L2 -> 0.10372168 | O6: 0 | P6: =SUM(J6:L6)*T6+SUM(M6:N6)*U6+O6 -> 646.46474 | Q6: =SUM(J6:L6)*VLOOKUP(max($S$4:$S$996),$S$4:$T$996,2,FALSE)+SUM(M6:N6)*VLOOKUP(max($S$4:$S$996),$S$4:$U$996,3,FALSE)+O6 -> 1063.1459 | S6: 45566 | T6: 70215.19 | U6: 2515.8
A7: 45596 | B7: ='BTC Yield Fund'!E9 -> 0.0040476615 | C7: =1.66%*0.8 -> 0.01328 | D7: 0.0132 | J7: ='BTC Yield Fund'!O2-'BTC Yield Fund'!N2 -> 0.010120998 | K7: 0 | L7: 0 | M7: 0 | N7: ='Done - ETH TAC Program'!O2-'Done - ETH TAC Program'!M2 -> 0.062925541 | O7: 0 | P7: =SUM(J7:L7)*T7+SUM(M7:N7)*U7+O7 -> 1209.3444 | Q7: =SUM(J7:L7)*VLOOKUP(max($S$4:$S$996),$S$4:$T$996,2,FALSE)+SUM(M7:N7)*VLOOKUP(max($S$4:$S$996),$S$4:$U$996,3,FALSE)+O7 -> 1394.4731 | S7: 45597 | T7: 96449.05 | U7: 3705.71
A8: 45626 | B8: =(1+'BTC Yield Fund'!E10)*(1+'BTC Yield Fund'!E12)-1 -> 0.0044053629 | C8: =1.66%*0.8 -> 0.01328 | D8: 0.0124 | J8: ='BTC Yield Fund'!Q2-'BTC Yield Fund'!O2 -> 0.011018794 | K8: 0 | L8: 0 | M8: 0 | N8: ='Done - ETH TAC Program'!P2-'Done - ETH TAC Program'!O2 -> 0 | O8: 0 | P8: =SUM(J8:L8)*T8+SUM(M8:N8)*U8+O8 -> 1029.4771 | Q8: =SUM(J8:L8)*VLOOKUP(max($S$4:$S$996),$S$4:$T$996,2,FALSE)+SUM(M8:N8)*VLOOKUP(max($S$4:$S$996),$S$4:$U$996,3,FALSE)+O8 -> 1216.2669 | S8: 45627 | T8: 93429.2 | U8: 3332.53
A9: 45657 | B9: =(1+'BTC Yield Fund'!E13)*(1+'BTC Yield Fund'!E16)-1 -> 0.0055623235 | C9: =1.66%*0.8 -> 0.01328 | D9: 0.0127 | J9: ='BTC Yield Fund'!T2-'BTC Yield Fund'!Q2 -> 0.007512658 | K9: ='DONE - BTC Boosted Program'!L2 -> 0.004558288 | L9: 0 | M9: 0 | N9: ='Done - ETH TAC Program'!Q2-'Done - ETH TAC Program'!P2 -> 0 | O9: 0 | P9: =SUM(J9:L9)*T9+SUM(M9:N9)*U9+O9 -> 1236.1255 | Q9: =SUM(J9:L9)*VLOOKUP(max($S$4:$S$996),$S$4:$T$996,2,FALSE)+SUM(M9:N9)*VLOOKUP(max($S$4:$S$996),$S$4:$U$996,3,FALSE)+O9 -> 1332.4047 | S9: 45658 | T9: 102405.02 | U9: 3298.27
A10: 45688 | B10: ='BTC Yield Fund'!E17 -> 0.0046875 | C10: ='Done - ETH TAC Program'!E12 -> 0.0044918294 | D10: 0.013 | J10: ='BTC Yield Fund'!U2-'BTC Yield Fund'!T2 -> 0.0044241688 | K10: ='DONE - BTC Boosted Program'!M2-'DONE - BTC Boosted Program'!L2 -> 0.013096594 | L10: 0 | M10: 0 | N10: ='Done - ETH TAC Program'!R2-'Done - ETH TAC Program'!Q2 -> 0.073401441 | O10: 0 | P10: =SUM(J10:L10)*T10+SUM(M10:N10)*U10+O10 -> 1642.5453 | Q10: =SUM(J10:L10)*VLOOKUP(max($S$4:$S$996),$S$4:$T$996,2,FALSE)+SUM(M10:N10)*VLOOKUP(max($S$4:$S$996),$S$4:$U$996,3,FALSE)+O10 -> 2257.4337 | S10: 45689 | T10: 84373.01 | U10: 2237.91
A11: 45716 | B11: ='BTC Yield Fund'!E18 -> 0.0031067961 | C11: ='Done - ETH TAC Program'!E13 -> 0.0099203852 | D11: 0.0126 | J11: ='BTC Yield Fund'!V2-'BTC Yield Fund'!U2 -> 0.0029624194 | K11: ='DONE - BTC Boosted Program'!N2-'DONE - BTC Boosted Program'!M2 -> 0.012113865 | L11: 0 | M11: 0 | N11: ='Done - ETH TAC Program'!S2-'Done - ETH TAC Program'!R2 -> 0.16372436 | O11: 0 | P11: =SUM(J11:L11)*T11+SUM(M11:N11)*U11+O11 -> 1543.0789 | Q11: =SUM(J11:L11)*VLOOKUP(max($S$4:$S$996),$S$4:$T$996,2,FALSE)+SUM(M11:N11)*VLOOKUP(max($S$4:$S$996),$S$4:$U$996,3,FALSE)+O11 -> 2385.6525 | S11: 45717 | T11: 82548.91 | U11: 1823.48
A12: 45747 | B12: ='BTC Yield Fund'!E19 -> 0.0030947776 | C12: ='Done - ETH TAC Program'!E15 -> 0.0022779697 | D12: 0.0131 | J12: ='BTC Yield Fund'!W2-'BTC Yield Fund'!V2 -> 0.0029710249 | K12: ='DONE - BTC Boosted Program'!O2-'DONE - BTC Boosted Program'!N2 -> 0.012212426 | L12: 0 | M12: 0 | N12: ='Done - ETH TAC Program'!T2-'Done - ETH TAC Program'!S2 -> 0.038420116 | O12: 0 | P12: =SUM(J12:L12)*T12+SUM(M12:N12)*U12+O12 -> 1499.3093 | Q12: =SUM(J12:L12)*VLOOKUP(max($S$4:$S$996),$S$4:$T$996,2,FALSE)+SUM(M12:N12)*VLOOKUP(max($S$4:$S$996),$S$4:$U$996,3,FALSE)+O12 -> 1845.2797 | S12: 45748 | T12: 94207.31 | U12: 1793.78
A13: 45777 | B13: =(1+'BTC Yield Fund'!E21)*(1+'BTC Yield Fund'!E23)-1 -> 0.0085239063 | C13: ='Done - ETH TAC Program'!E17 -> 0.0095670433 | D13: 0.00826 | J13: ='BTC Yield Fund'!Y2-'BTC Yield Fund'!W2-SUM(K9:K13) -> 0.013409014 | K13: ='DONE - BTC Boosted Program'!P2-'DONE - BTC Boosted Program'!O2 -> 0.0078336226 | L13: 0 | M13: 0 | N13: ='Done - ETH TAC Program'!U2-'Done - ETH TAC Program'!T2 -> 0.16216605 | O13: 0 | P13: =SUM(J13:L13)*T13+SUM(M13:N13)*U13+O13 -> 2632.9214 | Q13: =SUM(J13:L13)*VLOOKUP(max($S$4:$S$996),$S$4:$T$996,2,FALSE)+SUM(M13:N13)*VLOOKUP(max($S$4:$S$996),$S$4:$U$996,3,FALSE)+O13 -> 3059.4341 | S13: 45778 | T13: 104638.09 | U13: 2529.09
A14: 45808 | B14: =(1+'BTC Yield Fund'!E24)*(1+'BTC Yield Fund'!E27)-1 -> 0.0047702605 | C14: ='Done - ETH TAC Program'!E18 -> 0.0018952139 | D14: 0.00765 | J14: ='BTC Yield Fund'!AA2-'BTC Yield Fund'!Y2 -> 0.011343224 | K14: 0 | L14: 0 | M14: ='ETH Yield Fund'!M2 -> 0.0052947676 | N14: ='Done - ETH TAC Program'!V2-'Done - ETH TAC Program'!U2 -> 0.032800283 | O14: 0 | P14: =SUM(J14:L14)*T14+SUM(M14:N14)*U14+O14 -> 1309.982 | Q14: =SUM(J14:L14)*VLOOKUP(max($S$4:$S$996),$S$4:$T$996,2,FALSE)+SUM(M14:N14)*VLOOKUP(max($S$4:$S$996),$S$4:$U$996,3,FALSE)+O14 -> 1419.9586 | S14: 45809 | T14: 107135.34 | U14: 2486.46
A15: 45838 | B15: =(1+'BTC Yield Fund'!E29)*(1+'BTC Yield Fund'!E31)-1 -> 0.0030590121 | C15: ='Done - ETH TAC Program'!E19 -> 0.001812153 | D15: 0.0101 | J15: ='BTC Yield Fund'!AC2-'BTC Yield Fund'!AA2 -> 0.0073752863 | K15: 0 | L15: 0 | M15: ='ETH Yield Fund'!N2-'ETH Yield Fund'!M2 -> 0.086003382 | N15: ='Done - ETH TAC Program'!W2-'Done - ETH TAC Program'!V2 -> 0.031492761 | O15: 0 | P15: =SUM(J15:L15)*T15+SUM(M15:N15)*U15+O15 -> 1288.099 | Q15: =SUM(J15:L15)*VLOOKUP(max($S$4:$S$996),$S$4:$T$996,2,FALSE)+SUM(M15:N15)*VLOOKUP(max($S$4:$S$996),$S$4:$U$996,3,FALSE)+O15 -> 1331.885 | S15: 45839 | T15: 115758.2 | U15: 3696.71
A16: 45869 | B16: =(1+'BTC Yield Fund'!E32)*(1+'BTC Yield Fund'!E34)*(1+'BTC Yield Fund'!E36)*(1+'BTC Yield Fund'!E38)-1 -> 0.0038619908 | C16: =(1+'ETH Yield Fund'!E7)*(1+'ETH Yield Fund'!E9)-1 -> 0.008016547 | D16: =(1+'USDT Yield Fund'!E4)*(1+'USDT Yield Fund'!E6)*(1+'USDT Yield Fund'!E8)*(1+'USDT Yield Fund'!E10)-1 -> 0.0052673241 | J16: ='BTC Yield Fund'!AG2-'BTC Yield Fund'!AC2 -> 0.011218837 | K16: 0 | L16: 0 | M16: ='ETH Yield Fund'!Q2-'ETH Yield Fund'!N2-SUM(N4:N16) -> 0.17080406 | N16: ='Done - ETH TAC Program'!X2-'Done - ETH TAC Program'!W2 -> -0.035774526 | O16: ='USDT Yield Fund'!Q2 -> 919.77244 | P16: =SUM(J16:L16)*T16+SUM(M16:N16)*U16+O16 -> 2726.8448 | Q16: =SUM(J16:L16)*VLOOKUP(max($S$4:$S$996),$S$4:$T$996,2,FALSE)+SUM(M16:N16)*VLOOKUP(max($S$4:$S$996),$S$4:$U$996,3,FALSE)+O16 -> 2753.1807 | S16: 45870 | T16: 108236.71 | U16: 4390.02
A17: 45900 | B17: =(1+'BTC Yield Fund'!E40)*(1+'BTC Yield Fund'!E42)*(1+'BTC Yield Fund'!E44)-1 -> 0.0029239748 | C17: ='ETH Yield Fund'!E12 -> 0.0068533771 | D17: =(1+'USDT Yield Fund'!E11)*(1+'USDT Yield Fund'!E13)*(1+'USDT Yield Fund'!E15)*(1+'USDT Yield Fund'!E17)-1 -> 0.0079734105 | J17: ='BTC Yield Fund'!AJ2-'BTC Yield Fund'!AG2 -> 0.010233571 | K17: 0 | L17: 0 | M17: ='ETH Yield Fund'!R2-'ETH Yield Fund'!Q2 -> 0.25972111 | N17: 0 | O17: ='USDT Yield Fund'!U2-'USDT Yield Fund'!Q2 -> 2238.0896 | P17: =SUM(J17:L17)*T17+SUM(M17:N17)*U17+O17 -> 4512.2451 | Q17: =SUM(J17:L17)*VLOOKUP(max($S$4:$S$996),$S$4:$T$996,2,FALSE)+SUM(M17:N17)*VLOOKUP(max($S$4:$S$996),$S$4:$U$996,3,FALSE)+O17 -> 4512.2451 | S17: 45901 | T17: 110381.13 | U17: 4406.89
